Workbook
Name language: [1]INDEX!$E$103:$E$104
Name language: [2]INDEX!$E$102:$E$103
Name language: [3]INDEX!$E$103:$E$104
Name language: [4]INDEX!$E$102:$E$103
Name language: [4]INDEX!$E$102:$E$103
Name language: [5]INDEX!$E$103:$E$104
Name language: [6]INDEX!$E$103:$E$104
Name language: [7]INDEX!$E$102:$E$103
Name language: [8]INDEX!$E$102:$E$103
Name language: [8]INDEX!$E$102:$E$103
Name language: [9]INDEX!$E$103:$E$104
Name language: [10]INDEX!$E$103:$E$104
Name language: INDEX!$E$103:$E$104
Name 손익분석: [11]INDEX!$G$9

Sheet INDEX
G2: =VLOOKUP(G103,$G$103:$H$138,$F$103,0) -> 재무 실적 | I2: =VLOOKUP(G124,$G$103:$H$138,$F$103,0) -> 경영효율성
G3: =VLOOKUP(G104,$G$103:$H$138,$F$103,0) -> 재무실적 요약 | I3: =VLOOKUP(G124,$G$103:$H$138,$F$103,0) -> 경영효율성
G4: =VLOOKUP(G105,$G$103:$H$138,$F$103,0) -> K-IFRS 재무상태표 | I4: =VLOOKUP(G125,$G$103:$H$138,$F$103,0) -> 손해율
G5: =VLOOKUP(G106,$G$103:$H$138,$F$103,0) -> K-IFRS 손익계산서 | I5: =VLOOKUP(G126,$G$103:$H$138,$F$103,0) -> 유지율
G6: =VLOOKUP(G107,$G$103:$H$138,$F$103,0) -> 보험회계기준 (SAP) 재무상태표 | I6: =VLOOKUP(G127,$G$103:$H$138,$F$103,0) -> 보유고객
G7: =VLOOKUP(G108,$G$103:$H$138,$F$103,0) -> 보험회계기준 (SAP) 손익계산서
G8: =VLOOKUP(G140,$G$103:$H$141,$F$103,0) -> CSM 현황 | I8: =VLOOKUP(G129,$G$103:$H$138,$F$103,0) -> 자산운용
G9: =VLOOKUP(G109,$G$103:$H$138,$F$103,0) -> 손익현황 | I9: =VLOOKUP(G130,$G$103:$H$138,$F$103,0) -> 자산 포트폴리오
B10: 2025 Q4 | G10: =VLOOKUP(G110,$G$103:$H$138,$F$103,0) -> 신계약현황 | I10: =VLOOKUP(G131,$G$103:$H$138,$F$103,0) -> 자산별 투자성과
B11: d | I11: =VLOOKUP(G132,$G$103:$H$138,$F$103,0) -> 자산건전성
G12: =VLOOKUP(G112,$G$103:$H$138,$F$103,0) -> 수입보험료 실적
G13: =VLOOKUP(G113,$G$103:$H$138,$F$103,0) -> 수입보험료 | I13: =VLOOKUP(G134,$G$103:$H$138,$F$103,0) -> 재무안정성
G14: =VLOOKUP(G114,$G$103:$H$138,$F$103,0) -> 초회보험료 | I14: =VLOOKUP(G135,$G$103:$H$138,$F$103,0) -> 적립금비중
G15: =VLOOKUP(G115,$G$103:$H$138,$F$103,0) -> 초년도보험료 | I15: =VLOOKUP(G136,$G$103:$H$138,$F$103,0) -> 평균부담금리
G16: =VLOOKUP(G116,$G$103:$H$138,$F$103,0) -> 채널별 초회보험료 | I16: =VLOOKUP(G137,$G$103:$H$138,$F$103,0) -> 자산부채 듀레이션
G17: =VLOOKUP(G117,$G$103:$H$138,$F$103,0) -> 채널별 초년도보험료 | I17: =VLOOKUP(G138,$G$103:$H$138,$F$103,0) -> 자산부채 금리
G18: =VLOOKUP(G118,$G$103:$H$138,$F$103,0) -> 상품/채널별 APE
I19: =VLOOKUP(G142,$G$103:$H$142,$F$103,0) -> 자회사
G20: =VLOOKUP(G120,$G$103:$H$138,$F$103,0) -> Fee-Biz 실적 | I20: =VLOOKUP(G143,$G$103:$H$143,$F$103,0) -> 미래에셋금융서비스
G21: =VLOOKUP(G121,$G$103:$H$138,$F$103,0) -> 변액보험
G22: =VLOOKUP(G122,$G$103:$H$138,$F$103,0) -> 퇴직연금 | I22: =VLOOKUP(G145,$G$103:$H$146,$F$103,0) -> 부채 변동
I23: =VLOOKUP(G146,$G$103:$H$146,$F$103,0) -> 잔여보장부채 무브먼트
G37: 0
D101: LANGUAGE SELECTOR
E103: KOREAN | F103: 1 | G103: 재무 실적 | H103: Financial Results
E104: ENGLISH | G104: 재무실적 요약 | H104: Condensed F/S
G105: K-IFRS 재무상태표 | H105: K-IFRS Balance Sheet
G106: K-IFRS 손익계산서 | H106: K-IFRS Income Statement
G107: 보험회계기준 (SAP) 재무상태표 | H107: SAP Balance Sheet
G108: 보험회계기준 (SAP) 손익계산서 | H108: SAP Income Statement
G109: 손익현황 | H109: Earnings Results
G110: 신계약현황 | H110: New Business
G112: 수입보험료 실적 | H112: Premium Income
G113: 수입보험료 | H113: Premium Breakdown
G114: 초회보험료 | H114: Initial Premium
G115: 초년도보험료 | H115: First Year Premium
G116: 채널별 초회보험료 | H116: Initial Premium by Channel
G117: 채널별 초년도보험료 | H117: First Year Premium by Channel
... G146: 잔여보장부채 무브먼트 | H146: Movement of Liabilities for Remaining Coverage

Sheet SUMMARY
B1: =[9]INDEX!$G$3 -> 재무실적 요약 | C1: Financial Highlights
B2: (BN KRW, %, %p)
B4: 별도기준 | C4: Unconsolidated Basis | D4: =I4 -> 2025 | E4: =N4 -> 2024 | F4: YoY | I4: 2025 | N4: 2024 | Q4: 2023 | V4: 2022 | Z4: 2021
D5: =I5 -> 4 | E5: =M5 -> 4 | I5: 4 | J5: 3 | K5: 2 | L5: 1 | M5: 4 | N5: 3 | O5: 2 | P5: 1 | Q5: 4 | R5: 3 | S5: 2 | T5: 1 | V5: 4 | W5: 3 | X5: 2 | Y5: 1 | Z5: FY
B6: 자산총계 | C6: Total Assets | D6: =I6 -> 32855.182 | E6: =M6 -> 32404.439 | F6: =+IFERROR(IF(E6<0,-(D6/E6-1),(D6/E6-1)),0) -> 0.013909919 | I6: 32855.182 | J6: 33165.463 | K6: 32215.468 | L6: 32214.589 | M6: 32404.439 | N6: 32232.653 | O6: 32188.593 | P6: 32333.017 | Q6: 33046.193 | R6: 32111.06 | S6: 32951.333 | T6: 33150.631 | V6: 34991.095 | W6: 36813.714 | X6: 36977.267 | Y6: 38438.524
B7: 부채총계 | C7: Total Liabilities | D7: =I7 -> 30418.68 | E7: =M7 -> 29851.201 | F7: =+IFERROR(IF(E7<0,-(D7/E7-1),(D7/E7-1)),0) -> 0.019010275 | I7: 30418.68 | J7: 30683.352 | K7: 29744.746 | L7: 29747.791 | M7: 29851.201 | N7: 29703.68 | O7: 29660.895 | P7: 29599.142 | Q7: 30027.166 | R7: 29140.784 | S7: 30008.69 | T7: 30274.4 | V7: 30902.57 | W7: 32521.422 | X7: 33072.626 | Y7: 35087.284
B8: 자본총계 | C8: Total Equity | D8: =I8 -> 2436.5016 | E8: =M8 -> 2553.2379 | F8: =+IFERROR(IF(E8<0,-(D8/E8-1),(D8/E8-1)),0) -> -0.045720922 | I8: 2436.5016 | J8: 2482.1114 | K8: 2470.7229 | L8: 2466.7972 | M8: 2553.2379 | N8: 2528.9733 | O8: 2527.6974 | P8: 2733.8755 | Q8: 3019.0271 | R8: 2970.276 | S8: 2942.6434 | T8: 2876.2309 | V8: 4088.5253 | W8: 4292.292 | X8: 3904.6406 | Y8: 3351.2394 | Z8: 2694.5031
D9: =D5 -> 4 | E9: =E5 -> 4 | F9: YoY | K9: =K8/M8-1 -> -0.03231781
B10: 보험서비스손익 | C10: Insurance service income | D10: =SUM(I10:L10) -> 111.99011 | E10: =SUM(M10:P10) -> 119.27554 | F10: =+IFERROR(IF(E10<0,-(D10/E10-1),(D10/E10-1)),0) -> -0.061080709 | I10: -5.880676 | J10: 34.30921 | K10: 44.676269 | L10: 38.885307 | M10: 19.855061 | N10: 31.404157 | O10: 45.718813 | P10: 22.297512 | Q10: 57.394659 | R10: 27.339907 | S10: 40.567695 | T10: 43.698505 | V10: 21.695846 | W10: 26.28169 | X10: 37.2643 | Y10: 37.705991
B11: 투자손익 | C11: Investment income | D11: =SUM(I11:L11) -> 73.866157 | E11: =SUM(M11:P11) -> -4.33664 | F11: =+IFERROR(IF(E11<0,-(D11/E11-1),(D11/E11-1)),0) -> 18.033038 | I11: 28.907445 | J11: 24.543101 | K11: 20.063001 | L11: 0.35260888 | M11: 33.294063 | N11: -27.967507 | O11: -30.821484 | P11: 21.158288 | Q11: -119.39884 | R11: -0.74453509 | S11: 3.7496379 | T11: 93.769318 | V11: -79.149764 | W11: 46.372237 | X11: 21.964919 | Y11: 38.640954
B12: 영업외손익 | C12: Non-Operating Income | D12: =SUM(I12:L12) -> 3.4005108 | E12: =SUM(M12:P12) -> 0.88398245 | F12: =+IFERROR(IF(E12<0,-(D12/E12-1),(D12/E12-1)),0) -> 2.846808 | I12: 6.0941748 | J12: -0.31653275 | K12: -1.4037297 | L12: -0.9734016 | M12: 0.99597178 | N12: -2.0731538 | O12: 3.3419551 | P12: -1.3807906 | Q12: -0.5314674 | R12: -0.80410659 | S12: -1.0082205 | T12: -1.6733323 | V12: 3.7365747 | W12: 1.1965876 | X12: -1.3374574 | Y12: -1.4611123
B13: 세전이익 | C13: Earnings Before Tax | D13: =SUM(I13:L13) -> 189.25678 | E13: =SUM(M13:P13) -> 115.82289 | F13: =+IFERROR(IF(E13<0,-(D13/E13-1),(D13/E13-1)),0) -> 0.63401882 | I13: 29.120944 | J13: 58.535778 | K13: 63.33554 | L13: 38.264514 | M13: 54.145096 | N13: 1.3634963 | O13: 18.239284 | P13: 42.07501 | Q13: -62.535653 | R13: 25.791266 | S13: 43.309113 | T13: 135.79449 | V13: -53.717343 | W13: 73.850514 | X13: 57.891762 | Y13: 74.885832
B14: 법인세비용 | C14: Income Tax Expenses | D14: =SUM(I14:L14) -> 64.356388 | E14: =SUM(M14:P14) -> -9.2160661 | F14: =+IFERROR(IF(E14<0,-(D14/E14-1),(D14/E14-1)),0) -> 7.9830649 | I14: 25.417778 | J14: 12.011954 | K14: 12.981909 | L14: 13.944746 | M14: -23.511844 | N14: 0.31603338 | O14: 4.2275306 | P14: 9.7522136 | Q14: -12.504168 | R14: 1.3247385 | S14: 9.2795916 | T14: 35.0592 | V14: -20.191077 | W14: 17.943629 | X14: 13.179629 | Y14: 18.507928
B15: 당기순이익 | C15: Net Income | D15: =SUM(I15:L15) -> 124.90039 | E15: =SUM(M15:P15) -> 125.03895 | F15: =+IFERROR(IF(E15<0,-(D15/E15-1),(D15/E15-1)),0) -> -0.0011081636 | I15: 3.7031661 | J15: 46.523824 | K15: 50.353631 | L15: 24.319768 | M15: 77.65694 | N15: 1.0474629 | O15: 14.011753 | P15: 32.322796 | Q15: -50.031485 | R15: 24.466527 | S15: 34.029521 | T15: 100.73529 | V15: -33.526266 | W15: 55.906885 | X15: 44.712132 | Y15: 56.377905
B16: ROE (YTD) | C16: ROE (YTD) | D16: =I16 -> 0.05006289 | E16: =M16 -> 0.04487904 | F16: =D16-E16 -> 0.0051838495 | I16: =SUM(I15:L15)/(SUM(I8,$M$8)/2)*(4/I5) -> 0.05006289 | J16: =SUM(J15:L15)/(SUM(J8,$M$8)/2)*(4/J5) -> 0.064184741 | K16: =SUM(K15:L15)/(SUM(K8,$M$8)/2)*(4/K5) -> 0.059453807 | L16: =SUM(L15)/(SUM(L8,$M$8)/2)*(4/L5) -> 0.038756331 | M16: =SUM(M15:P15)/(SUM(M8,$Q$8)/2)*(4/M5) -> 0.04487904 | N16: =SUM(N15:P15)/(SUM(N8,$Q$8)/2)*(4/N5) -> 0.022774338 | O16: =SUM(O15:P15)/(SUM(O8,$Q$8)/2)*(4/O5) -> 0.033413991 | P16: =SUM(P15)/(SUM(P8,$Q$8)/2)*(4/P5) -> 0.044948158 | Q16: =(SUM(Q15:T15)/(SUM(Q8,$AB$8)/2)*(4/Q5)) -> 0.07234109 | R16: =(SUM(R15:T15)/(SUM(R8,$AB$8)/2)*(4/R5)) -> 0.14295537 | S16: =(SUM(S15:U15)/(SUM(S8,$AB$8)/2)*(4/S5)) -> 0.18318878 | T16: =SUM(T15)/(SUM(T8,$AB$8)/2)*(4/T5) -> 0.28018694 | V16: =(SUM(V15:X15)/(SUM(V8+$Z$8)/2)*(4/V5)) -> 0.019782536 | W16: =(SUM(W15:Y15)/(SUM(W8+$Z$8)/2)*(4/W5)) -> 0.059921389 | X16: =(SUM(X15:Z15)/(SUM(X8+$Z$8)/2)*(4/X5)) -> 0.061274639 | Y16: =(SUM(Y15)/(SUM(Y8:$Z$8)/2)*(4/Y5)) -> 0.074601795
T17: IFRS 17 & IFRS 9 ◀ | V17: ▶IFRS 17 + IAS 39
M18: =D23/M23-1 -> -0.045076091
B19: 연결기준 | C19: Consolidated Basis | D19: =D4 -> 2025 | E19: =E4 -> 2024 | F19: YoY | K19: 2025 | N19: 2024 | Q19: 2023 | V19: 2022 | Z19: 2021
D20: =D5 -> 4 | E20: =E5 -> 4 | I20: 4 | J20: 3 | K20: 2 | L20: 1 | M20: 4 | N20: 3 | O20: 2 | P20: 1 | Q20: 4 | R20: 3 | S20: 2 | T20: 1 | V20: 4 | W20: 3 | X20: 2 | Y20: 1 | Z20: FY
B21: 자산총계 | C21: Total Assets | D21: =I21 -> 32920.825 | E21: =M21 -> 32493.624 | F21: =+IFERROR(IF(E21<0,-(D21/E21-1),(D21/E21-1)),0) -> 0.013147242 | I21: 32920.825 | J21: 33221.046 | K21: 32262.704 | L21: 32292.185 | M21: 32493.624 | N21: 32311.033 | O21: 32269.311 | P21: 32398.401 | Q21: 33092.023 | R21: 32212.292 | S21: 33053.385 | T21: 33188.803 | V21: 35041.5 | W21: 36745.351 | X21: 36936.579 | Y21: 38443.846
B22: 부채총계 | C22: Total Liabilities | D22: =I22 -> 30472.73 | E22: =M22 -> 29929.969 | F22: =+IFERROR(IF(E22<0,-(D22/E22-1),(D22/E22-1)),0) -> 0.018134367 | I22: 30472.73 | J22: 30729.498 | K22: 29786.394 | L22: 29814.766 | M22: 29929.969 | N22: 29777.861 | O22: 29737.477 | P22: 29662.595 | Q22: 30076.512 | R22: 29198.963 | S22: 30106.555 | T22: 30322.635 | V22: 30954.6 | W22: 32490.388 | X22: 33056.819 | Y22: 35123.626
B23: 자본총계 | C23: Total Equity | D23: =I23 -> 2448.0951 | E23: =M23 -> 2563.6547 | F23: =+IFERROR(IF(E23<0,-(D23/E23-1),(D23/E23-1)),0) -> -0.045076091 | I23: 2448.0951 | J23: 2491.5482 | K23: 2476.3106 | L23: 2477.4191 | M23: 2563.6547 | N23: 2533.172 | O23: 2531.8337 | P23: 2735.8059 | Q23: 3015.5111 | R23: 3013.3291 | S23: 2946.8304 | T23: 2866.1683 | V23: 4086.9469 | W23: 4254.963 | X23: 3879.7601 | Y23: 3320.2202
D24: =D20 -> 4 | E24: =E20 -> 4 | F24: YoY
B25: 보험서비스손익 | C25: Insurance service income | D25: =SUM(I25:L25) -> 77.004455 | E25: =SUM(M25:P25) -> 84.835761 | F25: =+IFERROR(IF(E25<0,-(D25/E25-1),(D25/E25-1)),0) -> -0.092311375 | I25: -17.474328 | J25: 26.371814 | K25: 36.656362 | L25: 31.450608 | M25: 8.0693026 | N25: 23.588147 | O25: 52.578253 | P25: 0.60005782 | Q25: 0.60005782 | R25: 12.291645 | S25: 27.381107 | T25: 24.494263 | V25: 11.251813 | W25: -2.9381434 | X25: 18.08135 | Y25: 17.281628
B26: 투자손익 | C26: Investment income | D26: =SUM(I26:L26) -> 117.50719 | E26: =SUM(M26:P26) -> 37.294734 | F26: =+IFERROR(IF(E26<0,-(D26/E26-1),(D26/E26-1)),0) -> 2.1507716 | I26: 45.81892 | J26: 35.402674 | K26: 28.38263 | L26: 7.9029618 | M26: 44.286762 | N26: -19.188509 | O26: -34.967611 | P26: 47.164091 | Q26: 47.164091 | R26: -3.113065 | S26: 25.804546 | T26: 115.64915 | V26: -65.481568 | W26: 82.575643 | X26: 41.650388 | Y26: 59.972617
B27: 영업외손익 | C27: Non-Operating Income | D27: =SUM(I27:L27) -> 4.1979196 | E27: =SUM(M27:P27) -> 1.0014912 | F27: =+IFERROR(IF(E27<0,-(D27/E27-1),(D27/E27-1)),0) -> 3.191669 | I27: 6.5440642 | J27: -0.071592624 | K27: -1.2866364 | L27: -0.98791555 | M27: 0.99295031 | N27: -2.0881124 | O27: 3.4873949 | P27: -1.3907415 | Q27: -4.1530448 | R27: 54.4 | S27: -0.85692421 | T27: -1.6587341 | V27: 3.654817 | W27: 1.2096452 | X27: -1.4630999 | Y27: -1.2601205
B28: 세전이익 | C28: Earnings Before Tax | D28: =SUM(I28:L28) -> 198.70956 | E28: =SUM(M28:P28) -> 123.13199 | F28: =+IFERROR(IF(E28<0,-(D28/E28-1),(D28/E28-1)),0) -> 0.6137932 | I28: 34.888656 | J28: 61.702895 | K28: 63.752355 | L28: 38.365654 | M28: 53.349015 | N28: 2.3115258 | O28: 21.098038 | P28: 46.373407 | Q28: 144.57265 | R28: 63.57218 | S28: 52.328729 | T28: 138.48468 | V28: -50.574939 | W28: 80.847145 | X28: 58.268638 | Y28: 75.994125
B29: 법인세비용 | C29: Income Tax Expenses | D29: =SUM(I29:L29) -> 67.933129 | E29: =SUM(M29:P29) -> -12.982885 | F29: =+IFERROR(IF(E29<0,-(D29/E29-1),(D29/E29-1)),0) -> 6.2325141 | I29: 29.34346 | J29: 11.946903 | K29: 13.06019 | L29: 13.582576 | M29: -27.697249 | N29: 0.50945688 | O29: 4.346611 | P29: 9.8582966 | Q29: 43.167939 | R29: 3.1808692 | S29: 6.9935997 | T29: 35.904757 | V29: -25.927837 | W29: 30.891043 | X29: 13.104666 | Y29: 21.651948
B30: 당기순이익 | C30: Net Income | D30: =SUM(I30:L30) -> 130.77643 | E30: =SUM(M30:P30) -> 136.11487 | F30: =+IFERROR(IF(E30<0,-(D30/E30-1),(D30/E30-1)),0) -> -0.0392201 | I30: 5.5451961 | J30: 49.755992 | K30: 50.692165 | L30: 24.783078 | M30: 81.046264 | N30: 1.8020689 | O30: 16.751427 | P30: 36.51511 | Q30: 101.40471 | R30: 60.391311 | S30: 45.335129 | T30: 102.57993 | V30: -24.647102 | W30: 49.956101 | X30: 45.163973 | Y30: 54.342177
B31: ROE (YTD) | C31: ROE (YTD) | D31: =I31 -> 0.052187933 | E31: =M31 -> 0.048793986 | F31: =D31-E31 -> 0.0033939467 | I31: =SUM(I30:L30)/(SUM(I23,M23)/2)*(4/I20) -> 0.052187933 | J31: =SUM(J30:L30)/(SUM(J23,M23)/2)*(4/J20) -> 0.066060644 | K31: =SUM(K30:L30)/(SUM(K23,M23)/2)*(4/K20) -> 0.059901399 | L31: =SUM(L30)/(SUM(L23,M23)/2)*(4/L20) -> 0.03932984 | M31: =SUM(M30:P30)/(SUM(M23,Q23)/2)*(4/M20) -> 0.048793986 | N31: =SUM(N30:P30)/(SUM(N23,Q23)/2)*(4/N20) -> 0.02646567 | O31: =SUM(O30:P30)/(SUM(O23,Q23)/2)*(4/O20) -> 0.038408672 | P31: =SUM(P30)/(SUM(P23,Q23)/2)*(4/P20) -> 0.050791998 | Q31: =SUM(Q30:T30)/(SUM(Q23,$AB$23)/2)*(4/Q20) -> 0.205412 | R31: =SUM(R30:T30)/(SUM(R23,$AB$23)/2)*(4/R20) -> 0.18434217 | S31: =SUM(S30:T30)/(SUM(S23,$AB$23)/2)*(4/S20) -> 0.20077851 | T31: =SUM(T30)/(SUM(T23,$AB$23)/2)*(4/T20) -> 0.28631934 | V31: =SUM(V30:X30)/(SUM(V23,$Z$23)/2)*(4/V20) -> 0.034486855 | W31: =SUM(W30:Y30)/(SUM(W23,$Z$23)/2)*(4/W20) -> 0.09367085 | X31: =SUM(X30:Y30)/(SUM(X23,Z23)/2)*(4/X20) -> 0.10259 | Y31: =SUM(Y30)/(SUM(Y23:$Z$23)/2)*(4/Y20) -> 0.13093632
D32: 25 Q4 | E32: 24 Q4 | F32: YTD | I32: =I20 -> 4 | J32: =J20 -> 3 | K32: =K20 -> 2 | L32: =L20 -> 1 | M32: =M20 -> 4 | N32: =N20 -> 3 | O32: =O20 -> 2 | P32: =P20 -> 1 | Q32: 4 | R32: 3 | S32: 2 | T32: 1 | V32: 4 | W32: 3 | X32: 2 | Y32: 1
B33: K-ICS 비율* | C33: K-ICS Ratio | D33: =D34/D35 -> 1.778836 | E33: =E34/E35 -> 1.9239452 | F33: =D33-E33 -> -0.14510921 | I33: =I34/I35 -> 1.778836 | J33: =J34/J35 -> 1.8297502 | K33: =K34/K35 -> 1.8349775 | L33: =L34/L35 -> 1.8327744 | M33: =M34/M35 -> 1.9239452 | N33: =N34/N35 -> 1.9378836 | O33: =O34/O35 -> 1.9798853 | P33: =P34/P35 -> 2.0716063 | Q33: =Q34/Q35 -> 2.1124457 | R33: 2.0544753 | S33: 2.0971471 | T33: 2.1837034 | V33: =V34/V35 -> 1.9152245 | W33: =W34/W35 -> 1.8340133 | X33: =X34/X35 -> 1.8646034 | Y33: =Y34/Y35 -> 1.8141082
B34: 지급여력금액 | C34: Solvency Capital | D34: =I34 -> 3698.2 | E34: =M34 -> 3579.6384 | F34: =+IFERROR(IF(E34<0,-(D34/E34-1),(D34/E34-1)),0) -> 0.033121113 | I34: 3698.2 | J34: 3666.9416 | K34: 3548.5268 | L34: 3451.1218 | M34: 3579.6384 | N34: 3408.5465 | O34: 3451.9017 | P34: 3604.7089 | Q34: 3815.5943 | R34: 4086.1028 | S34: 4097.0541 | T34: 4047.446 | V34: 3590.1157 | W34: 1933.4664 | X34: 1983.6369 | Y34: 1956.2716
B35: 위험기준지급여력금액 | C35: Required Capital | D35: =I35 -> 2079 | E35: =M35 -> 1860.5719 | F35: =+IFERROR(IF(E35<0,-(D35/E35-1),(D35/E35-1)),0) -> 0.11739835 | I35: 2079 | J35: 2004.0668 | K35: 1933.8258 | L35: 1883.0041 | M35: 1860.5719 | N35: 1758.9015 | O35: 1743.4857 | P35: 1740.055 | Q35: 1806.2449 | R35: 1998.6711 | S35: 1953.6322 | T35: 1853.478 | V35: 1874.5142 | W35: 1054.2271 | X35: 1063.8385 | Y35: 1078.3655
D36: =D28-E28 -> 75.577575 | I36: =I33-J33 -> -0.050914205 | J36: =J33-K33 -> -0.0052273371 | T36: IFRS 17 & IFRS 9 ◀ | V36: ▶IFRS 17 + IAS 39
B37: ▶ *) FY2022 Q4부터 K-ICS비율 기재, 당 분기는 추정치로 기재
B38: *) K-ICS represented from FY2022 Q4, and K-ICS for the current quarter is an estimate

Sheet KIFRS-BS
B1: =[4]INDEX!G4 -> K-IFRS 재무상태표 | C1: Financial Statements K-IFRS | AA1: =B1 -> K-IFRS 재무상태표
B2: (BN KRW, %, %p) | AA2: (BN KRW, %, %p)
B4: 별도 재무상태표 | C4: Unconsolidated B/S | D4: =SUMMARY!D4 -> 2025 | E4: =SUMMARY!E4 -> 2024 | F4: YoY | I4: 2025 | M4: 2024 | Q4: 2023 | U4: 2022 | AA4: 연결 재무상태표 | AB4: Consolidated B/S | AC4: =D4 -> 2025 | AD4: =E4 -> 2024 | AE4: YoY | AH4: 2025 | AL4: 2024 | AP4: 2023 | AT4: 2022
D5: =I5 -> Q4 | E5: =M5 -> Q4 | I5: Q4 | J5: Q3 | K5: Q2 | L5: Q1 | M5: Q4 | N5: Q3 | O5: Q2 | P5: Q1 | Q5: Q4 | R5: Q3 | S5: Q2 | T5: Q1 | U5: Q4 | V5: Q3 | W5: Q2 | X5: Q1 | AC5: =D5 -> Q4 | AD5: =E5 -> Q4 | AH5: Q4 | AI5: Q3 | AJ5: Q2 | AK5: Q1 | AL5: Q4 | AM5: Q3 | AN5: Q2 | AO5: Q1 | AP5: Q4 | AQ5: Q3 | AR5: Q2 | AS5: Q1 | AT5: Q4 | AU5: Q3 | AV5: Q2 | AW5: Q1
B6: 현금및현금성자산 | C6: Cash and cash equivalents | D6: =I6 -> 969.62 | E6: =M6 -> 921.9397 | F6: =IFERROR(IF(D6*E6<0,"-", IF(E6<0,-(D6/E6-1),(D6/E6-1))),0) -> 0.051717373 | I6: 969.62 | J6: 844.62282 | K6: 755.02019 | L6: 759.4889 | M6: 921.9397 | N6: 713.30968 | O6: 681.20769 | P6: 763.20705 | Q6: 1227.2485 | R6: 507.69983 | S6: 505.20667 | T6: 618.40593 | U6: 916.71105 | V6: 518.42812 | W6: ='[12]202206 BS(17및39기준)'!$X$12/1000000000 -> 521.7341 | X6: 671.3237 | AA6: 현금및현금성자산 | AB6: Cash and cash equivalents | AC6: =AH6 -> 982.15285 | AD6: =AL6 -> 932.1848 | AE6: =IFERROR(IF(AC6*AD6<0,"-", IF(AD6<0,-(AC6/AD6-1),(AC6/AD6-1))),0) -> 0.053603165 | AH6: 982.15285 | AI6: 855.30123 | AJ6: 763.67179 | AK6: 768.36804 | AL6: 932.1848 | AM6: 734.58002 | AN6: 702.53872 | AO6: 777.94916 | AP6: 1240.1903 | AQ6: 564.89408 | AR6: 519.50741 | AS6: 633.73853 | AT6: 941.89894 | AU6: 540.85937 | AV6: 552.2069 | AW6: 705.81954
B7: 당기손익-공정가치측정금융자산 | C7: Financial assets measured at fair value through profit or loss | D7: =I7 -> 16944.447 | E7: =M7 -> 15392.284 | F7: =IFERROR(IF(D7*E7<0,"-", IF(E7<0,-(D7/E7-1),(D7/E7-1))),0) -> 0.10084029 | I7: 16944.447 | J7: 16558.857 | K7: 15656.029 | L7: 15112.992 | M7: 15392.284 | N7: 15649.98 | O7: 15956.867 | P7: 16239.529 | Q7: 15850.238 | R7: 16008.301 | S7: 16432.039 | T7: 16441.119 | U7: 0 | V7: 0 | W7: 0 | X7: 0 | AA7: 당기손익-공정가치측정금융자산 | AB7: Fair value profit or loss financial assets | AC7: =AH7 -> 16948.053 | AD7: =AL7 -> 15422.585 | AE7: =IFERROR(IF(AC7*AD7<0,"-", IF(AD7<0,-(AC7/AD7-1),(AC7/AD7-1))),0) -> 0.098911238 | AH7: 16948.053 | AI7: 16563.484 | AJ7: 15652.467 | AK7: 15135.181 | AL7: 15422.585 | AM7: 15714.811 | AN7: 16012.987 | AO7: 16264.2 | AP7: 15868.274 | AQ7: 16065.55 | AR7: 16485.139 | AS7: 16432.28
B8: 기타포괄손익-공정가치측정금융자산 | C8: Fair value other comprehensive income financial assets | D8: =I8 -> 11663.557 | E8: =M8 -> 11969.183 | F8: =IFERROR(IF(D8*E8<0,"-", IF(E8<0,-(D8/E8-1),(D8/E8-1))),0) -> -0.025534405 | I8: 11663.557 | J8: 12326.567 | K8: 12053.809 | L8: 12442.118 | M8: 11969.183 | N8: 11814.069 | O8: 11285.427 | P8: 10964.242 | Q8: 11226.454 | R8: 11032.722 | S8: 11286.579 | T8: 11257.619 | U8: 0 | V8: 0 | W8: 0 | X8: 0 | AA8: 기타포괄손익-공정가치측정금융자산 | AB8: Fair value other comprehensive income financial assets | AC8: =AH8 -> 11663.557 | AD8: =AL8 -> 11969.183 | AE8: =IFERROR(IF(AC8*AD8<0,"-", IF(AD8<0,-(AC8/AD8-1),(AC8/AD8-1))),0) -> -0.025534405 | AH8: 11663.557 | AI8: 12326.567 | AJ8: 12053.809 | AK8: 12442.118 | AL8: 11969.183 | AM8: 11814.069 | AN8: 11285.427 | AO8: 10964.242 | AP8: 11226.454 | AQ8: 11032.722 | AR8: 11286.579 | AS8: 11257.619
B9: 상각후원가측정금융자산 | C9: Amortized cost financial assets | D9: =I9 -> 0 | E9: =M9 -> 0 | F9: =IFERROR(IF(D9*E9<0,"-", IF(E9<0,-(D9/E9-1),(D9/E9-1))),0) -> 0 | K9: 0 | L9: 0 | M9: 0 | N9: 0 | O9: 0 | P9: 0 | Q9: 0 | R9: 107.0486 | S9: 106.68145 | T9: 106.2235 | U9: 0 | V9: 0 | W9: 0 | X9: 0 | AA9: 상각후원가측정금융자산 | AB9: Amortized cost financial assets | AC9: =AH9 -> 0 | AD9: =AL9 -> 0 | AE9: =IFERROR(IF(AC9*AD9<0,"-", IF(AD9<0,-(AC9/AD9-1),(AC9/AD9-1))),0) -> 0 | AP9: 0 | AQ9: 107.0486 | AR9: 106.68145 | AS9: 106.2235
B10: 상각후원가측정대여금및수취채권 | C10: Amortized cost loans and receivables | D10: =I10 -> 2801.4504 | E10: =M10 -> 3499.4634 | F10: =IFERROR(IF(D10*E10<0,"-", IF(E10<0,-(D10/E10-1),(D10/E10-1))),0) -> -0.19946288 | I10: 2801.4504 | J10: 2883.514 | K10: 3067.0061 | L10: 3110.8277 | M10: 3499.4634 | N10: 3420.3512 | O10: 3831.4191 | P10: 3913.1983 | Q10: 4193.4674 | R10: 4115.6953 | S10: 4298.3258 | T10: 4358.1414 | U10: 0 | V10: 0 | W10: 0 | X10: 0 | AA10: 상각후원가측정대여금및수취채권 | AB10: Amortized cost loans and receivables | AC10: =AH10 -> 2881.4165 | AD10: =AL10 -> 3586.235 | AE10: =IFERROR(IF(AC10*AD10<0,"-", IF(AD10<0,-(AC10/AD10-1),(AC10/AD10-1))),0) -> -0.19653438 | AH10: 2881.4165 | AI10: 2963.7312 | AJ10: 3144.866 | AK10: 3192.3909 | AL10: 3586.235 | AM10: 3453.2854 | AN10: 3875.5302 | AO10: 3978.5065 | AP10: 4254.2938 | AQ10: 4145.9337 | AR10: 4337.4868 | AS10: 4399.2037
B11: 파생상품자산* | C11: Derivatives assets | D11: =I11 -> 28.506931 | E11: =M11 -> 238.17821 | F11: =IFERROR(IF(D11*E11<0,"-", IF(E11<0,-(D11/E11-1),(D11/E11-1))),0) -> -0.8803126 | I11: 28.506931 | J11: 141.19189 | K11: 291.83457 | L11: 336.6121 | M11: 238.17821 | N11: 269.18108 | O11: 97.756521 | P11: 69.234655 | Q11: 202.09472 | AA11: 파생상품자산 | AB11: Derivatives assets | AC11: =AH11 -> 31.088117 | AD11: =AL11 -> 238.17821 | AH11: 31.088117 | AI11: 141.19189 | AJ11: 295.1324 | AK11: 336.6121 | AL11: 238.17821 | AM11: 269.18108 | AN11: 97.756521 | AO11: 69.2 | AP11: 202.09472
B12: 종속기업투자주식 | C12: Investments in subsidiaries | D12: =I12 -> 142.04297 | E12: =M12 -> 142.04297 | F12: =IFERROR(IF(D12*E12<0,"-", IF(E12<0,-(D12/E12-1),(D12/E12-1))),0) -> 0 | I12: 142.04297 | J12: 142.04297 | K12: 142.04297 | L12: 142.04297 | M12: 142.04297 | N12: 142.04297 | O12: 142.04297 | P12: 142.04297 | Q12: 142.04297 | R12: 142.04297 | S12: 142.04297 | T12: 142.04297 | U12: 142.04297 | V12: 142.04297 | W12: ='[12]202206 BS(17및39기준)'!$X$110/1000000000 -> 142.04297 | X12: 142.04297 | AA12: 관계기업투자주식 | AB12: Investments in subsidiaries | AC12: =AH12 -> 78.496022 | AD12: =AL12 -> 84.308539 | AE12: =IFERROR(IF(AC12*AD12<0,"-", IF(AD12<0,-(AC12/AD12-1),(AC12/AD12-1))),0) -> -0.068943399 | AH12: 78.496022 | AI12: 77.386405 | AJ12: 76.943424 | AK12: 83.094261 | AL12: 84.308539 | AM12: 80.380294 | AN12: 80.425267 | AO12: 80.771018 | AP12: 78.659011 | AQ12: 79.857887 | AR12: 78.688551 | AS12: 75.518176 | AT12: 68.996458 | AU12: 75.652591 | AV12: 72.864087 | AW12: 72.296687
B13: 재보험계약자산 | C13: Reinsurance contract assets | D13: =I13 -> 37.355227 | E13: =M13 -> 29.754049 | F13: =IFERROR(IF(D13*E13<0,"-", IF(E13<0,-(D13/E13-1),(D13/E13-1))),0) -> 0.25546703 | I13: 37.355227 | J13: 35.615424 | K13: 30.622189 | L13: 27.189943 | M13: 29.754049 | N13: 28.884463 | O13: 26.43551 | P13: 24.546811 | Q13: 24.241131 | R13: 23.232249 | S13: 18.264456 | T13: 17.814597 | U13: 21.072555 | V13: 18.89734 | W13: ='[12]202206 BS(17및39기준)'!$X$160/1000000000 -> 16.274572 | X13: 14.699403 | AA13: 재보험계약자산 | AB13: Reinsurance contract assets | AC13: =AH13 -> 37.355227 | AD13: =AL13 -> 29.754049 | AE13: =IFERROR(IF(AC13*AD13<0,"-", IF(AD13<0,-(AC13/AD13-1),(AC13/AD13-1))),0) -> 0.25546703 | AH13: 37.355227 | AI13: 35.615424 | AJ13: 30.622189 | AK13: 27.189943 | AL13: 29.754049 | AM13: 28.884463 | AN13: 26.43551 | AO13: 24.546811 | AP13: 24.241131 | AQ13: 23.232249 | AR13: 18.264456 | AS13: 17.814597 | AT13: 21.072555 | AU13: 18.89734 | AV13: 16.274572 | AW13: 14.699403
B14: 유형자산 | C14: Tangible assets | D14: =I14 -> 88.612255 | E14: =M14 -> 95.90689 | F14: =IFERROR(IF(D14*E14<0,"-", IF(E14<0,-(D14/E14-1),(D14/E14-1))),0) -> -0.076059554 | I14: 88.612255 | J14: 88.579486 | K14: 91.945785 | L14: 94.110977 | M14: 95.90689 | N14: 90.089673 | O14: 92.276336 | P14: 92.707465 | Q14: 82.398665 | R14: 84.586468 | S14: 86.571404 | T14: 87.27067 | U14: 89.841052 | V14: 90.273192 | W14: ='[12]202206 BS(17및39기준)'!$X$168/1000000000 -> 94.898882 | X14: 96.105008 | AA14: 유형자산 | AB14: Tangible assets | AC14: =AH14 -> 95.345558 | AD14: =AL14 -> 102.37784 | AE14: =IFERROR(IF(AC14*AD14<0,"-", IF(AD14<0,-(AC14/AD14-1),(AC14/AD14-1))),0) -> -0.068689448 | AH14: 95.345558 | AI14: 94.954809 | AJ14: 99.185753 | AK14: 102.51351 | AL14: 102.37784 | AM14: 97.955409 | AN14: 101.40307 | AO14: 103.54285 | AP14: 89.642834 | AQ14: 92.572749 | AR14: 94.951976 | AS14: 95.961637 | AT14: 99.052884 | AU14: 101.07364 | AV14: 107.11983 | AW14: 111.62603
B15: 투자부동산 | C15: Investment in real estate | D15: =I15 -> 0 | E15: =M15 -> 0 | F15: =IFERROR(IF(D15*E15<0,"-", IF(E15<0,-(D15/E15-1),(D15/E15-1))),0) -> 0 | J15: 0 | K15: 0 | L15: 0 | M15: 0 | N15: 0 | O15: 0 | P15: 0 | Q15: 0 | R15: 0 | S15: 0 | T15: 0 | U15: 0 | V15: 0.39671993 | W15: ='[12]202206 BS(17및39기준)'!$X$190/1000000000 -> 0.40106329 | X15: 0.40540665 | AA15: 투자부동산 | AB15: Investment in real estate | AC15: =AH15 -> 0 | AD15: =AL15 | AE15: =IFERROR(IF(AC15*AD15<0,"-", IF(AD15<0,-(AC15/AD15-1),(AC15/AD15-1))),0) -> 0 | AH15: 0 | AI15: 0 | AJ15: 0 | AK15: 0 | AM15: 0 | AN15: 0 | AO15: 0 | AQ15: 0 | AR15: 40.354212 | AS15: 38.129054 | AT15: 42.647263 | AU15: 40.768124 | AV15: 41.823329 | AW15: 35.429156
B16: 무형자산 | C16: Intangible assets | D16: =I16 -> 27.860665 | E16: =M16 -> 31.396666 | F16: =IFERROR(IF(D16*E16<0,"-", IF(E16<0,-(D16/E16-1),(D16/E16-1))),0) -> -0.11262347 | I16: 27.860665 | J16: 31.664802 | K16: 30.797092 | L16: 33.05772 | M16: 31.396666 | N16: 30.860278 | O16: 33.586913 | P16: 36.163701 | Q16: 39.451616 | R16: 39.121364 | S16: 38.034476 | T16: 37.605681 | U16: 40.580946 | V16: 40.722345 | W16: ='[12]202206 BS(17및39기준)'!$X$198/1000000000 -> 43.330049 | X16: 46.022686 | AA16: 무형자산 | AB16: Intangible assets | AC16: =AH16 -> 28.55143 | AD16: =AL16 -> 31.913695 | AE16: =IFERROR(IF(AC16*AD16<0,"-", IF(AD16<0,-(AC16/AD16-1),(AC16/AD16-1))),0) -> -0.10535492 | AH16: 28.55143 | AI16: 32.415564 | AJ16: 31.611416 | AK16: 33.562825 | AL16: 31.913695 | AM16: 31.380678 | AN16: 34.14903 | AO16: 36.555716 | AP16: 39.871623 | AQ16: 39.506415 | AR16: 38.400615 | AS16: 37.997903 | AT16: 40.883601 | AU16: 41.229853 | AV16: 43.872593 | AW16: 46.600632
B17: 당기/이연법인세자산 | C17: Current/Deferred tax assets | D17: =I17 -> 81.38152 | E17: =M17 -> 77.265029 | F17: =IFERROR(IF(D17*E17<0,"-", IF(E17<0,-(D17/E17-1),(D17/E17-1))),0) -> 0.053277544 | I17: 81.38152 | J17: 67.433069 | K17: 46.391678 | L17: 105.2547 | M17: 77.265029 | N17: 65.780204 | O17: 30.646934 | P17: 75.895042 | Q17: 54.265765 | R17: 43.776388 | S17: 26.298066 | T17: 70.372656 | U17: 49.599011 | V17: 146.08034 | W17: =('[12]202206 BS(17및39기준)'!$X$207+'[12]202206 BS(17및39기준)'!$X$208)/1000000000 -> 94.573814 | X17: 70.471202 | AA17: 당기/이연법인세자산 | AB17: Current/Deferred tax assets | AC17: =AH17 -> 81.38152 | AD17: =AL17 -> 76.069044 | AE17: =IFERROR(IF(AC17*AD17<0,"-", IF(AD17<0,-(AC17/AD17-1),(AC17/AD17-1))),0) -> 0.069837557 | AH17: 81.38152 | AI17: 67.433069 | AJ17: 46.391678 | AK17: 104.76129 | AL17: 76.069044 | AM17: 65.780204 | AN17: 30.646934 | AO17: 75.894472 | AP17: 53.376079 | AQ17: 43.038421 | AR17: 25.693519 | AS17: 70.372656 | AT17: 48.7 | AU17: 20.081953 | AV17: 7.6694908 | AW17: 54.676898
B18: 기타자산 | C18: Other assets | D18: =I18 -> 70.347835 | E18: =M18 -> 7.0241426 | F18: =IFERROR(IF(D18*E18<0,"-", IF(E18<0,-(D18/E18-1),(D18/E18-1))),0) -> 9.0151491 | I18: 70.347835 | J18: 45.375303 | K18: 49.970359 | L18: 50.894161 | M18: 7.0241426 | N18: 8.1044417 | O18: 10.926691 | P18: 12.250387 | Q18: 4.2897519 | R18: 6.8333451 | S18: 11.289393 | T18: 14.015854 | U18: 7.6959271 | V18: 18.954167 | W18: ='[12]202206 BS(17및39기준)'!$X$209/1000000000 -> 16.921847 | X18: 15.111433 | AA18: 기타자산 | AB18: Other assets | AC18: =AH18 -> 93.428107 | AD18: =AL18 -> 20.833712 | AE18: =IFERROR(IF(AC18*AD18<0,"-", IF(AD18<0,-(AC18/AD18-1),(AC18/AD18-1))),0) -> 3.4844677 | AH18: 93.428107 | AI18: 62.965188 | AJ18: 68.004055 | AK18: 66.393112 | AL18: 20.833712 | AM18: 20.725821 | AN18: 22.010718 | AO18: 23.040548 | AP18: 14.925172 | AQ18: 17.935837 | AR18: 21.637624 | AS18: 23.945364 | AT18: 17.615291 | AU18: 23.142493 | AV18: 24.683081 | AW18: 22.198884
B20: 자산계 | C20: Total assets | D20: =I20 -> 32855.182 | E20: =M20 -> 32404.439 | F20: =IFERROR(IF(D20*E20<0,"-", IF(E20<0,-(D20/E20-1),(D20/E20-1))),0) -> 0.013909919 | I20: =SUM(I6:I18) -> 32855.182 | J20: 33165.463 | K20: 32215.468 | L20: 32214.589 | M20: 32404.439 | N20: =SUM(N6:N18) -> 32232.653 | O20: 32188.593 | P20: 32333.017 | Q20: 33046.193 | R20: =SUM(R6:R19) -> 32111.06 | S20: =SUM(S6:S19) -> 32951.333 | T20: =SUM(T6:T19) -> 33150.631 | U20: =SUM(U6:U19) -> 1267.5435 | V20: =SUM(V6:V19) -> 975.79519 | W20: =SUM(W6:W19) -> 930.1773 | X20: 38438.524 | AA20: 자산계 | AB20: Total assets | AC20: =AH20 -> 32920.825 | AD20: =AL20 -> 32493.624 | AE20: =IFERROR(IF(AC20*AD20<0,"-", IF(AD20<0,-(AC20/AD20-1),(AC20/AD20-1))),0) -> 0.013147242 | AH20: 32920.825 | AI20: =SUM(AI6:AI18) -> 33221.046 | AJ20: 32262.704 | AK20: 32292.185 | AL20: 32493.624 | AM20: 32311.033 | AN20: 32269.311 | AO20: 32398.449 | AP20: 33092.023 | AQ20: =SUM(AQ6:AQ19) -> 32212.292 | AR20: =SUM(AR6:AR19) -> 33053.385 | AS20: =SUM(AS6:AS19) -> 33188.803 | AT20: =SUM(AT6:AT19) -> 1280.867 | AU20: =SUM(AU6:AU19) -> 861.70537 | AV20: =SUM(AV6:AV19) -> 866.51389 | AW20: 38443.846
B21: 보험계약부채 | C21: Insurance contract liabilities | D21: =I21 -> 26996.698 | E21: =M21 -> 26248.412 | F21: =IFERROR(IF(D21*E21<0,"-", IF(E21<0,-(D21/E21-1),(D21/E21-1))),0) -> 0.028507874 | I21: 26996.698 | J21: 27342.068 | K21: 26726.92 | L21: 26550.413 | M21: 26248.412 | N21: 26174.335 | O21: 26039.097 | P21: 25784.114 | Q21: 25645.534 | R21: 24045.986 | S21: 24896.21 | T21: 25045.177 | U21: 24226.62 | V21: 24626.604 | W21: ='[12]202206 BS(17및39기준)'!$X$244/1000000000 -> 25468.918 | X21: 27685.787 | AA21: 보험계약부채 | AB21: Insurance contract liabilities | AC21: =AH21 -> 26996.698 | AD21: =AL21 -> 26248.412 | AE21: =IFERROR(IF(AC21*AD21<0,"-", IF(AD21<0,-(AC21/AD21-1),(AC21/AD21-1))),0) -> 0.028507874 | AH21: 26996.698 | AI21: 27342.068 | AJ21: 26726.92 | AK21: 26550.413 | AL21: 26248.412 | AM21: 26174.335 | AN21: 26039.097 | AO21: 25784.114 | AP21: 25645.534 | AQ21: 24045.986 | AR21: 24896.21 | AS21: 25045.177 | AT21: 24226.62 | AU21: 24626.604 | AV21: 25468.918 | AW21: 27685.787
B22: 재보험계약부채 | C22: Reinsurance contract liabilities | D22: =I22 -> 0 | E22: =M22 -> 1.3708267 | F22: =IFERROR(IF(D22*E22<0,"-", IF(E22<0,-(D22/E22-1),(D22/E22-1))),0) -> -1 | I22: 0 | J22: 0 | K22: 2.4165891 | L22: 4.3362653 | M22: 1.3708267 | N22: 3.5431381 | O22: 4.7247093 | P22: 5.9267047 | Q22: 0.84792661 | R22: 0.44620526 | S22: 4.5621519 | T22: 5.7090258 | U22: 1.9899343 | V22: 0.71071885 | W22: ='[12]202206 BS(17및39기준)'!$X$249/1000000000 -> 4.5136053 | X22: 8.3379812 | AA22: 재보험계약부채 | AB22: Reinsurance contract liabilities | AC22: =AH22 -> 0 | AD22: =AL22 -> 1.3708267 | AE22: =IFERROR(IF(AC22*AD22<0,"-", IF(AD22<0,-(AC22/AD22-1),(AC22/AD22-1))),0) -> -1 | AH22: 0 | AI22: 0 | AJ22: 2.4165891 | AK22: 4.3362653 | AL22: 1.3708267 | AM22: 3.5431381 | AN22: 4.7247093 | AO22: 5.9267047 | AP22: 0.84792661 | AQ22: 0.44620526 | AR22: 4.5621519 | AS22: 5.7090258 | AT22: 1.9899343 | AU22: 0.71071885 | AV22: 4.5136053 | AW22: 8.3379812
B23: 투자계약부채 | C23: Investment contract liabilities | D23: =I23 -> 2179.7499 | E23: =M23 -> 2425.5571 | F23: =IFERROR(IF(D23*E23<0,"-", IF(E23<0,-(D23/E23-1),(D23/E23-1))),0) -> -0.10134052 | I23: 2179.7499 | J23: 2211.5095 | K23: 2265.6968 | L23: 2314.6336 | M23: 2425.5571 | N23: 2827.468 | O23: 2848.5144 | P23: 2986.4151 | Q23: 3175.2494 | R23: 3899.8098 | S23: 3901.37 | T23: 4010.7684 | U23: 4625.3748 | V23: 5717.6542 | W23: ='[12]202206 BS(17및39기준)'!$X$254/1000000000 -> 5876.9669 | X23: 6050.3652 | AA23: 투자계약부채 | AB23: Investment contract liabilities | AC23: =AH23 -> 2179.7499 | AD23: =AL23 -> 2425.5571 | AE23: =IFERROR(IF(AC23*AD23<0,"-", IF(AD23<0,-(AC23/AD23-1),(AC23/AD23-1))),0) -> -0.10134052 | AH23: 2179.7499 | AI23: 2211.5095 | AJ23: 2265.6968 | AK23: 2314.6336 | AL23: 2425.5571 | AM23: 2827.468 | AN23: 2848.5144 | AO23: 2986.4151 | AP23: 3175.2494 | AQ23: 3899.8098 | AR23: 3901.37 | AS23: 4010.7684 | AT23: 4625.3748 | AU23: 5717.6542 | AV23: 5876.9669 | AW23: 6050.4
B24: 파생상품부채* | C24: Derivatives liabilities | D24: =I24 -> 254.69488 | E24: =M24 -> 284.03899 | F24: -0.43264058 | I24: 254.69488 | J24: 158.40516 | K24: 53.741222 | L24: 219.76782 | M24: 284.03899 | N24: 18.741529 | O24: 94.239883 | P24: 68.457891 | Q24: 20.641073 | R24: 194.00387 | S24: 166.10261 | T24: 0 | U24: 0 | V24: 0 | W24: 0 | X24: 0 | AA24: 파생상품부채 | AB24: Derivatives liabilities | AC24: =AH24 -> 264.30141 | AD24: =AL24 -> 318.41119 | AE24: -0.2982366 | AH24: 264.30141 | AI24: 166.57951 | AJ24: 57.17348 | AK24: 245.86955 | AL24: 318.41119 | AM24: 35.566112 | AN24: 120.49246 | AO24: 82.336924 | AP24: 28.034776 | AQ24: 205.52489 | AR24: 171.69955 | AS24: 234.86755 | AT24: 0 | AV24: 0
B25: 차입부채 | C25: Borrowings | D25: =I25 -> 598.64879 | E25: =M25 -> 499.42995 | F25: =IFERROR(IF(D25*E25<0,"-", IF(E25<0,-(D25/E25-1),(D25/E25-1))),0) -> 0.19866416 | I25: 598.64879 | J25: 299.48975 | K25: 299.4696 | L25: 299.44967 | M25: 499.42995 | N25: 299.40258 | O25: 299.37521 | P25: 299.34813 | Q25: 549.321 | R25: 498.89091 | S25: 498.85706 | T25: 498.82358 | U25: 998.79046 | V25: 498.75798 | W25: ='[12]202206 BS(17및39기준)'!$X$278/1000000000 -> 498.72551 | X25: 498.66878 | AA25: 차입부채 | AB25: Borrowings | AC25: =AH25 -> 598.64879 | AD25: =AL25 -> 499.42995 | AE25: =IFERROR(IF(AC25*AD25<0,"-", IF(AD25<0,-(AC25/AD25-1),(AC25/AD25-1))),0) -> 0.19866416 | AH25: 598.64879 | AI25: 299.48975 | AJ25: 299.4696 | AK25: 299.44967 | AL25: 499.42995 | AM25: 299.40258 | AN25: 299.37521 | AO25: 299.34813 | AP25: 549.321 | AQ25: 498.89091 | AR25: 498.85706 | AS25: 498.82358 | AT25: 998.79046 | AU25: 498.75798 | AV25: 498.72551 | AW25: 498.66878
B26: 확정급여부채 | C26: Defined benefit liabilities | D26: =I26 -> 7.0870528 | E26: =M26 -> 13.107426 | F26: =IFERROR(IF(D26*E26<0,"-", IF(E26<0,-(D26/E26-1),(D26/E26-1))),0) -> -0.4593101 | I26: 7.0870528 | J26: 12.703103 | K26: 13.105233 | L26: 13.158918 | M26: 13.107426 | N26: 11.811167 | O26: 11.694916 | P26: 11.287522 | Q26: 11.286507 | R26: 9.8877 | S26: 10.090391 | T26: 10.227591 | U26: 5.3353768 | V26: 7.1412103 | W26: ='[12]202206 BS(17및39기준)'!$X$288/1000000000 -> 8.0262876 | X26: 9.086525 | AA26: 확정급여부채 | AB26: Defined benefit liabilities | AC26: =AH26 -> 7.0870528 | AD26: =AL26 -> 13.107426 | AE26: =IFERROR(IF(AC26*AD26<0,"-", IF(AD26<0,-(AC26/AD26-1),(AC26/AD26-1))),0) -> -0.4593101 | AH26: 7.0870528 | AI26: 12.703103 | AJ26: 13.105233 | AK26: 13.158918 | AL26: 13.107426 | AM26: 11.811167 | AN26: 11.694916 | AO26: 11.287522 | AP26: 11.286507 | AQ26: 9.8877 | AR26: 10.090391 | AS26: 10.227591 | AT26: 5.3353768 | AU26: 7.1412103 | AV26: 8.0262876 | AW26: 9.086525
B27: 충당부채 | C27: Provisions | D27: =I27 -> 3.0801255 | E27: =M27 -> 2.5117498 | F27: =IFERROR(IF(D27*E27<0,"-", IF(E27<0,-(D27/E27-1),(D27/E27-1))),0) -> 0.22628674 | I27: 3.0801255 | J27: 2.3711717 | K27: 2.5508629 | L27: 2.5500789 | M27: 2.5117498 | N27: 2.0796219 | O27: 2.1344891 | P27: 2.2742992 | Q27: 1.0848891 | R27: 1.0930234 | S27: 1.0551871 | T27: 1.0755425 | U27: 0.97970742 | V27: 1.0115993 | W27: ='[12]202206 BS(17및39기준)'!$X$295/1000000000 -> 0.91826752 | X27: 1.0579353 | AA27: 충당부채 | AB27: Provisions | AC27: =AH27 -> 6.0452451 | AD27: =AL27 -> 5.4752186 | AE27: =IFERROR(IF(AC27*AD27<0,"-", IF(AD27<0,-(AC27/AD27-1),(AC27/AD27-1))),0) -> 0.10411028 | AH27: 6.0452451 | AI27: 5.2850347 | AJ27: 5.4437002 | AK27: 5.4271277 | AL27: 5.4752186 | AM27: 4.9878513 | AN27: 4.9954077 | AO27: 5.2122534 | AP27: 4.03218 | AQ27: 4.0753876 | AR27: 4.0095525 | AS27: 2.9228183 | AT27: 2.8054098 | AU27: 3.029751 | AV27: 2.9317537 | AW27: 3.3462832
B28: 당기/이연법인세부채 | C28: Current/Deferred tax liabilities | D28: =I28 -> 195.36614 | E28: =M28 -> 207.35141 | F28: =IFERROR(IF(D28*E28<0,"-", IF(E28<0,-(D28/E28-1),(D28/E28-1))),0) -> -0.05780173 | I28: 195.36614 | J28: 186.35796 | K28: 184.15353 | L28: 184.10475 | M28: 207.35141 | N28: 240.50888 | O28: 242.99641 | P28: 298.2571 | Q28: 379.82677 | R28: 364.0354 | S28: 361.13438 | T28: 331.98808 | U28: 692.58052 | V28: 912.46387 | W28: ='[12]202206 BS(17및39기준)'!$X$302/1000000000 -> 756.54369 | X28: 525.60829 | AA28: 당기/이연법인세부채 | AB28: Current/Deferred tax liabilities | AC28: =AH28 -> 198.51741 | AD28: =AL28 -> 208.43683 | AE28: =IFERROR(IF(AC28*AD28<0,"-", IF(AD28<0,-(AC28/AD28-1),(AC28/AD28-1))),0) -> -0.047589563 | AH28: 198.51741 | AI28: 185.50014 | AJ28: 183.20022 | AK28: 184.47135 | AL28: 208.43683 | AM28: 245.95059 | AN28: 248.44429 | AO28: 303.71386 | AP28: 384.86042 | AQ28: 353.07511 | AR28: 351.11183 | AS28: 323.69418 | AT28: 677.1 | AU28: 775.26483 | AV28: 647.65256 | AW28: 485.67008
B29: 기타부채 | C29: Other liabilities | D29: =I29 -> 183.35524 | E29: =M29 -> 169.42154 | F29: =IFERROR(IF(D29*E29<0,"-", IF(E29<0,-(D29/E29-1),(D29/E29-1))),0) -> 0.082242832 | I29: 183.35524 | J29: 470.44727 | K29: 196.69154 | L29: 159.37694 | M29: 169.42154 | N29: 125.78916 | O29: 118.11812 | P29: 143.0608 | Q29: 243.37464 | R29: 126.63089 | S29: 169.30767 | T29: =4150.265089409-T23 -> 139.49664 | U29: =4777.97312484492-U23 -> 152.59835 | V29: 135.51201 | W29: =('[12]202206 BS(17및39기준)'!$X$257+'[12]202206 BS(17및39기준)'!$X$303+'[12]202206 BS(17및39기준)'!$X$308)/1000000000 -> 139.96333 | X29: 188.39087 | AA29: 기타부채 | AB29: Other liabilities | AC29: =AH29 -> 221.68205 | AD29: =AL29 -> 209.76865 | AE29: =IFERROR(IF(AC29*AD29<0,"-", IF(AD29<0,-(AC29/AD29-1),(AC29/AD29-1))),0) -> 0.056793028 | AH29: 221.68205 | AI29: 506.36265 | AJ29: 232.96781 | AK29: 197.00589 | AL29: 209.76865 | AM29: 174.79634 | AN29: 160.13858 | AO29: 184.24073 | AP29: 277.34638 | AQ29: 181.26721 | AR29: 268.64374 | AS29: 190.4447 | AT29: 205.0556 | AU29: 183.44712 | AV29: 201.05767 | AW29: 244.2
B31: 부채계 | C31: Total liabilities | D31: =I31 -> 30418.68 | E31: =M31 -> 29851.201 | F31: =IFERROR(IF(D31*E31<0,"-", IF(E31<0,-(D31/E31-1),(D31/E31-1))),0) -> 0.019010275 | I31: =SUM(I21:I29) -> 30418.68 | J31: 30683.352 | K31: 29744.746 | L31: 29747.791 | M31: 29851.201 | N31: =SUM(N21:N29) -> 29703.68 | O31: 29660.895 | P31: 29599.142 | Q31: 30027.166 | R31: =SUM(R21:R30) -> 29140.784 | S31: =SUM(S21:S30) -> 30008.69 | T31: =SUM(T21:T30) -> 30043.266 | U31: =SUM(U21:U30) -> 30704.269 | V31: =SUM(V21:V30) -> 31899.856 | W31: =SUM(W21:W30) -> 32754.576 | X31: 35087.19 | AA31: 부채계 | AB31: Total liabilities | AC31: =AH31 -> 30472.73 | AD31: =AL31 -> 29929.969 | AE31: =IFERROR(IF(AC31*AD31<0,"-", IF(AD31<0,-(AC31/AD31-1),(AC31/AD31-1))),0) -> 0.018134367 | AH31: 30472.73 | AI31: =SUM(AI21:AI29) -> 30729.498 | AJ31: 29786.394 | AK31: 29814.766 | AL31: 29929.969 | AM31: 29777.861 | AN31: 29737.477 | AO31: 29662.595 | AP31: 30076.512 | AQ31: =SUM(AQ21:AQ30) -> 29198.963 | AR31: =SUM(AR21:AR30) -> 30106.555 | AS31: =SUM(AS21:AS30) -> 30322.635 | AT31: =SUM(AT21:AT30) -> 30743.071 | AU31: =SUM(AU21:AU30) -> 31812.61 | AV31: =SUM(AV21:AV30) -> 32708.793 | AW31: 35123.626
B32: 자본금 | C32: Capital stock | D32: =I32 -> 990.71474 | E32: =M32 -> 990.71474 | F32: =IFERROR(IF(D32*E32<0,"-", IF(E32<0,-(D32/E32-1),(D32/E32-1))),0) -> 0 | I32: 990.71474 | J32: 990.71474 | K32: 990.71474 | L32: 990.71474 | M32: 990.71474 | N32: 990.71474 | O32: 990.71474 | P32: 990.71474 | Q32: 990.71474 | R32: 990.71474 | S32: 990.71474 | T32: 990.71474 | U32: 990.71474 | V32: 990.71474 | W32: ='[12]202206 BS(17및39기준)'!$X$336/1000000000 -> 990.71474 | X32: 990.71474 | AA32: 자본금 | AB32: Capital stock | AC32: =AH32 -> 990.71474 | AD32: =AL32 -> 990.71474 | AE32: =IFERROR(IF(AC32*AD32<0,"-", IF(AD32<0,-(AC32/AD32-1),(AC32/AD32-1))),0) -> 0 | AH32: 990.71474 | AI32: 990.71474 | AJ32: 990.71474 | AK32: 990.71474 | AL32: 990.71474 | AM32: 990.71474 | AN32: 990.71474 | AO32: 990.71474 | AP32: 990.71474 | AQ32: 990.71474 | AR32: 990.71474 | AS32: 990.71474 | AT32: 990.71474 | AU32: 990.71474 | AV32: 990.71474 | AW32: 990.71474
B33: 자본잉여금 | C33: Capital surplus | D33: =I33 -> 181.38448 | E33: =M33 -> 181.38448 | F33: =IFERROR(IF(D33*E33<0,"-", IF(E33<0,-(D33/E33-1),(D33/E33-1))),0) -> 0 | I33: 181.38448 | J33: 181.38448 | K33: 181.38448 | L33: 181.38448 | M33: 181.38448 | N33: 181.38448 | O33: 181.38448 | P33: 181.38448 | Q33: 181.38448 | R33: 181.38448 | S33: 181.38448 | T33: 181.38448 | U33: 181.38448 | V33: 181.38448 | W33: ='[12]202206 BS(17및39기준)'!$X$339/1000000000 -> 181.38448 | X33: 181.38448 | AA33: 자본잉여금 | AB33: Capital surplus | AC33: =AH33 -> 181.38448 | AD33: =AL33 -> 181.38448 | AE33: =IFERROR(IF(AC33*AD33<0,"-", IF(AD33<0,-(AC33/AD33-1),(AC33/AD33-1))),0) -> 0 | AH33: 181.38448 | AI33: 181.38448 | AJ33: 181.38448 | AK33: 181.38448 | AL33: 181.38448 | AM33: 181.38448 | AN33: 181.38448 | AO33: 181.38448 | AP33: 181.38448 | AQ33: 181.38448 | AR33: 181.38448 | AS33: 181.38448 | AT33: 181.38448 | AU33: 181.38448 | AV33: 181.38448 | AW33: 181.38448
B34: 이익잉여금 | C34: Retained earnings | D34: =I34 -> 2067.8245 | E34: =M34 -> 1942.9241 | F34: =IFERROR(IF(D34*E34<0,"-", IF(E34<0,-(D34/E34-1),(D34/E34-1))),0) -> 0.06428475 | I34: 2067.8245 | J34: 2064.1213 | K34: 2017.5975 | L34: 1967.2438 | M34: 1942.9241 | N34: 1865.2671 | O34: 1864.2197 | P34: 1850.2079 | Q34: 1817.8844 | R34: 1747.4676 | S34: 1723.0011 | T34: 1688.9715 | U34: 1602.9448 | V34: 1636.4256 | W34: ='[12]202206 BS(17및39기준)'!$X$348/1000000000 -> 1580.4753 | X34: 1535.9903 | AA34: 이익잉여금 | AB34: Retained earnings | AC34: =AH34 -> 2073.912 | AD34: =AL34 -> 1943.1355 | AE34: =IFERROR(IF(AC34*AD34<0,"-", IF(AD34<0,-(AC34/AD34-1),(AC34/AD34-1))),0) -> 0.067301755 | AH34: 2073.912 | AI34: 2068.3668 | AJ34: 2018.6108 | AK34: 1967.9186 | AL34: 1943.1355 | AM34: 1862.0893 | AN34: 1860.2872 | AO34: 1843.5358 | AP34: 1807.02 | AQ34: 1820.0448 | AR34: 1759.6534 | AS34: 1714.3182 | AT34: 1686.3108 | AU34: 1710.9124 | AV34: 1660.9128 | AW34: 1615.976
B35: 자본조정 | C35: Capital adjustment | D35: =I35 -> -371.17545 | E35: =M35 -> -371.17545 | F35: =IFERROR(IF(D35*E35<0,"-", IF(E35<0,-(D35/E35-1),(D35/E35-1))),0) -> 0 | I35: -371.17545 | J35: -371.17545 | K35: -371.17545 | L35: -371.17545 | M35: -371.17545 | N35: -371.17545 | O35: -371.17545 | P35: -371.17545 | Q35: -371.17545 | R35: -371.17545 | S35: -371.17545 | T35: -371.17545 | U35: -371.17545 | V35: -371.17545 | W35: ='[12]202206 BS(17및39기준)'!$X$354/1000000000 -> -371.17545 | X35: -371.19135 | AA35: 자본조정 | AB35: Capital adjustment | AC35: =AH35 -> -371.27625 | AD35: =AL35 -> -371.27625 | AE35: =IFERROR(IF(AC35*AD35<0,"-", IF(AD35<0,-(AC35/AD35-1),(AC35/AD35-1))),0) -> 0 | AH35: -371.27625 | AI35: -371.27625 | AJ35: -371.27625 | AK35: -371.27625 | AL35: -371.27625 | AM35: -371.27625 | AN35: -371.27625 | AO35: -371.27625 | AP35: -371.27625 | AQ35: -371.27625 | AR35: -371.27625 | AS35: -371.27625 | AT35: -371.27625 | AU35: -371.27625 | AV35: -371.27625 | AW35: -371.29216
B36: 기타포괄손익누계액 | C36: Other comprehensive income | D36: =I36 -> -432.24669 | E36: =M36 -> -190.60991 | F36: =IFERROR(IF(D36*E36<0,"-", IF(E36<0,-(D36/E36-1),(D36/E36-1))),0) -> -1.2677032 | I36: -432.24669 | J36: -382.93365 | K36: -347.79837 | L36: -301.37041 | M36: -190.60991 | N36: -137.2176 | O36: -137.44607 | P36: 82.743767 | Q36: 400.21884 | R36: 421.88457 | S36: 418.71856 | T36: 386.33561 | U36: 1684.6568 | V36: 1854.9426 | W36: ='[12]202206 BS(17및39기준)'!$X$358/1000000000 -> 1523.2416 | X36: 1014.3412 | AA36: 기타포괄손익누계액 | AB36: Other comprehensive income | AC36: =AH36 -> -426.6398 | AD36: =AL36 -> -180.30384 | AE36: =IFERROR(IF(AC36*AD36<0,"-", IF(AD36<0,-(AC36/AD36-1),(AC36/AD36-1))),0) -> -1.3662269 | AH36: -426.6398 | AI36: -377.6415 | AJ36: -343.1231 | AK36: -291.32243 | AL36: -180.30384 | AM36: -129.74026 | AN36: -129.27649 | AO36: 91.447125 | AP36: 407.6682 | AQ36: 392.46139 | AR36: 386.35401 | AS36: 351.02706 | AT36: 1599.8132 | AU36: 1743.2277 | AV36: 1418.0242 | AW36: 903.43713
B38: 자본계 | C38: Total equity | D38: =I38 -> 2436.5016 | E38: =M38 -> 2553.2379 | F38: =IFERROR(IF(D38*E38<0,"-", IF(E38<0,-(D38/E38-1),(D38/E38-1))),0) -> -0.045720922 | I38: 2436.5016 | J38: 2482.1114 | K38: 2470.7229 | L38: 2466.7972 | M38: 2553.2379 | N38: =SUM(N32:N36) -> 2528.9733 | O38: 2527.6974 | P38: 2733.8755 | Q38: 3019.0271 | R38: =SUM(R32:R37) -> 2970.276 | S38: =SUM(S32:S37) -> 2942.6434 | T38: =SUM(T32:T37) -> 2876.2309 | U38: =SUM(U32:U37) -> 4088.5253 | V38: =SUM(V32:V37) -> 4292.292 | W38: =SUM(W32:W37) -> 3904.6406 | X38: 3351.2394 | AA38: 자본계 | AB38: Total equity | AC38: =AH38 -> 2448.0951 | AD38: =AL38 -> 2563.6547 | AE38: =IFERROR(IF(AC38*AD38<0,"-", IF(AD38<0,-(AC38/AD38-1),(AC38/AD38-1))),0) -> -0.045076091 | AH38: 2448.0951 | AI38: 2491.5 | AJ38: 2476.3106 | AK38: 2477.4191 | AL38: 2563.6547 | AM38: 2533.172 | AN38: 2531.8337 | AO38: 2735.8059 | AP38: 3015.5111 | AQ38: =SUM(AQ32:AQ37) -> 3013.3291 | AR38: =SUM(AR32:AR37) -> 2946.8304 | AS38: =SUM(AS32:AS37) -> 2866.1683 | AT38: =SUM(AT32:AT37) -> 4086.9469 | AU38: =SUM(AU32:AU37) -> 4254.963 | AV38: =SUM(AV32:AV37) -> 3879.7601 | AW38: =SUM(AW32:AW37) -> 3320.2202
T39: IFRS 17 & 9 ◀ | U39: ▶IFRS 17 + IAS39 | AL39: =AI38/AL38-1 -> -0.028145235 | AS39: IFRS 17 & 9 ◀ | AT39: ▶IFRS 17 + IAS39
B40: ▶ *) FY2024 Q2부터 파생상품 자산, 부채 별도 표기 | AA40: ▶ *) FY2024 Q2부터 파생상품 자산, 부채 별도 표기 | AL40: =AL38-AC38 -> 115.55953
B41: Assets and liabilities of derivatives represented from 24Q2 | AA41: Assets and liabilities of derivatives represented from 24Q2

Sheet KIFRS-IS
B1: =[13]INDEX!G5 -> K-IFRS 손익계산서 | C1: Income Statement K-IFRS | AE1: =B1 -> K-IFRS 손익계산서
B2: (BN KRW, %, %p) | AE2: (BN KRW, %, %p)
B4: 별도 손익계산서 | C4: Unconsolidated I/S | D4: =I4 -> 2025 | E4: =N4 -> 2024 | F4: YoY | I4: 2025 | N4: 2024 | S4: 2023 | X4: 2022 | AE4: 연결 손익계산서 | AF4: Consolidated I/S | AG4: =D4 -> 2025 | AH4: =E4 -> 2024 | AI4: YoY | AL4: 2025 | AQ4: 2024 | AV4: 2023 | BA4: 2022
D5: =I5 -> FY | E5: =N5 -> FY | I5: FY | J5: Q4 | K5: Q3 | L5: Q2 | M5: Q1 | N5: FY | O5: Q4 | P5: Q3 | Q5: Q2 | R5: Q1 | S5: FY | T5: Q4 | U5: Q3 | V5: Q2 | W5: Q1 | X5: FY | Y5: Q4 | Z5: Q3 | AA5: Q2 | AB5: Q1 | AG5: =D5 -> FY | AH5: =E5 -> FY | AL5: FY | AM5: Q4 | AN5: Q3 | AO5: Q2 | AP5: Q1 | AQ5: FY | AR5: Q4 | AS5: Q3 | AT5: Q2 | AU5: Q1 | AV5: FY | AW5: Q4 | AX5: Q3 | AY5: Q2 | AZ5: Q1 | BA5: FY | BB5: Q4 | BC5: Q3 | BD5: Q2 | BE5: Q1
B6: 보험서비스수익 | C6: Insurance service revenue | D6: =SUM(D7:D8) -> 1104.0767 | E6: =SUM(E7:E8) -> 983.39964 | F6: =IFERROR(IF(D6*E6<0,"-",IF(E6<0,-(D6/E6-1),(D6/E6-1))),0) -> 0.12271414 | I6: 1104.0767 | J6: 289.69317 | K6: 282.0901 | L6: 267.28716 | M6: 265.00626 | N6: 983.39964 | O6: 245.80271 | P6: 247.77268 | Q6: 244.15957 | R6: 245.66469 | S6: 918.97865 | T6: 226.98366 | U6: =SUM(U7:U9) -> 231.95241 | V6: =SUM(V7:V9) -> 227.65336 | W6: 232.38922 | X6: =SUM(Y6:AB6) -> 926.47844 | Y6: 226.56971 | Z6: =SUM(Z7:Z9) -> 233.12172 | AA6: =SUM(AA7:AA9) -> 236.90275 | AB6: =SUM(AB7:AB9) -> 229.88425 | AE6: 보험서비스수익 | AF6: Insurance service revenue | AG6: =SUM(AG7:AG8) -> 1104.0767 | AH6: =SUM(AH7:AH8) -> 983.39964 | AI6: =IFERROR(IF(AG6*AH6<0,"-",IF(AH6<0,-(AG6/AH6-1),(AG6/AH6-1))),0) -> 0.12271414 | AL6: =SUM(AM6:AP6) -> 1104.0767 | AM6: 289.69317 | AN6: 282.0901 | AO6: 267.28716 | AP6: 265.00626 | AQ6: 983.39964 | AR6: 245.80271 | AS6: 247.77268 | AT6: 244.15957 | AU6: 245.66469 | AV6: 918.97865 | AW6: 226.98366 | AX6: =SUM(AX7:AX9) -> 231.95241 | AY6: 227.65336 | AZ6: 232.38922 | BA6: =SUM(BB6:BE6) -> 926.47844 | BB6: 226.56971 | BC6: =SUM(BC7:BC9) -> 233.12172 | BD6: 236.90275 | BE6: 229.88425
B7: 일반보험서비스수익 | C7: Insurance service revenue | D7: =SUM(J7:M7) -> 1080.4115 | E7: =SUM(O7:R7) -> 963.96742 | F7: =IFERROR(IF(D7*E7<0,"-",IF(E7<0,-(D7/E7-1),(D7/E7-1))),0) -> 0.12079675 | I7: 1080.4115 | J7: 284.45398 | K7: 275.03755 | L7: 261.69215 | M7: 259.22787 | N7: 964 | O7: 245.75624 | P7: 243.42094 | Q7: 238.82729 | R7: 235.96295 | S7: 901.59925 | T7: 224.78729 | U7: 226.55462 | V7: 224.50184 | W7: 225.75549 | X7: =SUM(Y7:AB7) -> 903.85088 | Y7: 222.82169 | Z7: 226.80642 | AA7: 229.49368 | AB7: 224.72909 | AE7: 일반보험서비스수익 | AF7: Insurance service revenue | AG7: =SUM(AM7:AP7) -> 1080.4115 | AH7: =SUM(AR7:AU7) -> 963.96742 | AI7: =IFERROR(IF(AG7*AH7<0,"-",IF(AH7<0,-(AG7/AH7-1),(AG7/AH7-1))),0) -> 0.12079675 | AL7: =SUM(AM7:AP7) -> 1080.4115 | AM7: 284.45398 | AN7: 275.03755 | AO7: 261.69215 | AP7: 259.22787 | AQ7: 963.96742 | AR7: 245.75624 | AS7: 243.42094 | AT7: 238.82729 | AU7: 235.96295 | AV7: 901.59925 | AW7: 224.78729 | AX7: 226.55462 | AY7: 224.50184 | AZ7: 225.75549 | BA7: =SUM(BB7:BE7) -> 903.85088 | BB7: 222.82169 | BC7: 226.80642 | BD7: 229.49368 | BE7: 224.72909
B8: 출재보험서비스수익 | C8: Reinsurance service revenue | D8: =SUM(J8:M8) -> 23.66514 | E8: =SUM(O8:R8) -> 19.432224 | F8: =IFERROR(IF(D8*E8<0,"-",IF(E8<0,-(D8/E8-1),(D8/E8-1))),0) -> 0.21782971 | I8: 23.66514 | J8: 5.2391892 | K8: 7.0525496 | L8: 5.5950026 | M8: 5.7783983 | N8: 19.4 | O8: 0.046463727 | P8: 4.3517425 | Q8: 5.3322753 | R8: 9.7017426 | S8: 17.379404 | T8: 2.1963687 | U8: 5.3977887 | V8: 3.1515149 | W8: 6.6337314 | X8: =SUM(Y8:AB8) -> 22.627557 | Y8: 3.748025 | Z8: 6.3152986 | AA8: 7.4090743 | AB8: 5.1551594 | AE8: 출재보험서비스수익 | AF8: Reinsurance service revenue | AG8: =SUM(AM8:AP8) -> 23.66514 | AH8: =SUM(AR8:AU8) -> 19.432224 | AI8: =IFERROR(IF(AG8*AH8<0,"-",IF(AH8<0,-(AG8/AH8-1),(AG8/AH8-1))),0) -> 0.21782971 | AL8: =SUM(AM8:AP8) -> 23.66514 | AM8: 5.2391892 | AN8: 7.0525496 | AO8: 5.5950026 | AP8: 5.7783983 | AQ8: 19.432224 | AR8: 0.046463727 | AS8: 4.3517425 | AT8: 5.3322753 | AU8: 9.7017426 | AV8: 17.379404 | AW8: 2.1963687 | AX8: 5.3977887 | AY8: 3.1515149 | AZ8: 6.6337314 | BA8: =SUM(BB8:BE8) -> 22.627557 | BB8: 3.748025 | BC8: 6.3152986 | BD8: 7.4090743 | BE8: 5.1551594
BA9: =SUM(BB9:BE9) -> 0
B10: 보험서비스비용 | C10: Insurance service expense | D10: =SUM(D11:D13) -> 992.08658 | E10: =SUM(E11:E13) -> 864.1241 | F10: =IFERROR(IF(D10*E10<0,"-",IF(E10<0,-(D10/E10-1),(D10/E10-1))),0) -> 0.14808345 | I10: 992.08658 | J10: 295.57384 | K10: 247.78089 | L10: 222.61089 | M10: 226.12096 | N10: 864.1241 | O10: 225.94764 | P10: 216.36852 | Q10: 198.44075 | R10: 223.36718 | S10: 749.97788 | T10: 169.589 | U10: =SUM(U11:U14) -> 204.6125 | V10: =SUM(V11:V14) -> 187.08566 | W10: 188.69072 | X10: =SUM(Y10:AB10) -> 803.53061 | Y10: 204.87386 | Z10: =SUM(Z11:Z14) -> 206.84003 | AA10: =SUM(AA11:AA14) -> 199.63845 | AB10: =SUM(AB11:AB14) -> 192.17826 | AE10: 보험서비스비용 | AF10: Insurance service expense | AG10: =SUM(AG11:AG13) -> 1027.0722 | AH10: =SUM(AH11:AH13) -> 898.56388 | AI10: =IFERROR(IF(AG10*AH10<0,"-",IF(AH10<0,-(AG10/AH10-1),(AG10/AH10-1))),0) -> 0.14301526 | AL10: =SUM(AM10:AP10) -> 1027.0722 | AM10: 307.16749 | AN10: 255.71829 | AO10: 230.63079 | AP10: 233.55566 | AQ10: 898.56388 | AR10: 237.7334 | AS10: 224.18453 | AT10: 191.58131 | AU10: 245.06464 | AV10: 810.1529 | AW10: 182.32493 | AX10: =SUM(AX11:AX14) -> 219.66076 | AY10: 200.27225 | AZ10: 207.89496 | BA10: =SUM(BB10:BE10) -> 882.80179 | BB10: 215.3179 | BC10: =SUM(BC11:BC14) -> 236.05986 | BD10: 218.8214 | BE10: 212.60262
B11: 일반보험서비스비용 | C11: Insurance service expense | D11: =SUM(J11:M11) -> 897.78618 | E11: =SUM(O11:R11) -> 779.3599 | F11: =IFERROR(IF(D11*E11<0,"-",IF(E11<0,-(D11/E11-1),(D11/E11-1))),0) -> 0.15195326 | I11: 897.78618 | J11: 270.42917 | K11: 225.22661 | L11: 200.92326 | M11: 201.20714 | N11: 779.3599 | O11: 204.41137 | P11: 196.21563 | Q11: 177.73855 | R11: 200.99435 | S11: 659.29933 | T11: 143.95537 | U11: 184.73597 | V11: 165.79443 | W11: 164.81356 | X11: =SUM(Y11:AB11) -> 720.23201 | Y11: 180.98392 | Z11: 187.56243 | AA11: 179.99925 | AB11: 171.68641 | AE11: 일반보험서비스비용 | AF11: Insurance service expense | AG11: =SUM(AM11:AP11) -> 897.78618 | AH11: =SUM(AR11:AU11) -> 779.3599 | AI11: =IFERROR(IF(AG11*AH11<0,"-",IF(AH11<0,-(AG11/AH11-1),(AG11/AH11-1))),0) -> 0.15195326 | AL11: =SUM(AM11:AP11) -> 897.78618 | AM11: 270.42917 | AN11: 225.22661 | AO11: 200.92326 | AP11: 201.20714 | AQ11: 779.3599 | AR11: 204.41137 | AS11: 196.21563 | AT11: 177.73855 | AU11: 200.99435 | AV11: 659.29933 | AW11: 143.95537 | AX11: 184.73597 | AY11: 165.79443 | AZ11: 164.81356 | BA11: =SUM(BB11:BE11) -> 720.23201 | BB11: 180.98392 | BC11: 187.56243 | BD11: 179.99925 | BE11: 171.68641
B12: 출재보험서비스비용 | C12: Reinsurance service expense | D12: =SUM(J12:M12) -> 29.462123 | E12: =SUM(O12:R12) -> 17.104903 | F12: =IFERROR(IF(D12*E12<0,"-",IF(E12<0,-(D12/E12-1),(D12/E12-1))),0) -> 0.72243727 | I12: 29.462123 | J12: 6.8472044 | K12: 6.6855331 | L12: 6.5413245 | M12: 9.3880608 | N12: 17.104903 | O12: 0.82575048 | P12: 3.8437934 | Q12: 5.5573099 | R12: 6.8780494 | S12: 23.420482 | T12: 6.6872085 | U12: 4.3825992 | V12: 6.2475129 | W12: 6.1031613 | X12: =SUM(Y12:AB12) -> 23.193321 | Y12: 7.1323686 | Z12: 4.6266731 | AA12: 5.9179821 | AB12: 5.5162974 | AE12: 출재보험서비스비용 | AF12: Reinsurance service expense | AG12: =SUM(AM12:AP12) -> 29.462123 | AH12: =SUM(AR12:AU12) -> 17.104903 | AI12: =IFERROR(IF(AG12*AH12<0,"-",IF(AH12<0,-(AG12/AH12-1),(AG12/AH12-1))),0) -> 0.72243727 | AL12: =SUM(AM12:AP12) -> 29.462123 | AM12: 6.8472044 | AN12: 6.6855331 | AO12: 6.5413245 | AP12: 9.3880608 | AQ12: 17.104903 | AR12: 0.82575048 | AS12: 3.8437934 | AT12: 5.5573099 | AU12: 6.8780494 | AV12: 23.420482 | AW12: 6.6872085 | AX12: 4.3825992 | AY12: 6.2475129 | AZ12: 6.1031613 | BA12: =SUM(BB12:BE12) -> 23.193321 | BB12: 7.1323686 | BC12: 4.6266731 | BD12: 5.9179821 | BE12: 5.5162974
B13: 기타사업비용 | C13: Other expense | D13: =SUM(J13:M13) -> 64.838271 | E13: =SUM(O13:R13) -> 67.659293 | F13: =IFERROR(IF(D13*E13<0,"-",IF(E13<0,-(D13/E13-1),(D13/E13-1))),0) -> -0.041694534 | I13: 64.838271 | J13: 18.297465 | K13: 15.868745 | L13: 15.146306 | M13: 15.525754 | N13: 67.659293 | O13: 20.71052 | P13: 16.309096 | Q13: 15.144894 | R13: 15.494783 | S13: 67.258069 | T13: 18.946424 | U13: 15.493932 | V13: 15.04372 | W13: 17.773994 | X13: =SUM(Y13:AB13) -> 60.105278 | Y13: 16.757573 | Z13: 14.65093 | AA13: 13.721218 | AB13: 14.975558 | AE13: 기타사업비용 | AF13: Other expense | AG13: =SUM(AM13:AP13) -> 99.823925 | AH13: =SUM(AR13:AU13) -> 102.09908 | AI13: =IFERROR(IF(AG13*AH13<0,"-",IF(AH13<0,-(AG13/AH13-1),(AG13/AH13-1))),0) -> -0.022283764 | AL13: =SUM(AM13:AP13) -> 99.823925 | AM13: 29.891118 | AN13: 23.806142 | AO13: 23.166213 | AP13: 22.960453 | AQ13: 102.09908 | AR13: 32.496279 | AS13: 24.125107 | AT13: 8.2854541 | AU13: 37.192237 | AV13: 127.43309 | AW13: 31.682349 | AX13: 30.542194 | AY13: 28.230308 | AZ13: 36.978235 | BA13: =SUM(BB13:BE13) -> 139.37646 | BB13: 27.201606 | BC13: 43.870763 | BD13: 32.904168 | BE13: 35.399921
BA14: =SUM(BB14:BE14) -> 0
B15: 투자서비스수익 | C15: Investment service revenue | D15: =SUM(D16:D20) -> 3947.3207 | E15: =SUM(E16:E20) -> 3670.5623 | F15: =IFERROR(IF(D15*E15<0,"-",IF(E15<0,-(D15/E15-1),(D15/E15-1))),0) -> 0.075399442 | I15: 3947.3207 | J15: 912.85809 | K15: 936.30217 | L15: 1306.6928 | M15: 791.46758 | N15: 3670.5623 | O15: 1236.439 | P15: 370.59488 | Q15: 807.73918 | R15: 1255.7893 | S15: 3956.0401 | T15: 1157.8043 | U15: =SUM(U16:U21) -> 553.35421 | V15: =SUM(V16:V21) -> 936.43613 | W15: 1308.4454 | X15: =SUM(Y15:AB15) -> 5098.5172 | Y15: -32.990686 | Z15: =SUM(Z16:Z21) -> 1585.6088 | AA15: =SUM(AA16:AA21) -> 1978.1162 | AB15: =SUM(AB16:AB21) -> 1567.7829 | AE15: 투자서비스수익 | AF15: Investment service revenue | AG15: =SUM(AG16:AG20) -> 4084.3525 | AH15: =SUM(AH16:AH20) -> 3812.7456 | AI15: =IFERROR(IF(AG15*AH15<0,"-",IF(AH15<0,-(AG15/AH15-1),(AG15/AH15-1))),0) -> 0.071236554 | AL15: =SUM(AM15:AP15) -> 4084.3525 | AM15: 948.13796 | AN15: 972.81029 | AO15: 1350.8049 | AP15: 812.59937 | AQ15: 3812.7456 | AR15: 1280.1356 | AS15: 398.7627 | AT15: 842.05752 | AU15: 1291.7899 | AV15: 4134.4408 | AW15: 1254.1904 | AX15: =SUM(AX16:AX21) -> 572.68191 | AY15: 963.47575 | AZ15: 1344.0928 | BA15: =SUM(BB15:BE15) -> 5255.4749 | BB15: -9.0116594 | BC15: =SUM(BC16:BC21) -> 1650.3424 | BD15: 2015.1613 | BE15: 1598.9829
B16: 보험금융수익 | C16: Insurance financial revenue | D16: =SUM(J16:M16) -> 663.73185 | E16: =SUM(O16:R16) -> 319.18261 | F16: =IFERROR(IF(D16*E16<0,"-",IF(E16<0,-(D16/E16-1),(D16/E16-1))),0) -> 1.0794737 | I16: 663.73185 | J16: 185.32796 | K16: 18.61685 | L16: 183.86293 | M16: 275.92411 | N16: 319.18261 | O16: 11.835091 | P16: 214.57859 | Q16: 80.214362 | R16: 12.554571 | S16: 612.08324 | T16: 263.01093 | U16: 297.1408 | V16: 16.996267 | W16: 34.935246 | X16: =SUM(Y16:AB16) -> 3190.7457 | Y16: 402.69771 | Z16: 491.15596 | AA16: ='[14]공시용PL(변경후)'!$E$13/1000000000 -> 1188.2831 | AB16: 1108.6089 | AE16: 보험금융수익 | AF16: Insurance financial revenue | AG16: =SUM(AM16:AP16) -> 663.73185 | AH16: =SUM(AR16:AU16) -> 319.18261 | AI16: =IFERROR(IF(AG16*AH16<0,"-",IF(AH16<0,-(AG16/AH16-1),(AG16/AH16-1))),0) -> 1.0794737 | AL16: =SUM(AM16:AP16) -> 663.73185 | AM16: 185.32796 | AN16: 18.61685 | AO16: 183.86293 | AP16: 275.92411 | AQ16: 319.18261 | AR16: 11.835091 | AS16: 214.57859 | AT16: 80.214362 | AU16: 12.554571 | AV16: 612.08324 | AW16: 263.01093 | AX16: 297.1408 | AY16: 16.996267 | AZ16: 34.935246 | BA16: =SUM(BB16:BE16) -> 3190.7457 | BB16: 402.69771 | BC16: 491.15596 | BD16: 1188.2831 | BE16: 1108.6089
B17: 재보험금융수익 | C17: Reinsurance financial revenue | D17: =SUM(J17:M17) -> 3.3082494 | E17: =SUM(O17:R17) -> 2.0238661 | F17: =IFERROR(IF(D17*E17<0,"-",IF(E17<0,-(D17/E17-1),(D17/E17-1))),0) -> 0.63461875 | I17: 3.3082494 | J17: 0.85839144 | K17: 0.7929775 | L17: 0.82017629 | M17: 0.83670416 | N17: 2.0238661 | O17: 0.71158538 | P17: 0.44238611 | Q17: 0.45137617 | R17: 0.4185184 | S17: 1.4794636 | T17: 0.42160664 | U17: 0.37672875 | V17: 0.35146594 | W17: 0.32966222 | X17: =SUM(Y17:AB17) -> 1.0572867 | Y17: 0.36241421 | Z17: 0.27015163 | AA17: ='[14]공시용PL(변경후)'!$E$14/1000000000 -> 0.23331848 | AB17: 0.19140241 | AE17: 재보험금융수익 | AF17: Reinsurance financial revenue | AG17: =SUM(AM17:AP17) -> 3.3082494 | AH17: =SUM(AR17:AU17) -> 2.0238661 | AI17: =IFERROR(IF(AG17*AH17<0,"-",IF(AH17<0,-(AG17/AH17-1),(AG17/AH17-1))),0) -> 0.63461875 | AL17: =SUM(AM17:AP17) -> 3.3082494 | AM17: 0.85839144 | AN17: 0.7929775 | AO17: 0.82017629 | AP17: 0.83670416 | AQ17: 2.0238661 | AR17: 0.71158538 | AS17: 0.44238611 | AT17: 0.45137617 | AU17: 0.4185184 | AV17: 1.4794636 | AW17: 0.42160664 | AX17: 0.37672875 | AY17: 0.35146594 | AZ17: 0.32966222 | BA17: =SUM(BB17:BE17) -> 1.0572867 | BB17: 0.36241421 | BC17: 0.27015163 | BD17: 0.23331849 | BE17: 0.19140241
B18: 이자수익 | C18: Interest revenue | D18: =SUM(J18:M18) -> 490.9836 | E18: =SUM(O18:R18) -> 506.2994 | F18: =IFERROR(IF(D18*E18<0,"-",IF(E18<0,-(D18/E18-1),(D18/E18-1))),0) -> -0.030250484 | I18: 490.9836 | J18: 125.13326 | K18: 122.64968 | L18: 121.56156 | M18: 121.63909 | N18: 506.2994 | O18: 125.81762 | P18: 126.31674 | Q18: 126.49902 | R18: 127.66603 | S18: 551.78751 | T18: 139.0991 | U18: 142.30361 | V18: 136.20783 | W18: 136.89489 | X18: =SUM(Y18:AB18) -> 586.69578 | Y18: 147.08113 | Z18: 147.66878 | AA18: ='[14]공시용PL(변경후)'!$E$15/1000000000 -> 147.99681 | AB18: 143.94907 | AE18: 이자수익 | AF18: Interest revenue | AG18: =SUM(AM18:AP18) -> 493.83809 | AH18: =SUM(AR18:AU18) -> 509.57413 | AI18: =IFERROR(IF(AG18*AH18<0,"-",IF(AH18<0,-(AG18/AH18-1),(AG18/AH18-1))),0) -> -0.030880755 | AL18: =SUM(AM18:AP18) -> 493.83809 | AM18: 125.75551 | AN18: 123.29195 | AO18: 122.31264 | AP18: 122.47799 | AQ18: 509.57413 | AR18: 126.76422 | AS18: 126.647 | AT18: 127.71551 | AU18: 128.4474 | AV18: 554.71269 | AW18: 138.36947 | AX18: 141.32101 | AY18: 137.30716 | AZ18: 137.71506 | BA18: =SUM(BB18:BE18) -> 589.42513 | BB18: 147.95977 | BC18: 148.37085 | BD18: 148.55924 | BE18: 144.53527
B19: 금융자산관련이익 | C19: Financial assset related income | D19: =SUM(J19:M19) -> 2332.6962 | E19: =SUM(O19:R19) -> 2170.6459 | F19: =IFERROR(IF(D19*E19<0,"-",IF(E19<0,-(D19/E19-1),(D19/E19-1))),0) -> 0.074655334 | I19: 2332.6962 | J19: 536.01799 | K19: 809.52242 | L19: 694.41867 | M19: 292.7371 | N19: 2170.6459 | O19: 829.83927 | P19: -45.026928 | Q19: 437.39415 | R19: 948.4394 | S19: 2176.7596 | T19: 664.47782 | U19: -41.338623 | V19: 620.75643 | W19: 933.02094 | X19: =SUM(Y19:AB19) -> 360.1114 | Y19: -636.61954 | Z19: 451.63352 | AA19: =SUM('[14]공시용PL(변경후)'!$E$16:$E$21)/1000000000 -> 369.80004 | AB19: 175.29737 | AE19: 금융자산관련이익 | AF19: Financial assset related income | AG19: =SUM(AM19:AP19) -> 2351.3282 | AH19: =SUM(AR19:AU19) -> 2183.6887 | AI19: =IFERROR(IF(AG19*AH19<0,"-",IF(AH19<0,-(AG19/AH19-1),(AG19/AH19-1))),0) -> 0.076768946 | AL19: =SUM(AM19:AP19) -> 2351.3282 | AM19: 543.90571 | AN19: 817.99188 | AO19: 694.41867 | AP19: 295.01193 | AQ19: 2183.6887 | AR19: 832.91537 | AS19: -44.88711 | AT19: 447.05781 | AU19: 948.60265 | AV19: 2180.3168 | AW19: 672.21965 | AX19: -41.458968 | AY19: 618.61265 | AZ19: 931.2 | BA19: =SUM(BB19:BE19) -> 374.35368 | BB19: -636.3736 | BC19: 457.82013 | BD19: 369.82559 | BE19: 183.08156
B20: 기타투자수익 | C20: Other investment revenue | D20: =SUM(J20:M20) -> 456.60078 | E20: =SUM(O20:R20) -> 672.41054 | F20: =IFERROR(IF(D20*E20<0,"-",IF(E20<0,-(D20/E20-1),(D20/E20-1))),0) -> -0.3209494 | I20: 456.60078 | J20: 65.520489 | K20: -15.279767 | L20: 306.02947 | M20: 100.33058 | N20: 672.41054 | O20: 268.23541 | P20: 74.284093 | Q20: 163.18028 | R20: 166.71076 | S20: 613.93029 | T20: 90.794863 | U20: 154.87169 | V20: 162.12413 | W20: 203.26466 | X20: =SUM(Y20:AB20) -> 959.90706 | Y20: 53.487598 | Z20: 494.88043 | AA20: =SUM('[14]공시용PL(변경후)'!$E$22:$E$29)/1000000000 -> 271.80285 | AB20: 139.73618 | AE20: 기타투자수익 | AF20: Other investment revenue | AG20: =SUM(AM20:AP20) -> 572.1461 | AH20: =SUM(AR20:AU20) -> 798.27631 | AI20: =IFERROR(IF(AG20*AH20<0,"-",IF(AH20<0,-(AG20/AH20-1),(AG20/AH20-1))),0) -> -0.2832731 | AL20: =SUM(AM20:AP20) -> 572.1461 | AM20: 92.290391 | AN20: 12.116634 | AO20: 349.39045 | AP20: 118.34863 | AQ20: 798.27631 | AR20: 307.90929 | AS20: 101.98184 | AT20: 186.61846 | AU20: 201.76672 | AV20: 785.84864 | AW20: 180.16873 | AX20: 175.30234 | AY20: 190.20821 | AZ20: 239.9 | BA20: =SUM(BB20:BE20) -> 1099.8931 | BB20: 76.342049 | BC20: 552.72527 | BD20: 308.26001 | BE20: 162.56577
F21: =IFERROR(IF(D21*E21<0,"-",IF(E21<0,-(D21/E21-1),(D21/E21-1))),0) -> 0 | AI21: =IFERROR(IF(AG21*AH21<0,"-",IF(AH21<0,-(AG21/AH21-1),(AG21/AH21-1))),0) -> 0 | BA21: =SUM(BB21:BE21) -> 0
B22: 투자서비스비용 | C22: Investment service cost | D22: =SUM(D23:D28) -> 3873.4545 | E22: =SUM(E23:E28) -> 3674.8989 | F22: =IFERROR(IF(D22*E22<0,"-",IF(E22<0,-(D22/E22-1),(D22/E22-1))),0) -> 0.054030208 | I22: 3873.4545 | J22: 883.95065 | K22: 911.75907 | L22: 1286.6298 | M22: 791.11497 | N22: 3674.8989 | O22: 1203.1449 | P22: 398.56238 | Q22: 838.56067 | R22: 1234.631 | S22: 3978.6645 | T22: 1277.2032 | U22: =SUM(U23:U29) -> 554.09874 | V22: =SUM(V23:V29) -> 932.68649 | W22: 1214.6761 | X22: =SUM(Y22:AB22) -> 5070.6889 | Y22: 46.159078 | Z22: =SUM(Z23:Z29) -> 1539.2366 | AA22: =SUM(AA23:AA29) -> 1956.1512 | AB22: =SUM(AB23:AB29) -> 1529.142 | AE22: 투자서비스비용 | AF22: Investment service cost | AG22: =SUM(AG23:AG28) -> 3966.8453 | AH22: =SUM(AH23:AH28) -> 3775.4509 | AI22: =IFERROR(IF(AG22*AH22<0,"-",IF(AH22<0,-(AG22/AH22-1),(AG22/AH22-1))),0) -> 0.050694451 | AL22: =SUM(AM22:AP22) -> 3966.8453 | AM22: 902.31904 | AN22: 937.40761 | AO22: 1322.4222 | AP22: 804.69641 | AQ22: 3775.4509 | AR22: 1235.8488 | AS22: 417.9512 | AT22: 877.02513 | AU22: 1244.6258 | AV22: 4094.5409 | AW22: 1332.2356 | AX22: =SUM(AX23:AX29) -> 575.79497 | AY22: 937.67121 | AZ22: 1228.4436 | BA22: =SUM(BB22:BE22) -> 5136.7578 | BB22: 56.469909 | BC22: =SUM(BC23:BC29) -> 1567.7667 | BD22: 1973.5109 | BE22: 1539.0103
B23: 보험금융비용 | C23: Insurance financial expense | D23: =SUM(J23:M23) -> 2936.5108 | E23: =SUM(O23:R23) -> 2393.0878 | F23: =IFERROR(IF(D23*E23<0,"-",IF(E23<0,-(D23/E23-1),(D23/E23-1))),0) -> 0.22708028 | I23: 2936.5108 | J23: 825.58452 | K23: 1056.3991 | L23: 762.45996 | M23: 292.06727 | N23: 2393.0878 | O23: 636.38014 | P23: 270.90059 | Q23: 583.96862 | R23: 901.83841 | S23: 2954.241 | T23: 1152.9716 | U23: 280.52944 | V23: 668.20469 | W23: 852.5353 | X23: =SUM(Y23:AB23) -> 1300.0523 | Y23: 369.46105 | Z23: 504.94702 | AA23: 161.66444 | AB23: 263.97978 | AE23: 보험금융비용 | AF23: Insurance financial expense | AG23: =SUM(AM23:AP23) -> 2936.5108 | AH23: =SUM(AR23:AU23) -> 2393.0878 | AI23: =IFERROR(IF(AG23*AH23<0,"-",IF(AH23<0,-(AG23/AH23-1),(AG23/AH23-1))),0) -> 0.22708028 | AL23: =SUM(AM23:AP23) -> 2936.5108 | AM23: 825.58452 | AN23: 1056.3991 | AO23: 762.45996 | AP23: 292.06727 | AQ23: 2393.0878 | AR23: 636.38014 | AS23: 270.90059 | AT23: 583.96862 | AU23: 901.83841 | AV23: 2954.241 | AW23: 1132.5761 | AX23: 280.52944 | AY23: 668.20469 | AZ23: 852.5353 | BA23: =SUM(BB23:BE23) -> 1300.0523 | BB23: 369.46105 | BC23: 504.94702 | BD23: 161.66444 | BE23: 263.97978
B24: 재보험금융비용 | C24: Reinsurance financial expense | D24: =SUM(J24:M24) -> 2.2844399 | E24: =SUM(O24:R24) -> 1.2179844 | F24: =IFERROR(IF(D24*E24<0,"-",IF(E24<0,-(D24/E24-1),(D24/E24-1))),0) -> 0.87559039 | I24: 2.2844399 | J24: 0.57098708 | K24: 0.53995313 | L24: 0.58655794 | M24: 0.58694173 | N24: 1.2179844 | O24: 0.41565951 | P24: 0.25759183 | Q24: 0.275523 | R24: 0.26921007 | S24: 0.93647891 | T24: 0.24755853 | U24: 0.24106651 | V24: 0.22627746 | W24: 0.22157641 | X24: =SUM(Y24:AB24) -> 0.7114358 | Y24: 0.21052667 | Z24: 0.18914646 | AA24: 0.17244011 | AB24: 0.13932255 | AE24: 재보험금융비용 | AF24: Reinsurance financial expense | AG24: =SUM(AM24:AP24) -> 2.2844399 | AH24: =SUM(AR24:AU24) -> 1.2179844 | AI24: =IFERROR(IF(AG24*AH24<0,"-",IF(AH24<0,-(AG24/AH24-1),(AG24/AH24-1))),0) -> 0.87559039 | AL24: =SUM(AM24:AP24) -> 2.2844399 | AM24: 0.57098708 | AN24: 0.53995313 | AO24: 0.58655794 | AP24: 0.58694173 | AQ24: 1.2179844 | AR24: 0.41565951 | AS24: 0.25759184 | AT24: 0.275523 | AU24: 0.26921007 | AV24: 0.93647891 | AW24: 0.24755853 | AX24: 0.24106651 | AY24: 0.22627746 | AZ24: 0.22157641 | BA24: =SUM(BB24:BE24) -> 0.7114358 | BB24: 0.21052667 | BC24: 0.18914646 | BD24: 0.17244011 | BE24: 0.13932255
B25: 재산관리비 | C25: Property administrative expense | D25: =SUM(J25:M25) -> 20.65857 | E25: =SUM(O25:R25) -> 20.023981 | F25: =IFERROR(IF(D25*E25<0,"-",IF(E25<0,-(D25/E25-1),(D25/E25-1))),0) -> 0.031691424 | I25: 20.65857 | J25: 5.1746359 | K25: 5.3162936 | L25: 5.0850517 | M25: 5.0825886 | N25: 20.023981 | O25: 5.7686073 | P25: 4.663306 | Q25: 4.4209361 | R25: 5.1711318 | S25: 20.518134 | T25: 5.3998237 | U25: 5.0478455 | V25: 4.8599904 | W25: 5.2104742 | X25: =SUM(Y25:AB25) -> 20.767416 | Y25: 5.21714 | Z25: 4.9637951 | AA25: 4.4414368 | AB25: 6.1450445 | AE25: 재산관리비 | AF25: Property administrative expense | AG25: =SUM(AM25:AP25) -> 20.680406 | AH25: =SUM(AR25:AU25) -> 20.040339 | AI25: =IFERROR(IF(AG25*AH25<0,"-",IF(AH25<0,-(AG25/AH25-1),(AG25/AH25-1))),0) -> 0.031938925 | AL25: =SUM(AM25:AP25) -> 20.680406 | AM25: 5.1788999 | AN25: 5.3214381 | AO25: 5.0910672 | AP25: 5.0890006 | AQ25: 20.040339 | AR25: 5.7707573 | AS25: 4.6658293 | AT25: 4.4266527 | AU25: 5.1770995 | AV25: 21.479331 | AW25: 5.5631377 | AX25: 5.536398 | AY25: 5.0917595 | AZ25: 5.2880361 | BA25: =SUM(BB25:BE25) -> 21.21331 | BB25: 5.2819049 | BC25: 5.067415 | BD25: 4.4890809 | BE25: 6.3749087
B26: 이자비용 | C26: Interest expense | D26: =SUM(J26:M26) -> 14.65244 | E26: =SUM(O26:R26) -> 12.773507 | F26: =IFERROR(IF(D26*E26<0,"-",IF(E26<0,-(D26/E26-1),(D26/E26-1))),0) -> 0.1470961 | I26: 14.65244 | J26: 5.2246754 | K26: 3.1281597 | L26: 3.1408764 | M26: 3.1587288 | N26: 12.773507 | O26: 3.238034 | P26: 3.0996274 | Q26: 3.1038874 | R26: 3.3319584 | S26: 20.543698 | T26: 4.5496048 | U26: 5.2165036 | V26: 5.2448936 | W26: 5.5326957 | X26: =SUM(Y26:AB26) -> 21.706657 | Y26: 5.9347193 | Z26: 5.2485084 | AA26: 5.2977886 | AB26: 5.2256403 | AE26: 이자비용 | AF26: Interest expense | AG26: =SUM(AM26:AP26) -> 14.954775 | AH26: =SUM(AR26:AU26) -> 13.301691 | AI26: =IFERROR(IF(AG26*AH26<0,"-",IF(AH26<0,-(AG26/AH26-1),(AG26/AH26-1))),0) -> 0.12427622 | AL26: =SUM(AM26:AP26) -> 14.954775 | AM26: 5.2867448 | AN26: 3.1962062 | AO26: 3.2291855 | AP26: 3.2426381 | AQ26: 13.301691 | AR26: 3.3431166 | AS26: 3.2336243 | AT26: 3.2558347 | AU26: 3.4691152 | AV26: 20.95455 | AW26: 4.6553017 | AX26: 5.3236823 | AY26: 5.3310965 | AZ26: 5.6444692 | BA26: =SUM(BB26:BE26) -> 22.321862 | BB26: 5.9629599 | BC26: 5.4194365 | BD26: 5.5319888 | BE26: 5.4074767
B27: 금융자산관련비용 | C27: Financial asset related expense | D27: =SUM(J27:M27) -> 413.89875 | E27: =SUM(O27:R27) -> 513.72212 | F27: =IFERROR(IF(D27*E27<0,"-",IF(E27<0,-(D27/E27-1),(D27/E27-1))),0) -> -0.19431395 | I27: 413.89875 | J27: -57.598456 | K27: -225.54005 | L27: 294.89164 | M27: 402.14561 | N27: 513.72212 | O27: 140.40654 | P27: 166.35709 | Q27: 95.690601 | R27: 111.2679 | S27: 351.66379 | T27: 75.08081 | U27: 91.458163 | V27: 96.995635 | W27: 88.135236 | X27: =SUM(Y27:AB27) -> 2915.8123 | Y27: -143.3604 | Z27: 499.92173 | AA27: 1447.0178 | AB27: 1112.2332 | AE27: 금융자산관련비용 | AF27: Financial asset related expense | AG27: =SUM(AM27:AP27) -> 413.89675 | AH27: =SUM(AR27:AU27) -> 512.37958 | AI27: =IFERROR(IF(AG27*AH27<0,"-",IF(AH27<0,-(AG27/AH27-1),(AG27/AH27-1))),0) -> -0.19220678 | AL27: =SUM(AM27:AP27) -> 413.89675 | AM27: -59.29223 | AN27: -227.5199 | AO27: 300.41309 | AP27: 400.29578 | AQ27: 512.37958 | AR27: 140.19177 | AS27: 164.15466 | AT27: 97.405827 | AU27: 110.62732 | AV27: 427.48824 | AW27: 151.87681 | AX27: 92.867701 | AY27: 95.935572 | AZ27: 86.808152 | BA27: =SUM(BB27:BE27) -> 2925.7313 | BB27: -135.81352 | BC27: 499.92071 | BD27: 1449.3945 | BE27: 1112.2295
B28: 기타투자비용 | C28: Other investment expense | D28: =SUM(J28:M28) -> 485.4495 | E28: =SUM(O28:R28) -> 734.07359 | F28: =IFERROR(IF(D28*E28<0,"-",IF(E28<0,-(D28/E28-1),(D28/E28-1))),0) -> -0.33869096 | I28: 485.4495 | J28: 104.99429 | K28: 71.915656 | L28: 220.46573 | M28: 88.073833 | N28: 734.07359 | O28: 416.93593 | P28: -46.715823 | Q28: 151.1011 | R28: 212.75237 | S28: 630.76137 | T28: 38.953775 | U28: 171.60573 | V28: 157.155 | W28: 263.0408 | X28: =SUM(Y28:AB28) -> 811.63879 | Y28: -191.30395 | Z28: 523.96641 | AA28: 337.55733 | AB28: 141.41901 | AE28: 기타투자비용 | AF28: Other investment expense | AG28: =SUM(AM28:AP28) -> 578.51814 | AH28: =SUM(AR28:AU28) -> 835.42354 | AI28: =IFERROR(IF(AG28*AH28<0,"-",IF(AH28<0,-(AG28/AH28-1),(AG28/AH28-1))),0) -> -0.30751516 | AL28: =SUM(AM28:AP28) -> 578.51814 | AM28: 124.99012 | AN28: 99.47086 | AO28: 250.64237 | AP28: 103.41478 | AQ28: 835.42354 | AR28: 449.74735 | AS28: -25.26109 | AT28: 187.69268 | AU28: 223.24461 | AV28: 669.44127 | AW28: 37.316667 | AX28: 191.29669 | AY28: 162.88181 | AZ28: 277.94611 | BA28: =SUM(BB28:BE28) -> 866.72768 | BB28: -188.63301 | BC28: 552.223 | BD28: 352.25845 | BE28: 150.87925
BA29: =SUM(BB29:BE29) -> 0
B30: 영업손익 | C30: Operating income | D30: =+D6-D10+D15-D22 -> 185.85627 | E30: =+E6-E10+E15-E22 -> 114.9389 | F30: =IFERROR(IF(D30*E30<0,"-",IF(E30<0,-(D30/E30-1),(D30/E30-1))),0) -> 0.6170005 | I30: 185.85627 | J30: 23.026769 | K30: 58.852311 | L30: 64.73927 | M30: 39.237915 | N30: 114.9389 | O30: 53.149125 | P30: 3.4366501 | Q30: 14.897329 | R30: 43.455801 | S30: 146.37634 | T30: -62.004185 | U30: =U6-U10+U15-U22 -> 26.595372 | V30: =V6-V10+V15-V22 -> 44.317333 | W30: 137.46782 | X30: =SUM(Y30:AB30) -> 150.77617 | Y30: -57.453917 | Z30: =Z6-Z10+Z15-Z22 -> 72.653926 | AA30: =AA6-AA10+AA15-AA22 -> 59.229219 | AB30: =AB6-AB10+AB15-AB22 -> 76.346944 | AE30: 영업손익 | AF30: Operating income | AG30: =+AG6-AG10+AG15-AG22 -> 194.51164 | AH30: =+AH6-AH10+AH15-AH22 -> 122.13049 | AI30: =IFERROR(IF(AG30*AH30<0,"-",IF(AH30<0,-(AG30/AH30-1),(AG30/AH30-1))),0) -> 0.59265417 | AL30: =SUM(AM30:AP30) -> 194.51164 | AM30: 28.344592 | AN30: 61.774488 | AO30: 65.038992 | AP30: 39.35357 | AQ30: 122.13049 | AR30: 52.356065 | AS30: 4.3996382 | AT30: 17.610643 | AU30: 47.764149 | AV30: 148.7257 | AW30: -33.386486 | AX30: =AX6-AX10+AX15-AX22 -> 9.1785798 | AY30: 53.185653 | AZ30: 140.14342 | BA30: =SUM(BB30:BE30) -> 162.39373 | BB30: -54.229755 | BC30: =BC6-BC10+BC15-BC22 -> 79.637499 | BD30: 59.731738 | BE30: 77.254246
B31: 영업외손익 | C31: Non-operating income | D31: =+D32-D33 -> 3.4005108 | E31: =+E32-E33 -> 0.88398245 | F31: =IFERROR(IF(D31*E31<0,"-",IF(E31<0,-(D31/E31-1),(D31/E31-1))),0) -> 2.846808 | I31: 3.4005108 | J31: 6.0941748 | K31: -0.31653275 | L31: -1.4037297 | M31: -0.9734016 | N31: 0.88398245 | O31: 0.99597178 | P31: -2.0731538 | Q31: 3.3419551 | R31: -1.3807906 | S31: -4.0171268 | T31: -0.5314674 | U31: =U32-U33 -> -0.80410659 | V31: =V32-V33 -> -1.0082205 | W31: -1.6733323 | X31: =SUM(Y31:AB31) -> 2.1345925 | Y31: 3.7365747 | Z31: =Z32-Z33 -> 1.1965876 | AA31: =AA32-AA33 -> -1.3374574 | AB31: =AB32-AB33 -> -1.4611123 | AE31: 영업외손익 | AF31: Non-operating income | AG31: =+AG32-AG33 -> 4.1979196 | AH31: =+AH32-AH33 -> 1.0014912 | AI31: =IFERROR(IF(AG31*AH31<0,"-",IF(AH31<0,-(AG31/AH31-1),(AG31/AH31-1))),0) -> 3.191669 | AL31: =SUM(AM31:AP31) -> 4.1979196 | AM31: 6.5440642 | AN31: -0.071592624 | AO31: -1.2866364 | AP31: -0.98791555 | AQ31: 1.0014912 | AR31: 0.99295031 | AS31: -2.0881124 | AT31: 3.4873949 | AU31: -1.3907415 | AV31: -4.1530448 | AW31: -56.030987 | AX31: =AX32-AX33 -> 54.3936 | AY31: -0.85692421 | AZ31: -1.6587341 | BA31: =SUM(BB31:BE31) -> 2.1412418 | BB31: 3.654817 | BC31: =BC32-BC33 -> 1.2096452 | BD31: -1.4630999 | BE31: -1.2601205
B32: 영업외수익 | C32: Other Income | D32: =SUM(J32:M32) -> 12.711181 | E32: =SUM(O32:R32) -> 7.9327294 | F32: =IFERROR(IF(D32*E32<0,"-",IF(E32<0,-(D32/E32-1),(D32/E32-1))),0) -> 0.6023717 | I32: 12.711181 | J32: 8.7238049 | K32: 1.3509089 | L32: 1.1620696 | M32: 1.4743977 | N32: 7.9327294 | O32: 1.0727003 | P32: 1.796642 | Q32: 4.3399646 | R32: 0.72342248 | S32: 6.0782987 | T32: 1.1216141 | U32: 2.6563931 | V32: 1.2214277 | W32: 1.0788639 | X32: =SUM(Y32:AB32) -> 6.5871177 | Y32: 2.4483538 | Z32: 1.6025223 | AA32: 1.2106017 | AB32: 1.3256399 | AE32: 영업외수익 | AF32: Other Income | AG32: =SUM(AM32:AP32) -> 13.581305 | AH32: =SUM(AR32:AU32) -> 8.1437215 | AI32: =IFERROR(IF(AG32*AH32<0,"-",IF(AH32<0,-(AG32/AH32-1),(AG32/AH32-1))),0) -> 0.66770248 | AL32: =SUM(AM32:AP32) -> 13.581305 | AM32: 9.2050591 | AN32: 1.5977475 | AO32: 1.2853617 | AP32: 1.4931362 | AQ32: 8.1437215 | AR32: 1.0819113 | AS32: 1.826741 | AT32: 4.4915622 | AU32: 0.74350699 | AV32: 6.2629901 | AW32: -54 | AX32: 57.876159 | AY32: 1.3644415 | AZ32: 1.1091562 | BA32: =SUM(BB32:BE32) -> 7.0175787 | BB32: 2.6958383 | BC32: 1.6159877 | BD32: 1.173532 | BE32: 1.5322207
B33: 영업외비용 | C33: Other expenses | D33: =SUM(J33:M33) -> 9.3106703 | E33: =SUM(O33:R33) -> 7.0487469 | F33: =IFERROR(IF(D33*E33<0,"-",IF(E33<0,-(D33/E33-1),(D33/E33-1))),0) -> 0.32089723 | I33: 9.3106703 | J33: 2.6296301 | K33: 1.6674416 | L33: 2.5657993 | M33: 2.4477993 | N33: 7.0487469 | O33: 0.076728523 | P33: 3.8697958 | Q33: 0.99800953 | R33: 2.1042131 | S33: 10.095426 | T33: 1.6530815 | U33: 3.4604996 | V33: 2.2296482 | W33: 2.7521962 | X33: =SUM(Y33:AB33) -> 4.4525252 | Y33: -1.2882209 | Z33: 0.40593476 | AA33: 2.5480591 | AB33: 2.7867522 | AE33: 영업외비용 | AF33: Other expenses | AG33: =SUM(AM33:AP33) -> 9.3833849 | AH33: =SUM(AR33:AU33) -> 7.1422303 | AI33: =IFERROR(IF(AG33*AH33<0,"-",IF(AH33<0,-(AG33/AH33-1),(AG33/AH33-1))),0) -> 0.31378918 | AL33: =SUM(AM33:AP33) -> 9.3833849 | AM33: 2.6609949 | AN33: 1.6693401 | AO33: 2.5719981 | AP33: 2.4810517 | AQ33: 7.1422303 | AR33: 0.088960969 | AS33: 3.9148535 | AT33: 1.0041673 | AU33: 2.1342485 | AV33: 10.416035 | AW33: 1.9442207 | AX33: 3.4825583 | AY33: 2.2213657 | AZ33: 2.7678903 | BA33: =SUM(BB33:BE33) -> 4.8763368 | BB33: -0.95897869 | BC33: 0.40634245 | BD33: 2.6366319 | BE33: 2.7923412
B34: 세전이익 | C34: Earnings before tax | D34: =+D30+D31 -> 189.25678 | E34: =+E30+E31 -> 115.82289 | F34: =IFERROR(IF(D34*E34<0,"-",IF(E34<0,-(D34/E34-1),(D34/E34-1))),0) -> 0.63401882 | I34: 189.25678 | J34: 29.120944 | K34: 58.535778 | L34: 63.33554 | M34: 38.264514 | N34: 115.82289 | O34: 54.145096 | P34: 1.3634963 | Q34: 18.239284 | R34: 42.07501 | S34: 142.35922 | T34: -62.535653 | U34: =U30+U31 -> 25.791266 | V34: =V30+V31 -> 43.309113 | W34: 135.79449 | X34: =SUM(Y34:AB34) -> 152.91077 | Y34: -53.717343 | Z34: =Z30+Z31 -> 73.850514 | AA34: =AA30+AA31 -> 57.891762 | AB34: =AB30+AB31 -> 74.885832 | AE34: 세전이익 | AF34: Earnings before tax | AG34: =+AG30+AG31 -> 198.70956 | AH34: =+AH30+AH31 -> 123.13199 | AI34: =IFERROR(IF(AG34*AH34<0,"-",IF(AH34<0,-(AG34/AH34-1),(AG34/AH34-1))),0) -> 0.6137932 | AL34: =SUM(AM34:AP34) -> 198.70956 | AM34: 34.888656 | AN34: 61.702895 | AO34: 63.752355 | AP34: 38.365654 | AQ34: 123.13199 | AR34: 53.349015 | AS34: 2.3115258 | AT34: 21.098038 | AU34: 46.373407 | AV34: 144.57265 | AW34: -89.417472 | AX34: =AX30+AX31 -> 63.57218 | AY34: 52.328729 | AZ34: 138.48468 | BA34: =SUM(BB34:BE34) -> 164.53497 | BB34: -50.574939 | BC34: =BC30+BC31 -> 80.847145 | BD34: 58.268638 | BE34: 75.994125
B35: 법인세비용 | C35: Income tax expenses | D35: =SUM(J35:M35) -> 64.356388 | E35: =SUM(O35:R35) -> -9.2160661 | F35: =IFERROR(IF(D35*E35<0,"-",IF(E35<0,-(D35/E35-1),(D35/E35-1))),0) -> - | I35: 64.356388 | J35: 25.417778 | K35: 12.011954 | L35: 12.981909 | M35: 13.944746 | N35: -9.2160668 | O35: -23.511844 | P35: 0.31603338 | Q35: 4.2275306 | R35: 9.7522136 | S35: 33.159362 | T35: -12.504168 | U35: 1.3247385 | V35: 9.2795916 | W35: 35.0592 | X35: =SUM(Y35:AB35) -> 29.440109 | Y35: -20.191077 | Z35: 17.943629 | AA35: 13.179629 | AB35: 18.507928 | AE35: 법인세비용 | AF35: Income tax expenses | AG35: =SUM(AM35:AP35) -> 67.933129 | AH35: =SUM(AR35:AU35) -> -12.982885 | AI35: =IFERROR(IF(AG35*AH35<0,"-",IF(AH35<0,-(AG35/AH35-1),(AG35/AH35-1))),0) -> - | AL35: =SUM(AM35:AP35) -> 67.933129 | AM35: 29.34346 | AN35: 11.946903 | AO35: 13.06019 | AP35: 13.582576 | AQ35: -12.982885 | AR35: -27.697249 | AS35: 0.50945688 | AT35: 4.346611 | AU35: 9.8582966 | AV35: 43.167939 | AW35: 1.6838115 | AX35: 3.1808692 | AY35: 6.9935997 | AZ35: 35.904757 | BA35: =SUM(BB35:BE35) -> 39.71982 | BB35: -25.927837 | BC35: 30.891043 | BD35: 13.104666 | BE35: 21.651948
B36: 당기순이익 | C36: Net income | D36: =+D34-D35 -> 124.90039 | E36: =+E34-E35 -> 125.03895 | F36: =IFERROR(IF(D36*E36<0,"-",IF(E36<0,-(D36/E36-1),(D36/E36-1))),0) -> -0.0011081636 | I36: 124.90039 | J36: 3.7031661 | K36: 46.523824 | L36: 50.353631 | M36: 24.319768 | N36: 125.03895 | O36: 77.65694 | P36: 1.0474629 | Q36: 14.011753 | R36: 32.322796 | S36: 109.19985 | T36: -50.031485 | U36: =U34-U35 -> 24.466527 | V36: =V34-V35 -> 34.029521 | W36: 100.73529 | X36: =SUM(Y36:AB36) -> 123.47066 | Y36: -33.526266 | Z36: =Z34-Z35 -> 55.906885 | AA36: =AA34-AA35 -> 44.712132 | AB36: =AB34-AB35 -> 56.377905 | AE36: 당기순이익 | AF36: Net income | AG36: =+AG34-AG35 -> 130.77643 | AH36: =+AH34-AH35 -> 136.11487 | AI36: =IFERROR(IF(AG36*AH36<0,"-",IF(AH36<0,-(AG36/AH36-1),(AG36/AH36-1))),0) -> -0.0392201 | AL36: =SUM(AM36:AP36) -> 130.77643 | AM36: 5.5451961 | AN36: 49.755992 | AO36: 50.692165 | AP36: 24.783078 | AQ36: 136.11487 | AR36: 81.046264 | AS36: 1.8020689 | AT36: 16.751427 | AU36: 36.51511 | AV36: 101.40471 | AW36: -91.101284 | AX36: =AX34-AX35 -> 60.391311 | AY36: 45.335129 | AZ36: 102.57993 | BA36: =SUM(BB36:BE36) -> 124.81515 | BB36: -24.647102 | BC36: =BC34-BC35 -> 49.956101 | BD36: 45.163973 | BE36: 54.342177
W37: IFRS 17 & 9 ◀ | X37: ▶IFRS 17 + IAS 39 | Y37: ▶IFRS 17 + IAS 39 | AZ37: IFRS 17 & 9 ◀ | BA37: ▶IFRS 17 + IAS 39 | BB37: ▶IFRS 17 + IAS 39
AX39: =+AX32-AX33-AX31 -> 0 | AY39: =+AY32-AY33-AY31 -> 0 | AZ39: =+AZ32-AZ33-AZ31 -> 0
AG40: =AG6-AG10 -> 77.004455

Sheet PROFIT
B1: 손익 세부 | D1: Profit / loss breakdown
B2: (BN KRW, %, %p)
E4: =[15]SUMMARY!D4 -> 2025 | F4: =[15]SUMMARY!E4 -> 2024 | G4: YoY | L4: 2025 | O4: 2024 | T4: 2023 | Y4: 2022
E5: =J5 -> FY | F5: =O5 -> FY | J5: FY | K5: Q4 | L5: Q3 | M5: Q2 | N5: Q1 | O5: FY | P5: Q4 | Q5: Q3 | R5: Q2 | S5: Q1 | T5: FY | U5: Q4 | V5: Q3 | W5: Q2 | X5: Q1 | Y5: FY | Z5: Q4 | AA5: Q3 | AB5: Q2 | AC5: Q1
B6: 세전손익 | D6: Earnings before Tax | E6: =E9+E21+E27+E30 -> 198.70956 | F6: =F9+F21+F27+F30 -> 123.12499 | G6: =+IFERROR(IF(F6<0,-(E6/F6-1),(E6/F6-1)),0) -> 0.61388495 | J6: =J9+J21+J27+J30 -> 198.70956 | K6: =K9+K21+K27+K30 -> 34.888656 | L6: =L9+L21+L27+L30 -> 61.702895 | M6: =M9+M21+M27+M30 -> 63.752341 | N6: =N9+N21+N27+N30 -> 38.365668 | O6: =O9+O21+O27+O30 -> 123.12499 | P6: =P9+P21+P27+P30 -> 53.349015 | Q6: =Q9+Q21+Q27+Q30 -> 2.3045258 | ... AC6: =AC9+AC21+AC27+AC30 -> 74.885832
B9: 보험손익 (별도) | D9: Net income | E9: =+E10+E11+E12-E19+E20 -> 111.99011 | F9: =+F10+F11+F12-F19+F20 -> 119.27554 | G9: =+IFERROR(IF(F9<0,-(E9/F9-1),(E9/F9-1)),0) -> -0.061080709 | J9: =J10+J11+J12-J19+J20 -> 111.99011 | K9: =K10+K11+K12-K19+K20 -> -5.880676 | L9: =L10+L11+L12-L19+L20 -> 34.30921 | M9: =M10+M11+M12-M19+M20 -> 44.676269 | N9: =N10+N11+N12-N19+N20 -> 38.885307 | O9: =O10+O11+O12-O19+O20 -> 119.27554 | P9: =P10+P11+P12-P19+P20 -> 19.855061 | Q9: =Q10+Q11+Q12-Q19+Q20 -> 31.404157 | ... T9: =T10+T11+T12-T19+T20 -> 169.00077 | U9: 57.394659 | V9: 27.339907 | W9: 40.567695 | X9: 43.698505 | Y9: =Y10+Y11+Y12-Y19+Y20 -> 123.29368 | Z9: =Z10+Z11+Z12-Z19+Z20 -> 21.847734 | AA9: =AA10+AA11+AA12-AA19+AA20 -> 26.362695 | AB9: =AB10+AB11+AB12-AB19+AB20 -> 37.325178 | AC9: =AC10+AC11+AC12-AC19+AC20 -> 37.758071 | AE9: =+SUM([16]실적!$N$5:$P$5)/1000 -> 31.404157 | AF9: =+Q9-AE9 -> 9.9996811e-10
B10: CSM상각 | D10: CSM amortization | E10: =J10 -> 205.83148 | F10: =O10 -> 197.69092 | G10: =+IFERROR(IF(F10<0,-(E10/F10-1),(E10/F10-1)),0) -> 0.041178217 | J10: =SUM(K10:N10) -> 205.83148 | K10: 52.710967 | L10: 53.913119 | M10: 50.834694 | N10: 48.372704 | O10: =SUM(P10:S10) -> 197.69092 | P10: 48.978104 | Q10: 48.01644 | R10: 49.937282 | S10: 50.759098 | T10: =SUM(U10:X10) -> 197.76499 | U10: 49.398744 | V10: 45.96888 | W10: 50.38364 | X10: 52.01373 | Y10: =SUM(Z10:AC10) -> 213.96114 | Z10: 51.748243 | AA10: 55.251187 | AB10: 54.003419 | AC10: 52.95829
B11: RA변동 | D11: RA change | E11: =J11 -> 43.952027 | F11: =O11 -> 43.27423 | G11: =+IFERROR(IF(F11<0,-(E11/F11-1),(E11/F11-1)),0) -> 0.015662833 | J11: =SUM(K11:N11) -> 43.952027 | K11: 11.295955 | L11: 11.037654 | M11: 10.658694 | N11: 10.959724 | O11: =SUM(P11:S11) -> 43.27423 | P11: 10.643054 | Q11: 10.660785 | R11: 10.726994 | S11: 11.243396 | T11: =SUM(U11:X11) -> 46.001998 | U11: 10.844652 | V11: 11.548457 | W11: 11.578878 | X11: 12.03001 | Y11: =SUM(Z11:AC11) -> 54.918093 | Z11: 13.230891 | AA11: 13.631026 | AB11: 14.030483 | AC11: 14.025693
B12: 예실차 | D12: Expected vs. actual variance | E12: =J12 -> -0.44798281 | F12: =O12 -> -26.017888 | G12: =+IFERROR(IF(F12<0,-(E12/F12-1),(E12/F12-1)),0) -> 0.98278174 | J12: =SUM(K12:N12) -> -0.44798281 | K12: 5.8605533 | L12: -13.091038 | M12: 0.75202719 | N12: 6.0304749 | O12: =SUM(P12:S12) -> -26.017888 | P12: -2.3793017 | Q12: -1.0583873 | R12: 3.3231313 | S12: -25.903331 | T12: =SUM(U12:X12) -> -19.27512 | U12: =U13+U16 -> -4.1097882 | V12: =V13+V16 -> -7.7483366 | W12: =W13+W16 -> -5.3541183 | X12: =X13+X16 -> -2.0628764 | Y12: =SUM(Z12:AC12) -> -56.972757 | Z12: =Z13+Z16 -> -29.154516 | AA12: =AA13+AA16 -> -11.45318 | AB12: =AB13+AB16 -> -7.1739538 | AC12: =AC13+AC16 -> -9.1911083
B13: 보험금차 | D13: Claims variance | E13: =J13 -> -28.70811 | F13: =O13 -> -26.458127 | G13: =+IFERROR(IF(F13<0,-(E13/F13-1),(E13/F13-1)),0) -> -0.085039411 | J13: =SUM(K13:N13) -> -28.70811 | K13: -4.8641513 | L13: -18.945833 | M13: -4.2944346 | N13: -0.60369134 | O13: =SUM(P13:S13) -> -26.458127 | P13: -0.70005818 | Q13: -5.2922927 | R13: 2.5037454 | S13: -22.969521 | T13: =SUM(U13:X13) -> -0.85268764 | U13: =U14-U15 -> 0.073699059 | V13: =V14-V15 -> -5.9787686 | W13: =W14-W15 -> 5.6742779 | X13: =X14-X15 -> -0.62189592 | Y13: =SUM(Z13:AC13) -> -24.166026 | Z13: =Z14-Z15 -> -17.713574 | AA13: =AA14-AA15 -> -0.71338846 | AB13: =AB14-AB15 -> -6.8217579 | AC13: =AC14-AC15 -> 1.0826947
C14: 예상보험금 | D14: Expected claims | E14: =J14 -> 485.97816 | F14: =O14 -> 449.06122 | G14: =+IFERROR(IF(F14<0,-(E14/F14-1),(E14/F14-1)),0) -> 0.08220915 | J14: =SUM(K14:N14) -> 485.97816 | K14: 126.75068 | L14: 123.41308 | M14: 118.74185 | N14: 117.07254 | O14: =SUM(P14:S14) -> 449.06122 | P14: 114.65875 | Q14: 113.36898 | R14: 111.1853 | S14: 109.84818 | T14: =SUM(U14:X14) -> 435.09485 | U14: 109.13221 | V14: 110.05994 | W14: 108.55604 | X14: 107.34665 | Y14: =SUM(Z14:AC14) -> 397.23526 | Z14: 101.58025 | AA14: 100.58513 | AB14: 98.529099 | AC14: 96.540776
C15: 실제보험금 | D15: Actual claims | E15: =J15 -> 514.68627 | F15: =O15 -> 475.51935 | G15: =+IFERROR(IF(F15<0,-(E15/F15-1),(E15/F15-1)),0) -> 0.082366627 | J15: =SUM(K15:N15) -> 514.68627 | K15: 131.61483 | L15: 142.35892 | M15: 123.03629 | N15: 117.67624 | O15: =SUM(P15:S15) -> 475.51935 | P15: 115.35881 | Q15: 118.66128 | R15: 108.68156 | S15: 132.8177 | T15: =SUM(U15:X15) -> 435.94754 | U15: 109.05852 | V15: 116.03871 | W15: 102.88177 | X15: 107.96855 | Y15: =SUM(Z15:AC15) -> 421.40128 | Z15: 119.29382 | AA15: 101.29852 | AB15: 105.35086 | AC15: 95.458082
B16: 사업비차 | D16: Expences variance | E16: =J16 -> 28.260127 | F16: =O16 -> 0.44023835 | G16: =+IFERROR(IF(F16<0,-(E16/F16-1),(E16/F16-1)),0) -> 63.192789 | J16: =SUM(K16:N16) -> 28.260127 | K16: 10.724705 | L16: 5.8547948 | M16: 5.0464617 | N16: 6.6341662 | O16: =SUM(P16:S16) -> 0.44023835 | P16: -1.6792436 | Q16: 4.2339053 | R16: 0.81938591 | S16: -2.9338093 | T16: =SUM(U16:X16) -> -18.422432 | U16: -4.1834873 | V16: -1.769568 | W16: -11.028396 | X16: -1.4409805 | Y16: =SUM(Z16:AC16) -> -32.806732 | Z16: -11.440942 | AA16: -10.739791 | AB16: -0.35219592 | AC16: -10.273803
C17: 예상사업비 | D17: Expected expenses | E17: =J17 -> 191.9594 | F17: =O17 -> 155.07406 | G17: =+IFERROR(IF(F17<0,-(E17/F17-1),(E17/F17-1)),0) -> 0.23785629 | J17: =SUM(K17:N17) -> 191.9594 | K17: 50.905585 | L17: 50.106497 | M17: 44.404221 | N17: 46.543094 | O17: =SUM(P17:S17) -> 155.07406 | P17: 41.487814 | Q17: 39.928155 | R17: 36.995794 | S17: 36.662294 | T17: =SUM(U17:X17) -> 125.40551 | U17: 31.436048 | V17: 31.838062 | W17: 31.008304 | X17: 31.123091 | Y17: =SUM(Z17:AC17) -> 138.39002 | Z17: 31.421129 | AA17: 33.589997 | AB17: 34.93254 | AC17: 38.446351
C18: 실제사업비 | D18: Actual expenses | E18: =J18 -> 163.69927 | F18: =O18 -> 154.63382 | G18: =+IFERROR(IF(F18<0,-(E18/F18-1),(E18/F18-1)),0) -> 0.058625276 | J18: =SUM(K18:N18) -> 163.69927 | K18: 40.18088 | L18: 44.251702 | M18: 39.357759 | N18: 39.908928 | O18: =SUM(P18:S18) -> 154.63382 | P18: 43.167058 | Q18: 35.69425 | R18: 36.176408 | S18: 39.596103 | T18: =SUM(U18:X18) -> 143.82794 | U18: 35.619536 | V18: 33.60763 | W18: 42.0367 | X18: 32.564072 | Y18: =SUM(Z18:AC18) -> 171.19675 | Z18: 42.862071 | AA18: 44.329788 | AB18: 35.284736 | AC18: 48.720154
B19: 간접사업비 | D19: Indirect expenses | E19: =J19 -> 64.838271 | F19: =O19 -> 67.659293 | G19: =+IFERROR(IF(F19<0,-(E19/F19-1),(E19/F19-1)),0) -> -0.041694534 | J19: =SUM(K19:N19) -> 64.838271 | K19: 18.297465 | L19: 15.868745 | M19: 15.146306 | N19: 15.525754 | O19: =SUM(P19:S19) -> 67.659293 | P19: 20.71052 | Q19: 16.309096 | R19: 15.144894 | S19: 15.494783 | T19: =SUM(U19:X19) -> 67.258069 | U19: 18.946424 | V19: 15.493932 | W19: 15.04372 | X19: 17.773994 | Y19: =SUM(Z19:AC19) -> 60.105278 | Z19: 16.757573 | AA19: 14.65093 | AB19: 13.721218 | AC19: 14.975558
B20: 기타 | D20: Others | E20: =J20 -> -72.507147 | F20: =O20 -> -28.012427 | G20: =+IFERROR(IF(F20<0,-(E20/F20-1),(E20/F20-1)),0) -> -1.5883922 | J20: =SUM(K20:N20) -> -72.507147 | K20: -57.450687 | L20: -1.6817788 | M20: -2.4228399 | N20: -10.951842 | O20: =SUM(P20:S20) -> -28.012427 | P20: -16.676275 | Q20: -9.9055842 | R20: -3.1236998 | S20: 1.6931318 | T20: =SUM(U20:X20) -> 11.766963 | U20: =U9-(U10+U11+U12-U19) -> 20.207475 | V20: =V9-(V10+V11+V12-V19) -> -6.9351612 | W20: =W9-(W10+W11+W12-W19) -> -0.99698491 | X20: =X9-(X10+X11+X12-X19) -> -0.50836522 | Y20: =SUM(Z20:AC20) -> -28.507519 | Z20: 2.780688 | AA20: -16.415409 | AB20: -9.8135519 | AC20: -5.0592458
B21: 투자손익 (별도) | D21: Investment income | E21: =J21 -> 73.866157 | F21: =O21 -> -4.33664 | G21: =+IFERROR(IF(F21<0,-(E21/F21-1),(E21/F21-1)),0) -> 18.033038 | J21: =J22+J23-J24-J25+J26 -> 73.866157 | K21: =K22+K23-K24-K25+K26 -> 28.907445 | L21: =L22+L23-L24-L25+L26 -> 24.543101 | M21: =M22+M23-M24-M25+M26 -> 20.063001 | N21: =N22+N23-N24-N25+N26 -> 0.35260888 | O21: =O22+O23-O24-O25+O26 -> -4.33664 | P21: =P22+P23-P24-P25+P26 -> 33.294063 | Q21: =Q22+Q23-Q24-Q25+Q26 -> -27.967507 | ... T21: =T22+T23-T24-T25+T26 -> -22.624423 | U21: -99.003378 | V21: -0.74453509 | W21: 3.7496379 | X21: 93.769318 | Y21: =Y22+Y23-Y24-Y25+Y26 -> 27.482495 | Z21: =Z22+Z23-Z24-Z25+Z26 -> -79.301651 | AA21: =AA22+AA23-AA24-AA25+AA26 -> 46.291232 | AB21: 21.904041 | AC21: =[17]실적!$H$20/1000 -> 38.588874 | AE21: =+SUM([16]실적!$N$20:$P$20)/1000 -> -27.967507 | AF21: =+Q21-AE21 -> 2.344791e-13
B22: 보험금융수익 | D22: Insurance financial revenues | E22: =J22 -> 663.73185 | F22: =O22 -> 319.18261 | G22: =+IFERROR(IF(F22<0,-(E22/F22-1),(E22/F22-1)),0) -> 1.0794737 | J22: =SUM(K22:N22) -> 663.73185 | K22: 185.32796 | L22: 18.61685 | M22: 183.86293 | N22: 275.92411 | O22: =SUM(P22:S22) -> 319.18261 | P22: 11.835091 | Q22: 214.57859 | R22: 80.214362 | S22: 12.554571 | T22: 612.08324 | U22: 263.01093 | V22: 297.1408 | W22: 16.996267 | X22: 34.935246 | Y22: =SUM(Z22:AC22) -> 3190.7457 | Z22: 402.69771 | AA22: 491.15596 | AB22: 1188.2831 | AC22: 1108.6089
B23: 금융수익 | D23: Financial revenues | E23: =J23 -> 3105.4851 | F23: =O23 -> 4181.4642 | G23: =+IFERROR(IF(F23<0,-(E23/F23-1),(E23/F23-1)),0) -> -0.25732114 | J23: =SUM(K23:N23) -> 3105.4851 | K23: 686.45943 | L23: 869.5897 | M23: 1079.4942 | N23: 469.94175 | O23: =SUM(P23:S23) -> 4181.4642 | P23: 1179.7719 | Q23: 1117.0385 | R23: 687.66785 | S23: 1196.986 | T23: 3194.7402 | U23: 851.15006 | V23: 216.42109 | W23: 869.42072 | X23: 1257.7483 | Y23: =SUM(Z23:AC23) -> 1782.3932 | Z23: -472.99011 | AA23: 1026.227 | AB23: 789.19725 | AC23: 439.95911
B24: 보험금융비용 | D24: Insurance financial cost | E24: =J24 -> 2936.5108 | F24: =O24 -> 2393.0878 | G24: =+IFERROR(IF(F24<0,-(E24/F24-1),(E24/F24-1)),0) -> 0.22708028 | J24: =SUM(K24:N24) -> 2936.5108 | K24: 825.58452 | L24: 1056.3991 | M24: 762.45996 | N24: 292.06727 | O24: =SUM(P24:S24) -> 2393.0878 | P24: 636.38014 | Q24: 270.90059 | R24: 583.96862 | S24: 901.83841 | T24: 2954.241 | U24: 1152.9716 | V24: 280.52944 | W24: 668.20469 | X24: 852.5353 | Y24: =SUM(Z24:AC24) -> 1300.0523 | Z24: 369.46105 | AA24: 504.94702 | AB24: 161.66444 | AC24: 263.97978
B25: 금융비용 | D25: Financial cost | E25: =J25 -> 799.07009 | F25: =O25 -> 1111.2149 | G25: =+IFERROR(IF(F25<0,-(E25/F25-1),(E25/F25-1)),0) -> -0.28090409 | J25: =SUM(K25:N25) -> 799.07009 | K25: 24.681236 | L25: -191.87345 | M25: 489.54655 | N25: 476.71575 | O25: =SUM(P25:S25) -> 1111.2149 | P25: 521.15258 | Q25: 93.34089 | R25: 212.97125 | S25: 283.75018 | T25: 846.87577 | U25: 63.589762 | V25: 224.64333 | W25: 207.58647 | X25: 351.0562 | Y25: =SUM(Z25:AC25) -> 3623.8326 | Z25: -364.91801 | AA25: 991.05222 | AB25: 1745.2602 | AC25: 1252.4381
B26: 기타 | D26: Others | E26: =J26 -> 40.23008 | F26: =O26 -> -1000.6808 | G26: =+IFERROR(IF(F26<0,-(E26/F26-1),(E26/F26-1)),0) -> 1.0402027 | J26: =SUM(K26:N26) -> 40.23008 | K26: 7.385815 | L26: 0.86215113 | M26: 8.712343 | N26: 23.269771 | O26: =SUM(P26:S26) -> -1000.6808 | P26: -0.78024276 | Q26: -995.34312 | R26: -1.7638327 | S26: -2.7936539 | T26: -28.331064 | U26: -16.998481 | V26: -9.1336574 | W26: -6.876188 | X26: 4.6772627 | Y26: =SUM(Z26:AC26) -> -21.771576 | Z26: -4.4662109 | AA26: 24.907543 | AB26: -48.651672 | AC26: 6.4387643
B27: 영업외손익 (별도) | D27: Non-operating income | E27: =J27 -> 3.4005108 | F27: =O27 -> 0.88398245 | G27: =+IFERROR(IF(F27<0,-(E27/F27-1),(E27/F27-1)),0) -> 2.846808 | J27: =+J28-J29 -> 3.4005108 | K27: =+K28-K29 -> 6.0941748 | L27: =+L28-L29 -> -0.31653275 | M27: =+M28-M29 -> -1.4037297 | N27: =+N28-N29 -> -0.9734016 | O27: =+O28-O29 -> 0.88398245 | P27: =+P28-P29 -> 0.99597178 | Q27: =+Q28-Q29 -> -2.0731538 | ... AC27: =+AC28-AC29 -> -1.4611123 | AE27: =+SUM([16]실적!$N$31:$P$31)/1000 -> -2.0731538 | AF27: =+Q27-AE27 -> 0
B28: 영업외수익 | D28: Non-operating revenues | E28: =J28 -> 12.711181 | F28: =O28 -> 7.9327294 | G28: =+IFERROR(IF(F28<0,-(E28/F28-1),(E28/F28-1)),0) -> 0.6023717 | J28: =SUM(K28:N28) -> 12.711181 | K28: 8.7238049 | L28: 1.3509089 | M28: 1.1620696 | N28: 1.4743977 | O28: =SUM(P28:S28) -> 7.9327294 | P28: 1.0727003 | Q28: 1.796642 | R28: 4.3399646 | S28: 0.72342249 | T28: =SUM(U28:X28) -> 6.0782987 | U28: 1.1216141 | V28: 2.6563931 | W28: 1.2214277 | X28: 1.0788639 | Y28: =SUM(Z28:AC28) -> 6.5871177 | Z28: 2.4483538 | AA28: 1.6025223 | AB28: 1.2106017 | AC28: 1.3256399
B29: 영업외비용 | D29: Non-operating cost | E29: =J29 -> 9.3106703 | F29: =O29 -> 7.0487469 | G29: =+IFERROR(IF(F29<0,-(E29/F29-1),(E29/F29-1)),0) -> 0.32089723 | J29: =SUM(K29:N29) -> 9.3106703 | K29: 2.6296301 | L29: 1.6674416 | M29: 2.5657993 | N29: 2.4477993 | O29: =SUM(P29:S29) -> 7.0487469 | P29: 0.076728523 | Q29: 3.8697958 | R29: 0.99800953 | S29: 2.1042131 | T29: =SUM(U29:X29) -> 10.095426 | U29: 1.6530815 | V29: 3.4604996 | W29: 2.2296482 | X29: 2.7521962 | Y29: =SUM(Z29:AC29) -> 4.4525252 | Z29: -1.2882209 | AA29: 0.40593476 | AB29: 2.5480591 | AC29: 2.7867522
B30: 연결효과 | D30: Non-operating income | E30: =J30 -> 9.4527834 | F30: =O30 -> 7.3020986 | G30: =+IFERROR(IF(F30<0,-(E30/F30-1),(E30/F30-1)),0) -> 0.29452968 | J30: =SUM(K30:N30) -> 9.4527834 | K30: 5.7677116 | L30: 3.1671167 | M30: 0.41680114 | N30: 0.10115391 | O30: =SUM(P30:S30) -> 7.3020986 | P30: -0.79608152 | Q30: =0.948029486-0.007 -> 0.94102949 | R30: 2.8587536 | S30: 4.2983971 | T30: =SUM(U30:X30) -> 2.2134375 | U30: =[18]연결!$K$17/10 -> -47.277286 | V30: =+[18]연결!$I$17/10 -> 37.780914 | W30: =+[18]연결!$G$17/10 -> 9.0196165 | X30: =+[18]연결!$F$17/10 -> 2.6901924 | AE30: =+'[19]연결 (소급)'!$I$17/10 -> 0.94802949 | AF30: =+Q30-AE30 -> -0.007000001
B31: * 보험손익, 투자손익, 영업외손익은 별도 기준 | X31: IFRS 17 & 9 ◀

Sheet CSM
B1: CSM | D1: Contractual Service Margins
B2: (BN KRW, %, %p)
C5: CSM 무브먼트 | D5: CSM Movement | E5: 2025 | F5: 2024 | G5: YoY | L5: 2025 | O5: 2024 | T5: 2023 | Y5: 2022
E6: =J6 -> FY | F6: =O6 -> FY | J6: FY | K6: 4 | L6: 3 | M6: 2 | N6: 1 | O6: FY | P6: 4 | Q6: 3 | R6: 2 | S6: 1 | T6: FY | U6: Q4 | V6: Q3 | W6: Q2 | X6: Q1 | Y6: FY | Z6: Q4 | AA6: Q3 | AB6: Q2 | AC6: Q1
C7: 기시CSM | D7: Beginning CSM | E7: =N7 -> 2078.212 | F7: =S7 -> 2021.4508 | G7: =IFERROR(IF(F7<0, -(E7/F7-1), (E7/F7-1)),0) -> 0.028079443 | J7: 2078.212 | K7: 2332.9324 | L7: 2185.2269 | M7: 2084.7266 | N7: 2078.212 | O7: 2021.4508 | P7: 2065.4094 | Q7: 2090.3197 | R7: 2092.5236 | S7: 2021.4508 | T7: 1979.4946 | U7: 1943.9845 | V7: 2094.154 | W7: 2006.8573 | X7: 1979.4946 | Y7: 1983.7219 | Z7: 2151.8005 | AA7: 2087.3143 | AB7: 2019.9654 | AC7: 1983.7219
C8: 신계약CSM | D8: New business CSM | E8: =SUM(E9:E12) -> 539.87812 | F8: =SUM(F9:F12) -> 394.60483 | G8: =IFERROR(IF(F8<0, -(E8/F8-1), (E8/F8-1)),0) -> 0.36814879 | J8: 539.87812 | K8: 143.58882 | L8: 151.09433 | M8: =+SUM(M9:M12) -> 104.1558 | N8: =+SUM(N9:N12) -> 141.03917 | O8: =+SUM(O9:O12) -> 394.60483 | P8: =+SUM(P9:P12) -> 120.34869 | Q8: =+SUM(Q9:Q12) -> 101.86748 | R8: =+SUM(R9:R12) -> 76.193003 | S8: =+SUM(S9:S12) -> 96.195653 | T8: 291.84619 | U8: 80.294472 | V8: 85.409989 | W8: 68.894471 | X8: 57.247257 | Y8: 272.31826 | Z8: 56.454253 | AA8: 67.901435 | AB8: 69.880945 | AC8: 78.081629
C9: 보장성상품(일반,변액) | D9: Protection types | E9: =SUM(K9:N9) -> 471.49925 | F9: =SUM(P9:S9) -> 341.50019 | G9: =IFERROR(IF(F9<0, -(E9/F9-1), (E9/F9-1)),0) -> 0.38067053 | J9: 471.49925 | K9: 125.68081 | L9: 129.03724 | M9: 91.345473 | N9: 125.43573 | O9: =SUM(P9:S9) -> 341.50019 | P9: 103.89156 | Q9: 89.631877 | R9: 63.741162 | S9: 84.235589 | T9: 279.72142 | U9: 76.713553 | V9: 81.291891 | W9: 66.472176 | X9: 55.243796 | Y9: 241.29919 | Z9: 53.210825 | AA9: 62.839092 | AB9: 62.786996 | AC9: 62.462281
C10: 일반저축성 | D10: Non-unit-linked savings types | E10: =SUM(K10:N10) -> 0.23192137 | F10: =SUM(P10:S10) -> 0.64306448 | G10: =IFERROR(IF(F10<0, -(E10/F10-1), (E10/F10-1)),0) -> -0.63934973 | J10: 0.23192137 | K10: 0.037562016 | L10: 0.031405817 | M10: 0.10404697 | N10: 0.058906575 | O10: =SUM(P10:S10) -> 0.64306448 | P10: 0.049737348 | Q10: 0.22836558 | R10: 0.19400902 | S10: 0.17095252 | T10: 0.20430715 | U10: 0 | V10: 0.079243644 | W10: 0.10252409 | X10: 0.022539423 | Y10: 0.020526694 | Z10: 0 | AA10: 0 | AB10: 0 | AC10: 0.020526694
C11: 변액저축성 | D11: Unit-linked savings types | E11: =SUM(K11:N11) -> 64.334014 | F11: =SUM(P11:S11) -> 52.461571 | G11: =IFERROR(IF(F11<0, -(E11/F11-1), (E11/F11-1)),0) -> 0.22630743 | J11: 64.334014 | K11: 17.030451 | L11: 20.486036 | M11: 11.272991 | N11: 15.544537 | O11: =SUM(P11:S11) -> 52.461571 | P11: 16.407393 | Q11: 12.007234 | R11: 12.257833 | S11: 11.789111 | T11: 11.920465 | U11: 3.5809192 | V11: 4.0388535 | W11: 2.3197708 | X11: 1.9809216 | Y11: 30.99854 | Z11: 3.2434277 | AA11: 5.0623425 | AB11: 7.0939489 | AC11: 15.598821
C12: 기타 | D12: Others | E12: =SUM(K12:N12) -> 3.8129312 | F12: =SUM(P12:S12) -> 0 | G12: =IFERROR(IF(F12<0, -(E12/F12-1), (E12/F12-1)),0) -> 0 | J12: 3.8129312 | K12: 0.83999332 | L12: 1.5396473 | M12: 1.4332906 | N12: 0 | O12: 0 | P12: 0 | Q12: 0 | R12: 0 | S12: 0
C13: 이자비용 | D13: Interest expeses | E13: =SUM(K13:N13) -> 60.657923 | F13: =SUM(P13:S13) -> 51.398245 | G13: =IFERROR(IF(F13<0, -(E13/F13-1), (E13/F13-1)),0) -> 0.18015554 | J13: 60.657923 | K13: 15.789385 | L13: 15.291674 | M13: 14.872392 | N13: 14.704472 | O13: =SUM(P13:S13) -> 51.398245 | P13: 13.930687 | Q13: 13.135544 | R13: 12.508063 | S13: 11.823951 | T13: 45.451336 | U13: 11.600474 | V13: 11.722314 | W13: 10.528034 | X13: 11.600513 | Y13: 37.0305 | Z13: 10.947225 | AA13: 9.9997367 | AB13: 8.8037195 | AC13: 7.2798189
C14: 가정변경 등 | D14: Assumptions change, etc | E14: =SUM(K14:N14) -> -414.4935 | F14: =SUM(P14:S14) -> -191.55093 | G14: =IFERROR(IF(F14<0, -(E14/F14-1), (E14/F14-1)),0) -> -1.1638814 | J14: -414.4935 | K14: -381.17651 | L14: 35.23259 | M14: 32.306788 | N14: -100.85637 | O14: =SUM(P14:S14) -> -191.55093 | P14: -72.498668 | Q14: -91.896827 | R14: -40.967672 | S14: 13.812235 | T14: -97.576283 | U14: 34.97012 | V14: -201.33289 | W14: 58.257818 | X14: 10.528672 | Y14: -99.61496 | Z14: -187.95913 | AA14: 41.836137 | AB14: 42.667752 | AC14: 3.8402793
C15: CSM상각 | D15: CSM amortization | E15: =SUM(K15:N15) -> -205.83148 | F15: =SUM(P15:S15) -> -197.69092 | G15: =IFERROR(IF(F15<0, -(E15/F15-1), (E15/F15-1)),0) -> -0.041178217 | J15: -205.83148 | K15: -52.710967 | L15: -53.913119 | M15: -50.834694 | N15: -48.372704 | O15: =SUM(P15:S15) -> -197.69092 | P15: -48.978104 | Q15: -48.01644 | R15: -49.937282 | S15: -50.759098 | T15: -197.76499 | U15: -49.398744 | V15: -45.96888 | W15: -50.38364 | X15: -52.01373 | Y15: -213.96114 | Z15: -51.748243 | AA15: -55.251187 | AB15: -54.003419 | AC15: -52.95829
C16: 기말CSM | D16: Ending CSM | E16: =E7+E8+E13+E14+E15 -> 2058.4231 | F16: =F7+F8+F13+F14+F15 -> 2078.212 | G16: =IFERROR(IF(F16<0, -(E16/F16-1), (E16/F16-1)),0) -> -0.0095221029 | J16: 2058.4231 | K16: 2058.4231 | L16: 2332.9324 | M16: =M7+M8+M13+M14+M15 -> 2185.2269 | N16: =N7+N8+N13+N14+N15 -> 2084.7266 | O16: =O7+O8+O13+O14+O15 -> 2078.212 | P16: =P7+P8+P13+P14+P15 -> 2078.212 | Q16: =Q7+Q8+Q13+Q14+Q15 -> 2065.4094 | R16: =R7+R8+R13+R14+R15 -> 2090.3197 | S16: =S7+S8+S13+S14+S15 -> 2092.5236 | T16: =T7+T8+T13+T14+T15 -> 2021.4508 | ... X16: =X7+X8+X13+X14+X15 -> 2006.8573 | Y16: 1979.4946 | Z16: 1979.4946 | AA16: 2151.8005 | AB16: 2087.3143 | AC16: 2019.9654
C17: 상각률 | D17: Amortization rate | E17: =-E15/SUM(E7,E8,E13,E14) -> 0.090904745 | F17: =-F15/SUM(F7,F8,F13,F14) -> 0.086862633 | G17: =IFERROR(IF(F17<0, -(E17/F17-1), (E17/F17-1)),0) -> 0.046534527 | J17: 0.090904745 | K17: 0.099872325 | L17: =-L15/SUM(L7,L8,L13,L14)*4/1 -> 0.090350412 | M17: =-M15/SUM(M7,M8,M13,M14)*4/1 -> 0.090936123 | N17: =-N15/SUM(N7,N8,N13,N14)*4/1 -> 0.09070877 | O17: =-O15/SUM(O7,O8,O13,O14) -> 0.086862633 | P17: =-P15/SUM(P7,P8,P13,P14)*4 -> 0.092099156 | Q17: =-Q15/SUM(Q7,Q8,Q13,Q14)*4/1 -> 0.090878872 | R17: =-R15/SUM(R7,R8,R13,R14)*4/1 -> 0.093329508 | S17: =-S15/SUM(S7,S8,S13,S14)*4/1 -> 0.094731504 | T17: =+U17 -> 0.11881975 | U17: =-SUM(U15:X15) /SUM(X7,SUM(U8:X8),SUM(U13:X13),SUM(U14:X14)) *4/3 -> 0.11881975 | V17: =-SUM(V15:X15) /SUM(X7,SUM(V8:X8),SUM(V13:X13),SUM(V14:X14)) *4/3 -> 0.094545174 | W17: =-SUM(W15:X15)/SUM(X7,SUM(W8:X8),SUM(W13:X13),SUM(W14:X14))*4/2 -> 0.09323467 | X17: =-X15/SUM(X7,X8,X13,X14)*4/1 -> 0.10105292 | Y17: =-Y15/SUM(AC7,Y8,Y13,Y14,Y15)*4/4 -> 0.10808877 | Z17: =-SUM(Z15:AC15) /SUM(AC7,SUM(Z8:AC8),SUM(Z13:AC13),SUM(Z14:AC14)) *4/3 -> 0.1300603 | AA17: =-SUM(AA15:AC15)/SUM(AC7,AA8:AC8,AA13:AC13,AA14:AC14)*4/3 -> 0.093466989 | AB17: =-SUM(AB15:AC15)/SUM(AC7,AB8:AC8,AB13:AC13,AB14:AC14)*4/1 -> 0.19498314 | AC17: =-AC15/SUM(AC7,AC13,AC14) -> 0.026547611
C18: CSM순증 | D18: CSM net increase | E18: =E16-E7 -> -19.788949 | F18: =F16-F7 -> 56.761214 | G18: =IFERROR(IF(F18<0, -(E18/F18-1), (E18/F18-1)),0) -> -1.3486351 | J18: -19.788919 | K18: -274.50927 | L18: =L16-L7 -> 147.70547 | M18: =M16-M7 -> 100.50029 | N18: =N16-N7 -> 6.5145666 | O18: =O16-O7 -> 56.761214 | P18: =P16-P7 -> 12.802608 | Q18: =+Q16-Q7 -> -24.910247 | R18: =+R16-R7 -> -2.2038883 | S18: =+S16-S7 -> 71.072741 | T18: =+T16-T7 -> 41.956247 | U18: =+U16-U7 -> 77.466322 | V18: =+V16-V7 -> -150.16947 | W18: =+W16-W7 -> 87.296682 | X18: =+X16-X7 -> 27.362713 | ... AC18: =+AC16-AC7 -> 36.243436
C19: ▶ 상각률 산출은 당사 기준에 따름 | J19: =J16/J7-1 -> -0.0095220884
C20: Amortization rate calculated in line with internal guideline
C21: ▶ 기타: 보증형 IRP 포함
C22: Others: including IRP with guarantees
O24: =E27/P27-1 -> -0.0095221028
C25: CSM 구성현황 | D25: CSM Composition | E25: =E5 -> 2025 | F25: =F5 -> 2024 | G25: YoY | L25: 2025 | O25: 2024 | T25: 2023 | Y25: 2022
E26: =E6 -> FY | F26: =F6 -> FY | J26: FY | K26: Q4 | L26: Q3 | M26: Q2 | N26: Q1 | O26: FY | P26: Q4 | Q26: Q3 | R26: Q2 | S26: Q1 | T26: FY | U26: Q4 | V26: Q3 | W26: Q2 | X26: Q1 | Y26: FY | Z26: Q4 | AA26: Q3 | AB26: Q2 | AC26: Q1
C27: 보유CSM | D27: Remaining CSM | E27: =K27 -> 2058.4231 | F27: =SUM(F28:F33) -> 2078.2121 | G27: =IFERROR(IF(F27<0, -(E27/F27-1), (E27/F27-1)),0) -> -0.0095221028 | J27: =SUM(J28:J33) -> 2058.4231 | K27: =SUM(K28:K33) -> 2058.4231 | L27: =SUM(L28:L33) -> 2332.9324 | M27: =SUM(M28:M33) -> 2185.2269 | N27: =SUM(N28:N33) -> 2084.7266 | O27: =SUM(O28:O33) -> 2078.2121 | P27: =SUM(P28:P33) -> 2078.2121 | Q27: =SUM(Q28:Q33) -> 2065.4095 | ... U27: =SUM(U28:U33) -> 2021.4509 | V27: 1943.9845 | W27: =SUM(W28:W33) -> 2094.154 | X27: =SUM(X28:X33) -> 2006.8573 | Y27: =SUM(Y28:Y33) -> 1979.4946 | Z27: =SUM(Z28:Z33) -> 1979.4946 | AA27: 2151.8005 | AB27: =SUM(AB28:AB33) -> 2087.3143 | AC27: =SUM(AC28:AC33) -> 2019.9654
C28: 사망 | D28: Death | E28: =+K28 -> 408.59124 | F28: =+P28 -> 602.26124 | G28: =IFERROR(IF(F28<0, -(E28/F28-1), (E28/F28-1)),0) -> -0.32157142 | J28: 408.59124 | K28: 408.59124 | L28: 568.25814 | M28: 573.35063 | N28: 583.42947 | O28: 602.26124 | P28: 602.26124 | Q28: 763.53889 | R28: 768.96442 | S28: 762.55256 | T28: 756.0217 | U28: 756.0217 | V28: 738.78305 | W28: 716.18978 | X28: 707.51622 | Y28: 713.68931 | Z28: 713.68931 | AA28: 726.74594 | AB28: 701.18969 | AC28: 672.47367 | AD28: =E28/$E$27 -> 0.19849721
C29: 건강 | D29: Health | E29: =+K29 -> 942.95824 | F29: =+P29 -> 883.68816 | G29: =IFERROR(IF(F29<0, -(E29/F29-1), (E29/F29-1)),0) -> 0.067071257 | J29: 942.95824 | K29: 942.95824 | L29: 1085.9013 | M29: 1005.736 | N29: 951.27284 | O29: 883.68816 | P29: 883.68816 | Q29: 712.76677 | R29: 654.59635 | S29: 624.57346 | T29: 578.15772 | U29: 578.15772 | V29: 590.07979 | W29: 669.31332 | X29: 625.95036 | Y29: 595.48618 | Z29: 595.48618 | AA29: 714.65198 | AB29: 696.7429 | AC29: 665.1755 | AD29: =E29/$E$27 -> 0.45809738
C30: 변액사망 | D30: Variable death | E30: =+K30 -> 174.76565 | F30: =+P30 -> 183.67958 | G30: =IFERROR(IF(F30<0, -(E30/F30-1), (E30/F30-1)),0) -> -0.048529788 | J30: 174.76565 | K30: 174.76565 | L30: 206.08765 | M30: 174.37167 | N30: 140.62736 | O30: 183.67958 | P30: 183.67958 | Q30: 155.0502 | R30: 202.23676 | S30: 217.06406 | T30: 213.11181 | U30: 213.11181 | V30: 265.13088 | W30: 303.90983 | X30: 278.76016 | Y30: 286.36724 | Z30: 286.36724 | AA30: 330.1186 | AB30: 333.90001 | AC30: 323.03832 | AD30: =E30/$E$27 -> 0.084902686
C31: 변액저축 | D31: Unit-linked savings | E31: =+K31 -> 348.68903 | F31: =+P31 -> 203.55037 | G31: =IFERROR(IF(F31<0, -(E31/F31-1), (E31/F31-1)),0) -> 0.71303561 | J31: 348.68903 | K31: 348.68903 | L31: 276.14947 | M31: 233.07716 | N31: 204.28099 | O31: 203.55037 | P31: 203.55037 | Q31: 235.23478 | R31: 261.26777 | S31: 276.89685 | T31: 260.98463 | U31: 260.98463 | V31: 107.66042 | W31: 154.79302 | X31: 137.40957 | Y31: 119.05977 | Z31: 119.05977 | AA31: 148.22436 | AB31: 163.99094 | AC31: 213.0452 | AD31: =E31/$E$27 -> 0.16939619
C32: 일반저축 | D32: Non-unit-linked savings | E32: =+K32 -> 180.22532 | F32: =+P32 -> 204.38387 | G32: =IFERROR(IF(F32<0, -(E32/F32-1), (E32/F32-1)),0) -> -0.11820187 | J32: 180.22532 | K32: 180.22532 | L32: 192.92777 | M32: 196.58704 | N32: 204.46157 | O32: 204.38387 | P32: 204.38387 | Q32: 197.92297 | R32: 202.33342 | S32: 210.52155 | T32: 212.26519 | U32: 212.26519 | V32: 241.71994 | W32: 249.47349 | X32: 256.80166 | Y32: 264.66252 | Z32: 264.66252 | AA32: 231.51985 | AB32: 191.21984 | AC32: 146.11745 | AD32: =E32/$E$27 -> 0.087555038
C33: 기타 | D33: Others | E33: =+K33 -> 3.193643 | F33: =+P33 -> 0.64883932 | G33: =IFERROR(IF(F33<0, -(E33/F33-1), (E33/F33-1)),0) -> 3.9220862 | J33: 3.193643 | K33: 3.193643 | L33: 3.6080793 | M33: 2.1044073 | N33: 0.65440511 | O33: 0.64883932 | P33: 0.64883932 | Q33: 0.89584916 | R33: 0.92097642 | S33: 0.91511213 | T33: 0.90980762 | U33: 0.90980762 | V33: 0.61045004 | W33: 0.47455975 | X33: 0.41933234 | Y33: 0.22955306 | Z33: 0.22955306 | AA33: 0.53974135 | AB33: 0.27097311 | AC33: 0.11521561 | AD33: =E33/$E$27 -> 0.0015514998
C35: 신계약CSM | D35: New business CSM | E35: =SUM(E36:E41) -> 539.87812 | F35: =SUM(F36:F41) -> 394.60483 | G35: =IFERROR(IF(F35<0, -(E35/F35-1), (E35/F35-1)),0) -> 0.36814879 | J35: =SUM(J36:J41) -> 539.87812 | K35: =SUM(K36:K41) -> 143.58882 | L35: =SUM(L36:L41) -> 151.09433 | M35: =SUM(M36:M41) -> 104.1558 | N35: =SUM(N36:N41) -> 141.03917 | O35: =SUM(O36:O41) -> 394.60483 | P35: =SUM(P36:P41) -> 120.34869 | Q35: =SUM(Q36:Q41) -> 101.86748 | ... U35: =SUM(U36:U41) -> 80.294472 | V35: 85.409989 | W35: =SUM(W36:W41) -> 68.894471 | X35: =SUM(X36:X41) -> 57.247257 | Y35: =SUM(Y36:Y41) -> 272.31826 | Z35: =SUM(Z36:Z41) -> 56.454253 | AA35: 67.901435 | AB35: =SUM(AB36:AB41) -> 69.880945 | AC35: =SUM(AC36:AC41) -> 78.081629
C36: 사망 | D36: Death | E36: =SUM(K36:N36) -> 24.144122 | F36: =SUM(P36:S36) -> 92.059262 | G36: =IFERROR(IF(F36<0, -(E36/F36-1), (E36/F36-1)),0) -> -0.73773284 | J36: 24.144122 | K36: 6.3860294 | L36: 7.2167633 | M36: 4.2094865 | N36: 6.3318423 | O36: 92.059262 | P36: 16.130321 | Q36: 19.233053 | R36: 26.982352 | S36: 29.713536 | T36: 132.97594 | U36: 41.67453 | V36: 43.669784 | W36: 26.984018 | X36: 20.647606 | Y36: 87.268441 | Z36: 22.485 | AA36: 25.187585 | AB36: 23.663085 | AC36: 15.93277
C37: 건강 | D37: Health | E37: =SUM(K37:N37) -> 429.25027 | F37: =SUM(P37:S37) -> 231.73579 | G37: =IFERROR(IF(F37<0, -(E37/F37-1), (E37/F37-1)),0) -> 0.85232615 | J37: 429.25027 | K37: 113.89705 | L37: 116.78753 | M37: 83.398475 | N37: 115.16722 | O37: 231.73579 | P37: 82.428985 | Q37: 65.297471 | R37: 32.723915 | S37: 51.285421 | T37: 127.23411 | U37: 31.630754 | V37: 33.72636 | W37: 33.749301 | X37: 28.127695 | Y37: 104.75717 | Z37: 21.614978 | AA37: 27.016756 | AB37: 26.440715 | AC37: 29.684718
C38: 변액사망 | D38: Unit-linked death | E38: =SUM(K38:N38) -> 18.10486 | F38: =SUM(P38:S38) -> 17.705137 | G38: =IFERROR(IF(F38<0, -(E38/F38-1), (E38/F38-1)),0) -> 0.022576681 | J38: 18.10486 | K38: 5.3977359 | L38: 5.0329469 | M38: 3.7375115 | N38: 3.9366655 | O38: 17.705137 | P38: 5.3322568 | Q38: 5.1013527 | R38: 4.0348949 | S38: 3.2366322 | T38: 19.511369 | U38: 3.408269 | V38: 3.8957474 | W38: 5.7388571 | X38: 6.4684956 | Y38: 49.273587 | Z38: 9.1108475 | AA38: 10.634751 | AB38: 12.683196 | AC38: 16.844793
C39: 변액저축 | D39: Unit-linked savings | E39: =SUM(K39:N39) -> 64.334014 | F39: =SUM(P39:S39) -> 52.461571 | G39: =IFERROR(IF(F39<0, -(E39/F39-1), (E39/F39-1)),0) -> 0.22630743 | J39: 64.334014 | K39: 17.030451 | L39: 20.486036 | M39: 11.272991 | N39: 15.544537 | O39: 52.461571 | P39: 16.407393 | Q39: 12.007234 | R39: 12.257833 | S39: 11.789111 | T39: 11.920465 | U39: 3.5809192 | V39: 4.0388535 | W39: 2.3197708 | X39: 1.9809216 | Y39: 30.99854 | Z39: 3.2434277 | AA39: 5.0623425 | AB39: 7.0939489 | AC39: 15.598821
C40: 일반저축 | D40: Non-unit-linked savings | E40: =SUM(K40:N40) -> 0.23192137 | F40: =SUM(P40:S40) -> 0.64306448 | G40: =IFERROR(IF(F40<0, -(E40/F40-1), (E40/F40-1)),0) -> -0.63934973 | J40: 0.23192137 | K40: 0.037562016 | L40: 0.031405817 | M40: 0.10404697 | N40: 0.058906575 | O40: 0.64306448 | P40: 0.049737348 | Q40: 0.22836558 | R40: 0.19400902 | S40: 0.17095252 | T40: 0.20430715 | U40: 0 | V40: 0.079243644 | W40: 0.10252409 | X40: 0.022539423 | Y40: 0.020526694 | Z40: 0 | AA40: 0 | AB40: 0 | AC40: 0.020526694
C41: 기타 | D41: Others | E41: =SUM(K41:N41) -> 3.8129312 | F41: =SUM(P41:S41) -> 0 | G41: =IFERROR(IF(F41<0, -(E41/F41-1), (E41/F41-1)),0) -> 0 | J41: 3.8129312 | K41: 0.83999332 | L41: 1.5396473 | M41: 1.4332906 | N41: 0 | O41: 0 | P41: 0 | Q41: 0 | R41: 0 | S41: 0 | T41: 0 | U41: 0 | V41: 0 | W41: 0 | X41: 0 | Y41: 0 | Z41: 0 | AA41: 0 | AB41: 0 | AC41: 0

Sheet PREMIUM
B1: =[6]INDEX!G13 -> 수입보험료 | C1: Gross Written Premiums
B2: (BN KRW, %, %p)
B4: 수입보험료 | C4: Premium Income | D4: =U4 -> 2025 | G4: =AD4 -> 2024 | J4: YoY | U4: 2025 | AD4: 2024 | AS4: 2023 | BH4: 2022
D5: =O5 -> FY | G5: =AD5 -> FY | O5: FY | R5: Q4 | U5: Q3 | X5: Q2 | AA5: Q1 | AD5: FY | AG5: Q4 | AJ5: Q3 | AM5: Q2 | AP5: Q1 | AS5: FY | AV5: Q4 | AY5: Q3 | BB5: Q2 | BE5: Q1 | BH5: 22FY | BK5: Q4 | BN5: Q3 | BQ5: Q2 | BT5: Q1
D6: 일반 General | E6: 특별 Separate | F6: 합계 Total | G6: 일반 General | H6: 특별 Separate | I6: 합계 Total | J6: 일반 General | K6: 특별 Separate | L6: 합계 Total | O6: 일반 General | P6: 특별 Separate | Q6: 합계 Total | R6: 일반 General | S6: 특별 Separate | T6: 합계 Total | U6: 일반 General | V6: 특별 Separate | W6: 합계 Total | X6: 일반 General | Y6: 특별 Separate | Z6: 합계 Total | AA6: 일반 General | AB6: 특별 Separate | AC6: 합계 Total | AD6: 일반 General | AE6: 특별 Separate | AF6: 합계 Total | AG6: 일반 General | AH6: 특별 Separate | AI6: 합계 Total | AJ6: 일반 General | AK6: 특별 Separate | AL6: 합계 Total | AM6: 일반 General | AN6: 특별 Separate | AO6: 합계 Total | AP6: 일반 General | AQ6: 특별 Separate | AR6: 합계 Total | AS6: 일반 General | AT6: 특별 Separate | AU6: 합계 Total | AV6: 일반 General | AW6: 특별 Separate | AX6: 합계 Total | AY6: 일반 General | AZ6: 특별 Separate | BA6: 합계 Total | BB6: 일반 General | BC6: 특별 Separate | BD6: 합계 Total | BE6: 일반 General | BF6: 특별 Separate | BG6: 합계 Total | BH6: 일반 General | BI6: 특별 Separate | BJ6: 합계 Total | BK6: 일반 General | BL6: 특별 Separate | BM6: 합계 Total | BN6: 일반 General | BO6: 특별 Separate | BP6: 합계 Total | BQ6: 일반 General | BR6: 특별 Separate | BS6: 합계 Total | BT6: 일반 General | BU6: 특별 Separate | BV6: 합계 Total
B7: 개인보험 | C7: Individual | D7: =SUM(D8,D12,D15) -> 1622.0583 | E7: =E8+E12+E15 -> 2372.9175 | F7: =D7+E7 -> 3994.9758 | G7: =SUM(G8,G12,G15) -> 1557.1112 | H7: =H8+H12+H15 -> 1761.5118 | I7: =G7+H7 -> 3318.623 | J7: =+IFERROR(IF(G7<0,-(D7/G7-1),(D7/G7-1)),0) -> 0.041709982 | K7: =+IFERROR(IF(H7<0,-(E7/H7-1),(E7/H7-1)),0) -> 0.34709146 | L7: =+IFERROR(IF(I7<0,-(F7/I7-1),(F7/I7-1)),0) -> 0.20380524 | O7: 1622.0583 | P7: 2372.9175 | Q7: =O7+P7 -> 3994.9758 | R7: 416.80244 | S7: 665.29836 | T7: =R7+S7 -> 1082.1008 | U7: =U8+U12+U15 -> 409.15469 | V7: =V8+V12+V15 -> 699.22767 | W7: =U7+V7 -> 1108.3824 | X7: =X8+X12+X15 -> 397.50622 | Y7: =Y8+Y12+Y15 -> 451.54081 | Z7: =X7+Y7 -> 849.04703 | AA7: =AA8+AA12+AA15 -> 398.59496 | AB7: =AB8+AB12+AB15 -> 556.85067 | AC7: =AA7+AB7 -> 955.44563 | AD7: =AD8+AD12+AD15 -> 1557.1112 | AE7: =AE8+AE12+AE15 -> 1761.5118 | AF7: =AD7+AE7 -> 3318.623 | AG7: =AG8+AG12+AG15 -> 395.9223 | AH7: =AH8+AH12+AH15 -> 505.23043 | AI7: =AG7+AH7 -> 901.15272 | AJ7: =AJ8+AJ12+AJ15 -> 387.76808 | AK7: =AK8+AK12+AK15 -> 455.83478 | AL7: =AJ7+AK7 -> 843.60285 | AM7: =AM8+AM12+AM15 -> 388.55788 | AN7: =AN8+AN12+AN15 -> 400.64807 | AO7: =AM7+AN7 -> 789.20595 | AP7: =AP8+AP12+AP15 -> 384.86298 | AQ7: =AQ8+AQ12+AQ15 -> 399.79853 | AR7: =AP7+AQ7 -> 784.66151 | AS7: =AS8+AS12+AS15 -> 1540.4088 | AT7: =AT8+AT12+AT15 -> 1303.6975 | AU7: =AS7+AT7 -> 2844.1062 | AV7: =AV8+AV12+AV15 -> 387.28431 | AW7: =AW8+AW12+AW15 -> 322.01345 | AX7: =AV7+AW7 -> 709.29777 | AY7: =AY8+AY12+AY15 -> 383.4467 | AZ7: =AZ8+AZ12+AZ15 -> 346.29634 | BA7: =AY7+AZ7 -> 729.74304 | BB7: =BB8+BB12+BB15 -> 382.76731 | BC7: =BC8+BC12+BC15 -> 318.07512 | BD7: =BB7+BC7 -> 700.84243 | BE7: =BE8+BE12+BE15 -> 386.91044 | BF7: =BF8+BF12+BF15 -> 317.31255 | BG7: =BE7+BF7 -> 704.22299 | BH7: =BH8+BH12+BH15 -> 1633.6567 | BI7: =BI8+BI12+BI15 -> 1663.4779 | BJ7: =BH7+BI7 -> 3297.1346 | BK7: =BK8+BK12+BK15 -> 399.50828 | BL7: =BL8+BL12+BL15 -> 333.51338 | BM7: =BK7+BL7 -> 733.02166 | BN7: =BN8+BN12+BN15 -> 404.60765 | BO7: =BO8+BO12+BO15 -> 370.48826 | BP7: =BN7+BO7 -> 775.09591 | BQ7: =BQ8+BQ12+BQ15 -> 408.23945 | BR7: =BR8+BR12+BR15 -> 409.36294 | BS7: =BQ7+BR7 -> 817.60239 | BT7: =BT8+BT12+BT15 -> 421.30128 | BU7: =BU8+BU12+BU15 -> 550.11332 | BV7: =BT7+BU7 -> 971.41461
B8: 보장성보험 | C8: Protections | D8: =SUM(D9:D11) -> 1509.4713 | E8: =SUM(E9:E11) -> 294.89586 | F8: =D8+E8 -> 1804.3672 | G8: =SUM(G9:G11) -> 1412.9266 | H8: =SUM(H9:H11) -> 300.91364 | I8: =G8+H8 -> 1713.8402 | J8: =+IFERROR(IF(G8<0,-(D8/G8-1),(D8/G8-1)),0) -> 0.068329622 | K8: =+IFERROR(IF(H8<0,-(E8/H8-1),(E8/H8-1)),0) -> -0.019998357 | L8: =+IFERROR(IF(I8<0,-(F8/I8-1),(F8/I8-1)),0) -> 0.052821121 | O8: 1509.4713 | P8: 294.89586 | Q8: =O8+P8 -> 1804.3672 | R8: 389.46829 | S8: 74.289382 | T8: =R8+S8 -> 463.75767 | U8: 380.51267 | V8: 74.034433 | W8: =U8+V8 -> 454.5471 | X8: =SUM(X9:X11) -> 371.8002 | Y8: =SUM(Y9:Y11) -> 72.835474 | Z8: =X8+Y8 -> 444.63567 | AA8: =SUM(AA9:AA11) -> 367.69017 | AB8: =SUM(AB9:AB11) -> 73.736573 | AC8: =AA8+AB8 -> 441.42674 | AD8: =SUM(AD9:AD11) -> 1412.9266 | AE8: =SUM(AE9:AE11) -> 300.91364 | AF8: =AD8+AE8 -> 1713.8402 | AG8: =SUM(AG9:AG11) -> 362.39424 | AH8: =SUM(AH9:AH11) -> 74.04131 | AI8: =AG8+AH8 -> 436.43555 | AJ8: =SUM(AJ9:AJ11) -> 355.36849 | AK8: =SUM(AK9:AK11) -> 74.966111 | AL8: =AJ8+AK8 -> 430.3346 | AM8: =SUM(AM9:AM11) -> 349.48904 | AN8: =SUM(AN9:AN11) -> 75.454581 | AO8: =AM8+AN8 -> 424.94362 | AP8: =SUM(AP9:AP11) -> 345.67481 | AQ8: =SUM(AQ9:AQ11) -> 76.451639 | AR8: =AP8+AQ8 -> 422.12645 | AS8: =SUM(AS9:AS11) -> 1360.656 | AT8: =SUM(AT9:AT11) -> 324.86105 | AU8: =AS8+AT8 -> 1685.5171 | AV8: =SUM(AV9:AV11) -> 342.49484 | AW8: =SUM(AW9:AW11) -> 77.698791 | AX8: =AV8+AW8 -> 420.19363 | AY8: =SUM(AY9:AY11) -> 340.77879 | AZ8: =SUM(AZ9:AZ11) -> 79.831597 | BA8: =AY8+AZ8 -> 420.61039 | BB8: =SUM(BB9:BB11) -> 338.02064 | BC8: =SUM(BC9:BC11) -> 82.531167 | BD8: =BB8+BC8 -> 420.55181 | BE8: =SUM(BE9:BE11) -> 339.36174 | BF8: =SUM(BF9:BF11) -> 84.799497 | BG8: =BE8+BF8 -> 424.16123 | BH8: =SUM(BH9:BH11) -> 1380.4006 | BI8: =SUM(BI9:BI11) -> 367.86187 | BJ8: =BH8+BI8 -> 1748.2625 | BK8: =SUM(BK9:BK11) -> 343.59695 | BL8: =SUM(BL9:BL11) -> 88.597827 | BM8: =BK8+BL8 -> 432.19478 | BN8: =SUM(BN9:BN11) -> 345.8707 | BO8: =SUM(BO9:BO11) -> 90.803185 | BP8: =BN8+BO8 -> 436.67389 | BQ8: =SUM(BQ9:BQ11) -> 345.12579 | BR8: =SUM(BR9:BR11) -> 92.807601 | BS8: =BQ8+BR8 -> 437.93339 | BT8: =SUM(BT9:BT11) -> 345.80719 | BU8: =SUM(BU9:BU11) -> 95.653253 | BV8: =BT8+BU8 -> 441.46044
B9: 일반종신/CI | C9: General whole life | D9: =SUM(X9,AA9,U9,R9) -> 588.37123 | E9: =SUM(Y9,AB9,V9,S9) -> 0 | F9: =D9+E9 -> 588.37123 | G9: =SUM(AM9,AP9,AJ9,AG9) -> 613.0479 | H9: =SUM(AN9,AQ9,AK9,AH9) -> 0 | I9: =G9+H9 -> 613.0479 | J9: =+IFERROR(IF(G9<0,-(D9/G9-1),(D9/G9-1)),0) -> -0.040252429 | K9: =+IFERROR(IF(H9<0,-(E9/H9-1),(E9/H9-1)),0) -> 0 | L9: =+IFERROR(IF(I9<0,-(F9/I9-1),(F9/I9-1)),0) -> -0.040252429 | O9: 588.37123 | P9: 0 | Q9: =O9+P9 -> 588.37123 | R9: 143.94566 | S9: 0 | T9: =R9+S9 -> 143.94566 | U9: 146.25224 | V9: 0 | W9: =U9+V9 -> 146.25224 | X9: 147.831 | Y9: 0 | Z9: =X9+Y9 -> 147.831 | AA9: 150.34233 | AB9: 0 | AC9: =AA9+AB9 -> 150.34233 | AD9: =+AG9+AJ9+AM9+AP9 -> 613.0479 | AE9: =+AH9+AK9+AN9+AQ9 -> 0 | AF9: =AD9+AE9 -> 613.0479 | AG9: 152.04431 | AH9: 0 | AI9: =AG9+AH9 -> 152.04431 | AJ9: 153.15094 | AK9: 0 | AL9: =AJ9+AK9 -> 153.15094 | AM9: 153.5013 | AN9: 0 | AO9: =AM9+AN9 -> 153.5013 | AP9: 154.35134 | AQ9: 0 | AR9: =AP9+AQ9 -> 154.35134 | AS9: 616.10789 | AT9: 0 | AU9: =AS9+AT9 -> 616.10789 | AV9: 155.00521 | AW9: 0 | AX9: =AV9+AW9 -> 155.00521 | AY9: 154.10116 | AZ9: 0 | BA9: =AY9+AZ9 -> 154.10116 | BB9: 152.97367 | BC9: 0 | BD9: =BB9+BC9 -> 152.97367 | BE9: 154.02786 | BF9: 0 | BG9: =BE9+BF9 -> 154.02786 | BH9: =SUM(BK9,BN9,BQ9,BT9) -> 637.47002 | BI9: =SUM(BL9,BO9,BR9,BU9) -> 0 | BJ9: =BH9+BI9 -> 637.47002 | BK9: 156.80006 | BL9: 0 | BM9: =BK9+BL9 -> 156.80006 | BN9: 158.84474 | BO9: 0 | BP9: =BN9+BO9 -> 158.84474 | BQ9: 159.81601 | BR9: 0 | BS9: =BQ9+BR9 -> 159.81601 | BT9: 162.00921 | BU9: 0 | BV9: =BT9+BU9 -> 162.00921
B10: 변액종신/CI | C10: Variable whole life | D10: =SUM(X10,AA10,U10,R10) -> 74.270878 | E10: =SUM(Y10,AB10,V10,S10) -> 294.89586 | F10: =D10+E10 -> 369.16674 | G10: =SUM(AM10,AP10,AJ10,AG10) -> 68.517725 | H10: =SUM(AN10,AQ10,AK10,AH10) -> 300.91364 | I10: =G10+H10 -> 369.43136 | J10: =+IFERROR(IF(G10<0,-(D10/G10-1),(D10/G10-1)),0) -> 0.083965901 | K10: =+IFERROR(IF(H10<0,-(E10/H10-1),(E10/H10-1)),0) -> -0.019998357 | L10: =+IFERROR(IF(I10<0,-(F10/I10-1),(F10/I10-1)),0) -> -0.00071630626 | O10: 74.270878 | P10: 294.89586 | Q10: =O10+P10 -> 369.16674 | R10: 19.429262 | S10: 74.289382 | T10: =R10+S10 -> 93.718643 | U10: 18.772321 | V10: 74.034433 | W10: =U10+V10 -> 92.806754 | X10: 18.176193 | Y10: 72.835474 | Z10: =X10+Y10 -> 91.011667 | AA10: 17.893102 | AB10: 73.736573 | AC10: =AA10+AB10 -> 91.629675 | AD10: =+AG10+AJ10+AM10+AP10 -> 68.517725 | AE10: =+AH10+AK10+AN10+AQ10 -> 300.91364 | AF10: =AD10+AE10 -> 369.43136 | AG10: 17.563655 | AH10: 74.04131 | AI10: =AG10+AH10 -> 91.604964 | AJ10: 17.214434 | AK10: 74.966111 | AL10: =AJ10+AK10 -> 92.180545 | AM10: 16.845017 | AN10: 75.454581 | AO10: =AM10+AN10 -> 92.299597 | AP10: 16.89462 | AQ10: 76.451639 | AR10: =AP10+AQ10 -> 93.346258 | AS10: 77.953957 | AT10: 324.86105 | AU10: =AS10+AT10 -> 402.81501 | AV10: 17.635328 | AW10: 77.698791 | AX10: =AV10+AW10 -> 95.334119 | AY10: 18.740078 | AZ10: 79.831597 | BA10: =AY10+AZ10 -> 98.571676 | BB10: 20.150211 | BC10: 82.531167 | BD10: =BB10+BC10 -> 102.68138 | BE10: 21.42834 | BF10: 84.799497 | BG10: =BE10+BF10 -> 106.22784 | BH10: =SUM(BK10,BN10,BQ10,BT10) -> 96.093268 | BI10: =SUM(BL10,BO10,BR10,BU10) -> 367.86187 | BJ10: =BH10+BI10 -> 463.95513 | BK10: 22.7705 | BL10: 88.597827 | BM10: =BK10+BL10 -> 111.36833 | BN10: 23.784584 | BO10: 90.803185 | BP10: =BN10+BO10 -> 114.58777 | BQ10: 24.457027 | BR10: 92.807601 | BS10: =BQ10+BR10 -> 117.26463 | BT10: 25.081157 | BU10: 95.653253 | BV10: =BT10+BU10 -> 120.73441
B11: 기타보장 | C11: Others | D11: =SUM(X11,AA11,U11,R11) -> 846.82921 | E11: =SUM(Y11,AB11,V11,S11) -> 0 | F11: =D11+E11 -> 846.82921 | G11: =SUM(AM11,AP11,AJ11,AG11) -> 731.36096 | H11: =SUM(AN11,AQ11,AK11,AH11) -> 0 | I11: =G11+H11 -> 731.36096 | J11: =+IFERROR(IF(G11<0,-(D11/G11-1),(D11/G11-1)),0) -> 0.15788135 | K11: =+IFERROR(IF(H11<0,-(E11/H11-1),(E11/H11-1)),0) -> 0 | L11: =+IFERROR(IF(I11<0,-(F11/I11-1),(F11/I11-1)),0) -> 0.15788135 | O11: 846.82921 | P11: 0 | Q11: =O11+P11 -> 846.82921 | R11: 226.09337 | S11: 0 | T11: =R11+S11 -> 226.09337 | U11: 215.4881 | V11: 0 | W11: =U11+V11 -> 215.4881 | X11: 205.793 | Y11: 0 | Z11: =X11+Y11 -> 205.793 | AA11: 199.45474 | AB11: 0 | AC11: =AA11+AB11 -> 199.45474 | AD11: =+AG11+AJ11+AM11+AP11 -> 731.36096 | AE11: =+AH11+AK11+AN11+AQ11 -> 0 | AF11: =AD11+AE11 -> 731.36096 | AG11: 192.78628 | AH11: 0 | AI11: =AG11+AH11 -> 192.78628 | AJ11: 185.00312 | AK11: 0 | AL11: =AJ11+AK11 -> 185.00312 | AM11: 179.14272 | AN11: 0 | AO11: =AM11+AN11 -> 179.14272 | AP11: 174.42884 | AQ11: 0 | AR11: =AP11+AQ11 -> 174.42884 | AS11: 666.59415 | AT11: 0 | AU11: =AS11+AT11 -> 666.59415 | AV11: 169.8543 | AW11: 0 | AX11: =AV11+AW11 -> 169.8543 | AY11: 167.93756 | AZ11: 0 | BA11: =AY11+AZ11 -> 167.93756 | BB11: 164.89676 | BC11: 0 | BD11: =BB11+BC11 -> 164.89676 | BE11: 163.90554 | BF11: 0 | BG11: =BE11+BF11 -> 163.90554 | BH11: =SUM(BK11,BN11,BQ11,BT11) -> 646.83735 | BI11: =SUM(BL11,BO11,BR11,BU11) -> 0 | BJ11: =BH11+BI11 -> 646.83735 | BK11: 164.02639 | BL11: 0 | BM11: =BK11+BL11 -> 164.02639 | BN11: 163.24138 | BO11: 0 | BP11: =BN11+BO11 -> 163.24138 | BQ11: 160.85276 | BR11: 0 | BS11: =BQ11+BR11 -> 160.85276 | BT11: 158.71682 | BU11: 0 | BV11: =BT11+BU11 -> 158.71682
B12: 연금보험 | C12: Annuities | D12: =SUM(D13:D14) -> 84.077704 | E12: =SUM(E13:E14) -> 877.6777 | F12: =D12+E12 -> 961.7554 | G12: =SUM(G13:G14) -> 106.04536 | H12: =SUM(H13:H14) -> 671.11754 | I12: =G12+H12 -> 777.1629 | J12: =+IFERROR(IF(G12<0,-(D12/G12-1),(D12/G12-1)),0) -> -0.20715338 | K12: =+IFERROR(IF(H12<0,-(E12/H12-1),(E12/H12-1)),0) -> 0.30778537 | L12: =+IFERROR(IF(I12<0,-(F12/I12-1),(F12/I12-1)),0) -> 0.23752099 | O12: 84.077704 | P12: 877.6777 | Q12: =O12+P12 -> 961.7554 | R12: 20.965022 | S12: 269.82666 | T12: =R12+S12 -> 290.79168 | U12: 21.166203 | V12: 247.85772 | W12: =U12+V12 -> 269.02392 | X12: =SUM(X13:X14) -> 19.477109 | Y12: =SUM(Y13:Y14) -> 171.64337 | Z12: =X12+Y12 -> 191.12048 | AA12: =SUM(AA13:AA14) -> 22.469371 | AB12: =SUM(AB13:AB14) -> 188.34995 | AC12: =AA12+AB12 -> 210.81932 | AD12: =SUM(AD13:AD14) -> 106.04536 | AE12: =SUM(AE13:AE14) -> 671.11754 | AF12: =AD12+AE12 -> 777.1629 | AG12: =SUM(AG13:AG14) -> 25.912798 | AH12: =SUM(AH13:AH14) -> 210.3811 | AI12: =AG12+AH12 -> 236.2939 | AJ12: =SUM(AJ13:AJ14) -> 24.88113 | AK12: =SUM(AK13:AK14) -> 156.06275 | AL12: =AJ12+AK12 -> 180.94388 | AM12: =SUM(AM13:AM14) -> 26.50583 | AN12: =SUM(AN13:AN14) -> 157.43789 | AO12: =AM12+AN12 -> 183.94372 | AP12: =SUM(AP13:AP14) -> 28.745601 | AQ12: =SUM(AQ13:AQ14) -> 147.2358 | AR12: =AP12+AQ12 -> 175.9814 | AS12: =SUM(AS13:AS14) -> 133.53677 | AT12: =SUM(AT13:AT14) -> 455.46777 | AU12: =AS12+AT12 -> 589.00454 | AV12: =SUM(AV13:AV14) -> 32.753402 | AW12: =SUM(AW13:AW14) -> 119.47361 | AX12: =AV12+AW12 -> 152.22701 | AY12: =SUM(AY13:AY14) -> 31.905282 | AZ12: =SUM(AZ13:AZ14) -> 118.41852 | BA12: =AY12+AZ12 -> 150.3238 | BB12: =SUM(BB13:BB14) -> 33.309046 | BC12: =SUM(BC13:BC14) -> 108.89784 | BD12: =BB12+BC12 -> 142.20689 | BE12: =SUM(BE13:BE14) -> 35.569036 | BF12: =SUM(BF13:BF14) -> 108.6778 | BG12: =BE12+BF12 -> 144.24684 | BH12: =SUM(BH13:BH14) -> 184.16801 | BI12: =SUM(BI13:BI14) -> 564.71446 | BJ12: =BH12+BI12 -> 748.88247 | BK12: =SUM(BK13:BK14) -> 41.820566 | BL12: =SUM(BL13:BL14) -> 116.74467 | BM12: =BK12+BL12 -> 158.56523 | BN12: =SUM(BN13:BN14) -> 42.966466 | BO12: =SUM(BO13:BO14) -> 121.76705 | BP12: =BN12+BO12 -> 164.73351 | BQ12: =SUM(BQ13:BQ14) -> 46.632498 | BR12: =SUM(BR13:BR14) -> 142.88776 | BS12: =BQ12+BR12 -> 189.52026 | BT12: =SUM(BT13:BT14) -> 52.748484 | BU12: =SUM(BU13:BU14) -> 183.31499 | BV12: =BT12+BU12 -> 236.06347
B13: 일반연금 | C13: General annuities | D13: =SUM(X13,AA13,U13,R13) -> 51.465698 | E13: =SUM(Y13,AB13,V13,S13) -> 0 | F13: =D13+E13 -> 51.465698 | G13: =SUM(AM13,AP13,AJ13,AG13) -> 73.73483 | H13: =SUM(AN13,AQ13,AK13,AH13) -> 0 | I13: =G13+H13 -> 73.73483 | J13: =+IFERROR(IF(G13<0,-(D13/G13-1),(D13/G13-1)),0) -> -0.30201645 | K13: =+IFERROR(IF(H13<0,-(E13/H13-1),(E13/H13-1)),0) -> 0 | L13: =+IFERROR(IF(I13<0,-(F13/I13-1),(F13/I13-1)),0) -> -0.30201645 | O13: 51.465698 | P13: 0 | Q13: =O13+P13 -> 51.465698 | R13: 12.026214 | S13: 0 | T13: =R13+S13 -> 12.026214 | U13: 12.635357 | V13: 0 | W13: =U13+V13 -> 12.635357 | X13: 12.04803 | Y13: 0 | Z13: =X13+Y13 -> 12.04803 | AA13: 14.756097 | AB13: 0 | AC13: =AA13+AB13 -> 14.756097 | AD13: =+AG13+AJ13+AM13+AP13 -> 73.73483 | AE13: =+AH13+AK13+AN13+AQ13 -> 0 | AF13: =AD13+AE13 -> 73.73483 | AG13: 17.890151 | AH13: 0 | AI13: =AG13+AH13 -> 17.890151 | AJ13: 17.130478 | AK13: 0 | AL13: =AJ13+AK13 -> 17.130478 | AM13: 18.320157 | AN13: 0 | AO13: =AM13+AN13 -> 18.320157 | AP13: 20.394043 | AQ13: 0 | AR13: =AP13+AQ13 -> 20.394043 | AS13: 99.296086 | AT13: 0 | AU13: =AS13+AT13 -> 99.296086 | AV13: 24.577702 | AW13: 0 | AX13: =AV13+AW13 -> 24.577702 | AY13: 23.45196 | AZ13: 0 | BA13: =AY13+AZ13 -> 23.45196 | BB13: 24.611819 | BC13: 0 | BD13: =BB13+BC13 -> 24.611819 | BE13: 26.654605 | BF13: 0 | BG13: =BE13+BF13 -> 26.654605 | BH13: =SUM(BK13,BN13,BQ13,BT13) -> 144.85761 | BI13: =SUM(BL13,BO13,BR13,BU13) -> 0 | BJ13: =BH13+BI13 -> 144.85761 | BK13: 32.470304 | BL13: 0 | BM13: =BK13+BL13 -> 32.470304 | BN13: 33.319158 | BO13: 0 | BP13: =BN13+BO13 -> 33.319158 | BQ13: 36.725729 | BR13: 0 | BS13: =BQ13+BR13 -> 36.725729 | BT13: 42.34242 | BU13: 0 | BV13: =BT13+BU13 -> 42.34242
B14: 변액연금 | C14: Variable annuities | D14: =SUM(X14,AA14,U14,R14) -> 32.612005 | E14: =SUM(Y14,AB14,V14,S14) -> 877.6777 | F14: =D14+E14 -> 910.2897 | G14: =SUM(AM14,AP14,AJ14,AG14) -> 32.310528 | H14: =SUM(AN14,AQ14,AK14,AH14) -> 671.11754 | I14: =G14+H14 -> 703.42807 | J14: =+IFERROR(IF(G14<0,-(D14/G14-1),(D14/G14-1)),0) -> 0.0093306129 | K14: =+IFERROR(IF(H14<0,-(E14/H14-1),(E14/H14-1)),0) -> 0.30778537 | L14: =+IFERROR(IF(I14<0,-(F14/I14-1),(F14/I14-1)),0) -> 0.29407646 | O14: 32.612005 | P14: 877.6777 | Q14: =O14+P14 -> 910.2897 | R14: 8.9388076 | S14: 269.82666 | T14: =R14+S14 -> 278.76547 | U14: 8.5308459 | V14: 247.85772 | W14: =U14+V14 -> 256.38857 | X14: 7.4290785 | Y14: 171.64337 | Z14: =X14+Y14 -> 179.07245 | AA14: 7.7132734 | AB14: 188.34995 | AC14: =AA14+AB14 -> 196.06322 | AD14: =+AG14+AJ14+AM14+AP14 -> 32.310528 | AE14: =+AH14+AK14+AN14+AQ14 -> 671.11754 | AF14: =AD14+AE14 -> 703.42807 | AG14: 8.0226469 | AH14: 210.3811 | AI14: =AG14+AH14 -> 218.40375 | AJ14: 7.7506513 | AK14: 156.06275 | AL14: =AJ14+AK14 -> 163.8134 | AM14: 8.1856724 | AN14: 157.43789 | AO14: =AM14+AN14 -> 165.62356 | AP14: 8.3515578 | AQ14: 147.2358 | AR14: =AP14+AQ14 -> 155.58736 | AS14: 34.24068 | AT14: 455.46777 | AU14: =AS14+AT14 -> 489.70845 | AV14: 8.1757001 | AW14: 119.47361 | AX14: =AV14+AW14 -> 127.64931 | AY14: 8.4533227 | AZ14: 118.41852 | BA14: =AY14+AZ14 -> 126.87184 | BB14: 8.6972265 | BC14: 108.89784 | BD14: =BB14+BC14 -> 117.59507 | BE14: 8.9144307 | BF14: 108.6778 | BG14: =BE14+BF14 -> 117.59223 | BH14: =SUM(BK14,BN14,BQ14,BT14) -> 39.310403 | BI14: =SUM(BL14,BO14,BR14,BU14) -> 564.71446 | BJ14: =BH14+BI14 -> 604.02486 | BK14: 9.350262 | BL14: 116.74467 | BM14: =BK14+BL14 -> 126.09493 | BN14: 9.6473082 | BO14: 121.76705 | BP14: =BN14+BO14 -> 131.41436 | BQ14: 9.9067687 | BR14: 142.88776 | BS14: =BQ14+BR14 -> 152.79453 | BT14: 10.406064 | BU14: 183.31499 | BV14: =BT14+BU14 -> 193.72105
B15: 저축보험 | C15: Savings / Investments | D15: =SUM(D16:D17) -> 28.509295 | E15: =SUM(E16:E17) -> 1200.344 | F15: =D15+E15 -> 1228.8532 | G15: =SUM(G16:G17) -> 38.139299 | H15: =SUM(H16:H17) -> 789.48063 | I15: =G15+H15 -> 827.61993 | J15: =+IFERROR(IF(G15<0,-(D15/G15-1),(D15/G15-1)),0) -> -0.25249558 | K15: =+IFERROR(IF(H15<0,-(E15/H15-1),(E15/H15-1)),0) -> 0.52042229 | L15: =+IFERROR(IF(I15<0,-(F15/I15-1),(F15/I15-1)),0) -> 0.48480384 | O15: 28.509295 | P15: 1200.344 | Q15: =O15+P15 -> 1228.8532 | R15: 6.3691334 | S15: 321.18231 | T15: =R15+S15 -> 327.55145 | U15: 7.4758248 | V15: 377.33552 | W15: =U15+V15 -> 384.81135 | X15: =SUM(X16:X17) -> 6.2289143 | Y15: =SUM(Y16:Y17) -> 207.06197 | Z15: =X15+Y15 -> 213.29089 | AA15: =SUM(AA16:AA17) -> 8.4354222 | AB15: =SUM(AB16:AB17) -> 294.76415 | AC15: =AA15+AB15 -> 303.19957 | AD15: =SUM(AD16:AD17) -> 38.139299 | AE15: =SUM(AE16:AE17) -> 789.48063 | AF15: =AD15+AE15 -> 827.61993 | AG15: =SUM(AG16:AG17) -> 7.615259 | AH15: =SUM(AH16:AH17) -> 220.80802 | AI15: =AG15+AH15 -> 228.42328 | AJ15: =SUM(AJ16:AJ17) -> 7.5184532 | AK15: =SUM(AK16:AK17) -> 224.80592 | AL15: =AJ15+AK15 -> 232.32437 | AM15: =SUM(AM16:AM17) -> 12.563016 | AN15: =SUM(AN16:AN17) -> 167.7556 | AO15: =AM15+AN15 -> 180.31862 | AP15: =SUM(AP16:AP17) -> 10.442571 | AQ15: =SUM(AQ16:AQ17) -> 176.11109 | AR15: =AP15+AQ15 -> 186.55366 | AS15: =SUM(AS16:AS17) -> 46.215998 | AT15: =SUM(AT16:AT17) -> 523.36863 | AU15: =AS15+AT15 -> 569.58463 | AV15: =SUM(AV16:AV17) -> 12.036076 | AW15: =SUM(AW16:AW17) -> 124.84105 | AX15: =AV15+AW15 -> 136.87713 | AY15: =SUM(AY16:AY17) -> 10.76263 | AZ15: =SUM(AZ16:AZ17) -> 148.04622 | BA15: =AY15+AZ15 -> 158.80885 | BB15: =SUM(BB16:BB17) -> 11.437624 | BC15: =SUM(BC16:BC17) -> 126.64611 | BD15: =BB15+BC15 -> 138.08373 | BE15: =SUM(BE16:BE17) -> 11.979668 | BF15: =SUM(BF16:BF17) -> 123.83525 | BG15: =BE15+BF15 -> 135.81492 | BH15: =SUM(BH16:BH17) -> 69.088017 | BI15: =SUM(BI16:BI17) -> 730.90158 | BJ15: =BH15+BI15 -> 799.9896 | BK15: =SUM(BK16:BK17) -> 14.090767 | BL15: =SUM(BL16:BL17) -> 128.17089 | BM15: =BK15+BL15 -> 142.26165 | BN15: =SUM(BN16:BN17) -> 15.770478 | BO15: =SUM(BO16:BO17) -> 157.91803 | BP15: =BN15+BO15 -> 173.68851 | BQ15: =SUM(BQ16:BQ17) -> 16.481162 | BR15: =SUM(BR16:BR17) -> 173.66758 | BS15: =BQ15+BR15 -> 190.14874 | BT15: =SUM(BT16:BT17) -> 22.745609 | BU15: =SUM(BU16:BU17) -> 271.14508 | BV15: =BT15+BU15 -> 293.89069
B16: 일반저축 | C16: General savings | D16: =SUM(X16,AA16,U16,R16) -> 11.275805 | E16: =SUM(Y16,AB16,V16,S16) -> 0 | F16: =D16+E16 -> 11.275805 | G16: =SUM(AM16,AP16,AJ16,AG16) -> 19.687272 | H16: =SUM(AN16,AQ16,AK16,AH16) -> 0 | I16: =G16+H16 -> 19.687272 | J16: =+IFERROR(IF(G16<0,-(D16/G16-1),(D16/G16-1)),0) -> -0.42725403 | K16: =+IFERROR(IF(H16<0,-(E16/H16-1),(E16/H16-1)),0) -> 0 | L16: =+IFERROR(IF(I16<0,-(F16/I16-1),(F16/I16-1)),0) -> -0.42725403 | O16: 11.275805 | P16: 0 | Q16: =O16+P16 -> 11.275805 | R16: 2.0617718 | S16: 0 | T16: =R16+S16 -> 2.0617718 | U16: 3.0275712 | V16: 0 | W16: =U16+V16 -> 3.0275712 | X16: 2.0222229 | Y16: 0 | Z16: =X16+Y16 -> 2.0222229 | AA16: 4.1642396 | AB16: 0 | AC16: =AA16+AB16 -> 4.1642396 | AD16: =+AG16+AJ16+AM16+AP16 -> 19.687272 | AE16: =+AH16+AK16+AN16+AQ16 -> 0 | AF16: =AD16+AE16 -> 19.687272 | AG16: 3.3394317 | AH16: 0 | AI16: =AG16+AH16 -> 3.3394317 | AJ16: 2.9181645 | AK16: 0 | AL16: =AJ16+AK16 -> 2.9181645 | AM16: 7.8982658 | AN16: 0 | AO16: =AM16+AN16 -> 7.8982658 | AP16: 5.5314096 | AQ16: 0 | AR16: =AP16+AQ16 -> 5.5314096 | AS16: 23.743088 | AT16: 0 | AU16: =AS16+AT16 -> 23.743088 | AV16: 6.8821941 | AW16: 0 | AX16: =AV16+AW16 -> 6.8821941 | AY16: 5.3181483 | AZ16: 0 | BA16: =AY16+AZ16 -> 5.3181483 | BB16: 5.6624199 | BC16: 0 | BD16: =BB16+BC16 -> 5.6624199 | BE16: 5.8803257 | BF16: 0 | BG16: =BE16+BF16 -> 5.8803257 | BH16: =SUM(BK16,BN16,BQ16,BT16) -> 40.276997 | BI16: =SUM(BL16,BO16,BR16,BU16) -> 0 | BJ16: =BH16+BI16 -> 40.276997 | BK16: 7.581222 | BL16: 0 | BM16: =BK16+BL16 -> 7.581222 | BN16: 8.8011384 | BO16: 0 | BP16: =BN16+BO16 -> 8.8011384 | BQ16: 9.1181031 | BR16: 0 | BS16: =BQ16+BR16 -> 9.1181031 | BT16: 14.776533 | BU16: 0 | BV16: =BT16+BU16 -> 14.776533
B17: 변액저축 | C17: Variable investments | D17: =SUM(X17,AA17,U17,R17) -> 17.233489 | E17: =SUM(Y17,AB17,V17,S17) -> 1200.344 | F17: =D17+E17 -> 1217.5774 | G17: =SUM(AM17,AP17,AJ17,AG17) -> 18.452027 | H17: =SUM(AN17,AQ17,AK17,AH17) -> 789.48063 | I17: =G17+H17 -> 807.93266 | J17: =+IFERROR(IF(G17<0,-(D17/G17-1),(D17/G17-1)),0) -> -0.066038178 | K17: =+IFERROR(IF(H17<0,-(E17/H17-1),(E17/H17-1)),0) -> 0.52042229 | L17: =+IFERROR(IF(I17<0,-(F17/I17-1),(F17/I17-1)),0) -> 0.50702838 | O17: 17.233489 | P17: 1200.344 | Q17: =O17+P17 -> 1217.5774 | R17: 4.3073616 | S17: 321.18231 | T17: =R17+S17 -> 325.48968 | U17: 4.4482536 | V17: 377.33552 | W17: =U17+V17 -> 381.78377 | X17: 4.2066913 | Y17: 207.06197 | Z17: =X17+Y17 -> 211.26866 | AA17: 4.2711826 | AB17: 294.76415 | AC17: =AA17+AB17 -> 299.03533 | AD17: =+AG17+AJ17+AM17+AP17 -> 18.452027 | AE17: =+AH17+AK17+AN17+AQ17 -> 789.48063 | AF17: =AD17+AE17 -> 807.93266 | AG17: 4.2758274 | AH17: 220.80802 | AI17: =AG17+AH17 -> 225.08385 | AJ17: 4.6002887 | AK17: 224.80592 | AL17: =AJ17+AK17 -> 229.40621 | AM17: 4.6647502 | AN17: 167.7556 | AO17: =AM17+AN17 -> 172.42035 | AP17: 4.9111611 | AQ17: 176.11109 | AR17: =AP17+AQ17 -> 181.02225 | AS17: 22.47291 | AT17: 523.36863 | AU17: =AS17+AT17 -> 545.84154 | AV17: 5.1538818 | AW17: 124.84105 | AX17: =AV17+AW17 -> 129.99494 | AY17: 5.4444814 | AZ17: 148.04622 | BA17: =AY17+AZ17 -> 153.4907 | BB17: 5.7752038 | BC17: 126.64611 | BD17: =BB17+BC17 -> 132.42131 | BE17: 6.0993428 | BF17: 123.83525 | BG17: =BE17+BF17 -> 129.93459 | BH17: =SUM(BK17,BN17,BQ17,BT17) -> 28.811021 | BI17: =SUM(BL17,BO17,BR17,BU17) -> 730.90158 | BJ17: =BH17+BI17 -> 759.7126 | BK17: 6.5095451 | BL17: 128.17089 | BM17: =BK17+BL17 -> 134.68043 | BN17: 6.96934 | BO17: 157.91803 | BP17: =BN17+BO17 -> 164.88737 | BQ17: 7.3630594 | BR17: 173.66758 | BS17: =BQ17+BR17 -> 181.03064 | BT17: 7.9690762 | BU17: 271.14508 | BV17: =BT17+BU17 -> 279.11416
B18: 단체보험 | C18: Groups | D18: =SUM(D19:D20) -> 9.4668426 | E18: =SUM(E19:E20) -> 0 | F18: =D18+E18 -> 9.4668426 | G18: =SUM(G19:G20) -> 11.803656 | H18: =SUM(H19:H20) -> 0 | I18: =G18+H18 -> 11.803656 | J18: =+IFERROR(IF(G18<0,-(D18/G18-1),(D18/G18-1)),0) -> -0.19797372 | K18: =+IFERROR(IF(H18<0,-(E18/H18-1),(E18/H18-1)),0) -> 0 | L18: =+IFERROR(IF(I18<0,-(F18/I18-1),(F18/I18-1)),0) -> -0.19797372 | O18: 9.4668426 | P18: 0 | Q18: =O18+P18 -> 9.4668426 | R18: 2.1547327 | S18: 0 | T18: =R18+S18 -> 2.1547327 | U18: =SUM(U19:U20) -> 2.3092303 | V18: =SUM(V19:V20) -> 0 | W18: =U18+V18 -> 2.3092303 | X18: =SUM(X19:X20) -> 2.441692 | Y18: =SUM(Y19:Y20) -> 0 | Z18: =X18+Y18 -> 2.441692 | AA18: =SUM(AA19:AA20) -> 2.5611877 | AB18: =SUM(AB19:AB20) -> 0 | AC18: =AA18+AB18 -> 2.5611877 | AD18: =SUM(AD19:AD20) -> 11.803656 | AE18: =SUM(AE19:AE20) -> 0 | AF18: =AD18+AE18 -> 11.803656 | AG18: =SUM(AG19:AG20) -> 2.7448624 | AH18: =SUM(AH19:AH20) -> 0 | AI18: =AG18+AH18 -> 2.7448624 | AJ18: =SUM(AJ19:AJ20) -> 2.867943 | AK18: =SUM(AK19:AK20) -> 0 | AL18: =AJ18+AK18 -> 2.867943 | AM18: =SUM(AM19:AM20) -> 3.0096578 | AN18: =SUM(AN19:AN20) -> 0 | AO18: =AM18+AN18 -> 3.0096578 | AP18: =SUM(AP19:AP20) -> 3.1811932 | AQ18: =SUM(AQ19:AQ20) -> 0 | AR18: =AP18+AQ18 -> 3.1811932 | AS18: =SUM(AS19:AS20) -> 14.878783 | AT18: =SUM(AT19:AT20) -> 0 | AU18: =AS18+AT18 -> 14.878783 | AV18: =SUM(AV19:AV20) -> 3.4415607 | AW18: =SUM(AW19:AW20) -> 0 | AX18: =AV18+AW18 -> 3.4415607 | AY18: =SUM(AY19:AY20) -> 3.5393954 | AZ18: =SUM(AZ19:AZ20) -> 0 | BA18: =AY18+AZ18 -> 3.5393954 | BB18: =SUM(BB19:BB20) -> 3.8159431 | BC18: =SUM(BC19:BC20) -> 0 | BD18: =BB18+BC18 -> 3.8159431 | BE18: =SUM(BE19:BE20) -> 4.0818841 | BF18: =SUM(BF19:BF20) -> 0 | BG18: =BE18+BF18 -> 4.0818841 | BH18: =SUM(BH19:BH20) -> 18.846618 | BI18: =SUM(BI19:BI20) -> 0 | BJ18: =BH18+BI18 -> 18.846618 | BK18: =SUM(BK19:BK20) -> 4.4879835 | BL18: =SUM(BL19:BL20) -> 0 | BM18: =BK18+BL18 -> 4.4879835 | BN18: =SUM(BN19:BN20) -> 4.5485214 | BO18: =SUM(BO19:BO20) -> 0 | BP18: =BN18+BO18 -> 4.5485214 | BQ18: =SUM(BQ19:BQ20) -> 4.7908053 | BR18: =SUM(BR19:BR20) -> 0 | BS18: =BQ18+BR18 -> 4.7908053 | BT18: =SUM(BT19:BT20) -> 5.0193079 | BU18: =SUM(BU19:BU20) -> 0 | BV18: =BT18+BU18 -> 5.0193079
B19: 보장성 | C19: Protections | D19: =SUM(X19,AA19,U19,R19) -> 8.1012176 | E19: =SUM(Y19,AB19,V19,S19) -> 0 | F19: =D19+E19 -> 8.1012176 | G19: =SUM(AM19,AP19,AJ19,AG19) -> 10.381806 | H19: =SUM(AN19,AQ19,AK19,AH19) -> 0 | I19: =G19+H19 -> 10.381806 | J19: =+IFERROR(IF(G19<0,-(D19/G19-1),(D19/G19-1)),0) -> -0.21967168 | K19: =+IFERROR(IF(H19<0,-(E19/H19-1),(E19/H19-1)),0) -> 0 | L19: =+IFERROR(IF(I19<0,-(F19/I19-1),(F19/I19-1)),0) -> -0.21967168 | O19: 8.1012176 | P19: 0 | Q19: =O19+P19 -> 8.1012176 | R19: 1.8104027 | S19: 0 | T19: =R19+S19 -> 1.8104027 | U19: 1.9739003 | V19: 0 | W19: =U19+V19 -> 1.9739003 | X19: 2.102882 | Y19: 0 | Z19: =X19+Y19 -> 2.102882 | AA19: 2.2140327 | AB19: 0 | AC19: =AA19+AB19 -> 2.2140327 | AD19: =+AG19+AJ19+AM19+AP19 -> 10.381806 | AE19: =+AH19+AK19+AN19+AQ19 -> 0 | AF19: =AD19+AE19 -> 10.381806 | AG19: 2.3956874 | AH19: 0 | AI19: =AG19+AH19 -> 2.3956874 | AJ19: 2.513168 | AK19: 0 | AL19: =AJ19+AK19 -> 2.513168 | AM19: 2.6556828 | AN19: 0 | AO19: =AM19+AN19 -> 2.6556828 | AP19: 2.8172682 | AQ19: 0 | AR19: =AP19+AQ19 -> 2.8172682 | AS19: 13.353838 | AT19: 0 | AU19: =AS19+AT19 -> 13.353838 | AV19: 3.0707657 | AW19: 0 | AX19: =AV19+AW19 -> 3.0707657 | AY19: 3.1609204 | AZ19: 0 | BA19: =AY19+AZ19 -> 3.1609204 | BB19: 3.4335231 | BC19: 0 | BD19: =BB19+BC19 -> 3.4335231 | BE19: 3.6886291 | BF19: 0 | BG19: =BE19+BF19 -> 3.6886291 | BH19: =SUM(BK19,BN19,BQ19,BT19) -> 17.19376 | BI19: =SUM(BL19,BO19,BR19,BU19) -> 0 | BJ19: =BH19+BI19 -> 17.19376 | BK19: 4.0835025 | BL19: 0 | BM19: =BK19+BL19 -> 4.0835025 | BN19: 4.1353804 | BO19: 0 | BP19: =BN19+BO19 -> 4.1353804 | BQ19: 4.3790343 | BR19: 0 | BS19: =BQ19+BR19 -> 4.3790343 | BT19: 4.5958429 | BU19: 0 | BV19: =BT19+BU19 -> 4.5958429
B20: 저축성 | C20: Savings | D20: =SUM(X20,AA20,U20,R20) -> 1.365625 | E20: =SUM(Y20,AB20,V20,S20) -> 0 | F20: =D20+E20 -> 1.365625 | G20: =SUM(AM20,AP20,AJ20,AG20) -> 1.42185 | H20: =SUM(AN20,AQ20,AK20,AH20) -> 0 | I20: =G20+H20 -> 1.42185 | J20: =+IFERROR(IF(G20<0,-(D20/G20-1),(D20/G20-1)),0) -> -0.039543552 | K20: =+IFERROR(IF(H20<0,-(E20/H20-1),(E20/H20-1)),0) -> 0 | L20: =+IFERROR(IF(I20<0,-(F20/I20-1),(F20/I20-1)),0) -> -0.039543552 | O20: 1.365625 | P20: 0 | Q20: =O20+P20 -> 1.365625 | R20: 0.34433 | S20: 0 | T20: =R20+S20 -> 0.34433 | U20: 0.33533 | V20: 0 | W20: =U20+V20 -> 0.33533 | X20: 0.33881 | Y20: 0 | Z20: =X20+Y20 -> 0.33881 | AA20: 0.347155 | AB20: 0 | AC20: =AA20+AB20 -> 0.347155 | AD20: =+AG20+AJ20+AM20+AP20 -> 1.42185 | AE20: =+AH20+AK20+AN20+AQ20 -> 0 | AF20: =AD20+AE20 -> 1.42185 | AG20: 0.349175 | AH20: 0 | AI20: =AG20+AH20 -> 0.349175 | AJ20: 0.354775 | AK20: 0 | AL20: =AJ20+AK20 -> 0.354775 | AM20: 0.353975 | AN20: 0 | AO20: =AM20+AN20 -> 0.353975 | AP20: 0.363925 | AQ20: 0 | AR20: =AP20+AQ20 -> 0.363925 | AS20: 1.524945 | AT20: 0 | AU20: =AS20+AT20 -> 1.524945 | AV20: 0.370795 | AW20: 0 | AX20: =AV20+AW20 -> 0.370795 | AY20: 0.378475 | AZ20: 0 | BA20: =AY20+AZ20 -> 0.378475 | BB20: 0.38242 | BC20: 0 | BD20: =BB20+BC20 -> 0.38242 | BE20: 0.393255 | BF20: 0 | BG20: =BE20+BF20 -> 0.393255 | BH20: =SUM(BK20,BN20,BQ20,BT20) -> 1.652858 | BI20: =SUM(BL20,BO20,BR20,BU20) -> 0 | BJ20: =BH20+BI20 -> 1.652858 | BK20: 0.404481 | BL20: 0 | BM20: =BK20+BL20 -> 0.404481 | BN20: 0.413141 | BO20: 0 | BP20: =BN20+BO20 -> 0.413141 | BQ20: 0.411771 | BR20: 0 | BS20: =BQ20+BR20 -> 0.411771 | BT20: 0.423465 | BU20: 0 | BV20: =BT20+BU20 -> 0.423465
B21: 합계 | C21: Total | D21: =SUM(D7,D18) -> 1631.5252 | E21: =SUM(E7,E18) -> 2372.9175 | F21: =D21+E21 -> 4004.4427 | G21: =SUM(G7,G18) -> 1568.9149 | H21: =SUM(H7,H18) -> 1761.5118 | I21: =G21+H21 -> 3330.4267 | J21: =+IFERROR(IF(G21<0,-(D21/G21-1),(D21/G21-1)),0) -> 0.039906733 | K21: =+IFERROR(IF(H21<0,-(E21/H21-1),(E21/H21-1)),0) -> 0.34709146 | L21: =+IFERROR(IF(I21<0,-(F21/I21-1),(F21/I21-1)),0) -> 0.20238126 | O21: 1631.5252 | P21: 2372.9175 | Q21: =O21+P21 -> 4004.4427 | R21: 418.95717 | S21: 665.29836 | T21: =R21+S21 -> 1084.2555 | U21: =U7+U18 -> 411.46392 | V21: =V7+V18 -> 699.22767 | W21: =U21+V21 -> 1110.6916 | X21: =X7+X18 -> 399.94791 | Y21: =Y7+Y18 -> 451.54081 | Z21: =X21+Y21 -> 851.48873 | AA21: =AA7+AA18 -> 401.15615 | AB21: =AB7+AB18 -> 556.85067 | AC21: =AA21+AB21 -> 958.00682 | AD21: =AD7+AD18 -> 1568.9149 | AE21: =AE7+AE18 -> 1761.5118 | AF21: =AD21+AE21 -> 3330.4267 | AG21: =AG7+AG18 -> 398.66716 | AH21: =AH7+AH18 -> 505.23043 | AI21: =AG21+AH21 -> 903.89759 | AJ21: =AJ7+AJ18 -> 390.63602 | AK21: =AK7+AK18 -> 455.83478 | AL21: =AJ21+AK21 -> 846.4708 | AM21: =AM7+AM18 -> 391.56754 | AN21: =AN7+AN18 -> 400.64807 | AO21: =AM21+AN21 -> 792.21561 | AP21: =AP7+AP18 -> 388.04417 | AQ21: =AQ7+AQ18 -> 399.79853 | AR21: =AP21+AQ21 -> 787.84271 | AS21: =AS7+AS18 -> 1555.2876 | AT21: =AT7+AT18 -> 1303.6975 | AU21: =AS21+AT21 -> 2858.985 | AV21: =AV7+AV18 -> 390.72587 | AW21: =AW7+AW18 -> 322.01345 | AX21: =AV21+AW21 -> 712.73933 | AY21: =AY7+AY18 -> 386.9861 | AZ21: =AZ7+AZ18 -> 346.29634 | BA21: =AY21+AZ21 -> 733.28244 | BB21: =BB7+BB18 -> 386.58325 | BC21: =BC7+BC18 -> 318.07512 | BD21: =BB21+BC21 -> 704.65837 | BE21: =BE7+BE18 -> 390.99233 | BF21: =BF7+BF18 -> 317.31255 | BG21: =BE21+BF21 -> 708.30487 | BH21: =BH7+BH18 -> 1652.5033 | BI21: =BI7+BI18 -> 1663.4779 | BJ21: =BH21+BI21 -> 3315.9812 | BK21: =BK7+BK18 -> 403.99627 | BL21: =BL7+BL18 -> 333.51338 | BM21: =BK21+BL21 -> 737.50964 | BN21: =BN7+BN18 -> 409.15617 | BO21: =BO7+BO18 -> 370.48826 | BP21: =BN21+BO21 -> 779.64443 | BQ21: =BQ7+BQ18 -> 413.03026 | BR21: =BR7+BR18 -> 409.36294 | BS21: =BQ21+BR21 -> 822.3932 | BT21: =BT7+BT18 -> 426.32059 | BU21: =BU7+BU18 -> 550.11332 | BV21: =BT21+BU21 -> 976.43392
B22: 퇴직 | C22: Retirement pensions | D22: =SUM(X22,AA22,U22,R22) -> 0 | E22: =SUM(Y22,AB22,V22,S22) -> 967.19479 | F22: =D22+E22 -> 967.19479 | G22: =SUM(AM22,AP22,AJ22,AG22) -> 0 | H22: =SUM(AN22,AQ22,AK22,AH22) -> 1011.6652 | I22: =G22+H22 -> 1011.6652 | J22: =+IFERROR(IF(G22<0,-(D22/G22-1),(D22/G22-1)),0) -> 0 | K22: =+IFERROR(IF(H22<0,-(E22/H22-1),(E22/H22-1)),0) -> -0.043957588 | L22: =+IFERROR(IF(I22<0,-(F22/I22-1),(F22/I22-1)),0) -> -0.043957588 | O22: 0 | P22: 967.19479 | Q22: =O22+P22 -> 967.19479 | R22: 0 | S22: 461.02525 | T22: =R22+S22 -> 461.02525 | U22: 0 | V22: 138.3677 | W22: =U22+V22 -> 138.3677 | X22: 0 | Y22: 131.87549 | Z22: =X22+Y22 -> 131.87549 | AA22: 0 | AB22: 235.92636 | AC22: =AA22+AB22 -> 235.92636 | AD22: =+AG22+AJ22+AM22+AP22 -> 0 | AE22: =+AH22+AK22+AN22+AQ22 -> 1011.6652 | AF22: =AD22+AE22 -> 1011.6652 | AG22: 0 | AH22: 486.49098 | AI22: =AG22+AH22 -> 486.49098 | AJ22: 0 | AK22: 122.51843 | AL22: =AJ22+AK22 -> 122.51843 | AM22: 0 | AN22: 140.88856 | AO22: =AM22+AN22 -> 140.88856 | AP22: 0 | AQ22: 261.76718 | AR22: =AP22+AQ22 -> 261.76718 | AS22: 0 | AT22: 1210.1708 | AU22: =AS22+AT22 -> 1210.1708 | AV22: 0 | AW22: 702.61194 | AX22: =AV22+AW22 -> 702.61194 | AY22: 0 | AZ22: 137.79428 | BA22: =AY22+AZ22 -> 137.79428 | BB22: 0 | BC22: 134.49514 | BD22: =BB22+BC22 -> 134.49514 | BE22: 0 | BF22: 235.26947 | BG22: =BE22+BF22 -> 235.26947 | BH22: =SUM(BK22,BN22,BQ22,BT22) -> 0 | BI22: =SUM(BL22,BO22,BR22,BU22) -> 1982.9866 | BJ22: =BH22+BI22 -> 1982.9866 | BK22: 0 | BL22: 1349.4184 | BM22: =BK22+BL22 -> 1349.4184 | BN22: 0 | BO22: 214.44872 | BP22: =BN22+BO22 -> 214.44872 | BQ22: 0 | BR22: 198.48703 | BS22: =BQ22+BR22 -> 198.48703 | BT22: 0 | BU22: 220.63248 | BV22: =BT22+BU22 -> 220.63248
B24: 계정별 분류 | C24: Breakdown by Account Type
B25: 일반보험 | C25: General Types | D25: =D26+D27 -> 1507.4088 | E25: =E26+E27 -> 0 | F25: =F26+F27 -> 1507.4088 | G25: =G26+G27 -> 1449.6346 | H25: =H26+H27 -> 0 | I25: =I26+I27 -> 1449.6346 | J25: =+IFERROR(IF(G25<0,-(D25/G25-1),(D25/G25-1)),0) -> 0.039854302 | K25: =+IFERROR(IF(H25<0,-(E25/H25-1),(E25/H25-1)),0) -> 0 | L25: =+IFERROR(IF(I25<0,-(F25/I25-1),(F25/I25-1)),0) -> 0.039854302 | O25: =O26+O27 -> 1507.4088 | P25: =P26+P27 -> 0 | Q25: =Q26+Q27 -> 1507.4088 | R25: =R26+R27 -> 386.28174 | S25: =S26+S27 -> 0 | T25: =T26+T27 -> 386.28174 | U25: =U26+U27 -> 379.7125 | V25: =V26+V27 -> 0 | ... BV25: =BV26+BV27 -> 382.8643
B26: 일반보장성 | C26: General Protections | D26: =D9+D11+D19 -> 1443.3017 | E26: =E9+E11+E19 -> 0 | F26: =F9+F11+F19 -> 1443.3017 | G26: =G9+G11+G19 -> 1354.7907 | H26: =SUM(BC26,BF26) -> 0 | I26: =I9+I11+I19 -> 1354.7907 | J26: =+IFERROR(IF(G26<0,-(D26/G26-1),(D26/G26-1)),0) -> 0.065331863 | K26: =+IFERROR(IF(H26<0,-(E26/H26-1),(E26/H26-1)),0) -> 0 | L26: =+IFERROR(IF(I26<0,-(F26/I26-1),(F26/I26-1)),0) -> 0.065331863 | O26: =O9+O11+O19 -> 1443.3017 | P26: =P9+P11+P19 -> 0 | Q26: =Q9+Q11+Q19 -> 1443.3017 | R26: =R9+R11+R19 -> 371.84943 | S26: =S9+S11+S19 -> 0 | T26: =T9+T11+T19 -> 371.84943 | U26: =U9+U11+U19 -> 363.71424 | V26: =V9+V11+V19 -> 0 | ... BV26: =BV9+BV11+BV19 -> 325.32188
B27: 일반저축성 | C27: General Savings | D27: =D13+D16+D20 -> 64.107129 | E27: =E13+E16+E20 -> 0 | F27: =F13+F16+F20 -> 64.107129 | G27: =G13+G16+G20 -> 94.843951 | H27: =SUM(BC27,BF27) -> 0 | I27: =I13+I16+I20 -> 94.843951 | J27: =+IFERROR(IF(G27<0,-(D27/G27-1),(D27/G27-1)),0) -> -0.32407784 | K27: =+IFERROR(IF(H27<0,-(E27/H27-1),(E27/H27-1)),0) -> 0 | L27: =+IFERROR(IF(I27<0,-(F27/I27-1),(F27/I27-1)),0) -> -0.32407784 | O27: =O13+O16+O20 -> 64.107129 | P27: =P13+P16+P20 -> 0 | Q27: =Q13+Q16+Q20 -> 64.107129 | R27: =R13+R16+R20 -> 14.432316 | S27: =S13+S16+S20 -> 0 | T27: =T13+T16+T20 -> 14.432316 | U27: =U13+U16+U20 -> 15.998258 | V27: =V13+V16+V20 -> 0 | ... BV27: =BV13+BV16+BV20 -> 57.542418
B28: 변액보험 | C28: Variable Types | D28: =D29+D30 -> 124.11637 | E28: =E29+E30 -> 2372.9175 | F28: =F29+F30 -> 2497.0339 | G28: =G29+G30 -> 119.28028 | H28: =H29+H30 -> 635.38766 | I28: =I29+I30 -> 1880.7921 | J28: =+IFERROR(IF(G28<0,-(D28/G28-1),(D28/G28-1)),0) -> 0.04054393 | K28: =+IFERROR(IF(H28<0,-(E28/H28-1),(E28/H28-1)),0) -> 2.734598 | L28: =+IFERROR(IF(I28<0,-(F28/I28-1),(F28/I28-1)),0) -> 0.32765014 | O28: =O29+O30 -> 124.11637 | P28: =P29+P30 -> 2372.9175 | Q28: =Q29+Q30 -> 2497.0339 | R28: =R29+R30 -> 32.675431 | S28: =S29+S30 -> 665.29836 | T28: =T29+T30 -> 697.97379 | U28: =U29+U30 -> 31.75142 | V28: =V29+V30 -> 699.22767 | ... BV28: =BV29+BV30 -> 593.56962
B29: 변액보장형 | C29: Variable Protections | D29: =D10 -> 74.270878 | E29: =E10 -> 294.89586 | F29: =F10 -> 369.16674 | G29: =G10 -> 68.517725 | H29: =SUM(BC29,BF29) -> 167.33066 | I29: =I10 -> 369.43136 | J29: =+IFERROR(IF(G29<0,-(D29/G29-1),(D29/G29-1)),0) -> 0.083965901 | K29: =+IFERROR(IF(H29<0,-(E29/H29-1),(E29/H29-1)),0) -> 0.76235399 | L29: =+IFERROR(IF(I29<0,-(F29/I29-1),(F29/I29-1)),0) -> -0.00071630626 | O29: =O10 -> 74.270878 | P29: =P10 -> 294.89586 | Q29: =Q10 -> 369.16674 | R29: =R10 -> 19.429262 | S29: =S10 -> 74.289382 | T29: =T10 -> 93.718643 | U29: =U10 -> 18.772321 | V29: =V10 -> 74.034433 | ... BV29: =BV10 -> 120.73441
B30: 변액투자형 | C30: Variable Investments | D30: =D14+D17 -> 49.845495 | E30: =E14+E17 -> 2078.0217 | F30: =F14+F17 -> 2127.8671 | G30: =G14+G17 -> 50.762556 | H30: =SUM(BC30,BF30) -> 468.057 | I30: =I14+I17 -> 1511.3607 | J30: =+IFERROR(IF(G30<0,-(D30/G30-1),(D30/G30-1)),0) -> -0.018065703 | K30: =+IFERROR(IF(H30<0,-(E30/H30-1),(E30/H30-1)),0) -> 3.4396765 | L30: =+IFERROR(IF(I30<0,-(F30/I30-1),(F30/I30-1)),0) -> 0.40791481 | O30: =O14+O17 -> 49.845495 | P30: =P14+P17 -> 2078.0217 | Q30: =Q14+Q17 -> 2127.8671 | R30: =R14+R17 -> 13.246169 | S30: =S14+S17 -> 591.00898 | T30: =T14+T17 -> 604.25515 | U30: =U14+U17 -> 12.9791 | V30: =V14+V17 -> 625.19324 | ... BV30: =BV14+BV17 -> 472.83521
B31: 합계 | C31: Total | D31: =D25+D28 -> 1631.5252 | E31: =E25+E28 -> 2372.9175 | F31: =F25+F28 -> 4004.4427 | G31: =G25+G28 -> 1568.9149 | H31: =H25+H28 -> 635.38766 | I31: =I25+I28 -> 3330.4267 | J31: =+IFERROR(IF(G31<0,-(D31/G31-1),(D31/G31-1)),0) -> 0.039906733 | K31: =+IFERROR(IF(H31<0,-(E31/H31-1),(E31/H31-1)),0) -> 2.734598 | L31: =+IFERROR(IF(I31<0,-(F31/I31-1),(F31/I31-1)),0) -> 0.20238126 | O31: =O25+O28 -> 1631.5252 | P31: =P25+P28 -> 2372.9175 | Q31: =Q25+Q28 -> 4004.4427 | R31: =R25+R28 -> 418.95717 | S31: =S25+S28 -> 665.29836 | T31: =T25+T28 -> 1084.2555 | U31: =U25+U28 -> 411.46392 | V31: =V25+V28 -> 699.22767 | ... BV31: =BV25+BV28 -> 976.43392
B33: ※ 구성비 | C33: Breakdown by Product Type | D33: =CONCATENATE(D4," ",D5) -> 2025 FY | G33: =CONCATENATE(G4," ",G5) -> 2024 FY | J33: =J4 -> YoY
D34: 일반 General | E34: 특별 Separate | F34: 합계 Total | G34: 일반 General | H34: 특별 Separate | I34: 합계 Total | J34: 일반 General | K34: 특별 Separate | L34: 합계 Total
B35: 보장성 | C35: Protection types | D35: =(D8+D19)/D$21 -> 0.93015577 | E35: =(E8+E19)/E$21 -> 0.12427565 | F35: =(F8+F19)/F$21 -> 0.45261439 | G35: =(G8+G19)/G$21 -> 0.90719286 | H35: =(H8+H19)/H$21 -> 0.17082692 | I35: =(I8+I19)/I$21 -> 0.51771805 | J35: =D35-G35 -> 0.022962909 | K35: =E35-H35 -> -0.046551274 | L35: =F35-I35 -> -0.065103657
B36: 연금 | C36: Annuity | D36: =(D12)/D$21 -> 0.051533195 | E36: =(E12)/E$21 -> 0.36987282 | F36: =(F12)/F$21 -> 0.2401721 | G36: =(G12)/G$21 -> 0.06759153 | H36: =(H12)/H$21 -> 0.38098952 | I36: =(I12)/I$21 -> 0.23335235 | J36: =D36-G36 -> -0.016058335 | K36: =E36-H36 -> -0.011116698 | L36: =F36-I36 -> 0.006819749
B37: 저축성 | C37: Savings | D37: =(D15+D20)/D$21 -> 0.018311038 | E37: =(E15+E20)/E$21 -> 0.50585153 | F37: =(F15+F20)/F$21 -> 0.30721351 | G37: =(G15+G20)/G$21 -> 0.025215612 | H37: =(H15+H20)/H$21 -> 0.44818356 | I37: =(I15+I20)/I$21 -> 0.2489296 | J37: =D37-G37 -> -0.0069045736 | K37: =E37-H37 -> 0.057667971 | L37: =F37-I37 -> 0.058283908
B38: 일반보장성 | C38: Non-unit-linked protection types | D38: =(D9+D11+D19)/D$21 -> 0.88463341 | E38: =(E9+E11+E19)/E$21 -> 0 | F38: =(F9+F11+F19)/F$21 -> 0.3604251 | G38: =(G9+G11+G19)/G$21 -> 0.86352081 | H38: =(H9+H11+H19)/H$21 -> 0 | I38: =(I9+I11+I19)/I$21 -> 0.40679192 | J38: =D38-G38 -> 0.021112595 | K38: =E38-H38 -> 0 | L38: =F38-I38 -> -0.046366814
B39: 일반저축성 | C39: Non-unit-linked savings types | D39: =(D13+D16+D20)/D$21 -> 0.039292761 | E39: =(E13+E16+E20)/E$21 -> 0 | F39: =(F13+F16+F20)/F$21 -> 0.016009001 | G39: =(G13+G16+G20)/G$21 -> 0.060451941 | H39: =(H13+H16+H20)/H$21 -> 0 | I39: =(I13+I16+I20)/I$21 -> 0.028478018 | J39: =D39-G39 -> -0.02115918 | K39: =E39-H39 -> 0 | L39: =F39-I39 -> -0.012469016
B40: 변액 | C40: Uni-linked types | D40: =(D10+D14+D17)/D$21 -> 0.076073833 | E40: =(E10+E14+E17)/E$21 -> 1 | F40: =(F10+F14+F17)/F$21 -> 0.6235659 | G40: =(G10+G14+G17)/G$21 -> 0.076027248 | H40: =(H10+H14+H17)/H$21 -> 1 | I40: =(I10+I14+I17)/I$21 -> 0.56473007 | J40: =D40-G40 -> 4.6585259e-05 | K40: =E40-H40 -> 0 | L40: =F40-I40 -> 0.05883583

Sheet INITIAL
B1: =[6]INDEX!G14 -> 초회보험료 | C1: Initial Premiums
B2: (BN KRW, %, %p)
B4: 초회보험료 | C4: Initial Premiums | D4: =X4 -> 2025 | G4: =AD4 -> 2024 | J4: YoY | X4: 2025 | AD4: 2024 | AS4: 2023 | BH4: 2022
D5: =O5 -> FY | G5: =AD5 -> FY | O5: FY | R5: Q4 | U5: Q3 | X5: Q2 | AA5: Q1 | AD5: FY | AG5: Q4 | AJ5: Q3 | AM5: Q2 | AP5: Q1 | AS5: FY | AV5: Q4 | AY5: Q3 | BB5: Q2 | BE5: Q1 | BH5: FY | BK5: Q4 | BN5: Q3 | BQ5: Q2 | BT5: Q1
D6: 일반 General | E6: 특별 Separate | F6: 합계 Total | G6: 일반 General | H6: 특별 Separate | I6: 합계 Total | J6: 일반 General | K6: 특별 Separate | L6: 합계 Total | O6: 일반 General | P6: 특별 Separate | Q6: 합계 Total | R6: 일반 General | S6: 특별 Separate | T6: 합계 Total | U6: 일반 General | V6: 특별 Separate | W6: 합계 Total | X6: 일반 General | Y6: 특별 Separate | Z6: 합계 Total | AA6: 일반 General | AB6: 특별 Separate | AC6: 합계 Total | AD6: 일반 General | AE6: 특별 Separate | AF6: 합계 Total | AG6: 일반 General | AH6: 특별 Separate | AI6: 합계 Total | AJ6: 일반 General | AK6: 특별 Separate | AL6: 합계 Total | AM6: 일반 General | AN6: 특별 Separate | AO6: 합계 Total | AP6: 일반 General | AQ6: 특별 Separate | AR6: 합계 Total | AS6: 일반 General | AT6: 특별 Separate | AU6: 합계 Total | AV6: 일반 General | AW6: 특별 Separate | AX6: 합계 Total | AY6: 일반 General | AZ6: 특별 Separate | BA6: 합계 Total | BB6: 일반 General | BC6: 특별 Separate | BD6: 합계 Total | BE6: 일반 General | BF6: 특별 Separate | BG6: 합계 Total | BH6: 일반 General | BI6: 특별 Separate | BJ6: 합계 Total | BK6: 일반 General | BL6: 특별 Separate | BM6: 합계 Total | BN6: 일반 General | BO6: 특별 Separate | BP6: 합계 Total | BQ6: 일반 General | BR6: 특별 Separate | BS6: 합계 Total | BT6: 일반 General | BU6: 특별 Separate | BV6: 합계 Total
B7: 개인보험 | C7: Individual | D7: =D8+D12+D15 -> 33.41372 | E7: =E8+E12+E15 -> 1090.3925 | F7: =D7+E7 -> 1123.8062 | G7: =G8+G12+G15 -> 28.352873 | H7: =H8+H12+H15 -> 591.5706 | I7: =G7+H7 -> 619.92347 | J7: =+IFERROR(IF(G7<0,-(D7/G7-1),(D7/G7-1)),0) -> 0.17849503 | K7: =+IFERROR(IF(H7<0,-(E7/H7-1),(E7/H7-1)),0) -> 0.84321614 | L7: =+IFERROR(IF(I7<0,-(F7/I7-1),(F7/I7-1)),0) -> 0.8128144 | O7: =O8+O12+O15 -> 33.41372 | P7: =P8+P12+P15 -> 1090.3925 | Q7: =O7+P7 -> 1123.8062 | R7: =R8+R12+R15 -> 10.262717 | S7: =S8+S12+S15 -> 323.95061 | T7: =R7+S7 -> 334.21333 | U7: =U8+U12+U15 -> 9.699756 | V7: =V8+V12+V15 -> 374.86698 | W7: =U7+V7 -> 384.56673 | X7: =X8+X12+X15 -> 6.0877316 | Y7: =Y8+Y12+Y15 -> 150.37819 | Z7: =X7+Y7 -> 156.46592 | AA7: =AA8+AA12+AA15 -> 7.3635155 | AB7: =AB8+AB12+AB15 -> 241.1967 | AC7: =AA7+AB7 -> 248.56022 | AD7: =AD8+AD12+AD15 -> 28.352873 | AE7: =AE8+AE12+AE15 -> 591.5706 | AF7: =AD7+AE7 -> 619.92347 | AG7: =AG8+AG12+AG15 -> 8.1954249 | AH7: =AH8+AH12+AH15 -> 213.46305 | AI7: =AG7+AH7 -> 221.65847 | AJ7: =AJ8+AJ12+AJ15 -> 7.2602818 | AK7: =AK8+AK12+AK15 -> 168.36299 | AL7: =AJ7+AK7 -> 175.62327 | AM7: =AM8+AM12+AM15 -> 6.3629743 | AN7: =AN8+AN12+AN15 -> 109.76168 | AO7: =AM7+AN7 -> 116.12465 | AP7: =AP8+AP12+AP15 -> 6.5341924 | AQ7: =AQ8+AQ12+AQ15 -> 99.982884 | AR7: =AP7+AQ7 -> 106.51708 | AS7: =AS8+AS12+AS15 -> 17.697874 | AT7: =AT8+AT12+AT15 -> 115.16154 | AU7: =AS7+AT7 -> 132.85942 | AV7: =AV8+AV12+AV15 -> 5.0599444 | AW7: =AW8+AW12+AW15 -> 37.776592 | AX7: =AV7+AW7 -> 42.836536 | AY7: =AY8+AY12+AY15 -> 5.2351003 | AZ7: =AZ8+AZ12+AZ15 -> 38.026191 | BA7: =AY7+AZ7 -> 43.261291 | BB7: =BB8+BB12+BB15 -> 4.1819101 | BC7: =BC8+BC12+BC15 -> 27.002053 | BD7: =BB7+BC7 -> 31.183963 | BE7: =BE8+BE12+BE15 -> 3.2209191 | BF7: =BF8+BF12+BF15 -> 12.356708 | BG7: =BE7+BF7 -> 15.577627 | BH7: =BH8+BH12+BH15 -> 15.144007 | BI7: =BI8+BI12+BI15 -> 277.37857 | BJ7: =BH7+BI7 -> 292.52258 | BK7: =BK8+BK12+BK15 -> 3.1209452 | BL7: =BL8+BL12+BL15 -> 15.585064 | BM7: =BK7+BL7 -> 18.706009 | BN7: =BN8+BN12+BN15 -> 3.7417922 | BO7: =BO8+BO12+BO15 -> 40.319492 | BP7: =BN7+BO7 -> 44.061284 | BQ7: =BQ8+BQ12+BQ15 -> 3.9003214 | BR7: =BR8+BR12+BR15 -> 56.951029 | BS7: =BQ7+BR7 -> 60.851351 | BT7: =BT8+BT12+BT15 -> 4.3809485 | BU7: =BU8+BU12+BU15 -> 164.52299 | BV7: =BT7+BU7 -> 168.90394
B8: 보장성보험 | C8: Protections | D8: =SUM(D9:D11) -> 25.921721 | E8: =SUM(E9:E11) -> 5.1165285 | F8: =D8+E8 -> 31.03825 | G8: =SUM(G9:G11) -> 22.91161 | H8: =SUM(H9:H11) -> 3.7618272 | I8: =G8+H8 -> 26.673438 | J8: =+IFERROR(IF(G8<0,-(D8/G8-1),(D8/G8-1)),0) -> 0.13137927 | K8: =+IFERROR(IF(H8<0,-(E8/H8-1),(E8/H8-1)),0) -> 0.36011791 | L8: =+IFERROR(IF(I8<0,-(F8/I8-1),(F8/I8-1)),0) -> 0.1636389 | O8: 25.921721 | P8: 5.1165285 | Q8: =O8+P8 -> 31.03825 | R8: 7.7110693 | S8: 1.637158 | T8: =R8+S8 -> 9.3482273 | U8: 7.5102261 | V8: 1.5057402 | W8: =U8+V8 -> 9.0159664 | X8: =SUM(X9:X11) -> 4.9623771 | Y8: =SUM(Y9:Y11) -> 0.84091257 | Z8: =X8+Y8 -> 5.8032897 | AA8: =SUM(AA9:AA11) -> 5.7380487 | AB8: =SUM(AB9:AB11) -> 1.1327177 | AC8: =AA8+AB8 -> 6.8707664 | AD8: =SUM(AD9:AD11) -> 22.91161 | AE8: =SUM(AE9:AE11) -> 3.7618272 | AF8: =AD8+AE8 -> 26.673438 | AG8: =SUM(AG9:AG11) -> 6.5104684 | AH8: =SUM(AH9:AH11) -> 1.0460904 | AI8: =AG8+AH8 -> 7.5565588 | AJ8: =SUM(AJ9:AJ11) -> 6.0442234 | AK8: =SUM(AK9:AK11) -> 0.96844525 | AL8: =AJ8+AK8 -> 7.0126686 | AM8: =SUM(AM9:AM11) -> 4.9738864 | AN8: =SUM(AN9:AN11) -> 1.254717 | AO8: =AM8+AN8 -> 6.2286034 | AP8: =SUM(AP9:AP11) -> 5.3830323 | AQ8: =SUM(AQ9:AQ11) -> 0.49257446 | AR8: =AP8+AQ8 -> 5.8756068 | AS8: =SUM(AS9:AS11) -> 16.706406 | AT8: =SUM(AT9:AT11) -> 2.1417173 | AU8: =AS8+AT8 -> 18.848124 | AV8: =SUM(AV9:AV11) -> 4.6988065 | AW8: =SUM(AW9:AW11) -> 0.48371433 | AX8: =AV8+AW8 -> 5.1825209 | AY8: =SUM(AY9:AY11) -> 4.9053867 | AZ8: =SUM(AZ9:AZ11) -> 0.34444534 | BA8: =AY8+AZ8 -> 5.249832 | BB8: =SUM(BB9:BB11) -> 3.9952183 | BC8: =SUM(BC9:BC11) -> 0.64688769 | BD8: =BB8+BC8 -> 4.642106 | BE8: =SUM(BE9:BE11) -> 3.1069947 | BF8: =SUM(BF9:BF11) -> 0.66666995 | BG8: =BE8+BF8 -> 3.7736647 | BH8: =SUM(BH9:BH11) -> 12.970356 | BI8: =SUM(BI9:BI11) -> 5.7011009 | BJ8: =BH8+BI8 -> 18.671457 | BK8: =SUM(BK9:BK11) -> 2.9424235 | BL8: =SUM(BL9:BL11) -> 1.016034 | BM8: =BK8+BL8 -> 3.9584575 | BN8: =SUM(BN9:BN11) -> 3.398736 | BO8: =SUM(BO9:BO11) -> 1.0333746 | BP8: =BN8+BO8 -> 4.4321106 | BQ8: =SUM(BQ9:BQ11) -> 3.3794212 | BR8: =SUM(BR9:BR11) -> 1.358652 | BS8: =BQ8+BR8 -> 4.7380732 | BT8: =SUM(BT9:BT11) -> 3.2497755 | BU8: =SUM(BU9:BU11) -> 2.2930402 | BV8: =BT8+BU8 -> 5.5428158
B9: 일반종신/CI | C9: General whole life | D9: =SUM(X9,AA9,U9,R9) -> 2.0060432 | E9: =SUM(Y9,AB9,V9,S9) -> 0 | F9: =D9+E9 -> 2.0060432 | G9: =SUM(AM9,AP9,AJ9,AG9) -> 4.0769891 | H9: =SUM(AN9,AQ9,AK9,AH9) -> 0 | I9: =G9+H9 -> 4.0769891 | J9: =+IFERROR(IF(G9<0,-(D9/G9-1),(D9/G9-1)),0) -> -0.50795964 | K9: =+IFERROR(IF(H9<0,-(E9/H9-1),(E9/H9-1)),0) -> 0 | L9: =+IFERROR(IF(I9<0,-(F9/I9-1),(F9/I9-1)),0) -> -0.50795964 | O9: 2.0060432 | P9: 0 | Q9: =O9+P9 -> 2.0060432 | R9: 0.50864311 | S9: 0 | T9: =R9+S9 -> 0.50864311 | U9: 0.52775715 | V9: 0 | W9: =U9+V9 -> 0.52775715 | X9: 0.44888047 | Y9: 0 | Z9: =X9+Y9 -> 0.44888047 | AA9: 0.52076242 | AB9: 0 | AC9: =AA9+AB9 -> 0.52076242 | AD9: =+AG9+AJ9+AM9+AP9 -> 4.0769891 | AE9: =+AH9+AK9+AN9+AQ9 -> 0 | AF9: =AD9+AE9 -> 4.0769891 | AG9: 0.90095862 | AH9: 0 | AI9: =AG9+AH9 -> 0.90095862 | AJ9: 0.97583783 | AK9: 0 | AL9: =AJ9+AK9 -> 0.97583783 | AM9: 0.989227 | AN9: 0 | AO9: =AM9+AN9 -> 0.989227 | AP9: 1.2109656 | AQ9: 0 | AR9: =AP9+AQ9 -> 1.2109656 | AS9: =+AV9+AY9+BB9+BE9 -> 5.180244 | AT9: =+AW9+AZ9+BC9+BF9 -> 0 | AU9: =AS9+AT9 -> 5.180244 | AV9: 1.4547216 | AW9: 0 | AX9: =AV9+AW9 -> 1.4547216 | AY9: 1.9580654 | AZ9: 0 | BA9: =AY9+AZ9 -> 1.9580654 | BB9: 1.1245481 | BC9: 0 | BD9: =BB9+BC9 -> 1.1245481 | BE9: 0.64290898 | BF9: 0 | BG9: =BE9+BF9 -> 0.64290898 | BH9: =SUM(BK9,BN9,BQ9,BT9) -> 2.8678145 | BI9: =SUM(BL9,BO9,BR9,BU9) -> 0 | BJ9: =BH9+BI9 -> 2.8678145 | BK9: 0.70245773 | BL9: 0 | BM9: =BK9+BL9 -> 0.70245773 | BN9: 0.95914017 | BO9: 0 | BP9: =BN9+BO9 -> 0.95914017 | BQ9: 0.77799656 | BR9: 0 | BS9: =BQ9+BR9 -> 0.77799656 | BT9: 0.42822 | BU9: 0 | BV9: =BT9+BU9 -> 0.42822
B10: 변액종신/CI | C10: Variable whole life | D10: =SUM(X10,AA10,U10,R10) -> 2.3473917 | E10: =SUM(Y10,AB10,V10,S10) -> 5.1165285 | F10: =D10+E10 -> 7.4639203 | G10: =SUM(AM10,AP10,AJ10,AG10) -> 1.8362628 | H10: =SUM(AN10,AQ10,AK10,AH10) -> 3.7618272 | I10: =G10+H10 -> 5.59809 | J10: =+IFERROR(IF(G10<0,-(D10/G10-1),(D10/G10-1)),0) -> 0.27835283 | K10: =+IFERROR(IF(H10<0,-(E10/H10-1),(E10/H10-1)),0) -> 0.36011791 | L10: =+IFERROR(IF(I10<0,-(F10/I10-1),(F10/I10-1)),0) -> 0.33329766 | O10: 2.3473917 | P10: 5.1165285 | Q10: =O10+P10 -> 7.4639203 | R10: 0.70639556 | S10: 1.637158 | T10: =R10+S10 -> 2.3435536 | U10: 0.67146127 | V10: 1.5057402 | W10: =U10+V10 -> 2.1772015 | X10: 0.47764533 | Y10: 0.84091257 | Z10: =X10+Y10 -> 1.3185579 | AA10: 0.49188959 | AB10: 1.1327177 | AC10: =AA10+AB10 -> 1.6246073 | AD10: =+AG10+AJ10+AM10+AP10 -> 1.8362628 | AE10: =+AH10+AK10+AN10+AQ10 -> 3.7618272 | AF10: =AD10+AE10 -> 5.59809 | AG10: 0.50865922 | AH10: 1.0460904 | AI10: =AG10+AH10 -> 1.5547496 | AJ10: 0.52568558 | AK10: 0.96844525 | AL10: =AJ10+AK10 -> 1.4941308 | AM10: 0.52456751 | AN10: 1.254717 | AO10: =AM10+AN10 -> 1.7792845 | AP10: 0.27735049 | AQ10: 0.49257446 | AR10: =AP10+AQ10 -> 0.76992494 | AS10: =+AV10+AY10+BB10+BE10 -> 0.88627432 | AT10: =+AW10+AZ10+BC10+BF10 -> 2.1417173 | AU10: =AS10+AT10 -> 3.0279916 | AV10: 0.18274903 | AW10: 0.48371433 | AX10: =AV10+AW10 -> 0.66646336 | AY10: 0.15562082 | AZ10: 0.34444534 | BA10: =AY10+AZ10 -> 0.50006616 | BB10: 0.28396446 | BC10: 0.64688769 | BD10: =BB10+BC10 -> 0.93085216 | BE10: 0.26394001 | BF10: 0.66666995 | BG10: =BE10+BF10 -> 0.93060997 | BH10: =SUM(BK10,BN10,BQ10,BT10) -> 1.9177004 | BI10: =SUM(BL10,BO10,BR10,BU10) -> 5.7011009 | BJ10: =BH10+BI10 -> 7.6188013 | BK10: 0.35116651 | BL10: 1.016034 | BM10: =BK10+BL10 -> 1.3672005 | BN10: 0.36013958 | BO10: 1.0333746 | BP10: =BN10+BO10 -> 1.3935142 | BQ10: 0.47809421 | BR10: 1.358652 | BS10: =BQ10+BR10 -> 1.8367462 | BT10: 0.72830008 | BU10: 2.2930402 | BV10: =BT10+BU10 -> 3.0213403
B11: 기타보장 | C11: Others | D11: =SUM(X11,AA11,U11,R11) -> 21.568286 | E11: =SUM(Y11,AB11,V11,S11) -> 0 | F11: =D11+E11 -> 21.568286 | G11: =SUM(AM11,AP11,AJ11,AG11) -> 16.998359 | H11: =SUM(AN11,AQ11,AK11,AH11) -> 0 | I11: =G11+H11 -> 16.998359 | J11: =+IFERROR(IF(G11<0,-(D11/G11-1),(D11/G11-1)),0) -> 0.26884523 | K11: =+IFERROR(IF(H11<0,-(E11/H11-1),(E11/H11-1)),0) -> 0 | L11: =+IFERROR(IF(I11<0,-(F11/I11-1),(F11/I11-1)),0) -> 0.26884523 | O11: 21.568286 | P11: 0 | Q11: =O11+P11 -> 21.568286 | R11: 6.4960306 | S11: 0 | T11: =R11+S11 -> 6.4960306 | U11: 6.3110077 | V11: 0 | W11: =U11+V11 -> 6.3110077 | X11: 4.0358513 | Y11: 0 | Z11: =X11+Y11 -> 4.0358513 | AA11: 4.7253966 | AB11: 0 | AC11: =AA11+AB11 -> 4.7253966 | AD11: =+AG11+AJ11+AM11+AP11 -> 16.998359 | AE11: =+AH11+AK11+AN11+AQ11 -> 0 | AF11: =AD11+AE11 -> 16.998359 | AG11: 5.1008505 | AH11: 0 | AI11: =AG11+AH11 -> 5.1008505 | AJ11: 4.5427 | AK11: 0 | AL11: =AJ11+AK11 -> 4.5427 | AM11: 3.4600919 | AN11: 0 | AO11: =AM11+AN11 -> 3.4600919 | AP11: 3.8947162 | AQ11: 0 | AR11: =AP11+AQ11 -> 3.8947162 | AS11: =+AV11+AY11+BB11+BE11 -> 10.639888 | AT11: =+AW11+AZ11+BC11+BF11 -> 0 | AU11: =AS11+AT11 -> 10.639888 | AV11: 3.0613359 | AW11: 0 | AX11: =AV11+AW11 -> 3.0613359 | AY11: 2.7917005 | AZ11: 0 | BA11: =AY11+AZ11 -> 2.7917005 | BB11: 2.5867057 | BC11: 0 | BD11: =BB11+BC11 -> 2.5867057 | BE11: 2.2001457 | BF11: 0 | BG11: =BE11+BF11 -> 2.2001457 | BH11: =SUM(BK11,BN11,BQ11,BT11) -> 8.1848414 | BI11: =SUM(BL11,BO11,BR11,BU11) -> 0 | BJ11: =BH11+BI11 -> 8.1848414 | BK11: 1.8887993 | BL11: 0 | BM11: =BK11+BL11 -> 1.8887993 | BN11: 2.0794562 | BO11: 0 | BP11: =BN11+BO11 -> 2.0794562 | BQ11: 2.1233304 | BR11: 0 | BS11: =BQ11+BR11 -> 2.1233304 | BT11: 2.0932555 | BU11: 0 | BV11: =BT11+BU11 -> 2.0932555
B12: 연금보험 | C12: Annuities | D12: =SUM(D13:D14) -> 5.7690886 | E12: =SUM(E13:E14) -> 374.01552 | F12: =D12+E12 -> 379.7846 | G12: =SUM(G13:G14) -> 4.4744522 | H12: =SUM(H13:H14) -> 251.51947 | I12: =G12+H12 -> 255.99392 | J12: =+IFERROR(IF(G12<0,-(D12/G12-1),(D12/G12-1)),0) -> 0.28933963 | K12: =+IFERROR(IF(H12<0,-(E12/H12-1),(E12/H12-1)),0) -> 0.4870241 | L12: =+IFERROR(IF(I12<0,-(F12/I12-1),(F12/I12-1)),0) -> 0.48356882 | O12: 5.7690886 | P12: 374.01552 | Q12: =O12+P12 -> 379.7846 | R12: 2.1290537 | S12: 129.42008 | T12: =R12+S12 -> 131.54913 | U12: 1.5878107 | V12: 116.58687 | W12: =U12+V12 -> 118.17469 | X12: =SUM(X13:X14) -> 0.85770273 | Y12: =SUM(Y13:Y14) -> 57.772506 | Z12: =X12+Y12 -> 58.630209 | AA12: =SUM(AA13:AA14) -> 1.1945215 | AB12: =SUM(AB13:AB14) -> 70.236058 | AC12: =AA12+AB12 -> 71.430579 | AD12: =SUM(AD13:AD14) -> 4.4744522 | AE12: =SUM(AE13:AE14) -> 251.51947 | AF12: =AD12+AE12 -> 255.99392 | AG12: =SUM(AG13:AG14) -> 1.4447962 | AH12: =SUM(AH13:AH14) -> 103.01693 | AI12: =AG12+AH12 -> 104.46172 | AJ12: =SUM(AJ13:AJ14) -> 0.94447803 | AK12: =SUM(AK13:AK14) -> 52.701924 | AL12: =AJ12+AK12 -> 53.646402 | AM12: =SUM(AM13:AM14) -> 1.1639908 | AN12: =SUM(AN13:AN14) -> 51.78704 | AO12: =AM12+AN12 -> 52.951031 | AP12: =SUM(AP13:AP14) -> 0.92118726 | AQ12: =SUM(AQ13:AQ14) -> 44.013583 | AR12: =AP12+AQ12 -> 44.93477 | AS12: =SUM(AS13:AS14) -> 0.75040749 | AT12: =SUM(AT13:AT14) -> 41.219566 | AU12: =AS12+AT12 -> 41.969974 | AV12: =SUM(AV13:AV14) -> 0.30464205 | AW12: =SUM(AW13:AW14) -> 16.344203 | AX12: =AV12+AW12 -> 16.648845 | AY12: =SUM(AY13:AY14) -> 0.24018986 | AZ12: =SUM(AZ13:AZ14) -> 14.571259 | BA12: =AY12+AZ12 -> 14.811449 | BB12: =SUM(BB13:BB14) -> 0.1267805 | BC12: =SUM(BC13:BC14) -> 7.0495264 | BD12: =BB12+BC12 -> 7.1763069 | BE12: =SUM(BE13:BE14) -> 0.078795069 | BF12: =SUM(BF13:BF14) -> 3.2545771 | BG12: =BE12+BF12 -> 3.3333722 | BH12: =SUM(BH13:BH14) -> 1.6605565 | BI12: =SUM(BI13:BI14) -> 99.415198 | BJ12: =BH12+BI12 -> 101.07575 | BK12: =SUM(BK13:BK14) -> 0.151499 | BL12: =SUM(BL13:BL14) -> 5.9011324 | BM12: =BK12+BL12 -> 6.0526313 | BN12: =SUM(BN13:BN14) -> 0.24075783 | BO12: =SUM(BO13:BO14) -> 9.1262254 | BP12: =BN12+BO12 -> 9.3669832 | BQ12: =SUM(BQ13:BQ14) -> 0.42976557 | BR12: =SUM(BR13:BR14) -> 27.069412 | BS12: =BQ12+BR12 -> 27.499177 | BT12: =SUM(BT13:BT14) -> 0.83853411 | BU12: =SUM(BU13:BU14) -> 57.318429 | BV12: =BT12+BU12 -> 58.156963
B13: 일반연금 | C13: General annuities | D13: =SUM(X13,AA13,U13,R13) -> 0 | E13: =SUM(Y13,AB13,V13,S13) -> 0 | F13: =D13+E13 -> 0 | G13: =SUM(AM13,AP13,AJ13,AG13) -> 0 | H13: =SUM(AN13,AQ13,AK13,AH13) -> 0 | I13: =G13+H13 -> 0 | J13: =+IFERROR(IF(G13<0,-(D13/G13-1),(D13/G13-1)),0) -> 0 | K13: =+IFERROR(IF(H13<0,-(E13/H13-1),(E13/H13-1)),0) -> 0 | L13: =+IFERROR(IF(I13<0,-(F13/I13-1),(F13/I13-1)),0) -> 0 | O13: 0 | P13: 0 | Q13: =O13+P13 -> 0 | R13: 0 | S13: 0 | T13: =R13+S13 -> 0 | U13: 0 | V13: 0 | W13: =U13+V13 -> 0 | X13: 0 | Y13: 0 | Z13: =X13+Y13 -> 0 | AA13: 0 | AB13: 0 | AC13: =AA13+AB13 -> 0 | AD13: =+AG13+AJ13+AM13+AP13 -> 0 | AE13: =+AH13+AK13+AN13+AQ13 -> 0 | AF13: =AD13+AE13 -> 0 | AG13: 0 | AH13: 0 | AI13: =AG13+AH13 -> 0 | AJ13: 0 | AK13: 0 | AL13: =AJ13+AK13 -> 0 | AM13: 0 | AN13: 0 | AO13: =AM13+AN13 -> 0 | AP13: 0 | AQ13: 0 | AR13: =AP13+AQ13 -> 0 | AS13: =+AV13+AY13+BB13+BE13 -> 0 | AT13: =+AW13+AZ13+BC13+BF13 -> 0 | AU13: =AS13+AT13 -> 0 | AV13: 0 | AW13: 0 | AX13: =AV13+AW13 -> 0 | AY13: 0 | AZ13: 0 | BA13: =AY13+AZ13 -> 0 | BB13: 0 | BC13: 0 | BD13: =BB13+BC13 -> 0 | BE13: 0 | BF13: 0 | BG13: =BE13+BF13 -> 0 | BH13: =SUM(BK13,BN13,BQ13,BT13) -> 0 | BI13: =SUM(BL13,BO13,BR13,BU13) -> 0 | BJ13: =BH13+BI13 -> 0 | BK13: 0 | BL13: 0 | BM13: =BK13+BL13 -> 0 | BN13: 0 | BO13: 0 | BP13: =BN13+BO13 -> 0 | BQ13: 0 | BR13: 0 | BS13: =BQ13+BR13 -> 0 | BT13: 0 | BU13: 0 | BV13: =BT13+BU13 -> 0
B14: 변액연금 | C14: Variable annuities | D14: =SUM(X14,AA14,U14,R14) -> 5.7690886 | E14: =SUM(Y14,AB14,V14,S14) -> 374.01552 | F14: =D14+E14 -> 379.7846 | G14: =SUM(AM14,AP14,AJ14,AG14) -> 4.4744522 | H14: =SUM(AN14,AQ14,AK14,AH14) -> 251.51947 | I14: =G14+H14 -> 255.99392 | J14: =+IFERROR(IF(G14<0,-(D14/G14-1),(D14/G14-1)),0) -> 0.28933963 | K14: =+IFERROR(IF(H14<0,-(E14/H14-1),(E14/H14-1)),0) -> 0.4870241 | L14: =+IFERROR(IF(I14<0,-(F14/I14-1),(F14/I14-1)),0) -> 0.48356882 | O14: 5.7690886 | P14: 374.01552 | Q14: =O14+P14 -> 379.7846 | R14: 2.1290537 | S14: 129.42008 | T14: =R14+S14 -> 131.54913 | U14: 1.5878107 | V14: 116.58687 | W14: =U14+V14 -> 118.17469 | X14: 0.85770273 | Y14: 57.772506 | Z14: =X14+Y14 -> 58.630209 | AA14: 1.1945215 | AB14: 70.236058 | AC14: =AA14+AB14 -> 71.430579 | AD14: =+AG14+AJ14+AM14+AP14 -> 4.4744522 | AE14: =+AH14+AK14+AN14+AQ14 -> 251.51947 | AF14: =AD14+AE14 -> 255.99392 | AG14: 1.4447962 | AH14: 103.01693 | AI14: =AG14+AH14 -> 104.46172 | AJ14: 0.94447803 | AK14: 52.701924 | AL14: =AJ14+AK14 -> 53.646402 | AM14: 1.1639908 | AN14: 51.78704 | AO14: =AM14+AN14 -> 52.951031 | AP14: 0.92118726 | AQ14: 44.013583 | AR14: =AP14+AQ14 -> 44.93477 | AS14: =+AV14+AY14+BB14+BE14 -> 0.75040749 | AT14: =+AW14+AZ14+BC14+BF14 -> 41.219566 | AU14: =AS14+AT14 -> 41.969974 | AV14: 0.30464205 | AW14: 16.344203 | AX14: =AV14+AW14 -> 16.648845 | AY14: 0.24018986 | AZ14: 14.571259 | BA14: =AY14+AZ14 -> 14.811449 | BB14: 0.1267805 | BC14: 7.0495264 | BD14: =BB14+BC14 -> 7.1763069 | BE14: 0.078795069 | BF14: 3.2545771 | BG14: =BE14+BF14 -> 3.3333722 | BH14: =SUM(BK14,BN14,BQ14,BT14) -> 1.6605565 | BI14: =SUM(BL14,BO14,BR14,BU14) -> 99.415198 | BJ14: =BH14+BI14 -> 101.07575 | BK14: 0.151499 | BL14: 5.9011324 | BM14: =BK14+BL14 -> 6.0526313 | BN14: 0.24075783 | BO14: 9.1262254 | BP14: =BN14+BO14 -> 9.3669832 | BQ14: 0.42976557 | BR14: 27.069412 | BS14: =BQ14+BR14 -> 27.499177 | BT14: 0.83853411 | BU14: 57.318429 | BV14: =BT14+BU14 -> 58.156963
B15: 저축보험 | C15: Savings / Investments | D15: =SUM(D16:D17) -> 1.7229106 | E15: =SUM(E16:E17) -> 711.26043 | F15: =D15+E15 -> 712.98334 | G15: =SUM(G16:G17) -> 0.96681067 | H15: =SUM(H16:H17) -> 336.2893 | I15: =G15+H15 -> 337.25611 | J15: =+IFERROR(IF(G15<0,-(D15/G15-1),(D15/G15-1)),0) -> 0.78205589 | K15: =+IFERROR(IF(H15<0,-(E15/H15-1),(E15/H15-1)),0) -> 1.1150255 | L15: =+IFERROR(IF(I15<0,-(F15/I15-1),(F15/I15-1)),0) -> 1.1140709 | O15: 1.7229106 | P15: 711.26043 | Q15: =O15+P15 -> 712.98334 | R15: 0.42259437 | S15: 192.89338 | T15: =R15+S15 -> 193.31597 | U15: 0.60171922 | V15: 256.77436 | W15: =U15+V15 -> 257.37608 | X15: =SUM(X16:X17) -> 0.26765178 | Y15: =SUM(Y16:Y17) -> 91.764768 | Z15: =X15+Y15 -> 92.03242 | AA15: =SUM(AA16:AA17) -> 0.43094528 | AB15: =SUM(AB16:AB17) -> 169.82792 | AC15: =AA15+AB15 -> 170.25887 | AD15: =SUM(AD16:AD17) -> 0.96681067 | AE15: =SUM(AE16:AE17) -> 336.2893 | AF15: =AD15+AE15 -> 337.25611 | AG15: =SUM(AG16:AG17) -> 0.24016037 | AH15: =SUM(AH16:AH17) -> 109.40003 | AI15: =AG15+AH15 -> 109.64019 | AJ15: =SUM(AJ16:AJ17) -> 0.27158035 | AK15: =SUM(AK16:AK17) -> 114.69262 | AL15: =AJ15+AK15 -> 114.9642 | AM15: =SUM(AM16:AM17) -> 0.2250971 | AN15: =SUM(AN16:AN17) -> 56.719923 | AO15: =AM15+AN15 -> 56.94502 | AP15: =SUM(AP16:AP17) -> 0.22997283 | AQ15: =SUM(AQ16:AQ17) -> 55.476727 | AR15: =AP15+AQ15 -> 55.7067 | AS15: =SUM(AS16:AS17) -> 0.24106024 | AT15: =SUM(AT16:AT17) -> 71.80026 | AU15: =AS15+AT15 -> 72.04132 | AV15: =SUM(AV16:AV17) -> 0.056495831 | AW15: =SUM(AW16:AW17) -> 20.948674 | AX15: =AV15+AW15 -> 21.00517 | AY15: =SUM(AY16:AY17) -> 0.089523762 | AZ15: =SUM(AZ16:AZ17) -> 23.110486 | BA15: =AY15+AZ15 -> 23.20001 | BB15: =SUM(BB16:BB17) -> 0.05991129 | BC15: =SUM(BC16:BC17) -> 19.305639 | BD15: =BB15+BC15 -> 19.36555 | BE15: =SUM(BE16:BE17) -> 0.035129353 | BF15: =SUM(BF16:BF17) -> 8.4354606 | BG15: =BE15+BF15 -> 8.47059 | BH15: =SUM(BH16:BH17) -> 0.51309465 | BI15: =SUM(BI16:BI17) -> 172.26228 | BJ15: =BH15+BI15 -> 172.77537 | BK15: =SUM(BK16:BK17) -> 0.027022682 | BL15: =SUM(BL16:BL17) -> 8.6678973 | BM15: =BK15+BL15 -> 8.69492 | BN15: =SUM(BN16:BN17) -> 0.10229844 | BO15: =SUM(BO16:BO17) -> 30.159892 | BP15: =BN15+BO15 -> 30.26219 | BQ15: =SUM(BQ16:BQ17) -> 0.091134671 | BR15: =SUM(BR16:BR17) -> 28.522965 | BS15: =BQ15+BR15 -> 28.6141 | BT15: =SUM(BT16:BT17) -> 0.29263887 | BU15: =SUM(BU16:BU17) -> 104.91152 | BV15: =BT15+BU15 -> 105.20416
B16: 일반저축 | C16: General savings | D16: =SUM(X16,AA16,U16,R16) -> 0 | E16: =SUM(Y16,AB16,V16,S16) -> 0 | F16: =D16+E16 -> 0 | G16: =SUM(AM16,AP16,AJ16,AG16) -> 0 | H16: =SUM(AN16,AQ16,AK16,AH16) -> 0 | I16: =G16+H16 -> 0 | J16: =+IFERROR(IF(G16<0,-(D16/G16-1),(D16/G16-1)),0) -> 0 | K16: =+IFERROR(IF(H16<0,-(E16/H16-1),(E16/H16-1)),0) -> 0 | L16: =+IFERROR(IF(I16<0,-(F16/I16-1),(F16/I16-1)),0) -> 0 | O16: 0 | P16: 0 | Q16: =O16+P16 -> 0 | R16: 0 | S16: 0 | T16: =R16+S16 -> 0 | U16: 0 | V16: 0 | W16: =U16+V16 -> 0 | X16: 0 | Y16: 0 | Z16: =X16+Y16 -> 0 | AA16: 0 | AB16: 0 | AC16: =AA16+AB16 -> 0 | AD16: =+AG16+AJ16+AM16+AP16 -> 0 | AE16: =+AH16+AK16+AN16+AQ16 -> 0 | AF16: =AD16+AE16 -> 0 | AG16: 0 | AH16: 0 | AI16: =AG16+AH16 -> 0 | AJ16: 0 | AK16: 0 | AL16: =AJ16+AK16 -> 0 | AM16: 0 | AN16: 0 | AO16: =AM16+AN16 -> 0 | AP16: 0 | AQ16: 0 | AR16: =AP16+AQ16 -> 0 | AS16: =+AV16+AY16+BB16+BE16 -> 0 | AT16: =+AW16+AZ16+BC16+BF16 -> 0 | AU16: =AS16+AT16 -> 0 | AV16: 0 | AW16: 0 | AX16: =AV16+AW16 -> 0 | AY16: 0 | AZ16: 0 | BA16: =AY16+AZ16 -> 0 | BB16: 0 | BC16: 0 | BD16: =BB16+BC16 -> 0 | BE16: 0 | BF16: 0 | BG16: =BE16+BF16 -> 0 | BH16: =SUM(BK16,BN16,BQ16,BT16) -> 0 | BI16: =SUM(BL16,BO16,BR16,BU16) -> 0 | BJ16: =BH16+BI16 -> 0 | BK16: 0 | BL16: 0 | BM16: =BK16+BL16 -> 0 | BN16: 0 | BO16: 0 | BP16: =BN16+BO16 -> 0 | BQ16: 0 | BR16: 0 | BS16: =BQ16+BR16 -> 0 | BT16: 0 | BU16: 0 | BV16: =BT16+BU16 -> 0
B17: 변액저축 | C17: Variable investments | D17: =SUM(X17,AA17,U17,R17) -> 1.7229106 | E17: =SUM(Y17,AB17,V17,S17) -> 711.26043 | F17: =D17+E17 -> 712.98334 | G17: =SUM(AM17,AP17,AJ17,AG17) -> 0.96681067 | H17: =SUM(AN17,AQ17,AK17,AH17) -> 336.2893 | I17: =G17+H17 -> 337.25611 | J17: =+IFERROR(IF(G17<0,-(D17/G17-1),(D17/G17-1)),0) -> 0.78205589 | K17: =+IFERROR(IF(H17<0,-(E17/H17-1),(E17/H17-1)),0) -> 1.1150255 | L17: =+IFERROR(IF(I17<0,-(F17/I17-1),(F17/I17-1)),0) -> 1.1140709 | O17: 1.7229106 | P17: 711.26043 | Q17: =O17+P17 -> 712.98334 | R17: 0.42259437 | S17: 192.89338 | T17: =R17+S17 -> 193.31597 | U17: 0.60171922 | V17: 256.77436 | W17: =U17+V17 -> 257.37608 | X17: 0.26765178 | Y17: 91.764768 | Z17: =X17+Y17 -> 92.03242 | AA17: 0.43094528 | AB17: 169.82792 | AC17: =AA17+AB17 -> 170.25887 | AD17: =+AG17+AJ17+AM17+AP17 -> 0.96681067 | AE17: =+AH17+AK17+AN17+AQ17 -> 336.2893 | AF17: =AD17+AE17 -> 337.25611 | AG17: 0.24016037 | AH17: 109.40003 | AI17: =AG17+AH17 -> 109.64019 | AJ17: 0.27158035 | AK17: 114.69262 | AL17: =AJ17+AK17 -> 114.9642 | AM17: 0.2250971 | AN17: 56.719923 | AO17: =AM17+AN17 -> 56.94502 | AP17: 0.22997283 | AQ17: 55.476727 | AR17: =AP17+AQ17 -> 55.7067 | AS17: =+AV17+AY17+BB17+BE17 -> 0.24106024 | AT17: =+AW17+AZ17+BC17+BF17 -> 71.80026 | AU17: =AS17+AT17 -> 72.04132 | AV17: 0.056495831 | AW17: 20.948674 | AX17: =AV17+AW17 -> 21.00517 | AY17: 0.089523762 | AZ17: 23.110486 | BA17: =AY17+AZ17 -> 23.20001 | BB17: 0.05991129 | BC17: 19.305639 | BD17: =BB17+BC17 -> 19.36555 | BE17: 0.035129353 | BF17: 8.4354606 | BG17: =BE17+BF17 -> 8.47059 | BH17: =SUM(BK17,BN17,BQ17,BT17) -> 0.51309465 | BI17: =SUM(BL17,BO17,BR17,BU17) -> 172.26228 | BJ17: =BH17+BI17 -> 172.77537 | BK17: 0.027022682 | BL17: 8.6678973 | BM17: =BK17+BL17 -> 8.69492 | BN17: 0.10229844 | BO17: 30.159892 | BP17: =BN17+BO17 -> 30.26219 | BQ17: 0.091134671 | BR17: 28.522965 | BS17: =BQ17+BR17 -> 28.6141 | BT17: 0.29263887 | BU17: 104.91152 | BV17: =BT17+BU17 -> 105.20416
B18: 단체보험 | C18: Groups | D18: =SUM(D19:D20) -> 0.017317237 | E18: =SUM(E19:E20) -> 0 | F18: =D18+E18 -> 0.017317237 | G18: =SUM(G19:G20) -> 0.02137422 | H18: =SUM(H19:H20) -> 0 | I18: =G18+H18 -> 0.02137422 | J18: =+IFERROR(IF(G18<0,-(D18/G18-1),(D18/G18-1)),0) -> -0.1898073 | K18: =+IFERROR(IF(H18<0,-(E18/H18-1),(E18/H18-1)),0) -> 0 | L18: =+IFERROR(IF(I18<0,-(F18/I18-1),(F18/I18-1)),0) -> -0.1898073 | O18: 0.013362881 | P18: 0 | Q18: =O18+P18 -> 0.013362881 | R18: 0.00172747 | S18: 0 | T18: =R18+S18 -> 0.00172747 | U18: =SUM(U19:U20) -> 0.005196589 | V18: =SUM(V19:V20) -> 0 | W18: =U18+V18 -> 0.005196589 | X18: =SUM(X19:X20) -> 0.005196589 | Y18: =SUM(Y19:Y20) -> 0 | Z18: =X18+Y18 -> 0.005196589 | AA18: =SUM(AA19:AA20) -> 0.005196589 | AB18: =SUM(AB19:AB20) -> 0 | AC18: =AA18+AB18 -> 0.005196589 | AD18: =SUM(AD19:AD20) -> 0.02137422 | AE18: =SUM(AE19:AE20) -> 0 | AF18: =AD18+AE18 -> 0.02137422 | AG18: =SUM(AG19:AG20) -> 0.0052473 | AH18: =SUM(AH19:AH20) -> 0 | AI18: =AG18+AH18 -> 0.0052473 | AJ18: =SUM(AJ19:AJ20) -> 0.001661579 | AK18: =SUM(AK19:AK20) -> 0 | AL18: =AJ18+AK18 -> 0.001661579 | AM18: =SUM(AM19:AM20) -> 0.006886626 | AN18: =SUM(AN19:AN20) -> 0 | AO18: =AM18+AN18 -> 0.006886626 | AP18: =SUM(AP19:AP20) -> 0.007578715 | AQ18: =SUM(AQ19:AQ20) -> 0 | AR18: =AP18+AQ18 -> 0.007578715 | AS18: =SUM(AS19:AS20) -> 0.034267079 | AT18: =SUM(AT19:AT20) -> 0 | AU18: =AS18+AT18 -> 0.034267079 | AV18: =SUM(AV19:AV20) -> 0.006025608 | AW18: =SUM(AW19:AW20) -> 0 | AX18: =AV18+AW18 -> 0.006025608 | AY18: =SUM(AY19:AY20) -> 0.006148469 | AZ18: =SUM(AZ19:AZ20) -> 0 | BA18: =AY18+AZ18 -> 0.006148469 | BB18: =SUM(BB19:BB20) -> 0.005935552 | BC18: =SUM(BC19:BC20) -> 0 | BD18: =BB18+BC18 -> 0.005935552 | BE18: =SUM(BE19:BE20) -> 0.01615745 | BF18: =SUM(BF19:BF20) -> 0 | BG18: =BE18+BF18 -> 0.01615745 | BH18: =SUM(BH19:BH20) -> 0.047245861 | BI18: =SUM(BI19:BI20) -> 0 | BJ18: =BH18+BI18 -> 0.047245861 | BK18: =SUM(BK19:BK20) -> 0.008885993 | BL18: =SUM(BL19:BL20) -> 0 | BM18: =BK18+BL18 -> 0.008885993 | BN18: =SUM(BN19:BN20) -> 0.008335764 | BO18: =SUM(BO19:BO20) -> 0 | BP18: =BN18+BO18 -> 0.008335764 | BQ18: =SUM(BQ19:BQ20) -> 0.017088877 | BR18: =SUM(BR19:BR20) -> 0 | BS18: =BQ18+BR18 -> 0.017088877 | BT18: =SUM(BT19:BT20) -> 0.012935227 | BU18: =SUM(BU19:BU20) -> 0 | BV18: =BT18+BU18 -> 0.012935227
B19: 보장성 | C19: Protections | D19: =SUM(X19,AA19,U19,R19) -> 0.017317237 | E19: =SUM(Y19,AB19,V19,S19) -> 0 | F19: =D19+E19 -> 0.017317237 | G19: =SUM(AM19,AP19,AJ19,AG19) -> 0.02137422 | H19: =SUM(AN19,AQ19,AK19,AH19) -> 0 | I19: =G19+H19 -> 0.02137422 | J19: =+IFERROR(IF(G19<0,-(D19/G19-1),(D19/G19-1)),0) -> -0.1898073 | K19: =+IFERROR(IF(H19<0,-(E19/H19-1),(E19/H19-1)),0) -> 0 | L19: =+IFERROR(IF(I19<0,-(F19/I19-1),(F19/I19-1)),0) -> -0.1898073 | O19: 0.013362881 | P19: 0 | Q19: =O19+P19 -> 0.013362881 | R19: 0.00172747 | S19: 0 | T19: =R19+S19 -> 0.00172747 | U19: 0.005196589 | V19: 0 | W19: =U19+V19 -> 0.005196589 | X19: 0.005196589 | Y19: 0 | Z19: =X19+Y19 -> 0.005196589 | AA19: 0.005196589 | AB19: 0 | AC19: =AA19+AB19 -> 0.005196589 | AD19: =+AG19+AJ19+AM19+AP19 -> 0.02137422 | AE19: =+AH19+AK19+AN19+AQ19 -> 0 | AF19: =AD19+AE19 -> 0.02137422 | AG19: 0.0052473 | AH19: 0 | AI19: =AG19+AH19 -> 0.0052473 | AJ19: 0.001661579 | AK19: 0 | AL19: =AJ19+AK19 -> 0.001661579 | AM19: 0.006886626 | AN19: 0 | AO19: =AM19+AN19 -> 0.006886626 | AP19: 0.007578715 | AQ19: 0 | AR19: =AP19+AQ19 -> 0.007578715 | AS19: =+AV19+AY19+BB19+BE19 -> 0.034267079 | AT19: =+AW19+AZ19+BC19+BF19 -> 0 | AU19: =AS19+AT19 -> 0.034267079 | AV19: 0.006025608 | AW19: 0 | AX19: =AV19+AW19 -> 0.006025608 | AY19: 0.006148469 | AZ19: 0 | BA19: =AY19+AZ19 -> 0.006148469 | BB19: 0.005935552 | BC19: 0 | BD19: =BB19+BC19 -> 0.005935552 | BE19: 0.01615745 | BF19: 0 | BG19: =BE19+BF19 -> 0.01615745 | BH19: =SUM(BK19,BN19,BQ19,BT19) -> 0.047245861 | BI19: =SUM(BL19,BO19,BR19,BU19) -> 0 | BJ19: =BH19+BI19 -> 0.047245861 | BK19: 0.008885993 | BL19: 0 | BM19: =BK19+BL19 -> 0.008885993 | BN19: 0.008335764 | BO19: 0 | BP19: =BN19+BO19 -> 0.008335764 | BQ19: 0.017088877 | BR19: 0 | BS19: =BQ19+BR19 -> 0.017088877 | BT19: 0.012935227 | BU19: 0 | BV19: =BT19+BU19 -> 0.012935227
B20: 저축성 | C20: Savings | D20: =SUM(X20,AA20,U20,R20) -> 0 | E20: =SUM(Y20,AB20,V20,S20) -> 0 | F20: =D20+E20 -> 0 | G20: =SUM(AM20,AP20,AJ20,AG20) -> 0 | H20: =SUM(AN20,AQ20,AK20,AH20) -> 0 | I20: =G20+H20 -> 0 | J20: =+IFERROR(IF(G20<0,-(D20/G20-1),(D20/G20-1)),0) -> 0 | K20: =+IFERROR(IF(H20<0,-(E20/H20-1),(E20/H20-1)),0) -> 0 | L20: =+IFERROR(IF(I20<0,-(F20/I20-1),(F20/I20-1)),0) -> 0 | O20: 0 | P20: 0 | Q20: =O20+P20 -> 0 | R20: 0 | S20: 0 | T20: =R20+S20 -> 0 | U20: 0 | V20: 0 | W20: =U20+V20 -> 0 | X20: 0 | Y20: 0 | Z20: =X20+Y20 -> 0 | AA20: 0 | AB20: 0 | AC20: =AA20+AB20 -> 0 | AD20: =+AG20+AJ20+AM20+AP20 -> 0 | AE20: =+AH20+AK20+AN20+AQ20 -> 0 | AF20: =AD20+AE20 -> 0 | AG20: 0 | AH20: 0 | AI20: =AG20+AH20 -> 0 | AJ20: 0 | AK20: 0 | AL20: =AJ20+AK20 -> 0 | AM20: 0 | AN20: 0 | AO20: =AM20+AN20 -> 0 | AP20: 0 | AQ20: 0 | AR20: =AP20+AQ20 -> 0 | AS20: =+AV20+AY20+BB20+BE20 -> 0 | AT20: =+AW20+AZ20+BC20+BF20 -> 0 | AU20: =AS20+AT20 -> 0 | AV20: 0 | AW20: 0 | AX20: =AV20+AW20 -> 0 | AY20: 0 | AZ20: 0 | BA20: =AY20+AZ20 -> 0 | BB20: 0 | BC20: 0 | BD20: =BB20+BC20 -> 0 | BE20: 0 | BF20: 0 | BG20: =BE20+BF20 -> 0 | BH20: =SUM(BK20,BN20,BQ20,BT20) -> 0 | BI20: =SUM(BL20,BO20,BR20,BU20) -> 0 | BJ20: =BH20+BI20 -> 0 | BK20: 0 | BL20: 0 | BM20: =BK20+BL20 -> 0 | BN20: 0 | BO20: 0 | BP20: =BN20+BO20 -> 0 | BQ20: 0 | BR20: 0 | BS20: =BQ20+BR20 -> 0 | BT20: 0 | BU20: 0 | BV20: =BT20+BU20 -> 0
B21: 합계 | C21: Total | D21: =D7+D18 -> 33.431038 | E21: =E7+E18 -> 1090.3925 | F21: =D21+E21 -> 1123.8235 | G21: =G7+G18 -> 28.374248 | H21: =H7+H18 -> 591.5706 | I21: =G21+H21 -> 619.94485 | J21: =+IFERROR(IF(G21<0,-(D21/G21-1),(D21/G21-1)),0) -> 0.17821759 | K21: =+IFERROR(IF(H21<0,-(E21/H21-1),(E21/H21-1)),0) -> 0.84321614 | L21: =+IFERROR(IF(I21<0,-(F21/I21-1),(F21/I21-1)),0) -> 0.81277983 | O21: 33.427083 | P21: 1090.3925 | Q21: =O21+P21 -> 1123.8196 | R21: 10.264445 | S21: 323.95061 | T21: =R21+S21 -> 334.21505 | U21: =U7+U18 -> 9.7049526 | V21: =V7+V18 -> 374.86698 | W21: =U21+V21 -> 384.57193 | X21: =X7+X18 -> 6.0929282 | Y21: =Y7+Y18 -> 150.37819 | Z21: =X21+Y21 -> 156.47112 | AA21: =AA7+AA18 -> 7.3687121 | AB21: =AB7+AB18 -> 241.1967 | AC21: =AA21+AB21 -> 248.56541 | AD21: =AD7+AD18 -> 28.374248 | AE21: =AE7+AE18 -> 591.5706 | AF21: =AD21+AE21 -> 619.94485 | AG21: =AG7+AG18 -> 8.2006722 | AH21: =AH7+AH18 -> 213.46305 | AI21: =AG21+AH21 -> 221.66372 | AJ21: =AJ7+AJ18 -> 7.2619433 | AK21: =AK7+AK18 -> 168.36299 | AL21: =AJ21+AK21 -> 175.62493 | AM21: =AM7+AM18 -> 6.3698609 | AN21: =AN7+AN18 -> 109.76168 | AO21: =AM21+AN21 -> 116.13154 | AP21: =AP7+AP18 -> 6.5417711 | AQ21: =AQ7+AQ18 -> 99.982884 | AR21: =AP21+AQ21 -> 106.52466 | AS21: =AS7+AS18 -> 17.732141 | AT21: =AT7+AT18 -> 115.16154 | AU21: =AS21+AT21 -> 132.89368 | AV21: =AV7+AV18 -> 5.06597 | AW21: =AW7+AW18 -> 37.776592 | AX21: =AV21+AW21 -> 42.842562 | AY21: =AY7+AY18 -> 5.2412488 | AZ21: =AZ7+AZ18 -> 38.026191 | BA21: =AY21+AZ21 -> 43.26744 | BB21: =BB7+BB18 -> 4.1878456 | BC21: =BC7+BC18 -> 27.002053 | BD21: =BB21+BC21 -> 31.189898 | BE21: =BE7+BE18 -> 3.2370766 | BF21: =BF7+BF18 -> 12.356708 | BG21: =BE21+BF21 -> 15.593784 | BH21: =BH7+BH18 -> 15.191253 | BI21: =BI7+BI18 -> 277.37857 | BJ21: =BH21+BI21 -> 292.56983 | BK21: =BK7+BK18 -> 3.1298312 | BL21: =BL7+BL18 -> 15.585064 | BM21: =BK21+BL21 -> 18.714895 | BN21: =BN7+BN18 -> 3.750128 | BO21: =BO7+BO18 -> 40.319492 | BP21: =BN21+BO21 -> 44.06962 | BQ21: =BQ7+BQ18 -> 3.9174103 | BR21: =BR7+BR18 -> 56.951029 | BS21: =BQ21+BR21 -> 60.868439 | BT21: =BT7+BT18 -> 4.3938837 | BU21: =BU7+BU18 -> 164.52299 | BV21: =BT21+BU21 -> 168.91687
B22: 일시납 | C22: Lumpsum payments | D22: =SUM(X22,AA22,U22,R22) -> 6.9015296 | E22: =SUM(Y22,AB22,V22,S22) -> 1069.26 | F22: =D22+E22 -> 1076.1615 | G22: =SUM(AM22,AP22,AJ22,AG22) -> 5.0110298 | H22: =SUM(AN22,AQ22,AK22,AH22) -> 575.37978 | I22: =G22+H22 -> 580.39081 | J22: =+IFERROR(IF(G22<0,-(D22/G22-1),(D22/G22-1)),0) -> 0.37726772 | K22: =+IFERROR(IF(H22<0,-(E22/H22-1),(E22/H22-1)),0) -> 0.85835518 | L22: =+IFERROR(IF(I22<0,-(F22/I22-1),(F22/I22-1)),0) -> 0.85420152 | O22: 6.9015296 | P22: 1069.26 | Q22: =O22+P22 -> 1076.1615 | R22: 2.4452172 | S22: 319.72667 | T22: =R22+S22 -> 322.17188 | U22: 2.0608665 | V22: 368.38892 | W22: =U22+V22 -> 370.44979 | X22: 0.98759163 | Y22: 146.05593 | Z22: =X22+Y22 -> 147.04352 | AA22: 1.4078543 | AB22: 235.08847 | AC22: =AA22+AB22 -> 236.49632 | AD22: =+AG22+AJ22+AM22+AP22 -> 5.0110298 | AE22: =+AH22+AK22+AN22+AQ22 -> 575.37978 | AF22: =AD22+AE22 -> 580.39081 | AG22: 1.5736247 | AH22: 210.06988 | AI22: =AG22+AH22 -> 211.6435 | AJ22: 1.1152148 | AK22: 164.8917 | AL22: =AJ22+AK22 -> 166.00692 | AM22: 1.3048132 | AN22: 104.93144 | AO22: =AM22+AN22 -> 106.23626 | AP22: 1.0173771 | AQ22: 95.486753 | AR22: =AP22+AQ22 -> 96.50413 | AS22: =+AV22+AY22+BB22+BE22 -> 1.0481561 | AT22: =+AW22+AZ22+BC22+BF22 -> 108.91263 | AU22: =AS22+AT22 -> 109.96079 | AV22: 0.34819265 | AW22: 36.371103 | AX22: =AV22+AW22 -> 36.719295 | AY22: 0.2901394 | AZ22: 35.907594 | BA22: =AY22+AZ22 -> 36.197734 | BB22: 0.26229889 | BC22: 25.576207 | BD22: =BB22+BC22 -> 25.838506 | BE22: 0.14752519 | BF22: 11.05773 | BG22: =BE22+BF22 -> 11.205255 | BH22: =SUM(BK22,BN22,BQ22,BT22) -> 2.5414665 | BI22: =SUM(BL22,BO22,BR22,BU22) -> 267.0661 | BJ22: =BH22+BI22 -> 269.60756 | BK22: 0.3125779 | BL22: 13.994275 | BM22: =BK22+BL22 -> 14.306853 | BN22: 0.36284978 | BO22: 38.194251 | BP22: =BN22+BO22 -> 38.557101 | BQ22: 0.57902836 | BR22: 54.442018 | BS22: =BQ22+BR22 -> 55.021046 | BT22: 1.2870105 | BU22: 160.43555 | BV22: =BT22+BU22 -> 161.72256
B23: 비일시납 | C23: Installments | D23: =SUM(X23,AA23,U23,R23) -> 26.525554 | E23: =SUM(Y23,AB23,V23,S23) -> 21.132488 | F23: =D23+E23 -> 47.658041 | G23: =SUM(AM23,AP23,AJ23,AG23) -> 23.363218 | H23: =SUM(AN23,AQ23,AK23,AH23) -> 16.190822 | I23: =G23+H23 -> 39.554039 | J23: =+IFERROR(IF(G23<0,-(D23/G23-1),(D23/G23-1)),0) -> 0.13535532 | K23: =+IFERROR(IF(H23<0,-(E23/H23-1),(E23/H23-1)),0) -> 0.30521404 | L23: =+IFERROR(IF(I23<0,-(F23/I23-1),(F23/I23-1)),0) -> 0.20488431 | O23: 26.525554 | P23: 21.132488 | Q23: =O23+P23 -> 47.658041 | R23: 7.8192276 | S23: 4.2239449 | T23: =R23+S23 -> 12.043173 | U23: 7.6405041 | V23: 6.478052 | W23: =U23+V23 -> 14.118556 | X23: 5.1049642 | Y23: 4.3222563 | Z23: =X23+Y23 -> 9.4272205 | AA23: 5.9608578 | AB23: 6.1082345 | AC23: =AA23+AB23 -> 12.069092 | AD23: =+AG23+AJ23+AM23+AP23 -> 23.363218 | AE23: =+AH23+AK23+AN23+AQ23 -> 16.190822 | AF23: =AD23+AE23 -> 39.554039 | AG23: 6.6270475 | AH23: 3.3931676 | AI23: =AG23+AH23 -> 10.020215 | AJ23: 6.1467285 | AK23: 3.4712858 | AL23: =AJ23+AK23 -> 9.6180143 | AM23: 5.0650477 | AN23: 4.8302368 | AO23: =AM23+AN23 -> 9.8952845 | AP23: 5.524394 | AQ23: 4.4961313 | AR23: =AP23+AQ23 -> 10.020525 | AS23: =+AV23+AY23+BB23+BE23 -> 16.683985 | AT23: =+AW23+AZ23+BC23+BF23 -> 6.2489098 | AU23: =AS23+AT23 -> 22.932895 | AV23: 4.7177774 | AW23: 1.4054891 | AX23: =AV23+AW23 -> 6.1232665 | AY23: 4.9511094 | AZ23: 2.1185969 | BA23: =AY23+AZ23 -> 7.0697063 | BB23: 3.9255467 | BC23: 1.4258458 | BD23: =BB23+BC23 -> 5.3513925 | BE23: 3.0895514 | BF23: 1.2989781 | BG23: =BE23+BF23 -> 4.3885294 | BH23: =SUM(BK23,BN23,BQ23,BT23) -> 12.649787 | BI23: =SUM(BL23,BO23,BR23,BU23) -> 10.312479 | BJ23: =BH23+BI23 -> 22.962266 | BK23: 2.8172533 | BL23: 1.5907889 | BM23: =BK23+BL23 -> 4.4080422 | BN23: 3.3872782 | BO23: 2.1252401 | BP23: =BN23+BO23 -> 5.5125184 | BQ23: 3.338382 | BR23: 2.5090111 | BS23: =BQ23+BR23 -> 5.8473931 | BT23: 3.1068733 | BU23: 4.0874391 | BV23: =BT23+BU23 -> 7.1943123
B24: 퇴직 | C24: Retirement pensions | D24: =SUM(X24,AA24,U24,R24) -> 0 | E24: =SUM(Y24,AB24,V24,S24) -> 185.42358 | F24: =D24+E24 -> 185.42358 | G24: =SUM(AM24,AP24,AJ24,AG24) -> 0 | H24: =SUM(AN24,AQ24,AK24,AH24) -> 119.33471 | I24: =G24+H24 -> 119.33471 | J24: =+IFERROR(IF(G24<0,-(D24/G24-1),(D24/G24-1)),0) -> 0 | K24: =+IFERROR(IF(H24<0,-(E24/H24-1),(E24/H24-1)),0) -> 0.55381097 | L24: =+IFERROR(IF(I24<0,-(F24/I24-1),(F24/I24-1)),0) -> 0.55381097 | O24: 0 | P24: 185.42358 | Q24: =O24+P24 -> 185.42358 | R24: 0 | S24: 64.464328 | T24: =R24+S24 -> 64.464328 | U24: 0 | V24: 40.837398 | W24: =U24+V24 -> 40.837398 | X24: 0 | Y24: 31.668949 | Z24: =X24+Y24 -> 31.668949 | AA24: 0 | AB24: 48.45291 | AC24: =AA24+AB24 -> 48.45291 | AD24: =+AG24+AJ24+AM24+AP24 -> 0 | AE24: =+AH24+AK24+AN24+AQ24 -> 119.33471 | AF24: =AD24+AE24 -> 119.33471 | AG24: 0 | AH24: 23.468584 | AI24: =AG24+AH24 -> 23.468584 | AJ24: 0 | AK24: 18.795905 | AL24: =AJ24+AK24 -> 18.795905 | AM24: 0 | AN24: 21.847339 | AO24: =AM24+AN24 -> 21.847339 | AP24: 0 | AQ24: 55.222884 | AR24: =AP24+AQ24 -> 55.222884 | AS24: =+AV24+AY24+BB24+BE24 -> 0 | AT24: =+AW24+AZ24+BC24+BF24 -> 105.29944 | AU24: =AS24+AT24 -> 105.29944 | AV24: 0 | AW24: 20.253668 | AX24: =AV24+AW24 -> 20.253668 | AY24: 0 | AZ24: 22.700892 | BA24: =AY24+AZ24 -> 22.700892 | BB24: 0 | BC24: 26.070754 | BD24: =BB24+BC24 -> 26.070754 | BE24: 0 | BF24: 36.274125 | BG24: =BE24+BF24 -> 36.274125 | BH24: =SUM(BK24,BN24,BQ24,BT24) -> 0 | BI24: =SUM(BL24,BO24,BR24,BU24) -> 158.48914 | BJ24: =BH24+BI24 -> 158.48914 | BK24: 0 | BL24: 51.649307 | BM24: =BK24+BL24 -> 51.649307 | BN24: 0 | BO24: 33.923165 | BP24: =BN24+BO24 -> 33.923165 | BQ24: 0 | BR24: 31.837707 | BS24: =BQ24+BR24 -> 31.837707 | BT24: 0 | BU24: 41.078959 | BV24: =BT24+BU24 -> 41.078959
B26: 계정별 분류 | C26: Breakdown by Account Type
B27: 일반보험 | C27: General Types | D27: =D28+D29 -> 31.708127 | E27: =E28+E29 -> 0 | F27: =F28+F29 -> 23.591647 | G27: =G28+G29 -> 21.096722 | H27: =H28+H29 -> 0 | I27: =I28+I29 -> 21.096722 | J27: =+IFERROR(IF(G27<0,-(D27/G27-1),(D27/G27-1)),0) -> 0.50298834 | K27: =+IFERROR(IF(H27<0,-(E27/H27-1),(E27/H27-1)),0) -> 0 | L27: =+IFERROR(IF(I27<0,-(F27/I27-1),(F27/I27-1)),0) -> 0.11826125 | O27: =O28+O29 -> 23.587692 | P27: =P28+P29 -> 0 | Q27: =Q28+Q29 -> 23.587692 | R27: =R28+R29 -> 7.0064012 | S27: =S28+S29 -> 0 | T27: =T28+T29 -> 7.0064012 | U27: =U28+U29 -> 6.8439615 | V27: =V28+V29 -> 0 | ... BV27: =BV28+BV29 -> 2.5344107
B28: 일반보장성 | C28: General Protections | D28: =D9+D11+D19 -> 23.591647 | E28: =E9+E11+E19 -> 0 | F28: =F9+F11+F19 -> 23.591647 | G28: =G9+G11+G19 -> 21.096722 | H28: =H9+H11+H19 -> 0 | I28: =I9+I11+I19 -> 21.096722 | J28: =+IFERROR(IF(G28<0,-(D28/G28-1),(D28/G28-1)),0) -> 0.11826125 | K28: =+IFERROR(IF(H28<0,-(E28/H28-1),(E28/H28-1)),0) -> 0 | L28: =+IFERROR(IF(I28<0,-(F28/I28-1),(F28/I28-1)),0) -> 0.11826125 | O28: =O9+O11+O19 -> 23.587692 | P28: =P9+P11+P19 -> 0 | Q28: =Q9+Q11+Q19 -> 23.587692 | R28: =R9+R11+R19 -> 7.0064012 | S28: =S9+S11+S19 -> 0 | T28: =T9+T11+T19 -> 7.0064012 | U28: =U9+U11+U19 -> 6.8439615 | V28: =V9+V11+V19 -> 0 | ... BV28: =BV9+BV11+BV19 -> 2.5344107
B29: 일반저축성 | C29: General Savings | D29: =D10+D12+D20 -> 8.1164804 | E29: =E13+E16+E20 -> 0 | F29: =F13+F16+F20 -> 0 | G29: =G13+G16+G20 -> 0 | H29: =H13+H16+H20 -> 0 | I29: =I13+I16+I20 -> 0 | J29: =+IFERROR(IF(G29<0,-(D29/G29-1),(D29/G29-1)),0) -> 0 | K29: =+IFERROR(IF(H29<0,-(E29/H29-1),(E29/H29-1)),0) -> 0 | L29: =+IFERROR(IF(I29<0,-(F29/I29-1),(F29/I29-1)),0) -> 0 | O29: =O13+O16+O20 -> 0 | P29: =P13+P16+P20 -> 0 | Q29: =Q13+Q16+Q20 -> 0 | R29: =R13+R16+R20 -> 0 | S29: =S13+S16+S20 -> 0 | T29: =T13+T16+T20 -> 0 | U29: =U13+U16+U20 -> 0 | V29: =V13+V16+V20 -> 0 | ... BV29: =BV13+BV16+BV20 -> 0
B30: 변액보험 | C30: Variable Types | D30: =D31+D32 -> 9.839391 | E30: =E31+E32 -> 1090.3925 | F30: =F31+F32 -> 1100.2319 | G30: =G31+G32 -> 7.2775257 | H30: =H31+H32 -> 591.5706 | I30: =I31+I32 -> 598.84812 | J30: =+IFERROR(IF(G30<0,-(D30/G30-1),(D30/G30-1)),0) -> 0.35202422 | K30: =+IFERROR(IF(H30<0,-(E30/H30-1),(E30/H30-1)),0) -> 0.84321614 | L30: =+IFERROR(IF(I30<0,-(F30/I30-1),(F30/I30-1)),0) -> 0.83724691 | O30: =O31+O32 -> 9.839391 | P30: =P31+P32 -> 1090.3925 | Q30: =Q31+Q32 -> 1100.2319 | R30: =R31+R32 -> 3.2580436 | S30: =S31+S32 -> 323.95061 | T30: =T31+T32 -> 327.20865 | U30: =U31+U32 -> 2.8609911 | V30: =V31+V32 -> 374.86698 | ... BV30: =BV31+BV32 -> 166.38246
B31: 변액보장형 | C31: Variable Protections | D31: =D10 -> 2.3473917 | E31: =E10 -> 5.1165285 | F31: =F10 -> 7.4639203 | G31: =G10 -> 1.8362628 | H31: =H10 -> 3.7618272 | I31: =I10 -> 5.59809 | J31: =+IFERROR(IF(G31<0,-(D31/G31-1),(D31/G31-1)),0) -> 0.27835283 | K31: =+IFERROR(IF(H31<0,-(E31/H31-1),(E31/H31-1)),0) -> 0.36011791 | L31: =+IFERROR(IF(I31<0,-(F31/I31-1),(F31/I31-1)),0) -> 0.33329766 | O31: =O10 -> 2.3473917 | P31: =P10 -> 5.1165285 | Q31: =Q10 -> 7.4639203 | R31: =R10 -> 0.70639556 | S31: =S10 -> 1.637158 | T31: =T10 -> 2.3435536 | U31: =U10 -> 0.67146127 | V31: =V10 -> 1.5057402 | ... BV31: =BV10 -> 3.0213403
B32: 변액투자형 | C32: Variable Investments | D32: =D14+D17 -> 7.4919993 | E32: =E14+E17 -> 1085.2759 | F32: =F14+F17 -> 1092.7679 | G32: =G14+G17 -> 5.4412629 | H32: =H14+H17 -> 587.80877 | I32: =I14+I17 -> 593.25003 | J32: =+IFERROR(IF(G32<0,-(D32/G32-1),(D32/G32-1)),0) -> 0.3768861 | K32: =+IFERROR(IF(H32<0,-(E32/H32-1),(E32/H32-1)),0) -> 0.84630784 | L32: =+IFERROR(IF(I32<0,-(F32/I32-1),(F32/I32-1)),0) -> 0.84200233 | O32: =O14+O17 -> 7.4919993 | P32: =P14+P17 -> 1085.2759 | Q32: =Q14+Q17 -> 1092.7679 | R32: =R14+R17 -> 2.5516481 | S32: =S14+S17 -> 322.31345 | T32: =T14+T17 -> 324.8651 | U32: =U14+U17 -> 2.1895299 | V32: =V14+V17 -> 373.36124 | ... BV32: =BV14+BV17 -> 163.36112
B33: 합계 | C33: Total | D33: =D27+D30 -> 41.547518 | E33: =E27+E30 -> 1090.3925 | F33: =F27+F30 -> 1123.8235 | G33: =G27+G30 -> 28.374248 | H33: =H27+H30 -> 591.5706 | I33: =I27+I30 -> 619.94485 | J33: =+IFERROR(IF(G33<0,-(D33/G33-1),(D33/G33-1)),0) -> 0.46426854 | K33: =+IFERROR(IF(H33<0,-(E33/H33-1),(E33/H33-1)),0) -> 0.84321614 | L33: =+IFERROR(IF(I33<0,-(F33/I33-1),(F33/I33-1)),0) -> 0.81277983 | O33: =O27+O30 -> 33.427083 | P33: =P27+P30 -> 1090.3925 | Q33: =Q27+Q30 -> 1123.8196 | R33: =R27+R30 -> 10.264445 | S33: =S27+S30 -> 323.95061 | T33: =T27+T30 -> 334.21505 | U33: =U27+U30 -> 9.7049526 | V33: =V27+V30 -> 374.86698 | ... BV33: =BV27+BV30 -> 168.91687

Sheet FIRSTYR
B1: =[6]INDEX!G15 -> 초년도보험료 | C1: First Year Premiums
B2: (BN KRW, %, %p)
B4: 초년도보험료 | C4: First Year Premiums | D4: =O4 -> 2025 | G4: =AD4 -> 2024 | J4: YoY | O4: 2025 | AD4: 2024 | AS4: 2023 | BH4: 2022
D5: =O5 -> FY | G5: =AD5 -> FY | O5: FY | R5: Q4 | U5: Q3 | X5: Q2 | AA5: Q1 | AD5: FY | AG5: Q4 | AJ5: Q3 | AM5: Q2 | AP5: Q1 | AS5: FY | AV5: Q4 | AY5: Q3 | BB5: Q2 | BE5: Q1 | BH5: FY | BK5: Q4 | BN5: Q3 | BQ5: Q2 | BT5: Q1
D6: 일반 General | E6: 특별 Separate | F6: 합계 Total | G6: 일반 General | H6: 특별 Separate | I6: 합계 Total | J6: 일반 General | K6: 특별 Separate | L6: 합계 Total | O6: 일반 General | P6: 특별 Separate | Q6: 합계 Total | R6: 일반 General | S6: 특별 Separate | T6: 합계 Total | U6: 일반 General | V6: 특별 Separate | W6: 합계 Total | X6: 일반 General | Y6: 특별 Separate | Z6: 합계 Total | AA6: 일반 General | AB6: 특별 Separate | AC6: 합계 Total | AD6: 일반 General | AE6: 특별 Separate | AF6: 합계 Total | AG6: 일반 General | AH6: 특별 Separate | AI6: 합계 Total | AJ6: 일반 General | AK6: 특별 Separate | AL6: 합계 Total | AM6: 일반 General | AN6: 특별 Separate | AO6: 합계 Total | AP6: 일반 General | AQ6: 특별 Separate | AR6: 합계 Total | AS6: 일반 General | AT6: 특별 Separate | AU6: 합계 Total | AV6: 일반 General | AW6: 특별 Separate | AX6: 합계 Total | AY6: 일반 General | AZ6: 특별 Separate | BA6: 합계 Total | BB6: 일반 General | BC6: 특별 Separate | BD6: 합계 Total | BE6: 일반 General | BF6: 특별 Separate | BG6: 합계 Total | BH6: 일반 General | BI6: 특별 Separate | BJ6: 합계 Total | BK6: 일반 General | BL6: 특별 Separate | BM6: 합계 Total | BN6: 일반 General | BO6: 특별 Separate | BP6: 합계 Total | BQ6: 일반 General | BR6: 특별 Separate | BS6: 합계 Total | BT6: 일반 General | BU6: 특별 Separate | BV6: 합계 Total
B7: 개인보험 | C7: Individual | D7: =D8+D12+D15 -> 287.96833 | E7: =E8+E12+E15 -> 1378.5724 | F7: =D7+E7 -> 1666.5407 | G7: =G8+G12+G15 -> 268.91618 | H7: =H8+H12+H15 -> 799.13153 | I7: =G7+H7 -> 1068.0477 | J7: =+IFERROR(IF(G7<0,-(D7/G7-1),(D7/G7-1)),0) -> 0.070847898 | K7: =+IFERROR(IF(H7<0,-(E7/H7-1),(E7/H7-1)),0) -> 0.72508825 | L7: =+IFERROR(IF(I7<0,-(F7/I7-1),(F7/I7-1)),0) -> 0.5603617 | O7: 287.96833 | P7: 1378.5724 | Q7: =O7+P7 -> 1666.5407 | R7: 75.743005 | S7: 410.06554 | T7: =R7+S7 -> 485.80855 | U7: 71.99506 | V7: 450.85336 | W7: =U7+V7 -> 522.84842 | X7: =X8+X12+X15 -> 68.819011 | Y7: =Y8+Y12+Y15 -> 211.5354 | Z7: =X7+Y7 -> 280.35441 | AA7: =AA8+AA12+AA15 -> 71.411255 | AB7: =AB8+AB12+AB15 -> 306.1181 | AC7: =AA7+AB7 -> 377.52936 | AD7: =AD8+AD12+AD15 -> 268.91618 | AE7: =AE8+AE12+AE15 -> 799.13153 | AF7: =AD7+AE7 -> 1068.0477 | AG7: =AG8+AG12+AG15 -> 71.723134 | AH7: =AH8+AH12+AH15 -> 274.56786 | AI7: =AG7+AH7 -> 346.291 | AJ7: =AJ8+AJ12+AJ15 -> 68.863858 | AK7: =AK8+AK12+AK15 -> 225.92962 | AL7: =AJ7+AK7 -> 294.79348 | AM7: =AM8+AM12+AM15 -> 67.349296 | AN7: =AN8+AN12+AN15 -> 159.551 | AO7: =AM7+AN7 -> 226.9003 | AP7: =AP8+AP12+AP15 -> 60.979896 | AQ7: =AQ8+AQ12+AQ15 -> 139.08304 | AR7: =AP7+AQ7 -> 200.06294 | AS7: =AS8+AS12+AS15 -> 186.6273 | AT7: =AT8+AT12+AT15 -> 223.44055 | AU7: =AS7+AT7 -> 410.06785 | AV7: =AV8+AV12+AV15 -> 53.080102 | AW7: =AW8+AW12+AW15 -> 63.110275 | AX7: =AV7+AW7 -> 116.19038 | AY7: =AY8+AY12+AY15 -> 47.44911 | AZ7: =AZ8+AZ12+AZ15 -> 78.775576 | BA7: =AY7+AZ7 -> 126.22469 | BB7: =BB8+BB12+BB15 -> 43.405559 | BC7: =BC8+BC12+BC15 -> 45.559014 | BD7: =BB7+BC7 -> 88.964573 | BE7: =BE8+BE12+BE15 -> 42.692528 | BF7: =BF8+BF12+BF15 -> 35.995685 | BG7: =BE7+BF7 -> 78.688213 | BH7: =BH8+BH12+BH15 -> 245.56899 | BI7: =BI8+BI12+BI15 -> 553.22769 | BJ7: =BH7+BI7 -> 798.79667 | BK7: =BK8+BK12+BK15 -> 47.553969 | BL7: =BL8+BL12+BL15 -> 53.582287 | BM7: =BK7+BL7 -> 101.13626 | BN7: =BN8+BN12+BN15 -> 56.415623 | BO7: =BO8+BO12+BO15 -> 95.158185 | BP7: =BN7+BO7 -> 151.57381 | BQ7: =BQ8+BQ12+BQ15 -> 65.968232 | BR7: =BR8+BR12+BR15 -> 135.12769 | BS7: =BQ7+BR7 -> 201.09593 | BT7: =BT8+BT12+BT15 -> 75.631164 | BU7: =BU8+BU12+BU15 -> 269.35952 | BV7: =BT7+BU7 -> 344.99068
B8: 보장성보험 | C8: Protections | D8: =SUM(D9:D11) -> 270.30415 | E8: =SUM(E9:E11) -> 36.506353 | F8: =D8+E8 -> 306.8105 | G8: =SUM(G9:G11) -> 256.94392 | H8: =SUM(H9:H11) -> 21.753126 | I8: =G8+H8 -> 278.69705 | J8: =+IFERROR(IF(G8<0,-(D8/G8-1),(D8/G8-1)),0) -> 0.051996642 | K8: =+IFERROR(IF(H8<0,-(E8/H8-1),(E8/H8-1)),0) -> 0.6782118 | L8: =+IFERROR(IF(I8<0,-(F8/I8-1),(F8/I8-1)),0) -> 0.10087458 | O8: 270.30415 | P8: 36.506353 | Q8: =O8+P8 -> 306.8105 | R8: 70.37267 | S8: 9.9293153 | T8: =R8+S8 -> 80.301986 | U8: 67.241557 | V8: 9.2424758 | W8: =U8+V8 -> 76.484032 | X8: =SUM(X9:X11) -> 65.226951 | Y8: =SUM(Y9:Y11) -> 8.7553598 | Z8: =X8+Y8 -> 73.982311 | AA8: =SUM(AA9:AA11) -> 67.462968 | AB8: =SUM(AB9:AB11) -> 8.5792023 | AC8: =AA8+AB8 -> 76.04217 | AD8: =SUM(AD9:AD11) -> 256.94392 | AE8: =SUM(AE9:AE11) -> 21.753126 | AF8: =AD8+AE8 -> 278.69705 | AG8: =SUM(AG9:AG11) -> 67.891964 | AH8: =SUM(AH9:AH11) -> 7.1970615 | AI8: =AG8+AH8 -> 75.089025 | AJ8: =SUM(AJ9:AJ11) -> 65.669993 | AK8: =SUM(AK9:AK11) -> 5.8348173 | AL8: =AJ8+AK8 -> 71.50481 | AM8: =SUM(AM9:AM11) -> 64.458154 | AN8: =SUM(AN9:AN11) -> 4.7851051 | AO8: =AM8+AN8 -> 69.24326 | AP8: =SUM(AP9:AP11) -> 58.923813 | AQ8: =SUM(AQ9:AQ11) -> 3.9361424 | AR8: =AP8+AQ8 -> 62.859956 | AS8: =SUM(AS9:AS11) -> 182.16735 | AT8: =SUM(AT9:AT11) -> 23.236926 | AU8: =AS8+AT8 -> 205.40428 | AV8: =SUM(AV9:AV11) -> 51.973286 | AW8: =SUM(AW9:AW11) -> 4.4860846 | AX8: =AV8+AW8 -> 56.45937 | AY8: =SUM(AY9:AY11) -> 46.391977 | AZ8: =SUM(AZ9:AZ11) -> 5.2259458 | BA8: =AY8+AZ8 -> 51.617923 | BB8: =SUM(BB9:BB11) -> 42.372579 | BC8: =SUM(BC9:BC11) -> 6.2963297 | BD8: =BB8+BC8 -> 48.668909 | BE8: =SUM(BE9:BE11) -> 41.42951 | BF8: =SUM(BF9:BF11) -> 7.2285663 | BG8: =BE8+BF8 -> 48.658076 | BH8: =SUM(BH9:BH11) -> 231.28477 | BI8: =SUM(BI9:BI11) -> 61.657722 | BJ8: =BH8+BI8 -> 292.94249 | BK8: =SUM(BK9:BK11) -> 45.565945 | BL8: =SUM(BL9:BL11) -> 10.068515 | BM8: =BK8+BL8 -> 55.63446 | BN8: =SUM(BN9:BN11) -> 53.400489 | BO8: =SUM(BO9:BO11) -> 13.346891 | BP8: =BN8+BO8 -> 66.74738 | BQ8: =SUM(BQ9:BQ11) -> 61.992357 | BR8: =SUM(BR9:BR11) -> 17.167326 | BS8: =BQ8+BR8 -> 79.159683 | BT8: =SUM(BT9:BT11) -> 70.325981 | BU8: =SUM(BU9:BU11) -> 21.07499 | BV8: =BT8+BU8 -> 91.400971
B9: 일반종신/CI | C9: General whole life | D9: =SUM(X9,AA9,U9,R9) -> 32.459623 | E9: =SUM(Y9,AB9,V9,S9) -> 0 | F9: =D9+E9 -> 32.459623 | G9: =SUM(AM9,AP9,AJ9,AG9) -> 60.830608 | H9: =SUM(AN9,AQ9,AK9,AH9) -> 0 | I9: =G9+H9 -> 60.830608 | J9: =+IFERROR(IF(G9<0,-(D9/G9-1),(D9/G9-1)),0) -> -0.46639325 | K9: =+IFERROR(IF(H9<0,-(E9/H9-1),(E9/H9-1)),0) -> 0 | L9: =+IFERROR(IF(I9<0,-(F9/I9-1),(F9/I9-1)),0) -> -0.46639325 | O9: 32.459623 | P9: 0 | Q9: =O9+P9 -> 32.459623 | R9: 6.021266 | S9: 0 | T9: =R9+S9 -> 6.021266 | U9: 7.136028 | V9: 0 | W9: =U9+V9 -> 7.136028 | X9: 8.5908282 | Y9: 0 | Z9: =X9+Y9 -> 8.5908282 | AA9: 10.711501 | AB9: 0 | AC9: =AA9+AB9 -> 10.711501 | AD9: =+AG9+AJ9+AM9+AP9 -> 60.830608 | AE9: =+AH9+AK9+AN9+AQ9 -> 0 | AF9: =AD9+AE9 -> 60.830608 | AG9: 12.651863 | AH9: 0 | AI9: =AG9+AH9 -> 12.651863 | AJ9: 14.870675 | AK9: 0 | AL9: =AJ9+AK9 -> 14.870675 | AM9: 16.946715 | AN9: 0 | AO9: =AM9+AN9 -> 16.946715 | AP9: 16.361355 | AQ9: 0 | AR9: =AP9+AQ9 -> 16.361355 | AS9: =+AV9+AY9+BB9+BE9 -> 44.609038 | AT9: =+AW9+AZ9+BC9+BF9 -> 0 | AU9: =AS9+AT9 -> 44.609038 | AV9: 14.319351 | AW9: 0 | AX9: =AV9+AW9 -> 14.319351 | AY9: 11.933263 | AZ9: 0 | BA9: =AY9+AZ9 -> 11.933263 | BB9: 9.6025011 | BC9: 0 | BD9: =BB9+BC9 -> 9.6025011 | BE9: 8.7539219 | BF9: 0 | BG9: =BE9+BF9 -> 8.7539219 | BH9: =+BT9+BQ9+BN9+BK9 -> 42.771128 | BI9: =+BU9+BR9+BO9+BL9 -> 0 | BJ9: =BH9+BI9 -> 42.771128 | BK9: 9.1266539 | BL9: 0 | BM9: =BK9+BL9 -> 9.1266539 | BN9: 9.8276004 | BO9: 0 | BP9: =BN9+BO9 -> 9.8276004 | BQ9: 10.917251 | BR9: 0 | BS9: =BQ9+BR9 -> 10.917251 | BT9: 12.899623 | BU9: 0 | BV9: =BT9+BU9 -> 12.899623
