Workbook

Sheet Cover
D4: IR Factsheet
D5: As of June. 2026
C8: 재무현황 (Financial Highlights)
C10: 요약재무상태표 (Selected Balance sheet)
C11: 요약손익계산서 (Selected Income Statement)
C13: RA, CSM, BEL Movement
C14: 신계약 CSM (New Business CSM)
C15: 신계약 CSM 배수 (New Business CSM Margin)
C17: 주요지표 (Key Index)
D18: 재무 안정성 (Financial Stability)
D19: 생산성 / 경영효율 (Productivity / Operating Efficiency)
C21: 상품별 수입보험료 (Premium by Product-type)
D22: 상품별 APE (Annualized Premium Equivalent (APE))
D23: 상품별 수입보험료 (Premium Income)
D24: 상품별 초회보험료 (Initial Premium)
D25: 상품별 초년도보험료 (First Year Premium)
C27: 채널별 수입보험료 (Premium by Distribution Channel)
D28: 채널별 APE (Annualized Premium Equivalent (APE))
D29: 채널별 수입보험료 (Premium Income)
D30: 채널별 초년도보험료 (First Year Premium)
C33: 투자영업 현황 (Investment)
D34: 대출 (Loan)/ 자산건전성 (Asset Quality of Loan)
D35: 채권 (Bond)
C37: 재무제표 (Full Financial Statements)
D38: 연결재무상태표 (Consolidated Balance Sheet - KIFRS)
D39: 연결손익계산서 (Consolidated Income Statement - KIFRS)

Sheet FH
F1: 재무현황 (Financial Highlights)
F2: (단위: 십억원) | J2: 45747 | K2: 45838 | L2: 45930 | M2: 46022 | N2: 46112 | O2: 46203 | P2: 46295 | Q2: 46387
A3: Disclaimer & Contact Information | F3: (Unit: KRW bn)
F4: 자산총계 (Total Assets) | J4: 35159.11 | K4: 35613.337 | L4: 35694.263 | M4: 35347.237 | N4: 34495.304 | O4: 35287.666
B5: 재무현황 (Financial Highlights) | G5: 운용자산 (Invested Assets) | J5: 32574.977 | K5: 33014.314 | L5: 33114.563 | M5: 32704.988 | N5: 31850.898 | O5: 32334.841
F6: 부채총계 (Total Liabilities) | J6: 33673.418 | K6: 33960.73 | L6: 34351.543 | M6: 33798.362 | N6: 32650.991 | O6: 32950.699
B7: 요약재무상태표 (Selected Balance sheet) | G7: 보험부채_CSM (Contract Service Margin) | J7: 2661.1771 | K7: 2744.2353 | L7: 2796.9809 | M7: 2457.0955 | N7: 2510.8346 | O7: 2645.7062
B8: 요약손익계산서 (Selected Income Statement) | G8: 신계약CSM (New Business CSM) | J8: 190.38142 | K8: 302.88629 | L8: 425.84844 | M8: 529.13223 | N8: 94.465158 | O8: 242.48659
F9: 자본총계 (Total Shareholders' Equity) | J9: 1485.6917 | K9: 1652.6077 | L9: 1342.7199 | M9: 1548.8747 | N9: 1844.313 | O9: 2336.9666
B10: RA, CSM, BEL Movement | F10: 수입보험료 (Premium Income) | J10: =SUM(J11:J12) -> 993.99903 | K10: =SUM(K11:K12) -> 2060.3062 | L10: =SUM(L11:L12) -> 3290.0986 | M10: =SUM(M11:M12) -> 4814.4476 | N10: =SUM(N11:N12) -> 1237.0425 | O10: =SUM(O11:O12) -> 3598.2557
B11: 신계약 CSM (New Business CSM) | G11: 일반계정 (General Account) | J11: 900.07486 | K11: 1828.9108 | L11: 3001.2197 | M11: 3986.9339 | N11: 1108.0866 | O11: 2393.8077
B12: 신계약 CSM 배수 (New Business CSM Margin) | G12: 특별계정 (Separate Account) | J12: 93.924172 | K12: 231.3954 | L12: 288.87884 | M12: 827.51371 | N12: 128.95594 | O12: 1204.448
F13: 보험손익 (Insurance Profit) | J13: 4.0710674 | K13: 70.419566 | L13: 94.982299 | M13: 113.77081 | N13: 22.386 | O13: 97.012122
B14: 주요지표 (Key Index) | F14: 투자손익 (Investment Profit) | J14: 54.593749 | K14: 29.633785 | L14: 52.81492 | M14: 85.040866 | N14: 8.719 | O14: 20.93199
C15: 재무 안정성 (Financial Stability) | F15: 영업이익 (Operating Profit) | J15: 58.664817 | K15: 100.05335 | L15: 147.79722 | M15: 198.81168 | N15: 31.104 | O15: 117.94411
C16: 생산성 / 경영효율 (Productivity / Operating Efficiency) | F16: 영업외손익(Non-Operating Profit) | J16: -5.0065737 | K16: -3.9254422 | L16: -21.179163 | M16: -23.383389 | N16: -0.105 | O16: 2.636382
F17: 법인세비용차감전순이익 (Earnings Before Income Tax) | J17: 53.658243 | K17: 96.127909 | L17: 126.61806 | M17: 175.42829 | N17: 31 | O17: 120.58049
B18: 상품별 수입보험료 (Premium by Product-type) | F18: 당기순이익 (Net Income) | J18: 46.19408 | K18: 82.412272 | L18: 109.85639 | M18: 124.49364 | N18: 25.024 | O18: 91.929677
C19: 상품별 APE (Annualized Premium Equivalent (APE))
C20: 상품별 수입보험료 (Premium Income)
C21: 상품별 초회보험료 (Initial Premium)
C22: 상품별 초년도보험료 (First Year Premium) | F22: (단위: 십억원) | J22: 45747 | K22: 45838 | L22: 45930 | M22: 46022 | N22: 46112 | O22: 46203 | P22: 46295 | Q22: 46387
F23: (Unit: KRW bn)
B24: 채널별 수입보험료 (Premium by Distribution Channel) | F24: 운용자산 이익율(Net Investment Yield) | J24: 0.038222661 | K24: 0.034722379 | L24: 0.035294828 | M24: 0.03428012 | N24: 0.035862482 | O24: 0.035666469
C25: 채널별 APE (Annualized Premium Equivalent (APE)) | F25: K-ICS 비율 (K-ICS Ratio) | J25: 1.2716316 | K25: 1.7696419 | L25: 1.735948 | M25: 1.7983878 | N25: 1.896 | O25: 2.0499919
C26: 채널별 수입보험료 (Premium Income) | F26: NPL 비율 (NPL Ratio) | J26: 0.0081432905 | K26: 0.017153668 | L26: 0.013365532 | M26: 0.013896943 | N26: 0.019631927 | O26: 0.011486652
C27: 채널별 초년도보험료 (First Year Premium) | F27: BPS (단위 원) (BPS (KRW)) | J27: 9519.8455 | K27: 10589.391 | L27: 8603.7273 | M27: 9924.7024 | N27: 11817.779 | O27: 14974.548
F28: EPS (단위 원) (EPS (KRW)) | J28: 286.28213 | K28: 510.73992 | L28: 680.82145 | M28: 771.53401 | N28: 155.08316 | O28: 589.05649
F29: 총자산이익율 (Retrun on Asset) | J29: 0.0053016209 | K29: 0.004698545 | L29: 0.0041706612 | M29: 0.0035623696 | N29: 0.0028663333 | O29: 0.0052059066
B30: 투자영업 현황 (Investment) | F30: 총자본이익율 (Return on Equity) | J30: 0.10696773 | K30: 0.09102001 | L30: 0.088455652 | M30: 0.070775476 | N30: 0.05899821 | O30: 0.094630398
C31: 대출 (Loan)/ 자산건전성 (Asset Quality of Loan) | F31: *1 K-ICS Ratio : 2026.1H 비율은 추정치로 추후 업데이트 예정
C32: 채권 (Bond) | F32: *2 공통 경과조치 적용 후 기준
B34: 재무제표 (Full Financial Statements)
C35: 재무상태표 (Balance Sheet - KIFRS)
C36: 손익계산서 (Income Statement - KIFRS)

Sheet FS
F1: 요약 재무상태표 (Selected Balance Sheet)
F2: (단위 십억원) | J2: FY25 | N2: FY26 | S2: Accumulated | U2: 증감
A3: Disclaimer & Contact Information | F3: (KRW bn) | J3: 45747 | K3: 45838 | L3: 45930 | M3: 46022 | N3: 46112 | O3: 46203 | P3: 46295 | Q3: 46387 | S3: FY25.1H | T3: FY26.1H | U3: YoY | V3: QoQ
F4: Ⅰ.자산총계 (Total assets) | J4: 35159.11 | K4: 35613.337 | L4: 35694.263 | M4: 35347.237 | N4: 34495.304 | O4: 35287.666 | S4: =K4 -> 35613.337 | T4: =O4 -> 35287.666 | U4: =IF(T4/S4<0,"n.a.",IF(S4>0,ROUND(T4,4)/ROUND(S4,4)-1,IF(S4<0,"n.a."))) -> -0.0091446442 | V4: =IF(O4/N4<0,"n.a.",IF(N4>0,ROUND(O4,4)/ROUND(N4,4)-1,IF(N4<0,"n.a."))) -> 0.022970138
B5: 재무현황 (Financial Highlights) | F5: ⅰ.현금및현금성자산 (Cash and cash equivalents) | G5: ⅰ. 현금및현금성자산 (Cash and cash equivalents) | J5: 244.56302 | K5: 286.41692 | L5: 278.6471 | M5: 250.36968 | N5: 356.19815 | O5: 412.27457 | S5: =K5 -> 286.41692 | T5: =O5 -> 412.27457 | U5: =IF(T5/S5<0,"n.a.",IF(S5>0,ROUND(T5,4)/ROUND(S5,4)-1,IF(S5<0,"n.a."))) -> 0.43942135 | V5: =IF(O5/N5<0,"n.a.",IF(N5>0,ROUND(O5,4)/ROUND(N5,4)-1,IF(N5<0,"n.a."))) -> 0.15743033
G6: ⅱ. 금융자산 (Financial assets) | J6: 33497.119 | K6: 34051.436 | L6: 34166.877 | M6: 33879.553 | N6: 32992.173 | O6: 33996.943 | S6: =K6 -> 34051.436 | T6: =O6 -> 33996.943 | U6: =IF(T6/S6<0,"n.a.",IF(S6>0,ROUND(T6,4)/ROUND(S6,4)-1,IF(S6<0,"n.a."))) -> -0.0016003114 | V6: =IF(O6/N6<0,"n.a.",IF(N6>0,ROUND(O6,4)/ROUND(N6,4)-1,IF(N6<0,"n.a."))) -> 0.030454793
B7: 요약재무상태표 (Selected Balance sheet) | H7: FVPL (Financial assets at fair value through profit or loss) | J7: 5927.7777 | K7: 5799.4486 | L7: 5516.1228 | M7: 5383.2564 | N7: 5180.8617 | O7: 6577.9176 | S7: =K7 -> 5799.4486 | T7: =O7 -> 6577.9176 | U7: =IF(T7/S7<0,"n.a.",IF(S7>0,ROUND(T7,4)/ROUND(S7,4)-1,IF(S7<0,"n.a."))) -> 0.13423155 | V7: =IF(O7/N7<0,"n.a.",IF(N7>0,ROUND(O7,4)/ROUND(N7,4)-1,IF(N7<0,"n.a."))) -> 0.26965705
B8: 요약손익계산서 (Selected Income Statement) | H8: FVOCI (Financial assets at fair value through other comprehensive income) | J8: 20858.794 | K8: 21635.551 | L8: 22988.363 | M8: 22837.835 | N8: 22414.696 | O8: 22307.75 | S8: =K8 -> 21635.551 | T8: =O8 -> 22307.75 | U8: =IF(T8/S8<0,"n.a.",IF(S8>0,ROUND(T8,4)/ROUND(S8,4)-1,IF(S8<0,"n.a."))) -> 0.031069206 | V8: =IF(O8/N8<0,"n.a.",IF(N8>0,ROUND(O8,4)/ROUND(N8,4)-1,IF(N8<0,"n.a."))) -> -0.0047712313
H9: AC (Financial assets at amortized cost) | J9: 6567.0127 | K9: 6444.1106 | L9: 5581.7322 | M9: 5630.3909 | N9: 5395.1925 | O9: 5106.6193 | S9: =K9 -> 6444.1106 | T9: =O9 -> 5106.6193 | U9: =IF(T9/S9<0,"n.a.",IF(S9>0,ROUND(T9,4)/ROUND(S9,4)-1,IF(S9<0,"n.a."))) -> -0.20755251 | V9: =IF(O9/N9<0,"n.a.",IF(N9>0,ROUND(O9,4)/ROUND(N9,4)-1,IF(N9<0,"n.a."))) -> -0.0534871
B10: RA, CSM, BEL Movement | G10: ⅲ. 관계기업투자자산 (Investments accounted for using equity method) | J10: 45.233889 | K10: 28.520989 | L10: 0 | M10: 0 | N10: 0 | O10: 0 | S10: =K10 -> 28.520989 | T10: =O10 -> 0 | U10: =IF(T10/S10<0,"n.a.",IF(S10>0,ROUND(T10,4)/ROUND(S10,4)-1,IF(S10<0,"n.a."))) -> -1 | V10: n.a.
B11: 신계약 CSM (New Business CSM) | G11: ⅳ. 유형자산 (Property, plant and equipment) | J11: 89.902195 | K11: 91.378958 | L11: 84.426651 | M11: 91.038645 | N11: 107.51994 | O11: 96.713842 | S11: =K11 -> 91.378958 | T11: =O11 -> 96.713842 | U11: =IF(T11/S11<0,"n.a.",IF(S11>0,ROUND(T11,4)/ROUND(S11,4)-1,IF(S11<0,"n.a."))) -> 0.058381028 | V11: =IF(O11/N11<0,"n.a.",IF(N11>0,ROUND(O11,4)/ROUND(N11,4)-1,IF(N11<0,"n.a."))) -> -0.10050326
B12: 신계약 CSM 배수 (New Business CSM Margin) | G12: ⅴ. 투자부동산 (Investment properties) | J12: 306.5213 | K12: 304.25952 | L12: 305.78205 | M12: 296.13489 | N12: 300.04131 | O12: 74.350688 | S12: =K12 -> 304.25952 | T12: =O12 -> 74.350688 | U12: =IF(T12/S12<0,"n.a.",IF(S12>0,ROUND(T12,4)/ROUND(S12,4)-1,IF(S12<0,"n.a."))) -> -0.75563392 | V12: =IF(O12/N12<0,"n.a.",IF(N12>0,ROUND(O12,4)/ROUND(N12,4)-1,IF(N12<0,"n.a."))) -> -0.75219845
G13: ⅵ. 무형자산 (Intangible assets other than goodwill) | J13: 17.070498 | K13: 29.952522 | L13: 28.75102 | M13: 27.795714 | N13: 26.13475 | O13: 24.128873 | S13: =K13 -> 29.952522 | T13: =O13 -> 24.128873 | U13: =IF(T13/S13<0,"n.a.",IF(S13>0,ROUND(T13,4)/ROUND(S13,4)-1,IF(S13<0,"n.a."))) -> -0.19442784 | V13: =IF(O13/N13<0,"n.a.",IF(N13>0,ROUND(O13,4)/ROUND(N13,4)-1,IF(N13<0,"n.a."))) -> -0.07675207
B14: 주요지표 (Key Index) | G14: ⅶ. 기타자산 (Other assets) | J14: 485.3665 | K14: 358.01457 | L14: 365.10381 | M14: 353.66306 | N14: 295.88875 | O14: 64.773205 | S14: =K14 -> 358.01457 | T14: =O14 -> 64.773205 | U14: =IF(T14/S14<0,"n.a.",IF(S14>0,ROUND(T14,4)/ROUND(S14,4)-1,IF(S14<0,"n.a."))) -> -0.81907665 | V14: =IF(O14/N14<0,"n.a.",IF(N14>0,ROUND(O14,4)/ROUND(N14,4)-1,IF(N14<0,"n.a."))) -> -0.78108931
C15: 재무 안정성 (Financial Stability) | G15: ⅷ. 재보험계약자산 (Reinsurance contracts assets) | J15: 473.33356 | K15: 463.3578 | L15: 464.67552 | M15: 448.68173 | N15: 417.34774 | O15: 397.10532 | S15: =K15 -> 463.3578 | T15: =O15 -> 397.10532 | U15: =IF(T15/S15<0,"n.a.",IF(S15>0,ROUND(T15,4)/ROUND(S15,4)-1,IF(S15<0,"n.a."))) -> -0.14298346 | V15: =IF(O15/N15<0,"n.a.",IF(N15>0,ROUND(O15,4)/ROUND(N15,4)-1,IF(N15<0,"n.a."))) -> -0.048502484
C16: 생산성 / 경영효율 (Productivity / Operating Efficiency) | F16: Ⅱ. 부채총계 (Total liabilities) | J16: 33673.418 | K16: 33960.73 | L16: 34351.543 | M16: 33798.362 | N16: 32650.991 | O16: 32950.699 | S16: =K16 -> 33960.73 | T16: =O16 -> 32950.699 | U16: =IF(T16/S16<0,"n.a.",IF(S16>0,ROUND(T16,4)/ROUND(S16,4)-1,IF(S16<0,"n.a."))) -> -0.029741122 | V16: =IF(O16/N16<0,"n.a.",IF(N16>0,ROUND(O16,4)/ROUND(N16,4)-1,IF(N16<0,"n.a."))) -> 0.0091791486
G17: ⅰ. 보험계약부채 (Insurance contracts issued that are liabilities) | J17: 29330.677 | K17: 29166.616 | L17: 29392.006 | M17: 28145.079 | N17: 26584.371 | O17: 25971.37 | S17: =K17 -> 29166.616 | T17: =O17 -> 25971.37 | U17: =IF(T17/S17<0,"n.a.",IF(S17>0,ROUND(T17,4)/ROUND(S17,4)-1,IF(S17<0,"n.a."))) -> -0.10955147 | V17: =IF(O17/N17<0,"n.a.",IF(N17>0,ROUND(O17,4)/ROUND(N17,4)-1,IF(N17<0,"n.a."))) -> -0.02305868
B18: 상품별 수입보험료 (Premium by Product-type) | H18: CSM (Contract service margin) | J18: 2661.1771 | K18: 2744.2353 | L18: 2796.9809 | M18: 2457.0955 | N18: 2510.8346 | O18: 2645.7062 | S18: =K18 -> 2744.2353 | T18: =O18 -> 2645.7062 | U18: =IF(T18/S18<0,"n.a.",IF(S18>0,ROUND(T18,4)/ROUND(S18,4)-1,IF(S18<0,"n.a."))) -> -0.035904028 | V18: =IF(O18/N18<0,"n.a.",IF(N18>0,ROUND(O18,4)/ROUND(N18,4)-1,IF(N18<0,"n.a."))) -> 0.053715844
C19: 상품별 APE (Annualized Premium Equivalent (APE)) | G19: ⅱ. 투자계약부채 (Investment contracts liabilities) | J19: 3464.3864 | K19: 3474.4254 | L19: 3460.5865 | M19: 3702.7495 | N19: 3647.1587 | O19: 4461.0323 | S19: =K19 -> 3474.4254 | T19: =O19 -> 4461.0323 | U19: =IF(T19/S19<0,"n.a.",IF(S19>0,ROUND(T19,4)/ROUND(S19,4)-1,IF(S19<0,"n.a."))) -> 0.28396261 | V19: =IF(O19/N19<0,"n.a.",IF(N19>0,ROUND(O19,4)/ROUND(N19,4)-1,IF(N19<0,"n.a."))) -> 0.22315278
C20: 상품별 수입보험료 (Premium Income) | G20: ⅲ. 금융부채 (Financial liabilities) | J20: 814.48125 | K20: 1253.3246 | L20: 1409.0659 | M20: 1881.1728 | N20: 2353.8354 | O20: 2401.0461 | S20: =K20 -> 1253.3246 | T20: =O20 -> 2401.0461 | U20: =IF(T20/S20<0,"n.a.",IF(S20>0,ROUND(T20,4)/ROUND(S20,4)-1,IF(S20<0,"n.a."))) -> 0.91574162 | V20: =IF(O20/N20<0,"n.a.",IF(N20>0,ROUND(O20,4)/ROUND(N20,4)-1,IF(N20<0,"n.a."))) -> 0.020056925
C21: 상품별 초회보험료 (Initial Premium) | H21: 사채 (Borrowings) | J21: 299.09907 | K21: 971.25899 | L21: 994.26689 | M21: 1210.2125 | N21: 1249.5335 | O21: 1263.8484 | S21: =K21 -> 971.25899 | T21: =O21 -> 1263.8484 | U21: =IF(T21/S21<0,"n.a.",IF(S21>0,ROUND(T21,4)/ROUND(S21,4)-1,IF(S21<0,"n.a."))) -> 0.30124756 | V21: =IF(O21/N21<0,"n.a.",IF(N21>0,ROUND(O21,4)/ROUND(N21,4)-1,IF(N21<0,"n.a."))) -> 0.011456195
C22: 상품별 초년도보험료 (First Year Premium) | G22: ⅳ. 기타부채 (Other liabilities) | J22: 52.189581 | K22: 55.463708 | L22: 79.302011 | M22: 59.705326 | N22: 56.75185 | O22: 109.49829 | S22: =K22 -> 55.463708 | T22: =O22 -> 109.49829 | U22: =IF(T22/S22<0,"n.a.",IF(S22>0,ROUND(T22,4)/ROUND(S22,4)-1,IF(S22<0,"n.a."))) -> 0.9742336 | V22: =IF(O22/N22<0,"n.a.",IF(N22>0,ROUND(O22,4)/ROUND(N22,4)-1,IF(N22<0,"n.a."))) -> 0.92942426
G23: ⅴ. 재보험계약부채 (Reinsurance contracts assets) | J23: 11.68372 | K23: 10.899672 | L23: 10.582539 | M23: 9.6561702 | N23: 8.8742228 | O23: 7.7522609 | S23: =K23 -> 10.899672 | T23: =O23 -> 7.7522609 | U23: =IF(T23/S23<0,"n.a.",IF(S23>0,ROUND(T23,4)/ROUND(S23,4)-1,IF(S23<0,"n.a."))) -> -0.28876024 | V23: =IF(O23/N23<0,"n.a.",IF(N23>0,ROUND(O23,4)/ROUND(N23,4)-1,IF(N23<0,"n.a."))) -> -0.12642266
B24: 채널별 수입보험료 (Premium by Distribution Channel) | F24: Ⅲ. 자본총계 (Total Shareholders' Equity) | J24: 1485.6917 | K24: 1652.6077 | L24: 1342.7199 | M24: 1548.8747 | N24: 1844.313 | O24: 2336.9666 | S24: =K24 -> 1652.6077 | T24: =O24 -> 2336.9666 | U24: =IF(T24/S24<0,"n.a.",IF(S24>0,ROUND(T24,4)/ROUND(S24,4)-1,IF(S24<0,"n.a."))) -> 0.4141085 | V24: =IF(O24/N24<0,"n.a.",IF(N24>0,ROUND(O24,4)/ROUND(N24,4)-1,IF(N24<0,"n.a."))) -> 0.26712039
C25: 채널별 APE (Annualized Premium Equivalent (APE)) | G25: ⅰ. 자본금 (Issued capital) | J25: 806.79292 | K25: 806.79292 | L25: 806.79292 | M25: 806.79292 | N25: 806.79292 | O25: 806.79292 | S25: =K25 -> 806.79292 | T25: =O25 -> 806.79292 | U25: =IF(T25/S25<0,"n.a.",IF(S25>0,ROUND(T25,4)/ROUND(S25,4)-1,IF(S25<0,"n.a."))) -> 0 | V25: =IF(O25/N25<0,"n.a.",IF(N25>0,ROUND(O25,4)/ROUND(N25,4)-1,IF(N25<0,"n.a."))) -> 0
C26: 채널별 수입보험료 (Premium Income) | G26: ⅱ. 자본잉여금 (Capital surplus) | J26: 463.68039 | K26: 463.68039 | L26: 463.68039 | M26: 463.68039 | N26: 463.68039 | O26: 463.68039 | S26: =K26 -> 463.68039 | T26: =O26 -> 463.68039 | U26: =IF(T26/S26<0,"n.a.",IF(S26>0,ROUND(T26,4)/ROUND(S26,4)-1,IF(S26<0,"n.a."))) -> 0 | V26: =IF(O26/N26<0,"n.a.",IF(N26>0,ROUND(O26,4)/ROUND(N26,4)-1,IF(N26<0,"n.a."))) -> 0
C27: 채널별 초년도보험료 (First Year Premium) | G27: ⅲ. 신종자본증권 (Hybrid bonds) | J27: 344.56736 | K27: 344.56736 | L27: 0 | M27: 0 | N27: 0 | O27: 0 | S27: =K27 -> 344.56736 | T27: =O27 -> 0 | U27: =IF(T27/S27<0,"n.a.",IF(S27>0,ROUND(T27,4)/ROUND(S27,4)-1,IF(S27<0,"n.a."))) -> -1 | V27: n.a.
G28: ⅴ. 자본조정 (Capital Adjustments) | J28: -59.540575 | K28: -59.540575 | L28: -117.99152 | M28: -116.90631 | N28: -116.90631 | O28: -58.355691 | S28: =K28 -> -59.540575 | T28: =O28 -> -58.355691 | U28: =IF(T28/S28<0,"n.a.",IF(S28>0,ROUND(T28,4)/ROUND(S28,4)-1,IF(S28<0,"n.a."))) -> n.a. | V28: =IF(O28/N28<0,"n.a.",IF(N28>0,ROUND(O28,4)/ROUND(N28,4)-1,IF(N28<0,"n.a."))) -> n.a.
G29: ⅵ. 기타포괄손익누계액 (Accumulated other comprehensive income) | J29: -1621.937 | K29: -1491.2392 | L29: -1414.1059 | M29: -1223.6736 | N29: -953.56612 | O29: -530.12447 | S29: =K29 -> -1491.2392 | T29: =O29 -> -530.12447 | U29: =IF(T29/S29<0,"n.a.",IF(S29>0,ROUND(T29,4)/ROUND(S29,4)-1,IF(S29<0,"n.a."))) -> n.a. | V29: =IF(O29/N29<0,"n.a.",IF(N29>0,ROUND(O29,4)/ROUND(N29,4)-1,IF(N29<0,"n.a."))) -> n.a.
B30: 투자영업 현황 (Investment) | G30: ⅳ. 이익잉여금 (Retained earnings) | J30: 1552.1286 | K30: 1588.3468 | L30: 1604.344 | M30: 1618.9813 | N30: 1644.3121 | O30: 1654.9734 | S30: =K30 -> 1588.3468 | T30: =O30 -> 1654.9734 | U30: =IF(T30/S30<0,"n.a.",IF(S30>0,ROUND(T30,4)/ROUND(S30,4)-1,IF(S30<0,"n.a."))) -> 0.041947136 | V30: =IF(O30/N30<0,"n.a.",IF(N30>0,ROUND(O30,4)/ROUND(N30,4)-1,IF(N30<0,"n.a."))) -> 0.0064837448
C31: 대출 (Loan)/ 자산건전성 (Asset Quality of Loan) | F31: 자본과부채총계 (Total Shareholders' Equity and liabilities) | J31: 35159.11 | K31: 35613.337 | L31: 35694.263 | M31: 35347.237 | N31: 34495.304 | O31: 35287.666 | S31: =K31 -> 35613.337 | T31: =O31 -> 35287.666 | U31: =IF(T31/S31<0,"n.a.",IF(S31>0,ROUND(T31,4)/ROUND(S31,4)-1,IF(S31<0,"n.a."))) -> -0.0091446442 | V31: =IF(O31/N31<0,"n.a.",IF(N31>0,ROUND(O31,4)/ROUND(N31,4)-1,IF(N31<0,"n.a."))) -> 0.022970138
C32: 채권 (Bond)
B34: 재무제표 (Full Financial Statements) | F34: 요약 손익계산서 (Selected Income Statement)
C35: 재무상태표 (Balance Sheet - KIFRS) | F35: (단위 십억원) | J35: FY25 | N35: FY26 | S35: Accumulated | U35: 증감
C36: 손익계산서 (Income Statement - KIFRS) | F36: (KRW bn) | J36: 45747 | K36: 45838 | L36: 45930 | M36: 46022 | N36: 46112 | O36: 46203 | P36: 46295 | Q36: 46387 | S36: FY25.1H | T36: FY26.1H | U36: YoY | V36: QoQ
F37: 보험손익 (Insurance service result) | J37: 4.0710674 | K37: 66.348499 | L37: 24.562732 | M37: 18.788515 | N37: 22.385733 | O37: 74.626389 | S37: =+SUM(J37:K37) -> 70.419566 | T37: =+SUM(N37:Q37) -> 97.012122 | U37: =IF(T37/S37<0,"n.a.",IF(S37>0,ROUND(T37,4)/ROUND(S37,4)-1,IF(S37<0,"n.a."))) -> 0.37762924 | V37: =IF(O37/N37<0,"n.a.",IF(N37>0,ROUND(O37,4)/ROUND(N37,4)-1,IF(N37<0,"n.a."))) -> 2.3336639
G38: CSM 상각 (Amortization of CSM) | J38: 62.317797 | K38: 63.745714 | L38: 63.797646 | M38: 56.890212 | N38: 62.113713 | O38: 63.397781 | S38: =+SUM(J38:K38) -> 126.06351 | T38: =+SUM(N38:Q38) -> 125.51149 | U38: =IF(T38/S38<0,"n.a.",IF(S38>0,ROUND(T38,4)/ROUND(S38,4)-1,IF(S38<0,"n.a."))) -> -0.0043787456 | V38: =IF(O38/N38<0,"n.a.",IF(N38>0,ROUND(O38,4)/ROUND(N38,4)-1,IF(N38<0,"n.a."))) -> 0.020673378
G39: RA 상각 (Amortization of RA) | J39: 11.135398 | K39: 11.008743 | L39: 10.759074 | M39: 10.730104 | N39: 10.272807 | O39: 9.9859833 | S39: =+SUM(J39:K39) -> 22.144141 | T39: =+SUM(N39:Q39) -> 20.25879 | U39: =IF(T39/S39<0,"n.a.",IF(S39>0,ROUND(T39,4)/ROUND(S39,4)-1,IF(S39<0,"n.a."))) -> -0.085137802 | V39: =IF(O39/N39<0,"n.a.",IF(N39>0,ROUND(O39,4)/ROUND(N39,4)-1,IF(N39<0,"n.a."))) -> -0.027918386
G40: 예실차 (Difference between estimated and actual) | J40: -17.649083 | K40: -8.1693348 | L40: -39.308665 | M40: -6.7420452 | N40: -25.088176 | O40: -19.381523 | S40: =+SUM(J40:K40) -> -25.818418 | T40: =+SUM(N40:Q40) -> -44.469699 | U40: =IF(T40/S40<0,"n.a.",IF(S40>0,ROUND(T40,4)/ROUND(S40,4)-1,IF(S40<0,"n.a."))) -> n.a. | V40: =IF(O40/N40<0,"n.a.",IF(N40>0,ROUND(O40,4)/ROUND(N40,4)-1,IF(N40<0,"n.a."))) -> n.a.
H41: 보험금예실차 (Claims experience variance) | J41: -19.417094 | K41: -9.3369303 | L41: -26.88678 | M41: -13.162422 | N41: -21.808594 | O41: -21.527062 | S41: =+SUM(J41:K41) -> -28.754024 | T41: =+SUM(N41:Q41) -> -43.335656 | U41: =IF(T41/S41<0,"n.a.",IF(S41>0,ROUND(T41,4)/ROUND(S41,4)-1,IF(S41<0,"n.a."))) -> n.a. | V41: =IF(O41/N41<0,"n.a.",IF(N41>0,ROUND(O41,4)/ROUND(N41,4)-1,IF(N41<0,"n.a."))) -> n.a.
H42: 사업비예실차 (Expense experience variance) | J42: 1.7680113 | K42: 1.1675955 | L42: -12.421885 | M42: 6.420377 | N42: -3.279582 | O42: 2.1455388 | S42: =+SUM(J42:K42) -> 2.9356068 | T42: =+SUM(N42:Q42) -> -1.1340433 | U42: =IF(T42/S42<0,"n.a.",IF(S42>0,ROUND(T42,4)/ROUND(S42,4)-1,IF(S42<0,"n.a."))) -> n.a. | V42: =IF(O42/N42<0,"n.a.",IF(N42>0,ROUND(O42,4)/ROUND(N42,4)-1,IF(N42<0,"n.a."))) -> n.a.
G43: 기타 (Others) | J43: -51.733045 | K43: -0.23662303 | L43: -10.685323 | M43: -42.089756 | N43: -24.912612 | O43: 20.624148 | S43: =+SUM(J43:K43) -> -51.969668 | T43: =+SUM(N43:Q43) -> -4.2884635 | U43: =IF(T43/S43<0,"n.a.",IF(S43>0,ROUND(T43,4)/ROUND(S43,4)-1,IF(S43<0,"n.a."))) -> n.a. | V43: =IF(O43/N43<0,"n.a.",IF(N43>0,ROUND(O43,4)/ROUND(N43,4)-1,IF(N43<0,"n.a."))) -> n.a.
F44: 투자손익 (Investment Profit) | J44: 54.593749 | K44: -24.959965 | L44: 23.181135 | M44: 32.225946 | N44: 8.718764 | O44: 12.213226 | S44: =+SUM(J44:K44) -> 29.633785 | T44: =+SUM(N44:Q44) -> 20.93199 | U44: =IF(T44/S44<0,"n.a.",IF(S44>0,ROUND(T44,4)/ROUND(S44,4)-1,IF(S44<0,"n.a."))) -> -0.29364442 | V44: =IF(O44/N44<0,"n.a.",IF(N44>0,ROUND(O44,4)/ROUND(N44,4)-1,IF(N44<0,"n.a."))) -> 0.4007891
G45: 이자(배당)손익 (Interest(dividend) income or expense) | J45: 221.37862 | K45: 222.89585 | L45: 235.22259 | M45: 228.79414 | N45: 233.18163 | O45: 237.96858 | S45: =+SUM(J45:K45) -> 444.27447 | T45: =+SUM(N45:Q45) -> 471.15021 | U45: =IF(T45/S45<0,"n.a.",IF(S45>0,ROUND(T45,4)/ROUND(S45,4)-1,IF(S45<0,"n.a."))) -> 0.060493456 | V45: =IF(O45/N45<0,"n.a.",IF(N45>0,ROUND(O45,4)/ROUND(N45,4)-1,IF(N45<0,"n.a."))) -> 0.020529064
G46: 비이자손익(Non-Interest profit) | J46: 100.76539 | K46: 125.22237 | L46: 99.511743 | M46: 140.87743 | N46: 126.81938 | O46: 551.60737 | S46: =+SUM(J46:K46) -> 225.98776 | T46: =+SUM(N46:Q46) -> 678.42675 | U46: =IF(T46/S46<0,"n.a.",IF(S46>0,ROUND(T46,4)/ROUND(S46,4)-1,IF(S46<0,"n.a."))) -> 2.0020506 | V46: =IF(O46/N46<0,"n.a.",IF(N46>0,ROUND(O46,4)/ROUND(N46,4)-1,IF(N46<0,"n.a."))) -> 3.3495506
G47: 보험금융손익 (Insurance financial expense) | J47: -270.55463 | K47: -371.26771 | L47: -317.3999 | M47: -339.99401 | N47: -354.49783 | O47: -795.59178 | S47: =+SUM(J47:K47) -> -641.82234 | T47: =+SUM(N47:Q47) -> -1150.0896 | U47: =IF(T47/S47<0,"n.a.",IF(S47>0,ROUND(T47,4)/ROUND(S47,4)-1,IF(S47<0,"n.a."))) -> n.a. | V47: =IF(O47/N47<0,"n.a.",IF(N47>0,ROUND(O47,4)/ROUND(N47,4)-1,IF(N47<0,"n.a."))) -> n.a.
G48: 기타 (Others) | J48: 3.0043775 | K48: -1.8104795 | L48: 5.8467029 | M48: 2.5483787 | N48: 3.215575 | O48: 18.229058 | S48: =+SUM(J48:K48) -> 1.193898 | T48: =+SUM(N48:Q48) -> 21.444633 | U48: =IF(T48/S48<0,"n.a.",IF(S48>0,ROUND(T48,4)/ROUND(S48,4)-1,IF(S48<0,"n.a."))) -> 16.961806 | V48: =IF(O48/N48<0,"n.a.",IF(N48>0,ROUND(O48,4)/ROUND(N48,4)-1,IF(N48<0,"n.a."))) -> 4.6689576
F49: 영업이익(또는영업손실) ((Profit (loss) from operating activities) | J49: 58.664817 | K49: 41.388534 | L49: 47.743868 | M49: 51.01446 | N49: 31.104497 | O49: 86.839615 | S49: =+SUM(J49:K49) -> 100.05335 | T49: =+SUM(N49:Q49) -> 117.94411 | U49: =IF(T49/S49<0,"n.a.",IF(S49>0,ROUND(T49,4)/ROUND(S49,4)-1,IF(S49<0,"n.a."))) -> 0.17881151 | V49: =IF(O49/N49<0,"n.a.",IF(N49>0,ROUND(O49,4)/ROUND(N49,4)-1,IF(N49<0,"n.a."))) -> 1.7918661
F50: 영업외손익 (Non-operating profit or loss) | J50: -5.0065737 | K50: 1.0811315 | L50: -17.253721 | M50: -2.2042256 | N50: -0.10440069 | O50: 2.7407827 | S50: =+SUM(J50:K50) -> -3.9254422 | T50: =+SUM(N50:Q50) -> 2.636382 | U50: =IF(T50/S50<0,"n.a.",IF(S50>0,ROUND(T50,4)/ROUND(S50,4)-1,IF(S50<0,"n.a."))) -> n.a. | V50: =IF(O50/N50<0,"n.a.",IF(N50>0,ROUND(O50,4)/ROUND(N50,4)-1,IF(N50<0,"n.a."))) -> n.a.
F51: 법인세비용차감전순이익 (Profit (loss) before income taxes) | J51: 53.658243 | K51: 42.469666 | L51: 30.490147 | M51: 48.810235 | N51: 31.000096 | O51: 89.580398 | S51: =+SUM(J51:K51) -> 96.127909 | T51: =+SUM(N51:Q51) -> 120.58049 | U51: =IF(T51/S51<0,"n.a.",IF(S51>0,ROUND(T51,4)/ROUND(S51,4)-1,IF(S51<0,"n.a."))) -> 0.25437568 | V51: =IF(O51/N51<0,"n.a.",IF(N51>0,ROUND(O51,4)/ROUND(N51,4)-1,IF(N51<0,"n.a."))) -> 1.889681
F52: 당기순이익 (Net Income) | J52: 46.19408 | K52: 36.218191 | L52: 27.444115 | M52: 14.63725 | N52: 25.023874 | O52: 66.905803 | S52: =+SUM(J52:K52) -> 82.412272 | T52: =+SUM(N52:Q52) -> 91.929677 | U52: =IF(T52/S52<0,"n.a.",IF(S52>0,ROUND(T52,4)/ROUND(S52,4)-1,IF(S52<0,"n.a."))) -> 0.11548519 | V52: =IF(O52/N52<0,"n.a.",IF(N52>0,ROUND(O52,4)/ROUND(N52,4)-1,IF(N52<0,"n.a."))) -> 1.673676

Sheet CSM
F1: BEL, RA, CSM Movement
F2: (단위 십억원) | J2: FY25 | N2: FY26 | S2: Accumulated
A3: Disclaimer & Contact Information | F3: (KRW bn) | J3: 45747 | K3: 45838 | L3: 45930 | M3: 46022 | N3: 46112 | O3: 46203 | P3: 46295 | Q3: 46387 | S3: FY25.1H | T3: FY26.1H | U3: YoY | V3: QoQ
F4: BEL | I4: 기시 BEL (Beginning BEL) | J4: 23292.638 | K4: 24379.767 | L4: 24160.524 | M4: 24315.769 | N4: 23426.845 | O4: 21761.865 | S4: =J4 -> 23292.638 | T4: =N4 -> 23426.845 | U4: =IF(T4/S4<0,"n.a.",IF(S4>0,ROUND(T4,4)/ROUND(S4,4)-1,IF(S4<0,"n.a."))) -> 0.0057617863 | V4: =IF(O4/N4<0,"n.a.",IF(N4>0,ROUND(O4,4)/ROUND(N4,4)-1,IF(N4<0,"n.a."))) -> -0.071071444
B5: 재무현황 (Financial Highlights) | I5: 신계약 (New business) | J5: -206.71097 | K5: -123.42445 | L5: -135.56074 | M5: -112.52749 | N5: -103.94172 | O5: -162.93215 | S5: =+SUM(J5:K5) -> -330.13542 | T5: =+SUM(N5:Q5) -> -266.87387 | U5: =IF(T5/S5<0,"n.a.",IF(S5>0,ROUND(T5,4)/ROUND(S5,4)-1,IF(S5<0,"n.a."))) -> n.a. | V5: =IF(O5/N5<0,"n.a.",IF(N5>0,ROUND(O5,4)/ROUND(N5,4)-1,IF(N5<0,"n.a."))) -> n.a.
I6: 이자부리 (Unwinding) | J6: 224.28293 | K6: 326.06563 | L6: 272.09561 | M6: 291.67364 | N6: 312.79936 | O6: 753.45579 | S6: =+SUM(J6:K6) -> 550.34856 | T6: =+SUM(N6:Q6) -> 1066.2552 | U6: =IF(T6/S6<0,"n.a.",IF(S6>0,ROUND(T6,4)/ROUND(S6,4)-1,IF(S6<0,"n.a."))) -> 0.93741785 | V6: =IF(O6/N6<0,"n.a.",IF(N6>0,ROUND(O6,4)/ROUND(N6,4)-1,IF(N6<0,"n.a."))) -> 1.4087508
B7: 요약재무상태표 (Selected Balance sheet) | I7: 당기 현금흐름 (Cashflow) | J7: -80.928354 | K7: 19.204318 | L7: 212.07019 | M7: -176.78153 | N7: -310.62606 | O7: 37.415239 | S7: =+SUM(J7:K7) -> -61.724036 | T7: =+SUM(N7:Q7) -> -273.21082 | U7: =IF(T7/S7<0,"n.a.",IF(S7>0,ROUND(T7,4)/ROUND(S7,4)-1,IF(S7<0,"n.a."))) -> n.a. | V7: =IF(O7/N7<0,"n.a.",IF(N7>0,ROUND(O7,4)/ROUND(N7,4)-1,IF(N7<0,"n.a."))) -> n.a.
B8: 요약손익계산서 (Selected Income Statement) | I8: 기타 (Others) | J8: 1150.4855 | K8: -441.08821 | L8: -193.35993 | M8: -891.28893 | N8: -1563.2113 | O8: -1379.8324 | S8: =+SUM(J8:K8) -> 709.39731 | T8: =+SUM(N8:Q8) -> -2943.0437 | U8: =IF(T8/S8<0,"n.a.",IF(S8>0,ROUND(T8,4)/ROUND(S8,4)-1,IF(S8<0,"n.a."))) -> n.a. | V8: =IF(O8/N8<0,"n.a.",IF(N8>0,ROUND(O8,4)/ROUND(N8,4)-1,IF(N8<0,"n.a."))) -> n.a.
I9: 기말 BEL (Ending BEL) | J9: 24379.767 | K9: 24160.524 | L9: 24315.769 | M9: 23426.845 | N9: 21761.865 | O9: 21009.972 | S9: =K9 -> 24160.524 | T9: =O9 -> 21009.972 | U9: =IF(T9/S9<0,"n.a.",IF(S9>0,ROUND(T9,4)/ROUND(S9,4)-1,IF(S9<0,"n.a."))) -> -0.13040083 | V9: =IF(O9/N9<0,"n.a.",IF(N9>0,ROUND(O9,4)/ROUND(N9,4)-1,IF(N9<0,"n.a."))) -> -0.034550972
B10: RA, CSM, BEL Movement | F10: RA | I10: 기시 RA (Beginning RA) | J10: 466.33601 | K10: 472.4947 | L10: 488.93878 | M10: 493.99081 | N10: 470.44579 | O10: 489.20572 | S10: =J10 -> 466.33601 | T10: =N10 -> 470.44579 | U10: =IF(T10/S10<0,"n.a.",IF(S10>0,ROUND(T10,4)/ROUND(S10,4)-1,IF(S10<0,"n.a."))) -> 0.0088129589 | V10: =IF(O10/N10<0,"n.a.",IF(N10>0,ROUND(O10,4)/ROUND(N10,4)-1,IF(N10<0,"n.a."))) -> 0.039876857
B11: 신계약 CSM (New Business CSM) | I11: 신계약 (New business) | J11: 17.914724 | K11: 13.116019 | L11: 14.742877 | M11: 12.613123 | N11: 11.750924 | O11: 16.158727 | S11: =+SUM(J11:K11) -> 31.030743 | T11: =+SUM(N11:Q11) -> 27.909651 | U11: =IF(T11/S11<0,"n.a.",IF(S11>0,ROUND(T11,4)/ROUND(S11,4)-1,IF(S11<0,"n.a."))) -> -0.10057781 | V11: =IF(O11/N11<0,"n.a.",IF(N11>0,ROUND(O11,4)/ROUND(N11,4)-1,IF(N11<0,"n.a."))) -> 0.37510318
B12: 신계약 CSM 배수 (New Business CSM Margin) | I12: 이자부리 (Unwinding) | J12: 4.1129863 | K12: 4.2515465 | L12: 4.309212 | M12: 5.2846066 | N12: 4.1300512 | O12: 4.2226775 | S12: =+SUM(J12:K12) -> 8.3645328 | T12: =+SUM(N12:Q12) -> 8.3527287 | U12: =IF(T12/S12<0,"n.a.",IF(S12>0,ROUND(T12,4)/ROUND(S12,4)-1,IF(S12<0,"n.a."))) -> -0.0014107239 | V12: =IF(O12/N12<0,"n.a.",IF(N12>0,ROUND(O12,4)/ROUND(N12,4)-1,IF(N12<0,"n.a."))) -> 0.022420765
I13: RA 상각 (Amortization of RA) | J13: -11.135398 | K13: -11.008743 | L13: -10.759074 | M13: -10.730104 | N13: -10.272807 | O13: -9.9859833 | S13: =+SUM(J13:K13) -> -22.144141 | T13: =+SUM(N13:Q13) -> -20.25879 | U13: =IF(T13/S13<0,"n.a.",IF(S13>0,ROUND(T13,4)/ROUND(S13,4)-1,IF(S13<0,"n.a."))) -> n.a. | V13: =IF(O13/N13<0,"n.a.",IF(N13>0,ROUND(O13,4)/ROUND(N13,4)-1,IF(N13<0,"n.a."))) -> n.a.
B14: 주요지표 (Key Index) | I14: 기타 (Others) | J14: -4.7336266 | K14: 10.085262 | L14: -3.2409879 | M14: -30.712647 | N14: 13.151767 | O14: 23.963908 | S14: =+SUM(J14:K14) -> 5.3516355 | T14: =+SUM(N14:Q14) -> 37.115675 | U14: =IF(T14/S14<0,"n.a.",IF(S14>0,ROUND(T14,4)/ROUND(S14,4)-1,IF(S14<0,"n.a."))) -> 5.9354399 | V14: =IF(O14/N14<0,"n.a.",IF(N14>0,ROUND(O14,4)/ROUND(N14,4)-1,IF(N14<0,"n.a."))) -> 0.8221004
C15: 재무 안정성 (Financial Stability) | I15: 기말 RA (Ending RA) | J15: 472.4947 | K15: 488.93878 | L15: 493.99081 | M15: 470.44579 | N15: 489.20572 | O15: 523.56505 | S15: =K15 -> 488.93878 | T15: =O15 -> 523.56505 | U15: =IF(T15/S15<0,"n.a.",IF(S15>0,ROUND(T15,4)/ROUND(S15,4)-1,IF(S15<0,"n.a."))) -> 0.070819293 | V15: =IF(O15/N15<0,"n.a.",IF(N15>0,ROUND(O15,4)/ROUND(N15,4)-1,IF(N15<0,"n.a."))) -> 0.070235077
C16: 생산성 / 경영효율 (Productivity / Operating Efficiency) | F16: CSM | I16: 기시 CSM (Beginning CSM) | J16: 2671.0889 | K16: 2661.1771 | L16: 2744.2353 | M16: 2796.9809 | N16: 2457.0955 | O16: 2510.8346 | S16: =J16 -> 2671.0889 | T16: =N16 -> 2457.0955 | U16: =IF(T16/S16<0,"n.a.",IF(S16>0,ROUND(T16,4)/ROUND(S16,4)-1,IF(S16<0,"n.a."))) -> -0.080114668 | V16: =IF(O16/N16<0,"n.a.",IF(N16>0,ROUND(O16,4)/ROUND(N16,4)-1,IF(N16<0,"n.a."))) -> 0.021870985
I17: 신계약 (New business) | J17: 190.38142 | K17: 112.50486 | L17: 122.96216 | M17: 103.28378 | N17: 94.465158 | O17: 148.02143 | S17: =+SUM(J17:K17) -> 302.88629 | T17: =+SUM(N17:Q17) -> 242.48659 | U17: =IF(T17/S17<0,"n.a.",IF(S17>0,ROUND(T17,4)/ROUND(S17,4)-1,IF(S17<0,"n.a."))) -> -0.19941377 | V17: =IF(O17/N17<0,"n.a.",IF(N17>0,ROUND(O17,4)/ROUND(N17,4)-1,IF(N17<0,"n.a."))) -> 0.56694105
B18: 상품별 수입보험료 (Premium by Product-type) | I18: 이자부리 (Unwinding) | J18: 27.804562 | K18: 27.189727 | L18: 27.696868 | M18: 27.814268 | N18: 24.745961 | O18: 25.598145 | S18: =+SUM(J18:K18) -> 54.994289 | T18: =+SUM(N18:Q18) -> 50.344105 | U18: =IF(T18/S18<0,"n.a.",IF(S18>0,ROUND(T18,4)/ROUND(S18,4)-1,IF(S18<0,"n.a."))) -> -0.084557854 | V18: =IF(O18/N18<0,"n.a.",IF(N18>0,ROUND(O18,4)/ROUND(N18,4)-1,IF(N18<0,"n.a."))) -> 0.034433848
C19: 상품별 APE (Annualized Premium Equivalent (APE)) | I19: CSM 상각 (Amortization of CSM) | J19: -62.317686 | K19: -63.745714 | L19: -63.797646 | M19: -56.890212 | N19: -62.113713 | O19: -63.397781 | S19: =+SUM(J19:K19) -> -126.0634 | T19: =+SUM(N19:Q19) -> -125.51149 | U19: =IF(T19/S19<0,"n.a.",IF(S19>0,ROUND(T19,4)/ROUND(S19,4)-1,IF(S19<0,"n.a."))) -> n.a. | V19: =IF(O19/N19<0,"n.a.",IF(N19>0,ROUND(O19,4)/ROUND(N19,4)-1,IF(N19<0,"n.a."))) -> n.a.
C20: 상품별 수입보험료 (Premium Income) | I20: 기타 (Others) | J20: -165.78003 | K20: 7.1092549 | L20: -34.115748 | M20: -414.09326 | N20: -3.35827 | O20: 24.649774 | S20: =+SUM(J20:K20) -> -158.67078 | T20: =+SUM(N20:Q20) -> 21.291504 | U20: =IF(T20/S20<0,"n.a.",IF(S20>0,ROUND(T20,4)/ROUND(S20,4)-1,IF(S20<0,"n.a."))) -> n.a. | V20: =IF(O20/N20<0,"n.a.",IF(N20>0,ROUND(O20,4)/ROUND(N20,4)-1,IF(N20<0,"n.a."))) -> n.a.
C21: 상품별 초회보험료 (Initial Premium) | I21: 기말 CSM (Ending CSM) | J21: 2661.1771 | K21: 2744.2353 | L21: 2796.9809 | M21: 2457.0955 | N21: 2510.8346 | O21: 2645.7062 | S21: =K21 -> 2744.2353 | T21: =O21 -> 2645.7062 | U21: =IF(T21/S21<0,"n.a.",IF(S21>0,ROUND(T21,4)/ROUND(S21,4)-1,IF(S21<0,"n.a."))) -> -0.035904028 | V21: =IF(O21/N21<0,"n.a.",IF(N21>0,ROUND(O21,4)/ROUND(N21,4)-1,IF(N21<0,"n.a."))) -> 0.053715844
C22: 상품별 초년도보험료 (First Year Premium)
B24: 채널별 수입보험료 (Premium by Distribution Channel) | F24: 신계약 CSM (New Business CSM)
C25: 채널별 APE (Annualized Premium Equivalent (APE)) | F25: (단위 십억원, %) | J25: FY25 | N25: FY26 | S25: Accumulated
C26: 채널별 수입보험료 (Premium Income) | F26: (KRW bn, %) | J26: 45747 | K26: 45838 | L26: 45930 | M26: 46022 | N26: 46112 | O26: 46203 | P26: 46295 | Q26: 46387 | S26: FY25.1H | T26: FY26.1H | U26: YoY | V26: QoQ
C27: 채널별 초년도보험료 (First Year Premium) | F27: 보장성 (Protection-type) | J27: 190.08209 | K27: 111.85241 | L27: 118.75089 | M27: 100.53123 | N27: 85.627267 | O27: 133.20411 | S27: =+SUM(J27:K27) -> 301.9345 | T27: =+SUM(N27:Q27) -> 218.83138 | U27: =IF(T27/S27<0,"n.a.",IF(S27>0,ROUND(T27,4)/ROUND(S27,4)-1,IF(S27<0,"n.a."))) -> -0.27523552 | V27: =IF(O27/N27<0,"n.a.",IF(N27>0,ROUND(O27,4)/ROUND(N27,4)-1,IF(N27<0,"n.a."))) -> 0.55562653
H28: 사망 (Death) | J28: 24.36491 | K28: 20.799178 | L28: 24.486239 | M28: 33.3637 | N28: 32.12895 | O28: 73.297422 | S28: =+SUM(J28:K28) -> 45.164087 | T28: =+SUM(N28:Q28) -> 105.42637 | U28: =IF(T28/S28<0,"n.a.",IF(S28>0,ROUND(T28,4)/ROUND(S28,4)-1,IF(S28<0,"n.a."))) -> 1.3342965 | V28: =IF(O28/N28<0,"n.a.",IF(N28>0,ROUND(O28,4)/ROUND(N28,4)-1,IF(N28<0,"n.a."))) -> 1.2813471
H29: 건강 (Health) | J29: 165.71718 | K29: 91.053229 | L29: 94.264653 | M29: 67.167528 | N29: 53.498317 | O29: 59.906689 | S29: =+SUM(J29:K29) -> 256.77041 | T29: =+SUM(N29:Q29) -> 113.40501 | U29: =IF(T29/S29<0,"n.a.",IF(S29>0,ROUND(T29,4)/ROUND(S29,4)-1,IF(S29<0,"n.a."))) -> -0.55834084 | V29: =IF(O29/N29<0,"n.a.",IF(N29>0,ROUND(O29,4)/ROUND(N29,4)-1,IF(N29<0,"n.a."))) -> 0.11978698
B30: 투자영업 현황 (Investment) | F30: 저축성 (Savings/Annuities) | J30: 0.29932859 | K30: 0.65245749 | L30: 4.211266 | M30: 2.7525558 | N30: 8.8378914 | O30: 14.817323 | S30: =+SUM(J30:K30) -> 0.95178609 | T30: =+SUM(N30:Q30) -> 23.655215 | U30: =IF(T30/S30<0,"n.a.",IF(S30>0,ROUND(T30,4)/ROUND(S30,4)-1,IF(S30<0,"n.a."))) -> 23.85312 | V30: =IF(O30/N30<0,"n.a.",IF(N30>0,ROUND(O30,4)/ROUND(N30,4)-1,IF(N30<0,"n.a."))) -> 0.67656344
C31: 대출 (Loan)/ 자산건전성 (Asset Quality of Loan) | F31: 합계 (Total) | J31: 190.38142 | K31: 112.50486 | L31: 122.96216 | M31: 103.28378 | N31: 94.465158 | O31: 148.02143 | S31: =+SUM(J31:K31) -> 302.88629 | T31: =+SUM(N31:Q31) -> 242.48659 | U31: =IF(T31/S31<0,"n.a.",IF(S31>0,ROUND(T31,4)/ROUND(S31,4)-1,IF(S31<0,"n.a."))) -> -0.19941377 | V31: =IF(O31/N31<0,"n.a.",IF(N31>0,ROUND(O31,4)/ROUND(N31,4)-1,IF(N31<0,"n.a."))) -> 0.56694105
C32: 채권 (Bond)
B34: 재무제표 (Full Financial Statements) | F34: APE 대비 신계약 CSM 배수 (New Business CSM Margin compared to New Business APE)
C35: 재무상태표 (Balance Sheet - KIFRS) | F35: (단위 십억원, %) | J35: FY25 | N35: FY26 | S35: Accumulated
C36: 손익계산서 (Income Statement - KIFRS) | F36: (KRW bn, %) | J36: 45747 | K36: 45838 | L36: 45930 | M36: 46022 | N36: 46112 | O36: 46203 | P36: 46295 | Q36: 46387 | S36: FY25.1H | T36: FY26.1H | U36: YoY | V36: QoQ
F37: 보장성 (Protection-type) | J37: 1.0389893 | K37: 0.73349618 | L37: 0.76006571 | M37: 0.74501429 | N37: 0.72366426 | O37: 0.79080181 | S37: 0.9001116 | T37: 0.76309975 | U37: =T37-S37 -> -0.13701185 | V37: =O37-N37 -> 0.067137557
H38: 사망 (Death) | J38: 0.36687917 | K38: 0.42548371 | L38: 0.49007954 | M38: 0.57811709 | N38: 0.62758905 | O38: 0.68467673 | S38: 0.39172677 | T38: 0.66620853 | U38: =T38-S38 -> 0.27448176 | V38: =O38-N38 -> 0.057087675
H39: 건강 (Health) | J39: 1.422004 | K39: 0.87881972 | L39: 0.88699754 | M39: 0.86973381 | N39: 0.79693216 | O39: 0.9758732 | S39: 1.1663625 | T39: 0.88240489 | U39: =T39-S39 -> -0.28395765 | V39: =O39-N39 -> 0.17894104
F40: 저축성 (Savings/Annuities) | J40: 0.21196606 | K40: 0.19958942 | L40: 0.15686798 | M40: 0.32997678 | N40: 0.42429236 | O40: 0.38929627 | S40: 0.20332306 | T40: 0.40167426 | U40: =T40-S40 -> 0.19835121 | V40: =O40-N40 -> -0.034996089
F41: 합계 (Total) | J41: 1.0326545 | K41: 0.72229095 | L41: 0.67161758 | M41: 0.72085114 | N41: 0.67885189 | O41: 0.71679814 | S41: 0.8905216 | T41: 0.70152181 | U41: =T41-S41 -> -0.18899979 | V41: =O41-N41 -> 0.037946241
F44: 월초P 대비 신계약 CSM 배수 (New Business CSM Margin compared to Monthly initial premium)
F45: (단위 십억원, %) | J45: FY25 | N45: FY26 | S45: Accumulated
F46: (KRW bn, %) | J46: 45747 | K46: 45838 | L46: 45930 | M46: 46022 | N46: 46112 | O46: 46203 | P46: 46295 | Q46: 46387 | S46: FY25.1H | T46: FY26.1H | U46: YoY | V46: QoQ
F47: 보장성 (Protection-type) | J47: 12.467872 | K47: 8.8019542 | L47: 9.1207885 | M47: 8.9401715 | N47: 8.6839711 | O47: 9.4896218 | S47: 10.801339 | T47: 9.1571969 | U47: =+T47-S47 -> -1.6441422 | V47: =+O47-N47 -> 0.80565069
H48: 사망 (Death) | J48: 4.40255 | K48: 5.1058046 | L48: 5.8809545 | M48: 6.9374051 | N48: 7.5310686 | O48: 8.2161207 | S48: 4.7007213 | T48: 7.9945024 | U48: =+T48-S48 -> 3.2937811 | V48: =+O48-N48 -> 0.6850521
H49: 건강 (Health) | J49: 17.064048 | K49: 10.545837 | L49: 10.64397 | M49: 10.436806 | N49: 9.5631859 | O49: 11.710478 | S49: 13.99635 | T49: 10.588859 | U49: =+T49-S49 -> -3.4074918 | V49: =+O49-N49 -> 2.1472925
F50: 저축성 (Savings/Annuities) | J50: 2.5435927 | K50: 2.3950731 | L50: 1.8824158 | M50: 3.9597213 | N50: 5.0915084 | O50: 4.6715553 | S50: 2.4398767 | T50: 4.8200912 | U50: =+T50-S50 -> 2.3802145 | V50: =+O50-N50 -> -0.41995306
F51: 합계 (Total) | J51: 12.391854 | K51: 8.6674914 | L51: 8.0594109 | M51: 8.6502137 | N51: 8.1462227 | O51: 8.6015776 | S51: 10.686259 | T51: 8.4182617 | U51: =+T51-S51 -> -2.2679974 | V51: =+O51-N51 -> 0.4553549

Sheet Stability
F1: 재무안정성 (Financial Stability Index)
A3: Disclaimer & Contact Information | F3: <K-ICS 기준>
F4: (단위 십억원) | J4: FY25 | N4: FY26 | S4: 증감
B5: 재무현황 (Financial Highlights) | F5: (KRW bn) | J5: 45747 | K5: 45838 | L5: 45930 | M5: 46022 | N5: 46112 | O5: 46203 | P5: 46295 | Q5: 46387 | S5: YoY | T5: QoQ
F6: 지급여력비율 (K-ICS ratio) (A)÷(B) | J6: =J7/J8 -> 1.2716316 | K6: =K7/K8 -> 1.7696419 | L6: =L7/L8 -> 1.735948 | M6: =M7/M8 -> 1.7983878 | N6: =N7/N8 -> 1.8955182 | O6: =O7/O8 -> 2.0499919 | S6: =O6-K6 -> 0.28035005 | T6: =O6-N6 -> 0.15447376
B7: 요약재무상태표 (Selected Balance sheet) | G7: 지급여력금액 (Available Capital) (A) | J7: 3386.1573 | K7: 4285.0285 | L7: 4020.0403 | M7: 4059.4964 | N7: 4345.7256 | O7: 4927.3892 | S7: =IF(O7/K7<0,"n.a.",IF(K7>0,ROUND(O7,4)/ROUND(K7,4)-1,IF(K7<0,"n.a."))) -> 0.14990815 | T7: =IF(O7/N7<0,"n.a.",IF(N7>0,ROUND(O7,4)/ROUND(N7,4)-1,IF(N7<0,"n.a."))) -> 0.13384729
B8: 요약손익계산서 (Selected Income Statement) | G8: 지급여력기준금액 (Required Capital) (B) | J8: 2662.8445 | K8: 2421.41 | L8: 2315.7608 | M8: 2257.2976 | N8: 2292.632 | O8: 2403.6139 | S8: =IF(O8/K8<0,"n.a.",IF(K8>0,ROUND(O8,4)/ROUND(K8,4)-1,IF(K8<0,"n.a."))) -> -0.0073494782 | T8: =IF(O8/N8<0,"n.a.",IF(N8>0,ROUND(O8,4)/ROUND(N8,4)-1,IF(N8<0,"n.a."))) -> 0.048408074
H9: 보험위험액 (Insurance Risk) | J9: 1955.9436 | K9: 1997.3053 | L9: 2016.3067 | M9: 1863.7667 | N9: 1984.2305 | O9: 2166.102 | S9: =IF(O9/K9<0,"n.a.",IF(K9>0,ROUND(O9,4)/ROUND(K9,4)-1,IF(K9<0,"n.a."))) -> 0.084512218 | T9: =IF(O9/N9<0,"n.a.",IF(N9>0,ROUND(O9,4)/ROUND(N9,4)-1,IF(N9<0,"n.a."))) -> 0.091658454
B10: RA, CSM, BEL Movement | H10: 시장위험액 (Market Risk) | J10: 1219.7393 | K10: 867.3994 | L10: 612.62056 | M10: 669.76496 | N10: 665.03461 | O10: 684.43741 | S10: =IF(O10/K10<0,"n.a.",IF(K10>0,ROUND(O10,4)/ROUND(K10,4)-1,IF(K10<0,"n.a."))) -> -0.21093167 | T10: =IF(O10/N10<0,"n.a.",IF(N10>0,ROUND(O10,4)/ROUND(N10,4)-1,IF(N10<0,"n.a."))) -> 0.029175625
B11: 신계약 CSM (New Business CSM) | H11: 신용위험액 (Credit Risk) | J11: 627.84819 | K11: 665.54097 | L11: 588.82625 | M11: 589.58549 | N11: 576.58746 | O11: 585.78746 | S11: =IF(O11/K11<0,"n.a.",IF(K11>0,ROUND(O11,4)/ROUND(K11,4)-1,IF(K11<0,"n.a."))) -> -0.11983259 | T11: =IF(O11/N11<0,"n.a.",IF(N11>0,ROUND(O11,4)/ROUND(N11,4)-1,IF(N11<0,"n.a."))) -> 0.015955948
B12: 신계약 CSM 배수 (New Business CSM Margin) | H12: 운영위험액 (Operation Risk) | J12: 151.63117 | K12: 141.85425 | L12: 195.73361 | M12: 245.18693 | N12: 268.65444 | O12: 318.11633 | S12: =IF(O12/K12<0,"n.a.",IF(K12>0,ROUND(O12,4)/ROUND(K12,4)-1,IF(K12<0,"n.a."))) -> 1.2425582 | T12: =IF(O12/N12<0,"n.a.",IF(N12>0,ROUND(O12,4)/ROUND(N12,4)-1,IF(N12<0,"n.a."))) -> 0.18410977
F13: *1 K-ICS Ratio : 2026.1H 비율은 추정치로 추후 업데이트 예정
B14: 주요지표 (Key Index) | F14: *2 공통 경과조치 적용 후 기준
C15: 재무 안정성 (Financial Stability)
C16: 생산성 / 경영효율 (Productivity / Operating Efficiency)
F17: (단위 십억원) | J17: FY25 | N17: FY26 | S17: 증감
B18: 상품별 수입보험료 (Premium by Product-type) | F18: (KRW bn) | J18: 45747 | K18: 45838 | L18: 45930 | M18: 46022 | N18: 46112 | O18: 46203 | P18: 46295 | Q18: 46387 | S18: YoY | T18: QoQ
C19: 상품별 APE (Annualized Premium Equivalent (APE)) | F19: 책임준비금 (Premium Reserve Breakdown) | J19: 29579.996 | K19: 29788.906 | L19: 30268.852 | M19: 30352.361 | N19: 30252.027 | O19: 30487.415 | S19: =IF(O19/K19<0,"n.a.",IF(K19>0,ROUND(O19,4)/ROUND(K19,4)-1,IF(K19<0,"n.a."))) -> 0.023448636 | T19: =IF(O19/N19<0,"n.a.",IF(N19>0,ROUND(O19,4)/ROUND(N19,4)-1,IF(N19<0,"n.a."))) -> 0.0077808967
C20: 상품별 수입보험료 (Premium Income) | G20: 연동이율 (Floating rate) | J20: 0.41094196 | K20: 0.40217874 | L20: 0.3984 | M20: 0.39293181 | N20: 0.37965838 | O20: 0.37180702 | S20: =O20-K20 -> -0.03037172 | T20: =O20-N20 -> -0.0078513567
C21: 상품별 초회보험료 (Initial Premium) | G21: 고정이율 (Fixed rate) | J21: 0.58905804 | K21: 0.59782126 | L21: 0.6017 | M21: 0.60706819 | N21: 0.62034162 | O21: 0.62819298 | S21: =O21-K21 -> 0.03037172 | T21: =O21-N21 -> 0.0078513567
C22: 상품별 초년도보험료 (First Year Premium) | H22: ≥ 6.0% | J22: 0.075259446 | K22: 0.074639296 | L22: 0.0733 | M22: 0.072856848 | N22: 0.072971375 | O22: 0.072187384 | S22: =O22-K22 -> -0.0024519121 | T22: =O22-N22 -> -0.00078399109
H23: ＜ 6.0% | J23: 0.5137986 | K23: 0.52318196 | L23: 0.5284 | M23: 0.53421134 | N23: 0.54737025 | O23: 0.55600559 | S23: =O23-K23 -> 0.032823632 | T23: =O23-N23 -> 0.0086353477
B24: 채널별 수입보험료 (Premium by Distribution Channel) | F24: 부담이율 (Crediting rate) | J24: 0.035551845 | K24: 0.035492069 | L24: 0.035638137 | M24: 0.03574576 | N24: 0.036067514 | O24: 0.036931006 | S24: =O24-K24 -> 0.0014389368 | T24: =O24-N24 -> 0.00086349134
C25: 채널별 APE (Annualized Premium Equivalent (APE)) | F25: 운용자산 이익율 (Net Investment Yield) (F) | J25: 0.038222661 | K25: 0.034722379 | L25: 0.035294828 | M25: 0.03428012 | N25: 0.035862482 | O25: 0.035666469 | S25: =O25-K25 -> 0.00094409046 | T25: =O25-N25 -> -0.00019601259
C26: 채널별 수입보험료 (Premium Income) | F26: 스프레드 (Spread) (F)－(E) | J26: =J25-J24 -> 0.0026708165 | K26: =K25-K24 -> -0.00076968995 | L26: =L25-L24 -> -0.00034330942 | M26: =M25-M24 -> -0.0014656408 | N26: =N25-N24 -> -0.00020503236 | O26: =O25-O24 -> -0.0012645363 | S26: =O26-K26 -> -0.00049484634 | T26: =O26-N26 -> -0.0010595039
C27: 채널별 초년도보험료 (First Year Premium)
B30: 투자영업 현황 (Investment)
C31: 대출 (Loan)/ 자산건전성 (Asset Quality of Loan)
C32: 채권 (Bond)
B34: 재무제표 (Full Financial Statements)
C35: 재무상태표 (Balance Sheet - KIFRS)
C36: 손익계산서 (Income Statement - KIFRS)

Sheet Productivity
F1: 생산성/경영효율 (Productivity / Operating Efficiency)
F2: (단위 십억원, 명, %) | J2: FY25 | N2: FY26 | S2: 증감
A3: Disclaimer & Contact Information | F3: (KRW bn, persons, %) | J3: 45747 | K3: 45838 | L3: 45930 | M3: 46022 | N3: 46112 | O3: 46203 | P3: 46295 | Q3: 46387 | S3: YoY | T3: QoQ
F4: 신계약 비율 (New Business ratio)
B5: 재무현황 (Financial Highlights) | G5: 일반계정 (General Account) | J5: 0.014338999 | K5: 0.024947613 | L5: 0.03958901 | M5: 0.054271011 | N5: 0.01474388 | O5: 0.035923147 | S5: =O5-K5 -> 0.010975535 | T5: =O5-N5 -> 0.021179268
G6: 특별계정 (Separate Account) | J6: 7.9135192e-05 | K6: 0.0001185179 | L6: 0.00018433945 | M6: 0.0040072716 | N6: 0.00011096503 | O6: 0.0016942914 | S6: =O6-K6 -> 0.0015757735 | T6: =O6-N6 -> 0.0015833263
B7: 요약재무상태표 (Selected Balance sheet) | F7: 효력상실해약 비율 (Lapses & Surrenders Ratio)
B8: 요약손익계산서 (Selected Income Statement) | G8: 일반계정 (General Account) | J8: 0.020696707 | K8: 0.038037782 | L8: 0.054206474 | M8: 0.069134891 | N8: 0.017749656 | O8: 0.034387837 | S8: =O8-K8 -> -0.0036499453 | T8: =O8-N8 -> 0.01663818
G9: 특별계정 (Separate Account) | J9: 0.016496223 | K9: 0.035185052 | L9: 0.046912739 | M9: 0.060952619 | N9: 0.026312964 | O9: 0.056248341 | S9: =O9-K9 -> 0.021063289 | T9: =O9-N9 -> 0.029935377
B10: RA, CSM, BEL Movement | F10: 전체 유지율 (Persistency Ratio)
B11: 신계약 CSM (New Business CSM) | G11: 13회차 (13th month) | J11: 0.89433798 | K11: 0.89740794 | L11: 0.8992024 | M11: 0.89866683 | N11: 0.89469318 | O11: 0.89052152 | S11: =O11-K11 -> -0.006886419 | T11: =O11-N11 -> -0.0041716619
B12: 신계약 CSM 배수 (New Business CSM Margin) | G12: 25회차 (25th month) | J12: 0.78729115 | K12: 0.81167789 | L12: 0.83585764 | M12: 0.78552608 | N12: 0.80286634 | O12: 0.81026345 | S12: =O12-K12 -> -0.0014144453 | T12: =O12-N12 -> 0.0073971097
F13: 보장성 유지율 (Protection-type Persistency Ratio)
B14: 주요지표 (Key Index) | G14: 13회차 (13th month) | J14: 0.88719516 | K14: 0.88596781 | L14: 0.89507224 | M14: 0.89326946 | N14: 0.89321803 | O14: 0.88945289 | S14: =O14-K14 -> 0.003485081 | T14: =O14-N14 -> -0.0037651398
C15: 재무 안정성 (Financial Stability) | G15: 25회차 (25th month) | J15: 0.71177674 | K15: 0.74013702 | L15: 0.77708952 | M15: 0.77215343 | N15: 0.82394914 | O15: 0.79378328 | S15: =O15-K15 -> 0.053646263 | T15: =O15-N15 -> -0.030165862
C16: 생산성 / 경영효율 (Productivity / Operating Efficiency) | F16: 손해율
G17: 위험보험료 | J17: 155.96826 | K17: 313.99646 | L17: 473.71381 | M17: 634.73319 | N17: 161.28534 | O17: 324.18271 | S17: =IF(O17/K17<0,"n.a.",IF(K17>0,ROUND(O17,4)/ROUND(K17,4)-1,IF(K17<0,"n.a."))) -> 0.032440489 | T17: =IF(O17/N17<0,"n.a.",IF(N17>0,ROUND(O17,4)/ROUND(N17,4)-1,IF(N17<0,"n.a."))) -> 1.0099953
B18: 상품별 수입보험료 (Premium by Product-type) | G18: 사고보험금 | J18: 143.56175 | K18: 282.45168 | L18: 435.23598 | M18: 579.64822 | N18: 161.00965 | O18: 319.70036 | S18: =IF(O18/K18<0,"n.a.",IF(K18>0,ROUND(O18,4)/ROUND(K18,4)-1,IF(K18<0,"n.a."))) -> 0.13187635 | T18: =IF(O18/N18<0,"n.a.",IF(N18>0,ROUND(O18,4)/ROUND(N18,4)-1,IF(N18<0,"n.a."))) -> 0.98559714
C19: 상품별 APE (Annualized Premium Equivalent (APE)) | G19: IBNR비용 | J19: 7.9477561 | K19: 13.770922 | L19: 22.681382 | M19: 28.484494 | N19: 3.9919162 | O19: 11.259486 | S19: =IF(O19/K19<0,"n.a.",IF(K19>0,ROUND(O19,4)/ROUND(K19,4)-1,IF(K19<0,"n.a."))) -> -0.18237007 | T19: =IF(O19/N19<0,"n.a.",IF(N19>0,ROUND(O19,4)/ROUND(N19,4)-1,IF(N19<0,"n.a."))) -> 1.8205867
C20: 상품별 수입보험료 (Premium Income) | G20: 손해율 | J20: 0.97141245 | K20: 0.94339472 | L20: 0.96665402 | M20: 0.95809188 | N20: 1.0230413 | O20: 1.0209053 | S20: =O20-K20 -> 0.077510573 | T20: =O20-N20 -> -0.0021360026
C21: 상품별 초회보험료 (Initial Premium) | G21: IBNR제외시 손해율 | J21: 0.92045492 | K21: 0.89953779 | L21: 0.9187741 | M21: 0.91321556 | N21: 0.99829065 | O21: 0.98617338 | S21: =O21-K21 -> 0.086635592 | T21: =O21-N21 -> -0.012117272
C22: 상품별 초년도보험료 (First Year Premium) | F22: 전속설계사 (# of Tied Agents) | J22: 1558 | K22: 1589 | L22: 1585 | M22: 1644 | N22: 1586 | O22: 1782 | S22: =IF(O22/K22<0,"n.a.",IF(K22>0,ROUND(O22,4)/ROUND(K22,4)-1,IF(K22<0,"n.a."))) -> 0.12146004 | T22: =IF(O22/N22<0,"n.a.",IF(N22>0,ROUND(O22,4)/ROUND(N22,4)-1,IF(N22<0,"n.a."))) -> 0.12358134
B24: 채널별 수입보험료 (Premium by Distribution Channel)
C25: 채널별 APE (Annualized Premium Equivalent (APE))
C26: 채널별 수입보험료 (Premium Income)
C27: 채널별 초년도보험료 (First Year Premium)
B30: 투자영업 현황 (Investment)
C31: 대출 (Loan)/ 자산건전성 (Asset Quality of Loan)
C32: 채권 (Bond)
B34: 재무제표 (Full Financial Statements)
C35: 재무상태표 (Balance Sheet - KIFRS)
C36: 손익계산서 (Income Statement - KIFRS)

Sheet APE by P.T
F1: APE by Product-type (1/2) | G1: 상품별 APE (APE by Product-type)
F2: Total (General acc. + Separate acc.) | G2: 합계 (일반계정 + 특별계정) (Total (General acc. + Separate acc.))
A3: Disclaimer & Contact Information | J3: Accumulated Data | L3: Quarterly Data
F4: (KRW mn) | G4: 단위 십억원 (KRW bn) | J4: Jun '26 | K4: Jun '25 | L4: Jun '26 | M4: Jun '25 | N4: 46112 | O4: YoY | P4: QoQ
B5: 재무현황 (Financial Highlights) | F5: Individual | G5: 개인보험 (Individual) | J5: =SUM(J6,J10,J14) -> 345.65795 | K5: =SUM(K6,K10,K14) -> 340.12234 | L5: =SUM(L6,L10,L14) -> 206.50365 | M5: =SUM(M6,M10,M14) -> 155.76114 | N5: =SUM(N6,N10,N14) -> 139.1543 | O5: =IF(J5/K5<0,"n.a.",IF(K5>0,ROUND(J5,4)/ROUND(K5,4)-1,IF(K5<0,"n.a."))) -> 0.016275616 | P5: =IF(L5/N5<0,"n.a.",IF(N5>0,ROUND(L5,4)/ROUND(N5,4)-1,IF(N5<0,"n.a."))) -> 0.48399079
G6: 보장성보험 (Protection-type) | J6: =SUM(J7:J9) -> 286.76641 | K6: =SUM(K7:K9) -> 335.44118 | L6: =SUM(L7:L9) -> 168.44184 | M6: =SUM(M7:M9) -> 152.49215 | N6: =SUM(N7:N9) -> 118.32458 | O6: =IF(J6/K6<0,"n.a.",IF(K6>0,ROUND(J6,4)/ROUND(K6,4)-1,IF(K6<0,"n.a."))) -> -0.1451068 | P6: =IF(L6/N6<0,"n.a.",IF(N6>0,ROUND(L6,4)/ROUND(N6,4)-1,IF(N6<0,"n.a."))) -> 0.42355689
B7: 요약재무상태표 (Selected Balance sheet) | H7: 종신/CI/정기 (Whole life/CI/Term life) | J7: 158.27297 | K7: 115.30587 | L7: 107.07872 | M7: 48.886779 | N7: 51.194249 | O7: =IF(J7/K7<0,"n.a.",IF(K7>0,ROUND(J7,4)/ROUND(K7,4)-1,IF(K7<0,"n.a."))) -> 0.37263575 | P7: =IF(L7/N7<0,"n.a.",IF(N7>0,ROUND(L7,4)/ROUND(N7,4)-1,IF(N7<0,"n.a."))) -> 1.0916178
B8: 요약손익계산서 (Selected Income Statement) | H8: 변액종신/CI (Variable whole life/CI) | J8: -0.000613284 | K8: -0.011003604 | L8: -0.000613284 | M8: -0.003173796 | N8: 0
H9: 기타보장 (Other protection-type) | J9: 128.49406 | K9: 220.14631 | L9: 61.363734 | M9: 103.60854 | N9: 67.130327 | O9: =IF(J9/K9<0,"n.a.",IF(K9>0,ROUND(J9,4)/ROUND(K9,4)-1,IF(K9<0,"n.a."))) -> -0.41632405 | P9: =IF(L9/N9<0,"n.a.",IF(N9>0,ROUND(L9,4)/ROUND(N9,4)-1,IF(N9<0,"n.a."))) -> -0.085901597
B10: RA, CSM, BEL Movement | G10: 연금보험 (Annuities) | J10: =SUM(J11:J13) -> 58.686549 | K10: =SUM(K11:K13) -> 4.365706 | L10: =SUM(L11:L13) -> 37.982231 | M10: =SUM(M11:M13) -> 3.1650245 | N10: =SUM(N11:N13) -> 20.704319 | O10: =IF(J10/K10<0,"n.a.",IF(K10>0,ROUND(J10,4)/ROUND(K10,4)-1,IF(K10<0,"n.a."))) -> 12.442632 | P10: =IF(L10/N10<0,"n.a.",IF(N10>0,ROUND(L10,4)/ROUND(N10,4)-1,IF(N10<0,"n.a."))) -> 0.83450781
B11: 신계약 CSM (New Business CSM) | H11: 금리확정형 (Fixed-rate) | J11: 0.047386415 | K11: 0.045906351 | L11: 0.020211099 | M11: 0.027818386 | N11: 0.027175316 | O11: =IF(J11/K11<0,"n.a.",IF(K11>0,ROUND(J11,4)/ROUND(K11,4)-1,IF(K11<0,"n.a."))) -> 0.032679739 | P11: =IF(L11/N11<0,"n.a.",IF(N11>0,ROUND(L11,4)/ROUND(N11,4)-1,IF(N11<0,"n.a."))) -> -0.25735294
B12: 신계약 CSM 배수 (New Business CSM Margin) | H12: 금리연동형 (Floating-rate) | J12: 58.639163 | K12: 4.3197997 | L12: 37.96202 | M12: 3.1372061 | N12: 20.677143 | O12: =IF(J12/K12<0,"n.a.",IF(K12>0,ROUND(J12,4)/ROUND(K12,4)-1,IF(K12<0,"n.a."))) -> 12.574517 | P12: =IF(L12/N12<0,"n.a.",IF(N12>0,ROUND(L12,4)/ROUND(N12,4)-1,IF(N12<0,"n.a."))) -> 0.83594411
H13: 변액연금 (Variable) | J13: 0 | K13: 0 | L13: 0 | M13: 0 | N13: 0
B14: 주요지표 (Key Index) | G14: 저축보험 (Savings) | J14: =SUM(J15:J17) -> 0.20498741 | K14: =SUM(K15:K17) -> 0.31544573 | L14: =SUM(L15:L17) -> 0.079585444 | M14: =SUM(M15:M17) -> 0.10397389 | N14: =SUM(N15:N17) -> 0.12540197 | O14: =IF(J14/K14<0,"n.a.",IF(K14>0,ROUND(J14,4)/ROUND(K14,4)-1,IF(K14<0,"n.a."))) -> -0.35003171 | P14: =IF(L14/N14<0,"n.a.",IF(N14>0,ROUND(L14,4)/ROUND(N14,4)-1,IF(N14<0,"n.a."))) -> -0.36523126
C15: 재무 안정성 (Financial Stability) | H15: 금리확정형 (Fixed-rate) | J15: 0 | K15: 0 | L15: 0 | M15: 0 | N15: 0
C16: 생산성 / 경영효율 (Productivity / Operating Efficiency) | H16: 금리연동형 (Floating-rate) | J16: 0.20498741 | K16: 0.31544573 | L16: 0.079585444 | M16: 0.10397389 | N16: 0.12540197 | O16: =IF(J16/K16<0,"n.a.",IF(K16>0,ROUND(J16,4)/ROUND(K16,4)-1,IF(K16<0,"n.a."))) -> -0.35003171 | P16: =IF(L16/N16<0,"n.a.",IF(N16>0,ROUND(L16,4)/ROUND(N16,4)-1,IF(N16<0,"n.a."))) -> -0.36523126
H17: 변액저축 (Variable) | J17: 0 | K17: 0 | L17: 0 | M17: 0 | N17: 0
B18: 상품별 수입보험료 (Premium by Product-type) | F18: Group | G18: 단체보험 (Group) | J18: =SUM(J19:J20) -> 0 | K18: =SUM(K19:K20) -> 0 | L18: =SUM(L19:L20) -> 0 | M18: =SUM(M19:M20) -> 0 | N18: =SUM(N19:N20) -> 0
C19: 상품별 APE (Annualized Premium Equivalent (APE)) | G19: 단체보장 (Protection-type) | J19: 0 | K19: 0 | L19: 0 | M19: 0 | N19: 0
C20: 상품별 수입보험료 (Premium Income) | G20: 단체저축 (Savings) | J20: 0 | K20: 0 | L20: 0 | M20: 0 | N20: 0
C21: 상품별 초회보험료 (Initial Premium) | G21: 개인보험 + 단체보험 (Individual+Group) | J21: =SUM(J22:J24) -> 345.65795 | K21: =SUM(K22:K24) -> 340.12234 | L21: =SUM(L22:L24) -> 206.50365 | M21: =SUM(M22:M24) -> 155.76114 | N21: =SUM(N22:N24) -> 139.1543 | O21: =IF(J21/K21<0,"n.a.",IF(K21>0,ROUND(J21,4)/ROUND(K21,4)-1,IF(K21<0,"n.a."))) -> 0.016275616 | P21: =IF(L21/N21<0,"n.a.",IF(N21>0,ROUND(L21,4)/ROUND(N21,4)-1,IF(N21<0,"n.a."))) -> 0.48399079
C22: 상품별 초년도보험료 (First Year Premium) | F22: Individual+Group | G22: 보장성보험 (Protection-type) | J22: =SUM(J6,J19) -> 286.76641 | K22: =SUM(K6,K19) -> 335.44118 | L22: =SUM(L6,L19) -> 168.44184 | M22: =SUM(M6,M19) -> 152.49215 | N22: =SUM(N6,N19) -> 118.32458 | O22: =IF(J22/K22<0,"n.a.",IF(K22>0,ROUND(J22,4)/ROUND(K22,4)-1,IF(K22<0,"n.a."))) -> -0.1451068 | P22: =IF(L22/N22<0,"n.a.",IF(N22>0,ROUND(L22,4)/ROUND(N22,4)-1,IF(N22<0,"n.a."))) -> 0.42355689
G23: 연금보험 (Annuities) | J23: =J10 -> 58.686549 | K23: =K10 -> 4.365706 | L23: =L10 -> 37.982231 | M23: =M10 -> 3.1650245 | N23: =N10 -> 20.704319 | O23: =IF(J23/K23<0,"n.a.",IF(K23>0,ROUND(J23,4)/ROUND(K23,4)-1,IF(K23<0,"n.a."))) -> 12.442632 | P23: =IF(L23/N23<0,"n.a.",IF(N23>0,ROUND(L23,4)/ROUND(N23,4)-1,IF(N23<0,"n.a."))) -> 0.83450781
B24: 채널별 수입보험료 (Premium by Distribution Channel) | G24: 저축보험 (Savings) | J24: =SUM(J14,J20) -> 0.20498741 | K24: =SUM(K14,K20) -> 0.31544573 | L24: =SUM(L14,L20) -> 0.079585444 | M24: =SUM(M14,M20) -> 0.10397389 | N24: =SUM(N14,N20) -> 0.12540197 | O24: =IF(J24/K24<0,"n.a.",IF(K24>0,ROUND(J24,4)/ROUND(K24,4)-1,IF(K24<0,"n.a."))) -> -0.35003171 | P24: =IF(L24/N24<0,"n.a.",IF(N24>0,ROUND(L24,4)/ROUND(N24,4)-1,IF(N24<0,"n.a."))) -> -0.36523126
C25: 채널별 APE (Annualized Premium Equivalent (APE)) | G25: 퇴직관련 보험 (Retirement-related) | J25: =SUM(J26:J27) -> 13.746759 | K25: =SUM(K26:K27) -> 0.15814577 | L25: =SUM(L26:L27) -> 11.805564 | M25: =SUM(M26:M27) -> 0.030803075 | N25: =SUM(N26:N27) -> 1.9411947 | O25: =IF(J25/K25<0,"n.a.",IF(K25>0,ROUND(J25,4)/ROUND(K25,4)-1,IF(K25<0,"n.a."))) -> 85.950032 | P25: =IF(L25/N25<0,"n.a.",IF(N25>0,ROUND(L25,4)/ROUND(N25,4)-1,IF(N25<0,"n.a."))) -> 5.081599
C26: 채널별 수입보험료 (Premium Income) | F26: Retirement-related | G26: 퇴직보험 (Retirement insurance) | J26: 0 | K26: 0 | L26: 0 | M26: 0 | N26: 0
C27: 채널별 초년도보험료 (First Year Premium) | G27: 퇴직연금 (Corporate pension) | J27: 13.746759 | K27: 0.15814577 | L27: 11.805564 | M27: 0.030803075 | N27: 1.9411947 | O27: =IF(J27/K27<0,"n.a.",IF(K27>0,ROUND(J27,4)/ROUND(K27,4)-1,IF(K27<0,"n.a."))) -> 85.950032 | P27: =IF(L27/N27<0,"n.a.",IF(N27>0,ROUND(L27,4)/ROUND(N27,4)-1,IF(N27<0,"n.a."))) -> 5.081599
B30: 투자영업 현황 (Investment)
C31: 대출 (Loan)/ 자산건전성 (Asset Quality of Loan) | F31: Premium Income by Product-type (2/2)
C32: 채권 (Bond) | F32: General Account
B34: 재무제표 (Full Financial Statements) | F34: (KRW mn)
C35: 재무상태표 (Balance Sheet - KIFRS) | F35: Individual
C36: 손익계산서 (Income Statement - KIFRS)
F48: Group
F52: Individual+Group
F56: Retirement-related
F60: Separate Account
F62: (KRW mn)
F63: Individual
F76: Group
F80: Individual+Group
F84: Retirement-related
F88: 월초 대신 월납환산? --> 어차피 APE 쓰는 마당에 월초보다 월납환산이 더 적절한 지표일 수도

Sheet Premium Income by P.T.(GA+SA)
F1: APE by Product-type (1/2) | G1: 상품별 수입보험료 (Premium Income by Product-type(GA+SA)
F2: Total (General acc. + Separate acc.) | G2: 합계 (일반계정 + 특별계정) (Total (General acc. + Separate acc.))
A3: Disclaimer & Contact Information | J3: Accumulated Data | L3: Quarterly Data
F4: (KRW mn) | G4: 단위 십억원 (KRW bn) | J4: Jun '26 | K4: Jun '25 | L4: Jun '26 | M4: Jun '25 | N4: 46112 | O4: YoY | P4: QoQ
B5: 재무현황 (Financial Highlights) | F5: Individual | G5: 개인보험 (Individual) | J5: =SUM(J6,J10,J14) -> 2422.9979 | K5: =SUM(K6,K10,K14) -> 1852.7689 | L5: =SUM(L6,L10,L14) -> 1303.2229 | M5: =SUM(M6,M10,M14) -> 940.3237 | N5: =SUM(N6,N10,N14) -> 1119.775 | O5: =IF(J5/K5<0,"n.a.",IF(K5>0,ROUND(J5,4)/ROUND(K5,4)-1,IF(K5<0,"n.a."))) -> 0.30777125 | P5: =IF(L5/N5<0,"n.a.",IF(N5>0,ROUND(L5,4)/ROUND(N5,4)-1,IF(N5<0,"n.a."))) -> 0.16382568
G6: 보장성보험 (Protection-type) | J6: =SUM(J7:J9) -> 1672.4269 | K6: =SUM(K7:K9) -> 1601.7945 | L6: =SUM(L7:L9) -> 840.00158 | M6: =SUM(M7:M9) -> 809.86168 | N6: =SUM(N7:N9) -> 832.42531 | O6: =IF(J6/K6<0,"n.a.",IF(K6>0,ROUND(J6,4)/ROUND(K6,4)-1,IF(K6<0,"n.a."))) -> 0.044095794 | P6: =IF(L6/N6<0,"n.a.",IF(N6>0,ROUND(L6,4)/ROUND(N6,4)-1,IF(N6<0,"n.a."))) -> 0.0091014773
B7: 요약재무상태표 (Selected Balance sheet) | H7: 종신/CI/정기 (Whole life/CI/Term life) | J7: 767.80564 | K7: 755.72088 | L7: 385.43555 | M7: 378.76417 | N7: 382.37009 | O7: =IF(J7/K7<0,"n.a.",IF(K7>0,ROUND(J7,4)/ROUND(K7,4)-1,IF(K7<0,"n.a."))) -> 0.015990956 | P7: =IF(L7/N7<0,"n.a.",IF(N7>0,ROUND(L7,4)/ROUND(N7,4)-1,IF(N7<0,"n.a."))) -> 0.0080171018
B8: 요약손익계산서 (Selected Income Statement) | H8: 변액종신/CI (Variable whole life/CI) | J8: 37.977042 | K8: 41.70247 | L8: 18.766878 | M8: 20.660828 | N8: 19.210164 | O8: =IF(J8/K8<0,"n.a.",IF(K8>0,ROUND(J8,4)/ROUND(K8,4)-1,IF(K8<0,"n.a."))) -> -0.089335172 | P8: =IF(L8/N8<0,"n.a.",IF(N8>0,ROUND(L8,4)/ROUND(N8,4)-1,IF(N8<0,"n.a."))) -> -0.023076282
H9: 기타보장 (Other protection-type) | J9: 866.64421 | K9: 804.37115 | L9: 435.79916 | M9: 410.43669 | N9: 430.84506 | O9: =IF(J9/K9<0,"n.a.",IF(K9>0,ROUND(J9,4)/ROUND(K9,4)-1,IF(K9<0,"n.a."))) -> 0.077418237 | P9: =IF(L9/N9<0,"n.a.",IF(N9>0,ROUND(L9,4)/ROUND(N9,4)-1,IF(N9<0,"n.a."))) -> 0.011498564
B10: RA, CSM, BEL Movement | G10: 연금보험 (Annuities) | J10: =SUM(J11:J13) -> 635.93934 | K10: =SUM(K11:K13) -> 114.33653 | L10: =SUM(L11:L13) -> 404.9494 | M10: =SUM(M11:M13) -> 65.420963 | N10: =SUM(N11:N13) -> 230.98994 | O10: =IF(J10/K10<0,"n.a.",IF(K10>0,ROUND(J10,4)/ROUND(K10,4)-1,IF(K10<0,"n.a."))) -> 4.5619973 | P10: =IF(L10/N10<0,"n.a.",IF(N10>0,ROUND(L10,4)/ROUND(N10,4)-1,IF(N10<0,"n.a."))) -> 0.75310436
B11: 신계약 CSM (New Business CSM) | H11: 금리확정형 (Fixed-rate) | J11: 0.64890327 | K11: 0.69800452 | L11: 0.31240078 | M11: 0.39482719 | N11: 0.33650249 | O11: =IF(J11/K11<0,"n.a.",IF(K11>0,ROUND(J11,4)/ROUND(K11,4)-1,IF(K11<0,"n.a."))) -> -0.07034384 | P11: =IF(L11/N11<0,"n.a.",IF(N11>0,ROUND(L11,4)/ROUND(N11,4)-1,IF(N11<0,"n.a."))) -> -0.071619614
B12: 신계약 CSM 배수 (New Business CSM Margin) | H12: 금리연동형 (Floating-rate) | J12: 630.61834 | K12: 107.43377 | L12: 402.3862 | M12: 62.039884 | N12: 228.23214 | O12: =IF(J12/K12<0,"n.a.",IF(K12>0,ROUND(J12,4)/ROUND(K12,4)-1,IF(K12<0,"n.a."))) -> 4.8698315 | P12: =IF(L12/N12<0,"n.a.",IF(N12>0,ROUND(L12,4)/ROUND(N12,4)-1,IF(N12<0,"n.a."))) -> 0.76305699
H13: 변액연금 (Variable) | J13: 4.6720909 | K13: 6.2047563 | L13: 2.2508019 | M13: 2.9862513 | N13: 2.4212889 | O13: =IF(J13/K13<0,"n.a.",IF(K13>0,ROUND(J13,4)/ROUND(K13,4)-1,IF(K13<0,"n.a."))) -> -0.24701844 | P13: =IF(L13/N13<0,"n.a.",IF(N13>0,ROUND(L13,4)/ROUND(N13,4)-1,IF(N13<0,"n.a."))) -> -0.070416718
B14: 주요지표 (Key Index) | G14: 저축보험 (Savings) | J14: =SUM(J15:J17) -> 114.63165 | K14: =SUM(K15:K17) -> 136.63787 | L14: =SUM(L15:L17) -> 58.271889 | M14: =SUM(M15:M17) -> 65.04106 | N14: =SUM(N15:N17) -> 56.359766 | O14: =IF(J14/K14<0,"n.a.",IF(K14>0,ROUND(J14,4)/ROUND(K14,4)-1,IF(K14<0,"n.a."))) -> -0.16105488 | P14: =IF(L14/N14<0,"n.a.",IF(N14>0,ROUND(L14,4)/ROUND(N14,4)-1,IF(N14<0,"n.a."))) -> 0.033926664
C15: 재무 안정성 (Financial Stability) | H15: 금리확정형 (Fixed-rate) | J15: 5.877932 | K15: 6.7415457 | L15: 2.889184 | M15: 3.3210674 | N15: 2.9887479 | O15: =IF(J15/K15<0,"n.a.",IF(K15>0,ROUND(J15,4)/ROUND(K15,4)-1,IF(K15<0,"n.a."))) -> -0.12810205 | P15: =IF(L15/N15<0,"n.a.",IF(N15>0,ROUND(L15,4)/ROUND(N15,4)-1,IF(N15<0,"n.a."))) -> -0.033292067
C16: 생산성 / 경영효율 (Productivity / Operating Efficiency) | H16: 금리연동형 (Floating-rate) | J16: 95.064418 | K16: 124.62336 | L16: 45.375018 | M16: 59.374272 | N16: 49.6894 | O16: =IF(J16/K16<0,"n.a.",IF(K16>0,ROUND(J16,4)/ROUND(K16,4)-1,IF(K16<0,"n.a."))) -> -0.2371866 | P16: =IF(L16/N16<0,"n.a.",IF(N16>0,ROUND(L16,4)/ROUND(N16,4)-1,IF(N16<0,"n.a."))) -> -0.086827372
H17: 변액저축 (Variable) | J17: 13.689305 | K17: 5.2729595 | L17: 10.007687 | M17: 2.3457205 | N17: 3.6816176 | O17: =IF(J17/K17<0,"n.a.",IF(K17>0,ROUND(J17,4)/ROUND(K17,4)-1,IF(K17<0,"n.a."))) -> 1.5961123 | P17: =IF(L17/N17<0,"n.a.",IF(N17>0,ROUND(L17,4)/ROUND(N17,4)-1,IF(N17<0,"n.a."))) -> 1.7183018
B18: 상품별 수입보험료 (Premium by Product-type) | F18: Group | G18: 단체보험 (Group) | J18: =SUM(J19:J20) -> 0.12118571 | K18: =SUM(K19:K20) -> 0.17078142 | L18: =SUM(L19:L20) -> 0.059519668 | M18: =SUM(M19:M20) -> 0.081796296 | N18: =SUM(N19:N20) -> 0.061666038 | O18: =IF(J18/K18<0,"n.a.",IF(K18>0,ROUND(J18,4)/ROUND(K18,4)-1,IF(K18<0,"n.a."))) -> -0.29039813 | P18: =IF(L18/N18<0,"n.a.",IF(N18>0,ROUND(L18,4)/ROUND(N18,4)-1,IF(N18<0,"n.a."))) -> -0.035656402
C19: 상품별 APE (Annualized Premium Equivalent (APE)) | G19: 단체보장 (Protection-type) | J19: 0.1120359 | K19: 0.16056863 | L19: 0.054980407 | M19: 0.076853593 | N19: 0.057055497 | O19: =IF(J19/K19<0,"n.a.",IF(K19>0,ROUND(J19,4)/ROUND(K19,4)-1,IF(K19<0,"n.a."))) -> -0.30261519 | P19: =IF(L19/N19<0,"n.a.",IF(N19>0,ROUND(L19,4)/ROUND(N19,4)-1,IF(N19<0,"n.a."))) -> -0.036777583
C20: 상품별 수입보험료 (Premium Income) | G20: 단체저축 (Savings) | J20: 0.009149802 | K20: 0.010212798 | L20: 0.004539261 | M20: 0.004942703 | N20: 0.004610541 | O20: =IF(J20/K20<0,"n.a.",IF(K20>0,ROUND(J20,4)/ROUND(K20,4)-1,IF(K20<0,"n.a."))) -> -0.10784314 | P20: =IF(L20/N20<0,"n.a.",IF(N20>0,ROUND(L20,4)/ROUND(N20,4)-1,IF(N20<0,"n.a."))) -> -0.02173913
C21: 상품별 초회보험료 (Initial Premium) | G21: 개인보험 + 단체보험 (Individual+Group) | J21: =SUM(J22:J24) -> 2423.1191 | K21: =SUM(K22:K24) -> 1852.9397 | L21: =SUM(L22:L24) -> 1303.2824 | M21: =SUM(M22:M24) -> 940.4055 | N21: =SUM(N22:N24) -> 1119.8367 | O21: =IF(J21/K21<0,"n.a.",IF(K21>0,ROUND(J21,4)/ROUND(K21,4)-1,IF(K21<0,"n.a."))) -> 0.30771611 | P21: =IF(L21/N21<0,"n.a.",IF(N21>0,ROUND(L21,4)/ROUND(N21,4)-1,IF(N21<0,"n.a."))) -> 0.16381469
C22: 상품별 초년도보험료 (First Year Premium) | F22: Individual+Group | G22: 보장성보험 (Protection-type) | J22: =SUM(J6,J19) -> 1672.5389 | K22: =SUM(K6,K19) -> 1601.9551 | L22: =SUM(L6,L19) -> 840.05656 | M22: =SUM(M6,M19) -> 809.93854 | N22: =SUM(N6,N19) -> 832.48237 | O22: =IF(J22/K22<0,"n.a.",IF(K22>0,ROUND(J22,4)/ROUND(K22,4)-1,IF(K22<0,"n.a."))) -> 0.044061035 | P22: =IF(L22/N22<0,"n.a.",IF(N22>0,ROUND(L22,4)/ROUND(N22,4)-1,IF(N22<0,"n.a."))) -> 0.0090983305
G23: 연금보험 (Annuities) | J23: =J10 -> 635.93934 | K23: =K10 -> 114.33653 | L23: =L10 -> 404.9494 | M23: =M10 -> 65.420963 | N23: =N10 -> 230.98994 | O23: =IF(J23/K23<0,"n.a.",IF(K23>0,ROUND(J23,4)/ROUND(K23,4)-1,IF(K23<0,"n.a."))) -> 4.5619973 | P23: =IF(L23/N23<0,"n.a.",IF(N23>0,ROUND(L23,4)/ROUND(N23,4)-1,IF(N23<0,"n.a."))) -> 0.75310436
B24: 채널별 수입보험료 (Premium by Distribution Channel) | G24: 저축보험 (Savings) | J24: =SUM(J14,J20) -> 114.6408 | K24: =SUM(K14,K20) -> 136.64808 | L24: =SUM(L14,L20) -> 58.276428 | M24: =SUM(M14,M20) -> 65.046002 | N24: =SUM(N14,N20) -> 56.364376 | O24: =IF(J24/K24<0,"n.a.",IF(K24>0,ROUND(J24,4)/ROUND(K24,4)-1,IF(K24<0,"n.a."))) -> -0.1610509 | P24: =IF(L24/N24<0,"n.a.",IF(N24>0,ROUND(L24,4)/ROUND(N24,4)-1,IF(N24<0,"n.a."))) -> 0.033922121
C25: 채널별 APE (Annualized Premium Equivalent (APE)) | G25: 퇴직관련 보험 (Retirement-related) | J25: =SUM(J26:J27) -> 1175.1367 | K25: =SUM(K26:K27) -> 207.36649 | L25: =SUM(L26:L27) -> 1057.9308 | M25: =SUM(M26:M27) -> 125.90165 | N25: =SUM(N26:N27) -> 117.20582 | O25: =IF(J25/K25<0,"n.a.",IF(K25>0,ROUND(J25,4)/ROUND(K25,4)-1,IF(K25<0,"n.a."))) -> 4.6669554 | P25: =IF(L25/N25<0,"n.a.",IF(N25>0,ROUND(L25,4)/ROUND(N25,4)-1,IF(N25<0,"n.a."))) -> 8.0262666
C26: 채널별 수입보험료 (Premium Income) | F26: Retirement-related | G26: 퇴직보험 (Retirement insurance) | J26: 0 | K26: 0 | L26: 0 | M26: 0 | N26: 0
C27: 채널별 초년도보험료 (First Year Premium) | G27: 퇴직연금 (Corporate pension) | J27: 1175.1367 | K27: 207.36649 | L27: 1057.9308 | M27: 125.90165 | N27: 117.20582 | O27: =IF(J27/K27<0,"n.a.",IF(K27>0,ROUND(J27,4)/ROUND(K27,4)-1,IF(K27<0,"n.a."))) -> 4.6669554 | P27: =IF(L27/N27<0,"n.a.",IF(N27>0,ROUND(L27,4)/ROUND(N27,4)-1,IF(N27<0,"n.a."))) -> 8.0262666
B30: 투자영업 현황 (Investment)
C31: 대출 (Loan)/ 자산건전성 (Asset Quality of Loan) | F31: Premium Income by Product-type (2/2)
C32: 채권 (Bond) | F32: General Account
B34: 재무제표 (Full Financial Statements) | F34: (KRW mn)
C35: 재무상태표 (Balance Sheet - KIFRS) | F35: Individual
C36: 손익계산서 (Income Statement - KIFRS)
F48: Group
F52: Individual+Group
F56: Retirement-related
F60: Separate Account
F62: (KRW mn)
F63: Individual
F76: Group
F80: Individual+Group
F84: Retirement-related
F88: 월초 대신 월납환산? --> 어차피 APE 쓰는 마당에 월초보다 월납환산이 더 적절한 지표일 수도

Sheet Premium Income by P.T.
F1: APE by Product-type (1/2) | G1: 상품별 수입보험료 (Premium Income by Product type)
F2: Total (General acc. + Separate acc.) | G2: 일반계정 (General Account)
A3: Disclaimer & Contact Information | J3: Accumulated Data | L3: Quarterly Data
F4: (KRW mn) | G4: 단위 십억원 (KRW bn) | J4: Jun '26 | K4: Jun '25 | L4: Jun '26 | M4: Jun '25 | N4: 46112 | O4: YoY | P4: QoQ
B5: 재무현황 (Financial Highlights) | F5: Individual | G5: 개인보험 (Individual) | J5: =SUM(J6,J10,J14) -> 2393.5736 | K5: =SUM(K6,K10,K14) -> 1828.6148 | L5: =SUM(L6,L10,L14) -> 1285.593 | M5: =SUM(M6,M10,M14) -> 928.68874 | N5: =SUM(N6,N10,N14) -> 1107.9806 | O5: =IF(J5/K5<0,"n.a.",IF(K5>0,ROUND(J5,4)/ROUND(K5,4)-1,IF(K5<0,"n.a."))) -> 0.30895452 | P5: =IF(L5/N5<0,"n.a.",IF(N5>0,ROUND(L5,4)/ROUND(N5,4)-1,IF(N5<0,"n.a."))) -> 0.16030281
G6: 보장성보험 (Protection-type) | J6: =SUM(J7:J9) -> 1660.4037 | K6: =SUM(K7:K9) -> 1588.1851 | L6: =SUM(L7:L9) -> 834.08409 | M6: =SUM(M7:M9) -> 803.11801 | N6: =SUM(N7:N9) -> 826.31957 | O6: =IF(J6/K6<0,"n.a.",IF(K6>0,ROUND(J6,4)/ROUND(K6,4)-1,IF(K6<0,"n.a."))) -> 0.045472407 | P6: =IF(L6/N6<0,"n.a.",IF(N6>0,ROUND(L6,4)/ROUND(N6,4)-1,IF(N6<0,"n.a."))) -> 0.0093964853
B7: 요약재무상태표 (Selected Balance sheet) | H7: 종신/CI/정기 (Whole life/CI/Term life) | J7: 767.80564 | K7: 755.72088 | L7: 385.43555 | M7: 378.76417 | N7: 382.37009 | O7: =IF(J7/K7<0,"n.a.",IF(K7>0,ROUND(J7,4)/ROUND(K7,4)-1,IF(K7<0,"n.a."))) -> 0.015990956 | P7: =IF(L7/N7<0,"n.a.",IF(N7>0,ROUND(L7,4)/ROUND(N7,4)-1,IF(N7<0,"n.a."))) -> 0.0080171018
B8: 요약손익계산서 (Selected Income Statement) | H8: 변액종신/CI (Variable whole life/CI) | J8: 25.953808 | K8: 28.093063 | L8: 12.849382 | M8: 13.917158 | N8: 13.104426 | O8: =IF(J8/K8<0,"n.a.",IF(K8>0,ROUND(J8,4)/ROUND(K8,4)-1,IF(K8<0,"n.a."))) -> -0.076150371 | P8: =IF(L8/N8<0,"n.a.",IF(N8>0,ROUND(L8,4)/ROUND(N8,4)-1,IF(N8<0,"n.a."))) -> -0.019459113
H9: 기타보장 (Other protection-type) | J9: 866.64421 | K9: 804.37115 | L9: 435.79916 | M9: 410.43669 | N9: 430.84506 | O9: =IF(J9/K9<0,"n.a.",IF(K9>0,ROUND(J9,4)/ROUND(K9,4)-1,IF(K9<0,"n.a."))) -> 0.077418237 | P9: =IF(L9/N9<0,"n.a.",IF(N9>0,ROUND(L9,4)/ROUND(N9,4)-1,IF(N9<0,"n.a."))) -> 0.011498564
B10: RA, CSM, BEL Movement | G10: 연금보험 (Annuities) | J10: =SUM(J11:J13) -> 631.52309 | K10: =SUM(K11:K13) -> 108.53362 | L10: =SUM(L11:L13) -> 402.81636 | M10: =SUM(M11:M13) -> 62.61971 | N10: =SUM(N11:N13) -> 228.70673 | O10: =IF(J10/K10<0,"n.a.",IF(K10>0,ROUND(J10,4)/ROUND(K10,4)-1,IF(K10<0,"n.a."))) -> 4.8186875 | P10: =IF(L10/N10<0,"n.a.",IF(N10>0,ROUND(L10,4)/ROUND(N10,4)-1,IF(N10<0,"n.a."))) -> 0.7612794
B11: 신계약 CSM (New Business CSM) | H11: 금리확정형 (Fixed-rate) | J11: 0.64890327 | K11: 0.69800452 | L11: 0.31240078 | M11: 0.39482719 | N11: 0.33650249 | O11: =IF(J11/K11<0,"n.a.",IF(K11>0,ROUND(J11,4)/ROUND(K11,4)-1,IF(K11<0,"n.a."))) -> -0.07034384 | P11: =IF(L11/N11<0,"n.a.",IF(N11>0,ROUND(L11,4)/ROUND(N11,4)-1,IF(N11<0,"n.a."))) -> -0.071619614
B12: 신계약 CSM 배수 (New Business CSM Margin) | H12: 금리연동형 (Floating-rate) | J12: 630.61834 | K12: 107.43377 | L12: 402.3862 | M12: 62.039884 | N12: 228.23214 | O12: =IF(J12/K12<0,"n.a.",IF(K12>0,ROUND(J12,4)/ROUND(K12,4)-1,IF(K12<0,"n.a."))) -> 4.8698315 | P12: =IF(L12/N12<0,"n.a.",IF(N12>0,ROUND(L12,4)/ROUND(N12,4)-1,IF(N12<0,"n.a."))) -> 0.76305699
H13: 변액연금 (Variable) | J13: 0.25584358 | K13: 0.40185098 | L13: 0.11776065 | M13: 0.18499896 | N13: 0.13808293 | O13: =IF(J13/K13<0,"n.a.",IF(K13>0,ROUND(J13,4)/ROUND(K13,4)-1,IF(K13<0,"n.a."))) -> -0.36352326 | P13: =IF(L13/N13<0,"n.a.",IF(N13>0,ROUND(L13,4)/ROUND(N13,4)-1,IF(N13<0,"n.a."))) -> -0.14699493
B14: 주요지표 (Key Index) | G14: 저축보험 (Savings) | J14: =SUM(J15:J17) -> 101.64689 | K14: =SUM(K15:K17) -> 131.89608 | L14: =SUM(L15:L17) -> 48.692573 | M14: =SUM(M15:M17) -> 62.951023 | N14: =SUM(N15:N17) -> 52.954313 | O14: =IF(J14/K14<0,"n.a.",IF(K14>0,ROUND(J14,4)/ROUND(K14,4)-1,IF(K14<0,"n.a."))) -> -0.22934113 | P14: =IF(L14/N14<0,"n.a.",IF(N14>0,ROUND(L14,4)/ROUND(N14,4)-1,IF(N14<0,"n.a."))) -> -0.080478828
C15: 재무 안정성 (Financial Stability) | H15: 금리확정형 (Fixed-rate) | J15: 5.877932 | K15: 6.7415457 | L15: 2.889184 | M15: 3.3210674 | N15: 2.9887479 | O15: =IF(J15/K15<0,"n.a.",IF(K15>0,ROUND(J15,4)/ROUND(K15,4)-1,IF(K15<0,"n.a."))) -> -0.12810205 | P15: =IF(L15/N15<0,"n.a.",IF(N15>0,ROUND(L15,4)/ROUND(N15,4)-1,IF(N15<0,"n.a."))) -> -0.033292067
C16: 생산성 / 경영효율 (Productivity / Operating Efficiency) | H16: 금리연동형 (Floating-rate) | J16: 95.064418 | K16: 124.62336 | L16: 45.375018 | M16: 59.374272 | N16: 49.6894 | O16: =IF(J16/K16<0,"n.a.",IF(K16>0,ROUND(J16,4)/ROUND(K16,4)-1,IF(K16<0,"n.a."))) -> -0.2371866 | P16: =IF(L16/N16<0,"n.a.",IF(N16>0,ROUND(L16,4)/ROUND(N16,4)-1,IF(N16<0,"n.a."))) -> -0.086827372
H17: 변액저축 (Variable) | J17: 0.70453578 | K17: 0.53116924 | L17: 0.42837104 | M17: 0.25568392 | N17: 0.27616474 | O17: =IF(J17/K17<0,"n.a.",IF(K17>0,ROUND(J17,4)/ROUND(K17,4)-1,IF(K17<0,"n.a."))) -> 0.32624247 | P17: =IF(L17/N17<0,"n.a.",IF(N17>0,ROUND(L17,4)/ROUND(N17,4)-1,IF(N17<0,"n.a."))) -> 0.55104996
B18: 상품별 수입보험료 (Premium by Product-type) | F18: Group | G18: 단체보험 (Group) | J18: =SUM(J19:J20) -> 0.12118571 | K18: =SUM(K19:K20) -> 0.17078142 | L18: =SUM(L19:L20) -> 0.059519668 | M18: =SUM(M19:M20) -> 0.081796296 | N18: =SUM(N19:N20) -> 0.061666038 | O18: =IF(J18/K18<0,"n.a.",IF(K18>0,ROUND(J18,4)/ROUND(K18,4)-1,IF(K18<0,"n.a."))) -> -0.29039813 | P18: =IF(L18/N18<0,"n.a.",IF(N18>0,ROUND(L18,4)/ROUND(N18,4)-1,IF(N18<0,"n.a."))) -> -0.035656402
C19: 상품별 APE (Annualized Premium Equivalent (APE)) | G19: 단체보장 (Protection-type) | J19: 0.1120359 | K19: 0.16056863 | L19: 0.054980407 | M19: 0.076853593 | N19: 0.057055497 | O19: =IF(J19/K19<0,"n.a.",IF(K19>0,ROUND(J19,4)/ROUND(K19,4)-1,IF(K19<0,"n.a."))) -> -0.30261519 | P19: =IF(L19/N19<0,"n.a.",IF(N19>0,ROUND(L19,4)/ROUND(N19,4)-1,IF(N19<0,"n.a."))) -> -0.036777583
C20: 상품별 수입보험료 (Premium Income) | G20: 단체저축 (Savings) | J20: 0.009149802 | K20: 0.010212798 | L20: 0.004539261 | M20: 0.004942703 | N20: 0.004610541 | O20: =IF(J20/K20<0,"n.a.",IF(K20>0,ROUND(J20,4)/ROUND(K20,4)-1,IF(K20<0,"n.a."))) -> -0.10784314 | P20: =IF(L20/N20<0,"n.a.",IF(N20>0,ROUND(L20,4)/ROUND(N20,4)-1,IF(N20<0,"n.a."))) -> -0.02173913
C21: 상품별 초회보험료 (Initial Premium) | G21: 개인보험 + 단체보험 (Individual+Group) | J21: =SUM(J22:J24) -> 2393.6948 | K21: =SUM(K22:K24) -> 1828.7856 | L21: =SUM(L22:L24) -> 1285.6525 | M21: =SUM(M22:M24) -> 928.77054 | N21: =SUM(N22:N24) -> 1108.0423 | O21: =IF(J21/K21<0,"n.a.",IF(K21>0,ROUND(J21,4)/ROUND(K21,4)-1,IF(K21<0,"n.a."))) -> 0.30889854 | P21: =IF(L21/N21<0,"n.a.",IF(N21>0,ROUND(L21,4)/ROUND(N21,4)-1,IF(N21<0,"n.a."))) -> 0.16029189
C22: 상품별 초년도보험료 (First Year Premium) | F22: Individual+Group | G22: 보장성보험 (Protection-type) | J22: =SUM(J6,J19) -> 1660.5157 | K22: =SUM(K6,K19) -> 1588.3457 | L22: =SUM(L6,L19) -> 834.13907 | M22: =SUM(M6,M19) -> 803.19487 | N22: =SUM(N6,N19) -> 826.37663 | O22: =IF(J22/K22<0,"n.a.",IF(K22>0,ROUND(J22,4)/ROUND(K22,4)-1,IF(K22<0,"n.a."))) -> 0.045437212 | P22: =IF(L22/N22<0,"n.a.",IF(N22>0,ROUND(L22,4)/ROUND(N22,4)-1,IF(N22<0,"n.a."))) -> 0.009393417
G23: 연금보험 (Annuities) | J23: =J10 -> 631.52309 | K23: =K10 -> 108.53362 | L23: =L10 -> 402.81636 | M23: =M10 -> 62.61971 | N23: =N10 -> 228.70673 | O23: =IF(J23/K23<0,"n.a.",IF(K23>0,ROUND(J23,4)/ROUND(K23,4)-1,IF(K23<0,"n.a."))) -> 4.8186875 | P23: =IF(L23/N23<0,"n.a.",IF(N23>0,ROUND(L23,4)/ROUND(N23,4)-1,IF(N23<0,"n.a."))) -> 0.7612794
B24: 채널별 수입보험료 (Premium by Distribution Channel) | G24: 저축보험 (Savings) | J24: =SUM(J14,J20) -> 101.65604 | K24: =SUM(K14,K20) -> 131.90629 | L24: =SUM(L14,L20) -> 48.697112 | M24: =SUM(M14,M20) -> 62.955966 | N24: =SUM(N14,N20) -> 52.958923 | O24: =IF(J24/K24<0,"n.a.",IF(K24>0,ROUND(J24,4)/ROUND(K24,4)-1,IF(K24<0,"n.a."))) -> -0.22933173 | P24: =IF(L24/N24<0,"n.a.",IF(N24>0,ROUND(L24,4)/ROUND(N24,4)-1,IF(N24<0,"n.a."))) -> -0.080473726
C25: 채널별 APE (Annualized Premium Equivalent (APE)) | G25: 퇴직관련 보험 (Retirement-related) | J25: =SUM(J26:J27) -> 0.11291414 | K25: =SUM(K26:K27) -> 0.12519449 | L25: =SUM(L26:L27) -> 0.068637887 | M25: =SUM(M26:M27) -> 0.065380212 | N25: =SUM(N26:N27) -> 0.044276252 | O25: =IF(K25/J25<0,"n.a.",IF(J25>0,ROUND(K25,4)/ROUND(J25,4)-1,IF(J25<0,"n.a."))) -> 0.10894597 | P25: =IF(L25/N25<0,"n.a.",IF(N25>0,ROUND(L25,4)/ROUND(N25,4)-1,IF(N25<0,"n.a."))) -> 0.54853273
C26: 채널별 수입보험료 (Premium Income) | F26: Retirement-related | G26: 퇴직보험 (Retirement insurance) | J26: 0 | K26: 0 | L26: 0 | M26: 0 | N26: 0
C27: 채널별 초년도보험료 (First Year Premium) | G27: 퇴직연금 (Corporate pension) | J27: 0.11291414 | K27: 0.12519449 | L27: 0.068637887 | M27: 0.065380212 | N27: 0.044276252 | O27: =IF(J27/K27<0,"n.a.",IF(K27>0,ROUND(J27,4)/ROUND(K27,4)-1,IF(K27<0,"n.a."))) -> -0.098242812 | P27: =IF(L27/N27<0,"n.a.",IF(N27>0,ROUND(L27,4)/ROUND(N27,4)-1,IF(N27<0,"n.a."))) -> 0.54853273
G29: 특별계정 (Separate Account)
B30: 투자영업 현황 (Investment) | J30: Accumulated Data | L30: Quarterly Data
C31: 대출 (Loan)/ 자산건전성 (Asset Quality of Loan) | F31: Premium Income by Product-type (2/2) | G31: 단위 십억원 (KRW bn) | J31: Jun '26 | K31: Jun '25 | L31: Jun '26 | M31: Jun '25 | N31: 46112 | O31: YoY | P31: QoQ
C32: 채권 (Bond) | F32: General Account | G32: 개인보험 (Individual) | J32: =SUM(J33,J37,J41) -> 29.42425 | K32: =SUM(K33,K37,K41) -> 24.154103 | L32: =SUM(L33,L37,L41) -> 17.629853 | M32: =SUM(M33,M37,M41) -> 11.634959 | N32: =SUM(N33,N37,N41) -> 11.794397 | O32: =IF(J32/K32<0,"n.a.",IF(K32>0,ROUND(J32,4)/ROUND(K32,4)-1,IF(K32<0,"n.a."))) -> 0.2181907 | P32: =IF(L32/N32<0,"n.a.",IF(N32>0,ROUND(L32,4)/ROUND(N32,4)-1,IF(N32<0,"n.a."))) -> 0.4947687
G33: 보장성보험 (Protection-type) | J33: =SUM(J34:J36) -> 12.023234 | K33: =SUM(K34:K36) -> 13.609408 | L33: =SUM(L34:L36) -> 5.917496 | M33: =SUM(M34:M36) -> 6.7436704 | N33: =SUM(N34:N36) -> 6.1057381 | O33: =IF(J33/K33<0,"n.a.",IF(K33>0,ROUND(J33,4)/ROUND(K33,4)-1,IF(K33<0,"n.a."))) -> -0.1165518 | P33: =IF(L33/N33<0,"n.a.",IF(N33>0,ROUND(L33,4)/ROUND(N33,4)-1,IF(N33<0,"n.a."))) -> -0.030823657
B34: 재무제표 (Full Financial Statements) | F34: (KRW mn) | H34: 종신/CI/정기 (Whole life/CI/Term life) | J34: 0 | K34: 0 | L34: 0 | M34: 0 | N34: 0
C35: 재무상태표 (Balance Sheet - KIFRS) | F35: Individual | H35: 변액종신/CI (Variable whole life/CI) | J35: 12.023234 | K35: 13.609408 | L35: 5.917496 | M35: 6.7436704 | N35: 6.1057381 | O35: =IF(J35/K35<0,"n.a.",IF(K35>0,ROUND(J35,4)/ROUND(K35,4)-1,IF(K35<0,"n.a."))) -> -0.1165518 | P35: =IF(L35/N35<0,"n.a.",IF(N35>0,ROUND(L35,4)/ROUND(N35,4)-1,IF(N35<0,"n.a."))) -> -0.030823657
C36: 손익계산서 (Income Statement - KIFRS) | H36: 기타보장 (Other protection-type) | J36: 0 | K36: 0 | L36: 0 | M36: 0 | N36: 0
G37: 연금보험 (Annuities) | J37: =SUM(J38:J40) -> 4.4162473 | K37: =SUM(K38:K40) -> 5.8029053 | L37: =SUM(L38:L40) -> 2.1330413 | M37: =SUM(M38:M40) -> 2.8012523 | N37: =SUM(N38:N40) -> 2.283206 | O37: =IF(J37/K37<0,"n.a.",IF(K37>0,ROUND(J37,4)/ROUND(K37,4)-1,IF(K37<0,"n.a."))) -> -0.23896672 | P37: =IF(L37/N37<0,"n.a.",IF(N37>0,ROUND(L37,4)/ROUND(N37,4)-1,IF(N37<0,"n.a."))) -> -0.065784863
H38: 금리확정형 (Fixed-rate) | J38: 0 | K38: 0 | L38: 0 | M38: 0 | N38: 0
H39: 금리연동형 (Floating-rate) | J39: 0 | K39: 0 | L39: 0 | M39: 0 | N39: 0
H40: 변액연금 (Variable) | J40: 4.4162473 | K40: 5.8029053 | L40: 2.1330413 | M40: 2.8012523 | N40: 2.283206 | O40: =IF(J40/K40<0,"n.a.",IF(K40>0,ROUND(J40,4)/ROUND(K40,4)-1,IF(K40<0,"n.a."))) -> -0.23896672 | P40: =IF(L40/N40<0,"n.a.",IF(N40>0,ROUND(L40,4)/ROUND(N40,4)-1,IF(N40<0,"n.a."))) -> -0.065784863
G41: 저축보험 (Savings) | J41: =SUM(J42:J44) -> 12.984769 | K41: =SUM(K42:K44) -> 4.7417903 | L41: =SUM(L42:L44) -> 9.579316 | M41: =SUM(M42:M44) -> 2.0900365 | N41: =SUM(N42:N44) -> 3.4054529 | O41: =IF(J41/K41<0,"n.a.",IF(K41>0,ROUND(J41,4)/ROUND(K41,4)-1,IF(K41<0,"n.a."))) -> 1.7383694 | P41: =IF(L41/N41<0,"n.a.",IF(N41>0,ROUND(L41,4)/ROUND(N41,4)-1,IF(N41<0,"n.a."))) -> 1.8128909
H42: 금리확정형 (Fixed-rate) | J42: 0 | K42: 0 | L42: 0 | M42: 0 | N42: 0
H43: 금리연동형 (Floating-rate) | J43: 0 | K43: 0 | L43: 0 | M43: 0 | N43: 0
H44: 변액저축 (Variable) | J44: 12.984769 | K44: 4.7417903 | L44: 9.579316 | M44: 2.0900365 | N44: 3.4054529 | O44: =IF(J44/K44<0,"n.a.",IF(K44>0,ROUND(J44,4)/ROUND(K44,4)-1,IF(K44<0,"n.a."))) -> 1.7383694 | P44: =IF(L44/N44<0,"n.a.",IF(N44>0,ROUND(L44,4)/ROUND(N44,4)-1,IF(N44<0,"n.a."))) -> 1.8128909
G45: 단체보험 (Group) | J45: =SUM(J46:J47) -> 0 | K45: =SUM(K46:K47) -> 0 | L45: =SUM(L46:L47) -> 0 | M45: =SUM(M46:M47) -> 0 | N45: =SUM(N46:N47) -> 0
G46: 단체보장 (Protection-type) | J46: 0 | K46: 0 | L46: 0 | M46: 0 | N46: 0
G47: 단체저축 (Savings) | J47: 0 | K47: 0 | L47: 0 | M47: 0 | N47: 0
F48: Group | G48: 개인보험 + 단체보험 (Individual+Group) | J48: =SUM(J49:J51) -> 29.42425 | K48: =SUM(K49:K51) -> 24.154103 | L48: =SUM(L49:L51) -> 17.629853 | M48: =SUM(M49:M51) -> 11.634959 | N48: =SUM(N49:N51) -> 11.794397 | O48: =IF(J48/K48<0,"n.a.",IF(K48>0,ROUND(J48,4)/ROUND(K48,4)-1,IF(K48<0,"n.a."))) -> 0.2181907 | P48: =IF(L48/N48<0,"n.a.",IF(N48>0,ROUND(L48,4)/ROUND(N48,4)-1,IF(N48<0,"n.a."))) -> 0.4947687
G49: 보장성보험 (Protection-type) | J49: =SUM(J33,J46) -> 12.023234 | K49: =SUM(K33,K46) -> 13.609408 | L49: =SUM(L33,L46) -> 5.917496 | M49: =SUM(M33,M46) -> 6.7436704 | N49: =SUM(N33,N46) -> 6.1057381 | O49: =IF(J49/K49<0,"n.a.",IF(K49>0,ROUND(J49,4)/ROUND(K49,4)-1,IF(K49<0,"n.a."))) -> -0.1165518 | P49: =IF(L49/N49<0,"n.a.",IF(N49>0,ROUND(L49,4)/ROUND(N49,4)-1,IF(N49<0,"n.a."))) -> -0.030823657
G50: 연금보험 (Annuities) | J50: =J37 -> 4.4162473 | K50: =K37 -> 5.8029053 | L50: =L37 -> 2.1330413 | M50: =M37 -> 2.8012523 | N50: =N37 -> 2.283206 | O50: =IF(J50/K50<0,"n.a.",IF(K50>0,ROUND(J50,4)/ROUND(K50,4)-1,IF(K50<0,"n.a."))) -> -0.23896672 | P50: =IF(L50/N50<0,"n.a.",IF(N50>0,ROUND(L50,4)/ROUND(N50,4)-1,IF(N50<0,"n.a."))) -> -0.065784863
G51: 저축보험 (Savings) | J51: =SUM(J41,J47) -> 12.984769 | K51: =SUM(K41,K47) -> 4.7417903 | L51: =SUM(L41,L47) -> 9.579316 | M51: =SUM(M41,M47) -> 2.0900365 | N51: =SUM(N41,N47) -> 3.4054529 | O51: =IF(J51/K51<0,"n.a.",IF(K51>0,ROUND(J51,4)/ROUND(K51,4)-1,IF(K51<0,"n.a."))) -> 1.7383694 | P51: =IF(L51/N51<0,"n.a.",IF(N51>0,ROUND(L51,4)/ROUND(N51,4)-1,IF(N51<0,"n.a."))) -> 1.8128909
F52: Individual+Group | G52: 퇴직관련 보험 (Retirement-related) | J52: =SUM(J53:J54) -> 1175.0237 | K52: =SUM(K53:K54) -> 207.2413 | L52: =SUM(L53:L54) -> 1057.8622 | M52: =SUM(M53:M54) -> 125.83627 | N52: =SUM(N53:N54) -> 117.16154 | O52: =IF(K52/J52<0,"n.a.",IF(J52>0,ROUND(K52,4)/ROUND(J52,4)-1,IF(J52<0,"n.a."))) -> -0.82362798 | P52: =IF(L52/N52<0,"n.a.",IF(N52>0,ROUND(L52,4)/ROUND(N52,4)-1,IF(N52<0,"n.a."))) -> 8.029094
G53: 퇴직보험 (Retirement insurance) | J53: 0 | K53: 0 | L53: 0 | M53: 0 | N53: 0
G54: 퇴직연금 (Corporate pension) | J54: 1175.0237 | K54: 207.2413 | L54: 1057.8622 | M54: 125.83627 | N54: 117.16154 | O54: =IF(J54/K54<0,"n.a.",IF(K54>0,ROUND(J54,4)/ROUND(K54,4)-1,IF(K54<0,"n.a."))) -> 4.6698337 | P54: =IF(L54/N54<0,"n.a.",IF(N54>0,ROUND(L54,4)/ROUND(N54,4)-1,IF(N54<0,"n.a."))) -> 8.029094
F56: Retirement-related

Sheet Initial P. by P.T.
F1: APE by Product-type (1/2) | G1: 상품별 초회보험료 (Initial Premium by Product-type)
F2: Total (General acc. + Separate acc.) | G2: 합계 (일반계정 + 특별계정) (Total (General acc. + Separate acc.)
A3: Disclaimer & Contact Information | J3: Accumulated Data | L3: Quarterly Data
F4: (KRW mn) | G4: 단위 십억원 (KRW bn) | J4: Jun '26 | K4: Jun '25 | L4: Jun '26 | M4: Jun '25 | N4: 46112 | O4: YoY | P4: QoQ
B5: 재무현황 (Financial Highlights) | F5: Individual | G5: 개인보험 (Individual) | J5: =SUM(J6,J10,J14) -> 598.01973 | K5: =SUM(K6,K10,K14) -> 68.842925 | L5: =SUM(L6,L10,L14) -> 389.70304 | M5: =SUM(M6,M10,M14) -> 46.213885 | N5: =SUM(N6,N10,N14) -> 208.31669 | O5: =IF(J5/K5<0,"n.a.",IF(K5>0,ROUND(J5,4)/ROUND(K5,4)-1,IF(K5<0,"n.a."))) -> 7.6867302 | P5: =IF(L5/N5<0,"n.a.",IF(N5>0,ROUND(L5,4)/ROUND(N5,4)-1,IF(N5<0,"n.a."))) -> 0.87072376
G6: 보장성보험 (Protection-type) | J6: =SUM(J7:J9) -> 25.061861 | K6: =SUM(K7:K9) -> 39.079858 | L6: =SUM(L7:L9) -> 15.140791 | M6: =SUM(M7:M9) -> 20.080886 | N6: =SUM(N7:N9) -> 9.9210703 | O6: =IF(J6/K6<0,"n.a.",IF(K6>0,ROUND(J6,4)/ROUND(K6,4)-1,IF(K6<0,"n.a."))) -> -0.35870102 | P6: =IF(L6/N6<0,"n.a.",IF(N6>0,ROUND(L6,4)/ROUND(N6,4)-1,IF(N6<0,"n.a."))) -> 0.5261211
B7: 요약재무상태표 (Selected Balance sheet) | H7: 종신/CI/정기 (Whole life/CI/Term life) | J7: 13.189414 | K7: 9.3183568 | L7: 8.9232264 | M7: 4.0229115 | N7: 4.2661874 | O7: =IF(J7/K7<0,"n.a.",IF(K7>0,ROUND(J7,4)/ROUND(K7,4)-1,IF(K7<0,"n.a."))) -> 0.41541466 | P7: =IF(L7/N7<0,"n.a.",IF(N7>0,ROUND(L7,4)/ROUND(N7,4)-1,IF(N7<0,"n.a."))) -> 1.0916038
B8: 요약손익계산서 (Selected Income Statement) | H8: 변액종신/CI (Variable whole life/CI) | J8: -5.1107e-05 | K8: -0.000916967 | L8: -5.1107e-05 | M8: -0.000264483 | N8: 0
H9: 기타보장 (Other protection-type) | J9: 11.872499 | K9: 29.762418 | L9: 6.2176157 | M9: 16.058239 | N9: 5.6548828 | O9: =IF(J9/K9<0,"n.a.",IF(K9>0,ROUND(J9,4)/ROUND(K9,4)-1,IF(K9<0,"n.a."))) -> -0.60109064 | P9: =IF(L9/N9<0,"n.a.",IF(N9>0,ROUND(L9,4)/ROUND(N9,4)-1,IF(N9<0,"n.a."))) -> 0.099506623
B10: RA, CSM, BEL Movement | G10: 연금보험 (Annuities) | J10: =SUM(J11:J13) -> 572.72155 | K10: =SUM(K11:K13) -> 29.532071 | L10: =SUM(L11:L13) -> 374.51015 | M10: =SUM(M11:M13) -> 26.00361 | N10: =SUM(N11:N13) -> 198.21141 | O10: =IF(J10/K10<0,"n.a.",IF(K10>0,ROUND(J10,4)/ROUND(K10,4)-1,IF(K10<0,"n.a."))) -> 18.393189 | P10: =IF(L10/N10<0,"n.a.",IF(N10>0,ROUND(L10,4)/ROUND(N10,4)-1,IF(N10<0,"n.a."))) -> 0.88944783
B11: 신계약 CSM (New Business CSM) | H11: 금리확정형 (Fixed-rate) | J11: 0.42439525 | K11: 0.45906351 | L11: 0.20211099 | M11: 0.27818386 | N11: 0.22228426 | O11: =IF(J11/K11<0,"n.a.",IF(K11>0,ROUND(J11,4)/ROUND(K11,4)-1,IF(K11<0,"n.a."))) -> -0.075582662 | P11: =IF(L11/N11<0,"n.a.",IF(N11>0,ROUND(L11,4)/ROUND(N11,4)-1,IF(N11<0,"n.a."))) -> -0.090868196
B12: 신계약 CSM 배수 (New Business CSM Margin) | H12: 금리연동형 (Floating-rate) | J12: 572.29716 | K12: 29.073007 | L12: 374.30804 | M12: 25.725426 | N12: 197.98912 | O12: =IF(J12/K12<0,"n.a.",IF(K12>0,ROUND(J12,4)/ROUND(K12,4)-1,IF(K12<0,"n.a."))) -> 18.684835 | P12: =IF(L12/N12<0,"n.a.",IF(N12>0,ROUND(L12,4)/ROUND(N12,4)-1,IF(N12<0,"n.a."))) -> 0.89054852
H13: 변액연금 (Variable) | J13: 0 | K13: 0 | L13: 0 | M13: 0 | N13: 0
B14: 주요지표 (Key Index) | G14: 저축보험 (Savings) | J14: =SUM(J15:J17) -> 0.23631413 | K14: =SUM(K15:K17) -> 0.23099621 | L14: =SUM(L15:L17) -> 0.052104442 | M14: =SUM(M15:M17) -> 0.12938885 | N14: =SUM(N15:N17) -> 0.18420969 | O14: =IF(J14/K14<0,"n.a.",IF(K14>0,ROUND(J14,4)/ROUND(K14,4)-1,IF(K14<0,"n.a."))) -> 0.022943723 | P14: =IF(L14/N14<0,"n.a.",IF(N14>0,ROUND(L14,4)/ROUND(N14,4)-1,IF(N14<0,"n.a."))) -> -0.71715527
C15: 재무 안정성 (Financial Stability) | H15: 금리확정형 (Fixed-rate) | J15: 0 | K15: 0 | L15: 0 | M15: 0 | N15: 0
C16: 생산성 / 경영효율 (Productivity / Operating Efficiency) | H16: 금리연동형 (Floating-rate) | J16: 0.23631413 | K16: 0.23099621 | L16: 0.052104442 | M16: 0.12938885 | N16: 0.18420969 | O16: =IF(J16/K16<0,"n.a.",IF(K16>0,ROUND(J16,4)/ROUND(K16,4)-1,IF(K16<0,"n.a."))) -> 0.022943723 | P16: =IF(L16/N16<0,"n.a.",IF(N16>0,ROUND(L16,4)/ROUND(N16,4)-1,IF(N16<0,"n.a."))) -> -0.71715527
H17: 변액저축 (Variable) | J17: 0 | K17: 0 | L17: 0 | M17: 0 | N17: 0
B18: 상품별 수입보험료 (Premium by Product-type) | F18: Group | G18: 단체보험 (Group) | J18: =SUM(J19:J20) -> 0 | K18: =SUM(K19:K20) -> 0 | L18: =SUM(L19:L20) -> 0 | M18: =SUM(M19:M20) -> 0 | N18: =SUM(N19:N20) -> 0
C19: 상품별 APE (Annualized Premium Equivalent (APE)) | G19: 단체보장 (Protection-type) | J19: 0 | K19: 0 | L19: 0 | M19: 0 | N19: 0
C20: 상품별 수입보험료 (Premium Income) | G20: 단체저축 (Savings) | J20: 0 | K20: 0 | L20: 0 | M20: 0 | N20: 0
C21: 상품별 초회보험료 (Initial Premium) | G21: 개인보험 + 단체보험 (Individual+Group) | J21: =SUM(J22:J24) -> 598.01973 | K21: =SUM(K22:K24) -> 68.842925 | L21: =SUM(L22:L24) -> 389.70304 | M21: =SUM(M22:M24) -> 46.213885 | N21: =SUM(N22:N24) -> 208.31669 | O21: =IF(J21/K21<0,"n.a.",IF(K21>0,ROUND(J21,4)/ROUND(K21,4)-1,IF(K21<0,"n.a."))) -> 7.6867302 | P21: =IF(L21/N21<0,"n.a.",IF(N21>0,ROUND(L21,4)/ROUND(N21,4)-1,IF(N21<0,"n.a."))) -> 0.87072376
C22: 상품별 초년도보험료 (First Year Premium) | F22: Individual+Group | G22: 보장성보험 (Protection-type) | J22: =SUM(J6,J19) -> 25.061861 | K22: =SUM(K6,K19) -> 39.079858 | L22: =SUM(L6,L19) -> 15.140791 | M22: =SUM(M6,M19) -> 20.080886 | N22: =SUM(N6,N19) -> 9.9210703 | O22: =IF(J22/K22<0,"n.a.",IF(K22>0,ROUND(J22,4)/ROUND(K22,4)-1,IF(K22<0,"n.a."))) -> -0.35870102 | P22: =IF(L22/N22<0,"n.a.",IF(N22>0,ROUND(L22,4)/ROUND(N22,4)-1,IF(N22<0,"n.a."))) -> 0.5261211
G23: 연금보험 (Annuities) | J23: =J10 -> 572.72155 | K23: =K10 -> 29.532071 | L23: =L10 -> 374.51015 | M23: =M10 -> 26.00361 | N23: =N10 -> 198.21141 | O23: =IF(J23/K23<0,"n.a.",IF(K23>0,ROUND(J23,4)/ROUND(K23,4)-1,IF(K23<0,"n.a."))) -> 18.393189 | P23: =IF(L23/N23<0,"n.a.",IF(N23>0,ROUND(L23,4)/ROUND(N23,4)-1,IF(N23<0,"n.a."))) -> 0.88944783
B24: 채널별 수입보험료 (Premium by Distribution Channel) | G24: 저축보험 (Savings) | J24: =SUM(J14,J20) -> 0.23631413 | K24: =SUM(K14,K20) -> 0.23099621 | L24: =SUM(L14,L20) -> 0.052104442 | M24: =SUM(M14,M20) -> 0.12938885 | N24: =SUM(N14,N20) -> 0.18420969 | O24: =IF(J24/K24<0,"n.a.",IF(K24>0,ROUND(J24,4)/ROUND(K24,4)-1,IF(K24<0,"n.a."))) -> 0.022943723 | P24: =IF(L24/N24<0,"n.a.",IF(N24>0,ROUND(L24,4)/ROUND(N24,4)-1,IF(N24<0,"n.a."))) -> -0.71715527
C25: 채널별 APE (Annualized Premium Equivalent (APE)) | G25: 퇴직관련 보험 (Retirement-related) | J25: =SUM(J26:J27) -> 13.134638 | K25: =SUM(K26:K27) -> 0.92698439 | L25: =SUM(L26:L27) -> 12.274405 | M25: =SUM(M26:M27) -> 0.30803075 | N25: =SUM(N26:N27) -> 0.86023311 | O25: =IF(J25/K25<0,"n.a.",IF(K25>0,ROUND(J25,4)/ROUND(K25,4)-1,IF(K25<0,"n.a."))) -> 13.168932 | P25: =IF(L25/N25<0,"n.a.",IF(N25>0,ROUND(L25,4)/ROUND(N25,4)-1,IF(N25<0,"n.a."))) -> 13.26924
C26: 채널별 수입보험료 (Premium Income) | F26: Retirement-related | G26: 퇴직보험 (Retirement insurance) | J26: 0 | K26: 0 | L26: 0 | M26: 0 | N26: 0
C27: 채널별 초년도보험료 (First Year Premium) | G27: 퇴직연금 (Corporate pension) | J27: 13.134638 | K27: 0.92698439 | L27: 12.274405 | M27: 0.30803075 | N27: 0.86023311 | O27: =IF(J27/K27<0,"n.a.",IF(K27>0,ROUND(J27,4)/ROUND(K27,4)-1,IF(K27<0,"n.a."))) -> 13.168932 | P27: =IF(L27/N27<0,"n.a.",IF(N27>0,ROUND(L27,4)/ROUND(N27,4)-1,IF(N27<0,"n.a."))) -> 13.26924
B30: 투자영업 현황 (Investment)
C31: 대출 (Loan)/ 자산건전성 (Asset Quality of Loan) | F31: Premium Income by Product-type (2/2)
C32: 채권 (Bond) | F32: General Account
B34: 재무제표 (Full Financial Statements) | F34: (KRW mn)
C35: 재무상태표 (Balance Sheet - KIFRS) | F35: Individual
C36: 손익계산서 (Income Statement - KIFRS)
F48: Group
F52: Individual+Group
F56: Retirement-related
F60: Separate Account
F62: (KRW mn)
F63: Individual
F76: Group
F80: Individual+Group
F84: Retirement-related
F88: 월초 대신 월납환산? --> 어차피 APE 쓰는 마당에 월초보다 월납환산이 더 적절한 지표일 수도

Sheet First-year P. by P.T.
F1: APE by Product-type (1/2) | G1: 상품별 초년도보험료 (First-year Premium by Product-type)
F2: Total (General acc. + Separate acc.) | G2: 합계 (일반계정 + 특별계정) (Total (General acc. + Separate acc.)
A3: Disclaimer & Contact Information | J3: Accumulated Data | L3: Quarterly Data
F4: (KRW mn) | G4: 단위 십억원 (KRW bn) | J4: Jun '26 | K4: Jun '25 | L4: Jun '26 | M4: Jun '25 | N4: 46112 | O4: YoY | P4: QoQ
B5: 재무현황 (Financial Highlights) | F5: Individual | G5: 개인보험 (Individual) | J5: =SUM(J6,J10,J14) -> 833.27318 | K5: =SUM(K6,K10,K14) -> 418.43441 | L5: =SUM(L6,L10,L14) -> 500.87553 | M5: =SUM(M6,M10,M14) -> 220.64835 | N5: =SUM(N6,N10,N14) -> 332.39764 | O5: =IF(J5/K5<0,"n.a.",IF(K5>0,ROUND(J5,4)/ROUND(K5,4)-1,IF(K5<0,"n.a."))) -> 0.99140702 | P5: =IF(L5/N5<0,"n.a.",IF(N5>0,ROUND(L5,4)/ROUND(N5,4)-1,IF(N5<0,"n.a."))) -> 0.50685655
G6: 보장성보험 (Protection-type) | J6: =SUM(J7:J9) -> 258.84716 | K6: =SUM(K7:K9) -> 386.5534 | L6: =SUM(L7:L9) -> 125.51117 | M6: =SUM(M7:M9) -> 193.71368 | N6: =SUM(N7:N9) -> 133.33599 | O6: =IF(J6/K6<0,"n.a.",IF(K6>0,ROUND(J6,4)/ROUND(K6,4)-1,IF(K6<0,"n.a."))) -> -0.33037143 | P6: =IF(L6/N6<0,"n.a.",IF(N6>0,ROUND(L6,4)/ROUND(N6,4)-1,IF(N6<0,"n.a."))) -> -0.058684826
B7: 요약재무상태표 (Selected Balance sheet) | H7: 종신/CI/정기 (Whole life/CI/Term life) | J7: 101.47364 | K7: 180.74815 | L7: 52.509233 | M7: 84.411888 | N7: 48.964405 | O7: =IF(J7/K7<0,"n.a.",IF(K7>0,ROUND(J7,4)/ROUND(K7,4)-1,IF(K7<0,"n.a."))) -> -0.43859106 | P7: =IF(L7/N7<0,"n.a.",IF(N7>0,ROUND(L7,4)/ROUND(N7,4)-1,IF(N7<0,"n.a."))) -> 0.072395455
B8: 요약손익계산서 (Selected Income Statement) | H8: 변액종신/CI (Variable whole life/CI) | J8: 0.01908099 | K8: 0.009670809 | L8: 0.009233853 | M8: 0.006673341 | N8: 0.009847137 | O8: =IF(J8/K8<0,"n.a.",IF(K8>0,ROUND(J8,4)/ROUND(K8,4)-1,IF(K8<0,"n.a."))) -> 0.96907216 | P8: =IF(L8/N8<0,"n.a.",IF(N8>0,ROUND(L8,4)/ROUND(N8,4)-1,IF(N8<0,"n.a."))) -> -0.06122449
H9: 기타보장 (Other protection-type) | J9: 157.35444 | K9: 205.79558 | L9: 72.992703 | M9: 109.29512 | N9: 84.361738 | O9: =IF(J9/K9<0,"n.a.",IF(K9>0,ROUND(J9,4)/ROUND(K9,4)-1,IF(K9<0,"n.a."))) -> -0.23538501 | P9: =IF(L9/N9<0,"n.a.",IF(N9>0,ROUND(L9,4)/ROUND(N9,4)-1,IF(N9<0,"n.a."))) -> -0.13476495
B10: RA, CSM, BEL Movement | G10: 연금보험 (Annuities) | J10: =SUM(J11:J13) -> 574.03511 | K10: =SUM(K11:K13) -> 31.171959 | L10: =SUM(L11:L13) -> 375.2413 | M10: =SUM(M11:M13) -> 26.685574 | N10: =SUM(N11:N13) -> 198.79381 | O10: =IF(J10/K10<0,"n.a.",IF(K10>0,ROUND(J10,4)/ROUND(K10,4)-1,IF(K10<0,"n.a."))) -> 17.415087 | P10: =IF(L10/N10<0,"n.a.",IF(N10>0,ROUND(L10,4)/ROUND(N10,4)-1,IF(N10<0,"n.a."))) -> 0.88759056
B11: 신계약 CSM (New Business CSM) | H11: 금리확정형 (Fixed-rate) | J11: 0.42921502 | K11: 0.46062886 | L11: 0.20362825 | M11: 0.27928355 | N11: 0.22558678 | O11: =IF(J11/K11<0,"n.a.",IF(K11>0,ROUND(J11,4)/ROUND(K11,4)-1,IF(K11<0,"n.a."))) -> -0.06817195 | P11: =IF(L11/N11<0,"n.a.",IF(N11>0,ROUND(L11,4)/ROUND(N11,4)-1,IF(N11<0,"n.a."))) -> -0.09751773
B12: 신계약 CSM 배수 (New Business CSM Margin) | H12: 금리연동형 (Floating-rate) | J12: 573.6059 | K12: 30.71133 | L12: 375.03767 | M12: 26.40629 | N12: 198.56822 | O12: =IF(J12/K12<0,"n.a.",IF(K12>0,ROUND(J12,4)/ROUND(K12,4)-1,IF(K12<0,"n.a."))) -> 17.677357 | P12: =IF(L12/N12<0,"n.a.",IF(N12>0,ROUND(L12,4)/ROUND(N12,4)-1,IF(N12<0,"n.a."))) -> 0.88870977
H13: 변액연금 (Variable) | J13: 0 | K13: 0 | L13: 0 | M13: 0 | N13: 0
B14: 주요지표 (Key Index) | G14: 저축보험 (Savings) | J14: =SUM(J15:J17) -> 0.39090606 | K14: =SUM(K15:K17) -> 0.70904798 | L14: =SUM(L15:L17) -> 0.12306279 | M14: =SUM(M15:M17) -> 0.24909153 | N14: =SUM(N15:N17) -> 0.26784327 | O14: =IF(J14/K14<0,"n.a.",IF(K14>0,ROUND(J14,4)/ROUND(K14,4)-1,IF(K14<0,"n.a."))) -> -0.44866008 | P14: =IF(L14/N14<0,"n.a.",IF(N14>0,ROUND(L14,4)/ROUND(N14,4)-1,IF(N14<0,"n.a."))) -> -0.5403286
C15: 재무 안정성 (Financial Stability) | H15: 금리확정형 (Fixed-rate) | J15: 0 | K15: 0.2632191 | L15: 0 | M15: 0.00385 | N15: 0
C16: 생산성 / 경영효율 (Productivity / Operating Efficiency) | H16: 금리연동형 (Floating-rate) | J16: 0.39090606 | K16: 0.44582889 | L16: 0.12306279 | M16: 0.24524153 | N16: 0.26784327 | O16: =IF(J16/K16<0,"n.a.",IF(K16>0,ROUND(J16,4)/ROUND(K16,4)-1,IF(K16<0,"n.a."))) -> -0.12314939 | P16: =IF(L16/N16<0,"n.a.",IF(N16>0,ROUND(L16,4)/ROUND(N16,4)-1,IF(N16<0,"n.a."))) -> -0.5403286
H17: 변액저축 (Variable) | J17: 0 | K17: 0 | L17: 0 | M17: 0 | N17: 0
B18: 상품별 수입보험료 (Premium by Product-type) | F18: Group | G18: 단체보험 (Group) | J18: =SUM(J19:J20) -> 0 | K18: =SUM(K19:K20) -> 0 | L18: =SUM(L19:L20) -> 0 | M18: =SUM(M19:M20) -> 0 | N18: =SUM(N19:N20) -> 0
C19: 상품별 APE (Annualized Premium Equivalent (APE)) | G19: 단체보장 (Protection-type) | J19: 0 | K19: 0 | L19: 0 | M19: 0 | N19: 0
C20: 상품별 수입보험료 (Premium Income) | G20: 단체저축 (Savings) | J20: 0 | K20: 0 | L20: 0 | M20: 0 | N20: 0
C21: 상품별 초회보험료 (Initial Premium) | G21: 개인보험 + 단체보험 (Individual+Group) | J21: =SUM(J22:J24) -> 833.27318 | K21: =SUM(K22:K24) -> 418.43441 | L21: =SUM(L22:L24) -> 500.87553 | M21: =SUM(M22:M24) -> 220.64835 | N21: =SUM(N22:N24) -> 332.39764 | O21: =IF(J21/K21<0,"n.a.",IF(K21>0,ROUND(J21,4)/ROUND(K21,4)-1,IF(K21<0,"n.a."))) -> 0.99140702 | P21: =IF(L21/N21<0,"n.a.",IF(N21>0,ROUND(L21,4)/ROUND(N21,4)-1,IF(N21<0,"n.a."))) -> 0.50685655
C22: 상품별 초년도보험료 (First Year Premium) | F22: Individual+Group | G22: 보장성보험 (Protection-type) | J22: =SUM(J6,J19) -> 258.84716 | K22: =SUM(K6,K19) -> 386.5534 | L22: =SUM(L6,L19) -> 125.51117 | M22: =SUM(M6,M19) -> 193.71368 | N22: =SUM(N6,N19) -> 133.33599 | O22: =IF(J22/K22<0,"n.a.",IF(K22>0,ROUND(J22,4)/ROUND(K22,4)-1,IF(K22<0,"n.a."))) -> -0.33037143 | P22: =IF(L22/N22<0,"n.a.",IF(N22>0,ROUND(L22,4)/ROUND(N22,4)-1,IF(N22<0,"n.a."))) -> -0.058684826
G23: 연금보험 (Annuities) | J23: =J10 -> 574.03511 | K23: =K10 -> 31.171959 | L23: =L10 -> 375.2413 | M23: =M10 -> 26.685574 | N23: =N10 -> 198.79381 | O23: =IF(J23/K23<0,"n.a.",IF(K23>0,ROUND(J23,4)/ROUND(K23,4)-1,IF(K23<0,"n.a."))) -> 17.415087 | P23: =IF(L23/N23<0,"n.a.",IF(N23>0,ROUND(L23,4)/ROUND(N23,4)-1,IF(N23<0,"n.a."))) -> 0.88759056
B24: 채널별 수입보험료 (Premium by Distribution Channel) | G24: 저축보험 (Savings) | J24: =SUM(J14,J20) -> 0.39090606 | K24: =SUM(K14,K20) -> 0.70904798 | L24: =SUM(L14,L20) -> 0.12306279 | M24: =SUM(M14,M20) -> 0.24909153 | N24: =SUM(N14,N20) -> 0.26784327 | O24: =IF(J24/K24<0,"n.a.",IF(K24>0,ROUND(J24,4)/ROUND(K24,4)-1,IF(K24<0,"n.a."))) -> -0.44866008 | P24: =IF(L24/N24<0,"n.a.",IF(N24>0,ROUND(L24,4)/ROUND(N24,4)-1,IF(N24<0,"n.a."))) -> -0.5403286
C25: 채널별 APE (Annualized Premium Equivalent (APE)) | G25: 퇴직관련 보험 (Retirement-related) | J25: =SUM(J26:J27) -> 18.316527 | K25: =SUM(K26:K27) -> 27.844078 | L25: =SUM(L26:L27) -> 17.370442 | M25: =SUM(M26:M27) -> 27.21867 | N25: =SUM(N26:N27) -> 0.94608463 | O25: =IF(J25/K25<0,"n.a.",IF(K25>0,ROUND(J25,4)/ROUND(K25,4)-1,IF(K25<0,"n.a."))) -> -0.34217662 | P25: =IF(L25/N25<0,"n.a.",IF(N25>0,ROUND(L25,4)/ROUND(N25,4)-1,IF(N25<0,"n.a."))) -> 17.360004
C26: 채널별 수입보험료 (Premium Income) | F26: Retirement-related | G26: 퇴직보험 (Retirement insurance) | J26: 0 | K26: 0 | L26: 0 | M26: 0 | N26: 0
C27: 채널별 초년도보험료 (First Year Premium) | G27: 퇴직연금 (Corporate pension) | J27: 18.316527 | K27: 27.844078 | L27: 17.370442 | M27: 27.21867 | N27: 0.94608463 | O27: =IF(J27/K27<0,"n.a.",IF(K27>0,ROUND(J27,4)/ROUND(K27,4)-1,IF(K27<0,"n.a."))) -> -0.34217662 | P27: =IF(L27/N27<0,"n.a.",IF(N27>0,ROUND(L27,4)/ROUND(N27,4)-1,IF(N27<0,"n.a."))) -> 17.360004
B30: 투자영업 현황 (Investment)
C31: 대출 (Loan)/ 자산건전성 (Asset Quality of Loan) | F31: Premium Income by Product-type (2/2)
C32: 채권 (Bond) | F32: General Account
B34: 재무제표 (Full Financial Statements) | F34: (KRW mn)
C35: 재무상태표 (Balance Sheet - KIFRS) | F35: Individual
C36: 손익계산서 (Income Statement - KIFRS)
F48: Group
F52: Individual+Group
F56: Retirement-related
F60: Separate Account
F62: (KRW mn)
F63: Individual
F76: Group
F80: Individual+Group
F84: Retirement-related
F88: 월초 대신 월납환산? --> 어차피 APE 쓰는 마당에 월초보다 월납환산이 더 적절한 지표일 수도

Sheet APE by D.C
F1: 채널별 APE (APE by Distribution Channel)
F2: 합계 (일반계정 + 특별계정) (Total (General acc. + Separate acc.)
A3: Disclaimer & Contact Information | J3: Accumulated Data | L3: Quarterly Data
F4: 단위 십억원 (KRW bn) | J4: Jun '26 | K4: Jun '25 | L4: Jun '26 | M4: Jun '25 | N4: 46112 | O4: YoY | P4: QoQ
B5: 재무현황 (Financial Highlights) | F5: 개인 (Tied Agent) | J5: =+SUM(J6,J8,J9) -> 62.72392 | K5: =+SUM(K6,K8,K9) -> 70.92728 | L5: =+SUM(L6,L8,L9) -> 30.933667 | M5: =+SUM(M6,M8,M9) -> 33.595992 | N5: =+SUM(N6,N8,N9) -> 31.790253 | O5: =IF(J5/K5<0,"n.a.",IF(K5>0,ROUND(J5,4)/ROUND(K5,4)-1,IF(K5<0,"n.a."))) -> -0.11565927 | P5: =IF(L5/N5<0,"n.a.",IF(N5>0,ROUND(L5,4)/ROUND(N5,4)-1,IF(N5<0,"n.a."))) -> -0.026945326
G6: 보장성보험 (Protection-type) | J6: 61.333842 | K6: 70.132171 | L6: 30.260058 | M6: 33.202514 | N6: 31.073785 | O6: =IF(J6/K6<0,"n.a.",IF(K6>0,ROUND(J6,4)/ROUND(K6,4)-1,IF(K6<0,"n.a."))) -> -0.1254545 | P6: =IF(L6/N6<0,"n.a.",IF(N6>0,ROUND(L6,4)/ROUND(N6,4)-1,IF(N6<0,"n.a."))) -> -0.026186047
B7: 요약재무상태표 (Selected Balance sheet) | G7: % 보장성보험 (% Protection-type) | J7: =J6/J5 -> 0.97783816 | K7: =K6/K5 -> 0.9887898 | L7: =L6/L5 -> 0.97822407 | M7: =M6/M5 -> 0.98828793 | N7: =N6/N5 -> 0.97746266 | O7: =J7-K7 -> -0.010951634 | P7: =L7-N7 -> 0.00076140912
B8: 요약손익계산서 (Selected Income Statement) | G8: 연금보험 (Annuities) | J8: 1.3750263 | K8: 0.79057428 | L8: 0.67360949 | M8: 0.38894352 | N8: 0.70141681 | O8: =IF(J8/K8<0,"n.a.",IF(K8>0,ROUND(J8,4)/ROUND(K8,4)-1,IF(K8<0,"n.a."))) -> 0.73918543 | P8: =IF(L8/N8<0,"n.a.",IF(N8>0,ROUND(L8,4)/ROUND(N8,4)-1,IF(N8<0,"n.a."))) -> -0.039635016
G9: 저축보험 (Savings) | J9: 0.01505102 | K9: 0.0045349563 | L9: 0 | M9: 0.0045349563 | N9: 0.01505102
B10: RA, CSM, BEL Movement | F10: 다이렉트 (Tele Marketing) | J10: =+SUM(J11,J13,J14) -> 14.436888 | K10: =+SUM(K11,K13,K14) -> 16.78063 | L10: =+SUM(L11,L13,L14) -> 7.0749334 | M10: =+SUM(M11,M13,M14) -> 7.7518353 | N10: =+SUM(N11,N13,N14) -> 7.3619546 | O10: =IF(J10/K10<0,"n.a.",IF(K10>0,ROUND(J10,4)/ROUND(K10,4)-1,IF(K10<0,"n.a."))) -> -0.13966723 | P10: =IF(L10/N10<0,"n.a.",IF(N10>0,ROUND(L10,4)/ROUND(N10,4)-1,IF(N10<0,"n.a."))) -> -0.038997555
B11: 신계약 CSM (New Business CSM) | G11: 보장성보험 (Protection-type) | J11: 14.217127 | K11: 16.460119 | L11: 6.978126 | M11: 7.6457964 | N11: 7.2390014 | O11: =IF(J11/K11<0,"n.a.",IF(K11>0,ROUND(J11,4)/ROUND(K11,4)-1,IF(K11<0,"n.a."))) -> -0.13626892 | P11: =IF(L11/N11<0,"n.a.",IF(N11>0,ROUND(L11,4)/ROUND(N11,4)-1,IF(N11<0,"n.a."))) -> -0.03604089
B12: 신계약 CSM 배수 (New Business CSM Margin) | G12: % 보장성보험 (% Protection-type) | J12: =J11/J10 -> 0.98477784 | K12: =K11/K10 -> 0.98089996 | L12: =L11/L10 -> 0.98631685 | M12: =M11/M10 -> 0.9863208 | N12: =N11/N10 -> 0.98329884 | O12: =J12-K12 -> 0.0038778838 | P12: =L12-N12 -> 0.0030180102
G13: 연금보험 (Annuities) | J13: 0.02982423 | K13: 0.0096 | L13: 0.017221963 | M13: 0.0066 | N13: 0.012602267 | O13: =IF(J13/K13<0,"n.a.",IF(K13>0,ROUND(J13,4)/ROUND(K13,4)-1,IF(K13<0,"n.a."))) -> 2.1041667 | P13: =IF(L13/N13<0,"n.a.",IF(N13>0,ROUND(L13,4)/ROUND(N13,4)-1,IF(N13<0,"n.a."))) -> 0.36507937
B14: 주요지표 (Key Index) | G14: 저축보험 (Savings) | J14: 0.18993639 | K14: 0.31091077 | L14: 0.079585444 | M14: 0.099438929 | N14: 0.11035095 | O14: =IF(J14/K14<0,"n.a.",IF(K14>0,ROUND(J14,4)/ROUND(K14,4)-1,IF(K14<0,"n.a."))) -> -0.38919267 | P14: =IF(L14/N14<0,"n.a.",IF(N14>0,ROUND(L14,4)/ROUND(N14,4)-1,IF(N14<0,"n.a."))) -> -0.27898551
C15: 재무 안정성 (Financial Stability) | F15: GA (General Agency) | J15: =+SUM(J16,J18,J19) -> 186.74292 | K15: =+SUM(K16,K18,K19) -> 180.52628 | L15: =+SUM(L16,L18,L19) -> 118.18291 | M15: =+SUM(M16,M18,M19) -> 71.584314 | N15: =+SUM(N16,N18,N19) -> 68.560013 | O15: =IF(J15/K15<0,"n.a.",IF(K15>0,ROUND(J15,4)/ROUND(K15,4)-1,IF(K15<0,"n.a."))) -> 0.03443598 | P15: =IF(L15/N15<0,"n.a.",IF(N15>0,ROUND(L15,4)/ROUND(N15,4)-1,IF(N15<0,"n.a."))) -> 0.72378792
C16: 생산성 / 경영효율 (Productivity / Operating Efficiency) | G16: 보장성보험 (Protection-type) | J16: 186.18571 | K16: 179.5431 | L16: 118.05622 | M16: 71.224708 | N16: 68.129494 | O16: =IF(J16/K16<0,"n.a.",IF(K16>0,ROUND(J16,4)/ROUND(K16,4)-1,IF(K16<0,"n.a."))) -> 0.036997245 | P16: =IF(L16/N16<0,"n.a.",IF(N16>0,ROUND(L16,4)/ROUND(N16,4)-1,IF(N16<0,"n.a."))) -> 0.73282058
G17: % 보장성보험 (% Protection-type) | J17: =J16/J15 -> 0.99701617 | K17: =K16/K15 -> 0.99455377 | L17: =L16/L15 -> 0.99892801 | M17: =M16/M15 -> 0.99497646 | N17: =N16/N15 -> 0.99372055 | O17: =J17-K17 -> 0.0024623958 | P17: =L17-N17 -> 0.0052074579
B18: 상품별 수입보험료 (Premium by Product-type) | G18: 연금보험 (Annuities) | J18: 0.55720943 | K18: 0.98318718 | L18: 0.12669059 | M18: 0.35960669 | N18: 0.43051884 | O18: =IF(J18/K18<0,"n.a.",IF(K18>0,ROUND(J18,4)/ROUND(K18,4)-1,IF(K18<0,"n.a."))) -> -0.43327909 | P18: =IF(L18/N18<0,"n.a.",IF(N18>0,ROUND(L18,4)/ROUND(N18,4)-1,IF(N18<0,"n.a."))) -> -0.70569106
C19: 상품별 APE (Annualized Premium Equivalent (APE)) | G19: 저축보험 (Savings) | J19: 0 | K19: 0 | L19: 0 | M19: 0 | N19: 0
C20: 상품별 수입보험료 (Premium Income) | F20: 방카슈랑스 (Bancassurance) | J20: =+SUM(J21,J23,J24) -> 81.754219 | K20: =+SUM(K21,K23,K24) -> 71.888141 | L20: =+SUM(L21,L23,L24) -> 50.312141 | M20: =+SUM(M21,M23,M24) -> 42.829002 | N20: =+SUM(N21,N23,N24) -> 31.442077 | O20: =IF(J20/K20<0,"n.a.",IF(K20>0,ROUND(J20,4)/ROUND(K20,4)-1,IF(K20<0,"n.a."))) -> 0.13724246 | P20: =IF(L20/N20<0,"n.a.",IF(N20>0,ROUND(L20,4)/ROUND(N20,4)-1,IF(N20<0,"n.a."))) -> 0.60015075
C21: 상품별 초회보험료 (Initial Premium) | G21: 보장성보험 (Protection-type) | J21: 25.029729 | K21: 69.305797 | L21: 13.147433 | M21: 40.419128 | N21: 11.882296 | O21: =IF(J21/K21<0,"n.a.",IF(K21>0,ROUND(J21,4)/ROUND(K21,4)-1,IF(K21<0,"n.a."))) -> -0.63885129 | P21: =IF(L21/N21<0,"n.a.",IF(N21>0,ROUND(L21,4)/ROUND(N21,4)-1,IF(N21<0,"n.a."))) -> 0.10646929
C22: 상품별 초년도보험료 (First Year Premium) | G22: % 보장성보험 (% Protection-type) | J22: =J21/J20 -> 0.30615826 | K22: =K21/K20 -> 0.9640783 | L22: =L21/L20 -> 0.2613173 | M22: =M21/M20 -> 0.94373265 | N22: =N21/N20 -> 0.37791067 | O22: =J22-K22 -> -0.65792004 | P22: =L22-N22 -> -0.11659337
G23: 연금보험 (Annuities) | J23: 56.724489 | K23: 2.5823446 | L23: 37.164709 | M23: 2.4098743 | N23: 19.559781 | O23: =IF(J23/K23<0,"n.a.",IF(K23>0,ROUND(J23,4)/ROUND(K23,4)-1,IF(K23<0,"n.a."))) -> 20.966658 | P23: =IF(L23/N23<0,"n.a.",IF(N23>0,ROUND(L23,4)/ROUND(N23,4)-1,IF(N23<0,"n.a."))) -> 0.90005522
B24: 채널별 수입보험료 (Premium by Distribution Channel) | G24: 저축보험 (Savings) | J24: 0 | K24: 0 | L24: 0 | M24: 0 | N24: 0
C25: 채널별 APE (Annualized Premium Equivalent (APE)) | F25: 합계 (Total) | J25: =SUM(J26,J28:J29) -> 345.65795 | K25: =SUM(K26,K28:K29) -> 340.12234 | L25: =SUM(L26,L28:L29) -> 206.50365 | M25: =SUM(M26,M28:M29) -> 155.76114 | N25: =SUM(N26,N28:N29) -> 139.1543 | O25: =IF(J25/K25<0,"n.a.",IF(K25>0,ROUND(J25,4)/ROUND(K25,4)-1,IF(K25<0,"n.a."))) -> 0.016275616 | P25: =IF(L25/N25<0,"n.a.",IF(N25>0,ROUND(L25,4)/ROUND(N25,4)-1,IF(N25<0,"n.a."))) -> 0.48399079
C26: 채널별 수입보험료 (Premium Income) | G26: 보장성보험 (Protection-type) | J26: =SUM(J6,J11,J16,J21) -> 286.76641 | K26: =SUM(K6,K11,K16,K21) -> 335.44118 | L26: =SUM(L6,L11,L16,L21) -> 168.44184 | M26: =SUM(M6,M11,M16,M21) -> 152.49215 | N26: =SUM(N6,N11,N16,N21) -> 118.32458 | O26: =IF(J26/K26<0,"n.a.",IF(K26>0,ROUND(J26,4)/ROUND(K26,4)-1,IF(K26<0,"n.a."))) -> -0.1451068 | P26: =IF(L26/N26<0,"n.a.",IF(N26>0,ROUND(L26,4)/ROUND(N26,4)-1,IF(N26<0,"n.a."))) -> 0.42355689
C27: 채널별 초년도보험료 (First Year Premium) | G27: % 보장성보험 (% Protection-type) | J27: =J26/J25 -> 0.82962482 | K27: =K26/K25 -> 0.98623686 | L27: =L26/L25 -> 0.81568454 | M27: =M26/M25 -> 0.97901275 | N27: =N26/N25 -> 0.85031206 | O27: =J27-K27 -> -0.15661204 | P27: =L27-N27 -> -0.034627518
G28: 연금보험 (Annuities) | J28: =SUM(J8,J13,J18,J23) -> 58.686549 | K28: =SUM(K8,K13,K18,K23) -> 4.365706 | L28: =SUM(L8,L13,L18,L23) -> 37.982231 | M28: =SUM(M8,M13,M18,M23) -> 3.1650245 | N28: =SUM(N8,N13,N18,N23) -> 20.704319 | O28: =IF(J28/K28<0,"n.a.",IF(K28>0,ROUND(J28,4)/ROUND(K28,4)-1,IF(K28<0,"n.a."))) -> 12.442632 | P28: =IF(L28/N28<0,"n.a.",IF(N28>0,ROUND(L28,4)/ROUND(N28,4)-1,IF(N28<0,"n.a."))) -> 0.83450781
G29: 저축보험 (Savings) | J29: =SUM(J9,J14,J19,J24) -> 0.20498741 | K29: =SUM(K9,K14,K19,K24) -> 0.31544573 | L29: =SUM(L9,L14,L19,L24) -> 0.079585444 | M29: =SUM(M9,M14,M19,M24) -> 0.10397389 | N29: =SUM(N9,N14,N19,N24) -> 0.12540197 | O29: =IF(J29/K29<0,"n.a.",IF(K29>0,ROUND(J29,4)/ROUND(K29,4)-1,IF(K29<0,"n.a."))) -> -0.35003171 | P29: =IF(L29/N29<0,"n.a.",IF(N29>0,ROUND(L29,4)/ROUND(N29,4)-1,IF(N29<0,"n.a."))) -> -0.36523126
B30: 투자영업 현황 (Investment) | F30: *단체, 퇴직 제외
C31: 대출 (Loan)/ 자산건전성 (Asset Quality of Loan)
C32: 채권 (Bond)
B34: 재무제표 (Full Financial Statements)
C35: 재무상태표 (Balance Sheet - KIFRS)
C36: 손익계산서 (Income Statement - KIFRS)

Sheet Premium Income by D.C.(GA+SA)
F1: 채널별 수입보험료 (Premium Income by Distribution Channel (GA+SA)
F2: 합계 (일반계정 + 특별계정) (Total (General acc. + Separate acc.)
A3: Disclaimer & Contact Information | J3: Accumulated Data | L3: Quarterly Data
F4: 단위 십억원 (KRW bn) | J4: Jun '26 | K4: Jun '25 | L4: Jun '26 | M4: Jun '25 | N4: 46112 | O4: YoY | P4: QoQ
B5: 재무현황 (Financial Highlights) | F5: 개인 (Tied Agent) | J5: =+SUM(J6,J8,J9) -> 541.36357 | K5: =+SUM(K6,K8,K9) -> 521.02027 | L5: =+SUM(L6,L8,L9) -> 274.128 | M5: =+SUM(M6,M8,M9) -> 261.7531 | N5: =+SUM(N6,N8,N9) -> 267.23557 | O5: =IF(J5/K5<0,"n.a.",IF(K5>0,ROUND(J5,4)/ROUND(K5,4)-1,IF(K5<0,"n.a."))) -> 0.03904512 | P5: =IF(L5/N5<0,"n.a.",IF(N5>0,ROUND(L5,4)/ROUND(N5,4)-1,IF(N5<0,"n.a."))) -> 0.025791474
G6: 보장성보험 (Protection-type) | J6: 486.46171 | K6: 469.60128 | L6: 243.86707 | M6: 236.87836 | N6: 242.59463 | O6: =IF(J6/K6<0,"n.a.",IF(K6>0,ROUND(J6,4)/ROUND(K6,4)-1,IF(K6<0,"n.a."))) -> 0.035903648 | P6: =IF(L6/N6<0,"n.a.",IF(N6>0,ROUND(L6,4)/ROUND(N6,4)-1,IF(N6<0,"n.a."))) -> 0.0052453764
B7: 요약재무상태표 (Selected Balance sheet) | G7: % 보장성보험 (% Protection-type) | J7: =J6/J5 -> 0.89858598 | K7: =K6/K5 -> 0.90131096 | L7: =L6/L5 -> 0.88961024 | M7: =M6/M5 -> 0.90496868 | N7: =N6/N5 -> 0.90779322 | O7: =J7-K7 -> -0.0027249807 | P7: =L7-N7 -> -0.018182979
B8: 요약손익계산서 (Selected Income Statement) | G8: 연금보험 (Annuities) | J8: 17.874071 | K8: 19.457287 | L8: 8.9227761 | M8: 9.3995487 | N8: 8.9512946 | O8: =IF(J8/K8<0,"n.a.",IF(K8>0,ROUND(J8,4)/ROUND(K8,4)-1,IF(K8<0,"n.a."))) -> -0.081367918 | P8: =IF(L8/N8<0,"n.a.",IF(N8>0,ROUND(L8,4)/ROUND(N8,4)-1,IF(N8<0,"n.a."))) -> -0.0031838951
G9: 저축보험 (Savings) | J9: 37.027786 | K9: 31.961704 | L9: 21.338149 | M9: 15.475195 | N9: 15.689637 | O9: =IF(J9/K9<0,"n.a.",IF(K9>0,ROUND(J9,4)/ROUND(K9,4)-1,IF(K9<0,"n.a."))) -> 0.15850534 | P9: =IF(L9/N9<0,"n.a.",IF(N9>0,ROUND(L9,4)/ROUND(N9,4)-1,IF(N9<0,"n.a."))) -> 0.36001555
B10: RA, CSM, BEL Movement | F10: 다이렉트 (Tele Marketing) | J10: =+SUM(J11,J13,J14) -> 117.88733 | K10: =+SUM(K11,K13,K14) -> 134.16818 | L10: =+SUM(L11,L13,L14) -> 57.305204 | M10: =+SUM(M11,M13,M14) -> 65.150991 | N10: =+SUM(N11,N13,N14) -> 60.582122 | O10: =IF(J10/K10<0,"n.a.",IF(K10>0,ROUND(J10,4)/ROUND(K10,4)-1,IF(K10<0,"n.a."))) -> -0.12134694 | P10: =IF(L10/N10<0,"n.a.",IF(N10>0,ROUND(L10,4)/ROUND(N10,4)-1,IF(N10<0,"n.a."))) -> -0.054090235
B11: 신계약 CSM (New Business CSM) | G11: 보장성보험 (Protection-type) | J11: 91.460098 | K11: 104.74845 | L11: 44.674734 | M11: 50.933558 | N11: 46.785364 | O11: =IF(J11/K11<0,"n.a.",IF(K11>0,ROUND(J11,4)/ROUND(K11,4)-1,IF(K11<0,"n.a."))) -> -0.12686005 | P11: =IF(L11/N11<0,"n.a.",IF(N11>0,ROUND(L11,4)/ROUND(N11,4)-1,IF(N11<0,"n.a."))) -> -0.045114502
B12: 신계약 CSM 배수 (New Business CSM Margin) | G12: % 보장성보험 (% Protection-type) | J12: =J11/J10 -> 0.77582638 | K12: =K11/K10 -> 0.78072497 | L12: =L11/L10 -> 0.77959297 | M12: =M11/M10 -> 0.78177717 | N12: =N11/N10 -> 0.77226354 | O12: =J12-K12 -> -0.0048985875 | P12: =L12-N12 -> 0.0073294344
G13: 연금보험 (Annuities) | J13: 2.5501071 | K13: 3.2357231 | L13: 1.1307353 | M13: 1.4774505 | N13: 1.4193718 | O13: =IF(J13/K13<0,"n.a.",IF(K13>0,ROUND(J13,4)/ROUND(K13,4)-1,IF(K13<0,"n.a."))) -> -0.21188615 | P13: =IF(L13/N13<0,"n.a.",IF(N13>0,ROUND(L13,4)/ROUND(N13,4)-1,IF(N13<0,"n.a."))) -> -0.2033958
B14: 주요지표 (Key Index) | G14: 저축보험 (Savings) | J14: 23.877121 | K14: 26.184009 | L14: 11.499734 | M14: 12.739983 | N14: 12.377387 | O14: =IF(J14/K14<0,"n.a.",IF(K14>0,ROUND(J14,4)/ROUND(K14,4)-1,IF(K14<0,"n.a."))) -> -0.088103422 | P14: =IF(L14/N14<0,"n.a.",IF(N14>0,ROUND(L14,4)/ROUND(N14,4)-1,IF(N14<0,"n.a."))) -> -0.0709115
C15: 재무 안정성 (Financial Stability) | F15: GA (General Agency) | J15: =+SUM(J16,J18,J19) -> 929.08291 | K15: =+SUM(K16,K18,K19) -> 905.42573 | L15: =+SUM(L16,L18,L19) -> 466.16236 | M15: =+SUM(M16,M18,M19) -> 456.07043 | N15: =+SUM(N16,N18,N19) -> 462.92055 | O15: =IF(J15/K15<0,"n.a.",IF(K15>0,ROUND(J15,4)/ROUND(K15,4)-1,IF(K15<0,"n.a."))) -> 0.026128262 | P15: =IF(L15/N15<0,"n.a.",IF(N15>0,ROUND(L15,4)/ROUND(N15,4)-1,IF(N15<0,"n.a."))) -> 0.0070029288
C16: 생산성 / 경영효율 (Productivity / Operating Efficiency) | G16: 보장성보험 (Protection-type) | J16: 887.90559 | K16: 850.08781 | L16: 446.56012 | M16: 429.38221 | N16: 441.34546 | O16: =IF(J16/K16<0,"n.a.",IF(K16>0,ROUND(J16,4)/ROUND(K16,4)-1,IF(K16<0,"n.a."))) -> 0.044486934 | P16: =IF(L16/N16<0,"n.a.",IF(N16>0,ROUND(L16,4)/ROUND(N16,4)-1,IF(N16<0,"n.a."))) -> 0.011815233
G17: % 보장성보험 (% Protection-type) | J17: =J16/J15 -> 0.9556796 | K17: =K16/K15 -> 0.93888189 | L17: =L16/L15 -> 0.95794977 | M17: =M16/M15 -> 0.94148224 | N17: =N16/N15 -> 0.95339354 | O17: =J17-K17 -> 0.016797716 | P17: =L17-N17 -> 0.0045562281
B18: 상품별 수입보험료 (Premium by Product-type) | G18: 연금보험 (Annuities) | J18: 24.768246 | K18: 32.102201 | L18: 11.802137 | M18: 15.649405 | N18: 12.966109 | O18: =IF(J18/K18<0,"n.a.",IF(K18>0,ROUND(J18,4)/ROUND(K18,4)-1,IF(K18<0,"n.a."))) -> -0.22845786 | P18: =IF(L18/N18<0,"n.a.",IF(N18>0,ROUND(L18,4)/ROUND(N18,4)-1,IF(N18<0,"n.a."))) -> -0.089772561
C19: 상품별 APE (Annualized Premium Equivalent (APE)) | G19: 저축보험 (Savings) | J19: 16.409078 | K19: 23.235712 | L19: 7.8000988 | M19: 11.038815 | N19: 8.6089794 | O19: =IF(J19/K19<0,"n.a.",IF(K19>0,ROUND(J19,4)/ROUND(K19,4)-1,IF(K19<0,"n.a."))) -> -0.29379791 | P19: =IF(L19/N19<0,"n.a.",IF(N19>0,ROUND(L19,4)/ROUND(N19,4)-1,IF(N19<0,"n.a."))) -> -0.09395981
C20: 상품별 수입보험료 (Premium Income) | F20: 방카슈랑스 (Bancassurance) | J20: =+SUM(J21,J23,J24) -> 834.65708 | K20: =+SUM(K21,K23,K24) -> 292.14573 | L20: =+SUM(L21,L23,L24) -> 505.62418 | M20: =+SUM(M21,M23,M24) -> 157.34468 | N20: =+SUM(N21,N23,N24) -> 329.0329 | O20: =IF(J20/K20<0,"n.a.",IF(K20>0,ROUND(J20,4)/ROUND(K20,4)-1,IF(K20<0,"n.a."))) -> 1.8569892 | P20: =IF(L20/N20<0,"n.a.",IF(N20>0,ROUND(L20,4)/ROUND(N20,4)-1,IF(N20<0,"n.a."))) -> 0.536698
C21: 상품별 초회보험료 (Initial Premium) | G21: 보장성보험 (Protection-type) | J21: 206.59357 | K21: 177.35027 | L21: 104.89703 | M21: 92.664207 | N21: 101.69654 | O21: =IF(J21/K21<0,"n.a.",IF(K21>0,ROUND(J21,4)/ROUND(K21,4)-1,IF(K21<0,"n.a."))) -> 0.16489005 | P21: =IF(L21/N21<0,"n.a.",IF(N21>0,ROUND(L21,4)/ROUND(N21,4)-1,IF(N21<0,"n.a."))) -> 0.031471093
C22: 상품별 초년도보험료 (First Year Premium) | G22: % 보장성보험 (% Protection-type) | J22: =J21/J20 -> 0.2475191 | K22: =K21/K20 -> 0.60706098 | L22: =L21/L20 -> 0.20746047 | M22: =M21/M20 -> 0.58892495 | N22: =N21/N20 -> 0.3090771 | O22: =J22-K22 -> -0.35954188 | P22: =L22-N22 -> -0.10161662
G23: 연금보험 (Annuities) | J23: 590.74585 | K23: 59.539011 | L23: 383.09324 | M23: 38.893406 | N23: 207.65261 | O23: =IF(J23/K23<0,"n.a.",IF(K23>0,ROUND(J23,4)/ROUND(K23,4)-1,IF(K23<0,"n.a."))) -> 8.9219973 | P23: =IF(L23/N23<0,"n.a.",IF(N23>0,ROUND(L23,4)/ROUND(N23,4)-1,IF(N23<0,"n.a."))) -> 0.84487553
B24: 채널별 수입보험료 (Premium by Distribution Channel) | G24: 저축보험 (Savings) | J24: 37.317669 | K24: 55.256445 | L24: 17.633907 | M24: 25.787067 | N24: 19.683762 | O24: =IF(J24/K24<0,"n.a.",IF(K24>0,ROUND(J24,4)/ROUND(K24,4)-1,IF(K24<0,"n.a."))) -> -0.32464475 | P24: =IF(L24/N24<0,"n.a.",IF(N24>0,ROUND(L24,4)/ROUND(N24,4)-1,IF(N24<0,"n.a."))) -> -0.10414148
C25: 채널별 APE (Annualized Premium Equivalent (APE)) | F25: 합계 (Total) | J25: =SUM(J26,J28:J29) -> 2422.9909 | K25: =SUM(K26,K28:K29) -> 1852.7599 | L25: =SUM(L26,L28:L29) -> 1303.2197 | M25: =SUM(M26,M28:M29) -> 940.3192 | N25: =SUM(N26,N28:N29) -> 1119.7711 | O25: =IF(J25/K25<0,"n.a.",IF(K25>0,ROUND(J25,4)/ROUND(K25,4)-1,IF(K25<0,"n.a."))) -> 0.30777382 | P25: =IF(L25/N25<0,"n.a.",IF(N25>0,ROUND(L25,4)/ROUND(N25,4)-1,IF(N25<0,"n.a."))) -> 0.16382687
C26: 채널별 수입보험료 (Premium Income) | G26: 보장성보험 (Protection-type) | J26: =SUM(J6,J11,J16,J21) -> 1672.421 | K26: =SUM(K6,K11,K16,K21) -> 1601.7878 | L26: =SUM(L6,L11,L16,L21) -> 839.99896 | M26: =SUM(M6,M11,M16,M21) -> 809.85833 | N26: =SUM(N6,N11,N16,N21) -> 832.422 | O26: =IF(J26/K26<0,"n.a.",IF(K26>0,ROUND(J26,4)/ROUND(K26,4)-1,IF(K26<0,"n.a."))) -> 0.044096478 | P26: =IF(L26/N26<0,"n.a.",IF(N26>0,ROUND(L26,4)/ROUND(N26,4)-1,IF(N26<0,"n.a."))) -> 0.0091023543
C27: 채널별 초년도보험료 (First Year Premium) | G27: % 보장성보험 (% Protection-type) | J27: =J26/J25 -> 0.69022998 | K27: =K26/K25 -> 0.86454149 | L27: =L26/L25 -> 0.64455666 | M27: =M26/M25 -> 0.86125895 | N27: =N26/N25 -> 0.74338583 | O27: =J27-K27 -> -0.17431151 | P27: =L27-N27 -> -0.098829166
G28: 연금보험 (Annuities) | J28: =SUM(J8,J13,J18,J23) -> 635.93827 | K28: =SUM(K8,K13,K18,K23) -> 114.33422 | L28: =SUM(L8,L13,L18,L23) -> 404.94889 | M28: =SUM(M8,M13,M18,M23) -> 65.41981 | N28: =SUM(N8,N13,N18,N23) -> 230.98938 | O28: =IF(J28/K28<0,"n.a.",IF(K28>0,ROUND(J28,4)/ROUND(K28,4)-1,IF(K28<0,"n.a."))) -> 4.5621004 | P28: =IF(L28/N28<0,"n.a.",IF(N28>0,ROUND(L28,4)/ROUND(N28,4)-1,IF(N28<0,"n.a."))) -> 0.75310599
G29: 저축보험 (Savings) | J29: =SUM(J9,J14,J19,J24) -> 114.63165 | K29: =SUM(K9,K14,K19,K24) -> 136.63787 | L29: =SUM(L9,L14,L19,L24) -> 58.271889 | M29: =SUM(M9,M14,M19,M24) -> 65.04106 | N29: =SUM(N9,N14,N19,N24) -> 56.359766 | O29: =IF(J29/K29<0,"n.a.",IF(K29>0,ROUND(J29,4)/ROUND(K29,4)-1,IF(K29<0,"n.a."))) -> -0.16105488 | P29: =IF(L29/N29<0,"n.a.",IF(N29>0,ROUND(L29,4)/ROUND(N29,4)-1,IF(N29<0,"n.a."))) -> 0.033926664
B30: 투자영업 현황 (Investment) | F30: *단체, 퇴직 제외
C31: 대출 (Loan)/ 자산건전성 (Asset Quality of Loan)
C32: 채권 (Bond)
B34: 재무제표 (Full Financial Statements)
C35: 재무상태표 (Balance Sheet - KIFRS)
C36: 손익계산서 (Income Statement - KIFRS)

Sheet Premium Income by D.C.
F1: 채널별 수입보험료 (Premium Income by Distribution Channel)
F2: 일반계정 (General Account)
A3: Disclaimer & Contact Information | J3: Accumulated Data | L3: Quarterly Data
F4: 단위 십억원 (KRW bn) | J4: Jun '26 | K4: Jun '25 | L4: Jun '26 | M4: Jun '25 | N4: 46112 | O4: YoY | P4: QoQ
B5: 재무현황 (Financial Highlights) | F5: 개인 (Tied Agent) | J5: =+SUM(J6,J8,J9) -> 519.00338 | K5: =+SUM(K6,K8,K9) -> 504.25943 | L5: =+SUM(L6,L8,L9) -> 260.00214 | M5: =+SUM(M6,M8,M9) -> 253.76221 | N5: =+SUM(N6,N8,N9) -> 259.00124 | O5: =IF(J5/K5<0,"n.a.",IF(K5>0,ROUND(J5,4)/ROUND(K5,4)-1,IF(K5<0,"n.a."))) -> 0.029238919 | P5: =IF(L5/N5<0,"n.a.",IF(N5>0,ROUND(L5,4)/ROUND(N5,4)-1,IF(N5<0,"n.a."))) -> 0.0038644609
G6: 보장성보험 (Protection-type) | J6: ='Premium Income by D.C.(GA+SA)'!J6-'Premium Income by D.C.'!J35 -> 478.4312 | K6: ='Premium Income by D.C.(GA+SA)'!K6-'Premium Income by D.C.'!K35 -> 460.22689 | L6: ='Premium Income by D.C.(GA+SA)'!L6-'Premium Income by D.C.'!L35 -> 239.94665 | M6: ='Premium Income by D.C.(GA+SA)'!M6-'Premium Income by D.C.'!M35 -> 232.20437 | N6: ='Premium Income by D.C.(GA+SA)'!N6-'Premium Income by D.C.'!N35 -> 238.48455 | O6: =IF(J6/K6<0,"n.a.",IF(K6>0,ROUND(J6,4)/ROUND(K6,4)-1,IF(K6<0,"n.a."))) -> 0.039555054 | P6: =IF(L6/N6<0,"n.a.",IF(N6>0,ROUND(L6,4)/ROUND(N6,4)-1,IF(N6<0,"n.a."))) -> 0.0061312161
B7: 요약재무상태표 (Selected Balance sheet) | G7: % 보장성보험 (% Protection-type) | J7: =J6/J5 -> 0.92182675 | K7: =K6/K5 -> 0.9126788 | L7: =L6/L5 -> 0.92286415 | M7: =M6/M5 -> 0.9150471 | N7: =N6/N5 -> 0.92078534 | O7: =J7-K7 -> 0.0091479544 | P7: =L7-N7 -> 0.0020788077
B8: 요약손익계산서 (Selected Income Statement) | G8: 연금보험 (Annuities) | J8: ='Premium Income by D.C.(GA+SA)'!J8-'Premium Income by D.C.'!J37 -> 15.228407 | K8: ='Premium Income by D.C.(GA+SA)'!K8-'Premium Income by D.C.'!K37 -> 15.556691 | L8: ='Premium Income by D.C.(GA+SA)'!L8-'Premium Income by D.C.'!L37 -> 7.6365414 | M8: ='Premium Income by D.C.(GA+SA)'!M8-'Premium Income by D.C.'!M37 -> 7.5346782 | N8: ='Premium Income by D.C.(GA+SA)'!N8-'Premium Income by D.C.'!N37 -> 7.5918657 | O8: =IF(J8/K8<0,"n.a.",IF(K8>0,ROUND(J8,4)/ROUND(K8,4)-1,IF(K8<0,"n.a."))) -> -0.021103447 | P8: =IF(L8/N8<0,"n.a.",IF(N8>0,ROUND(L8,4)/ROUND(N8,4)-1,IF(N8<0,"n.a."))) -> 0.0058746822
G9: 저축보험 (Savings) | J9: ='Premium Income by D.C.(GA+SA)'!J9-'Premium Income by D.C.'!J38 -> 25.343772 | K9: ='Premium Income by D.C.(GA+SA)'!K9-'Premium Income by D.C.'!K38 -> 28.475849 | L9: ='Premium Income by D.C.(GA+SA)'!L9-'Premium Income by D.C.'!L38 -> 12.418944 | M9: ='Premium Income by D.C.(GA+SA)'!M9-'Premium Income by D.C.'!M38 -> 14.023157 | N9: ='Premium Income by D.C.(GA+SA)'!N9-'Premium Income by D.C.'!N38 -> 12.924828 | O9: =IF(J9/K9<0,"n.a.",IF(K9>0,ROUND(J9,4)/ROUND(K9,4)-1,IF(K9<0,"n.a."))) -> -0.10998813 | P9: =IF(L9/N9<0,"n.a.",IF(N9>0,ROUND(L9,4)/ROUND(N9,4)-1,IF(N9<0,"n.a."))) -> -0.039141805
B10: RA, CSM, BEL Movement | F10: 다이렉트 (Tele Marketing) | J10: =+SUM(J11,J13,J14) -> 116.70972 | K10: =+SUM(K11,K13,K14) -> 133.20837 | L10: =+SUM(L11,L13,L14) -> 56.722322 | M10: =+SUM(M11,M13,M14) -> 64.676336 | N10: =+SUM(N11,N13,N14) -> 59.987401 | O10: =IF(J10/K10<0,"n.a.",IF(K10>0,ROUND(J10,4)/ROUND(K10,4)-1,IF(K10<0,"n.a."))) -> -0.1238563 | P10: =IF(L10/N10<0,"n.a.",IF(N10>0,ROUND(L10,4)/ROUND(N10,4)-1,IF(N10<0,"n.a."))) -> -0.054429764
B11: 신계약 CSM (New Business CSM) | G11: 보장성보험 (Protection-type) | J11: ='Premium Income by D.C.(GA+SA)'!J11-'Premium Income by D.C.'!J40 -> 90.73501 | K11: ='Premium Income by D.C.(GA+SA)'!K11-'Premium Income by D.C.'!K40 -> 104.11208 | L11: ='Premium Income by D.C.(GA+SA)'!L11-'Premium Income by D.C.'!L40 -> 44.307218 | M11: ='Premium Income by D.C.(GA+SA)'!M11-'Premium Income by D.C.'!M40 -> 50.619456 | N11: ='Premium Income by D.C.(GA+SA)'!N11-'Premium Income by D.C.'!N40 -> 46.427792 | O11: =IF(J11/K11<0,"n.a.",IF(K11>0,ROUND(J11,4)/ROUND(K11,4)-1,IF(K11<0,"n.a."))) -> -0.12848747 | P11: =IF(L11/N11<0,"n.a.",IF(N11>0,ROUND(L11,4)/ROUND(N11,4)-1,IF(N11<0,"n.a."))) -> -0.04567522
B12: 신계약 CSM 배수 (New Business CSM Margin) | G12: % 보장성보험 (% Protection-type) | J12: =J11/J10 -> 0.77744175 | K12: =K11/K10 -> 0.78157308 | L12: =L11/L10 -> 0.7811249 | M12: =M11/M10 -> 0.78265807 | N12: =N11/N10 -> 0.77395906 | O12: =J12-K12 -> -0.0041313358 | P12: =L12-N12 -> 0.00716584
G13: 연금보험 (Annuities) | J13: ='Premium Income by D.C.(GA+SA)'!J13-'Premium Income by D.C.'!J42 -> 2.2956514 | K13: ='Premium Income by D.C.(GA+SA)'!K13-'Premium Income by D.C.'!K42 -> 3.0831057 | L13: ='Premium Income by D.C.(GA+SA)'!L13-'Premium Income by D.C.'!L42 -> 1.0298388 | M13: ='Premium Income by D.C.(GA+SA)'!M13-'Premium Income by D.C.'!M42 -> 1.4064106 | N13: ='Premium Income by D.C.(GA+SA)'!N13-'Premium Income by D.C.'!N42 -> 1.2658126 | O13: =IF(J13/K13<0,"n.a.",IF(K13>0,ROUND(J13,4)/ROUND(K13,4)-1,IF(K13<0,"n.a."))) -> -0.2553923 | P13: =IF(L13/N13<0,"n.a.",IF(N13>0,ROUND(L13,4)/ROUND(N13,4)-1,IF(N13<0,"n.a."))) -> -0.18644336
B14: 주요지표 (Key Index) | G14: 저축보험 (Savings) | J14: ='Premium Income by D.C.(GA+SA)'!J14-'Premium Income by D.C.'!J43 -> 23.679061 | K14: ='Premium Income by D.C.(GA+SA)'!K14-'Premium Income by D.C.'!K43 -> 26.013189 | L14: ='Premium Income by D.C.(GA+SA)'!L14-'Premium Income by D.C.'!L43 -> 11.385265 | M14: ='Premium Income by D.C.(GA+SA)'!M14-'Premium Income by D.C.'!M43 -> 12.650469 | N14: ='Premium Income by D.C.(GA+SA)'!N14-'Premium Income by D.C.'!N43 -> 12.293796 | O14: =IF(J14/K14<0,"n.a.",IF(K14>0,ROUND(J14,4)/ROUND(K14,4)-1,IF(K14<0,"n.a."))) -> -0.089727523 | P14: =IF(L14/N14<0,"n.a.",IF(N14>0,ROUND(L14,4)/ROUND(N14,4)-1,IF(N14<0,"n.a."))) -> -0.073899039
C15: 재무 안정성 (Financial Stability) | F15: GA (General Agency) | J15: =+SUM(J16,J18,J19) -> 923.30296 | K15: =+SUM(K16,K18,K19) -> 899.12194 | L15: =+SUM(L16,L18,L19) -> 463.29065 | M15: =+SUM(M16,M18,M19) -> 452.97647 | N15: =+SUM(N16,N18,N19) -> 460.01231 | O15: =IF(J15/K15<0,"n.a.",IF(K15>0,ROUND(J15,4)/ROUND(K15,4)-1,IF(K15<0,"n.a."))) -> 0.026894129 | P15: =IF(L15/N15<0,"n.a.",IF(N15>0,ROUND(L15,4)/ROUND(N15,4)-1,IF(N15<0,"n.a."))) -> 0.007126766
C16: 생산성 / 경영효율 (Productivity / Operating Efficiency) | G16: 보장성보험 (Protection-type) | J16: ='Premium Income by D.C.(GA+SA)'!J16-'Premium Income by D.C.'!J45 -> 884.64307 | K16: ='Premium Income by D.C.(GA+SA)'!K16-'Premium Income by D.C.'!K45 -> 846.49302 | L16: ='Premium Income by D.C.(GA+SA)'!L16-'Premium Income by D.C.'!L45 -> 444.93307 | M16: ='Premium Income by D.C.(GA+SA)'!M16-'Premium Income by D.C.'!M45 -> 427.62842 | N16: ='Premium Income by D.C.(GA+SA)'!N16-'Premium Income by D.C.'!N45 -> 439.71 | O16: =IF(J16/K16<0,"n.a.",IF(K16>0,ROUND(J16,4)/ROUND(K16,4)-1,IF(K16<0,"n.a."))) -> 0.045068418 | P16: =IF(L16/N16<0,"n.a.",IF(N16>0,ROUND(L16,4)/ROUND(N16,4)-1,IF(N16<0,"n.a."))) -> 0.011878511
G17: % 보장성보험 (% Protection-type) | J17: =J16/J15 -> 0.95812871 | K17: =K16/K15 -> 0.94146632 | L17: =L16/L15 -> 0.96037568 | M17: =M16/M15 -> 0.94404113 | N17: =N16/N15 -> 0.95586572 | O17: =J17-K17 -> 0.016662389 | P17: =L17-N17 -> 0.0045099565
B18: 상품별 수입보험료 (Premium by Product-type) | G18: 연금보험 (Annuities) | J18: ='Premium Income by D.C.(GA+SA)'!J18-'Premium Income by D.C.'!J47 -> 23.334041 | K18: ='Premium Income by D.C.(GA+SA)'!K18-'Premium Income by D.C.'!K47 -> 30.43471 | L18: ='Premium Income by D.C.(GA+SA)'!L18-'Premium Income by D.C.'!L47 -> 11.09435 | M18: ='Premium Income by D.C.(GA+SA)'!M18-'Premium Income by D.C.'!M47 -> 14.823942 | N18: ='Premium Income by D.C.(GA+SA)'!N18-'Premium Income by D.C.'!N47 -> 12.239691 | O18: =IF(J18/K18<0,"n.a.",IF(K18>0,ROUND(J18,4)/ROUND(K18,4)-1,IF(K18<0,"n.a."))) -> -0.23330935 | P18: =IF(L18/N18<0,"n.a.",IF(N18>0,ROUND(L18,4)/ROUND(N18,4)-1,IF(N18<0,"n.a."))) -> -0.093572555
C19: 상품별 APE (Annualized Premium Equivalent (APE)) | G19: 저축보험 (Savings) | J19: ='Premium Income by D.C.(GA+SA)'!J19-'Premium Income by D.C.'!J48 -> 15.325849 | K19: ='Premium Income by D.C.(GA+SA)'!K19-'Premium Income by D.C.'!K48 -> 22.19421 | L19: ='Premium Income by D.C.(GA+SA)'!L19-'Premium Income by D.C.'!L48 -> 7.2632284 | M19: ='Premium Income by D.C.(GA+SA)'!M19-'Premium Income by D.C.'!M48 -> 10.524109 | N19: ='Premium Income by D.C.(GA+SA)'!N19-'Premium Income by D.C.'!N48 -> 8.0626209 | O19: =IF(J19/K19<0,"n.a.",IF(K19>0,ROUND(J19,4)/ROUND(K19,4)-1,IF(K19<0,"n.a."))) -> -0.30946824 | P19: =IF(L19/N19<0,"n.a.",IF(N19>0,ROUND(L19,4)/ROUND(N19,4)-1,IF(N19<0,"n.a."))) -> -0.099149158
C20: 상품별 수입보험료 (Premium Income) | F20: 방카슈랑스 (Bancassurance) | J20: =+SUM(J21,J23,J24) -> 834.55058 | K20: =+SUM(K21,K23,K24) -> 292.01605 | L20: =+SUM(L21,L23,L24) -> 505.57478 | M20: =+SUM(M21,M23,M24) -> 157.26923 | N20: =+SUM(N21,N23,N24) -> 328.9758 | O20: =IF(J20/K20<0,"n.a.",IF(K20>0,ROUND(J20,4)/ROUND(K20,4)-1,IF(K20<0,"n.a."))) -> 1.8578924 | P20: =IF(L20/N20<0,"n.a.",IF(N20>0,ROUND(L20,4)/ROUND(N20,4)-1,IF(N20<0,"n.a."))) -> 0.53681456
C21: 상품별 초회보험료 (Initial Premium) | G21: 보장성보험 (Protection-type) | J21: ='Premium Income by D.C.(GA+SA)'!J21-'Premium Income by D.C.'!J50 -> 206.58845 | K21: ='Premium Income by D.C.(GA+SA)'!K21-'Premium Income by D.C.'!K50 -> 177.34641 | L21: ='Premium Income by D.C.(GA+SA)'!L21-'Premium Income by D.C.'!L50 -> 104.89453 | M21: ='Premium Income by D.C.(GA+SA)'!M21-'Premium Income by D.C.'!M50 -> 92.662412 | N21: ='Premium Income by D.C.(GA+SA)'!N21-'Premium Income by D.C.'!N50 -> 101.69392 | O21: =IF(J21/K21<0,"n.a.",IF(K21>0,ROUND(J21,4)/ROUND(K21,4)-1,IF(K21<0,"n.a."))) -> 0.16488691 | P21: =IF(L21/N21<0,"n.a.",IF(N21>0,ROUND(L21,4)/ROUND(N21,4)-1,IF(N21<0,"n.a."))) -> 0.031472881
C22: 상품별 초년도보험료 (First Year Premium) | G22: % 보장성보험 (% Protection-type) | J22: =J21/J20 -> 0.24754455 | K22: =K21/K20 -> 0.60731733 | L22: =L21/L20 -> 0.20747579 | M22: =M21/M20 -> 0.58919608 | N22: =N21/N20 -> 0.30912281 | O22: =J22-K22 -> -0.35977278 | P22: =L22-N22 -> -0.10164702
G23: 연금보험 (Annuities) | J23: ='Premium Income by D.C.(GA+SA)'!J23-'Premium Income by D.C.'!J52 -> 590.66393 | K23: ='Premium Income by D.C.(GA+SA)'!K23-'Premium Income by D.C.'!K52 -> 59.456811 | L23: ='Premium Income by D.C.(GA+SA)'!L23-'Premium Income by D.C.'!L52 -> 383.05512 | M23: ='Premium Income by D.C.(GA+SA)'!M23-'Premium Income by D.C.'!M52 -> 38.853526 | N23: ='Premium Income by D.C.(GA+SA)'!N23-'Premium Income by D.C.'!N52 -> 207.60881 | O23: =IF(J23/K23<0,"n.a.",IF(K23>0,ROUND(J23,4)/ROUND(K23,4)-1,IF(K23<0,"n.a."))) -> 8.9343372 | P23: =IF(L23/N23<0,"n.a.",IF(N23>0,ROUND(L23,4)/ROUND(N23,4)-1,IF(N23<0,"n.a."))) -> 0.84508123
B24: 채널별 수입보험료 (Premium by Distribution Channel) | G24: 저축보험 (Savings) | J24: ='Premium Income by D.C.(GA+SA)'!J24-'Premium Income by D.C.'!J53 -> 37.298204 | K24: ='Premium Income by D.C.(GA+SA)'!K24-'Premium Income by D.C.'!K53 -> 55.212832 | L24: ='Premium Income by D.C.(GA+SA)'!L24-'Premium Income by D.C.'!L53 -> 17.625136 | M24: ='Premium Income by D.C.(GA+SA)'!M24-'Premium Income by D.C.'!M53 -> 25.753288 | N24: ='Premium Income by D.C.(GA+SA)'!N24-'Premium Income by D.C.'!N53 -> 19.673068 | O24: =IF(J24/K24<0,"n.a.",IF(K24>0,ROUND(J24,4)/ROUND(K24,4)-1,IF(K24<0,"n.a."))) -> -0.32446462 | P24: =IF(L24/N24<0,"n.a.",IF(N24>0,ROUND(L24,4)/ROUND(N24,4)-1,IF(N24<0,"n.a."))) -> -0.10410154
C25: 채널별 APE (Annualized Premium Equivalent (APE)) | F25: 합계 (Total) | J25: =SUM(J26,J28:J29) -> 2393.5666 | K25: =SUM(K26,K28:K29) -> 1828.6058 | L25: =SUM(L26,L28:L29) -> 1285.5899 | M25: =SUM(M26,M28:M29) -> 928.68424 | N25: =SUM(N26,N28:N29) -> 1107.9767 | O25: =IF(J25/K25<0,"n.a.",IF(K25>0,ROUND(J25,4)/ROUND(K25,4)-1,IF(K25<0,"n.a."))) -> 0.30895713 | P25: =IF(L25/N25<0,"n.a.",IF(N25>0,ROUND(L25,4)/ROUND(N25,4)-1,IF(N25<0,"n.a."))) -> 0.16030409
C26: 채널별 수입보험료 (Premium Income) | G26: 보장성보험 (Protection-type) | J26: ='Premium Income by D.C.(GA+SA)'!J26-'Premium Income by D.C.'!J55 -> 1660.3977 | K26: ='Premium Income by D.C.(GA+SA)'!K26-'Premium Income by D.C.'!K55 -> 1588.1784 | L26: ='Premium Income by D.C.(GA+SA)'!L26-'Premium Income by D.C.'!L55 -> 834.08147 | M26: ='Premium Income by D.C.(GA+SA)'!M26-'Premium Income by D.C.'!M55 -> 803.11466 | N26: ='Premium Income by D.C.(GA+SA)'!N26-'Premium Income by D.C.'!N55 -> 826.31626 | O26: =IF(J26/K26<0,"n.a.",IF(K26>0,ROUND(J26,4)/ROUND(K26,4)-1,IF(K26<0,"n.a."))) -> 0.04547304 | P26: =IF(L26/N26<0,"n.a.",IF(N26>0,ROUND(L26,4)/ROUND(N26,4)-1,IF(N26<0,"n.a."))) -> 0.00939737
C27: 채널별 초년도보험료 (First Year Premium) | G27: % 보장성보험 (% Protection-type) | J27: =J26/J25 -> 0.69369187 | K27: =K26/K25 -> 0.86851874 | L27: =L26/L25 -> 0.6487928 | M27: =M26/M25 -> 0.86478765 | N27: =N26/N25 -> 0.74578845 | O27: =J27-K27 -> -0.17482686 | P27: =L27-N27 -> -0.096995645
G28: 연금보험 (Annuities) | J28: ='Premium Income by D.C.(GA+SA)'!J28-'Premium Income by D.C.'!J57 -> 631.52203 | K28: ='Premium Income by D.C.(GA+SA)'!K28-'Premium Income by D.C.'!K57 -> 108.53132 | L28: ='Premium Income by D.C.(GA+SA)'!L28-'Premium Income by D.C.'!L57 -> 402.81585 | M28: ='Premium Income by D.C.(GA+SA)'!M28-'Premium Income by D.C.'!M57 -> 62.618557 | N28: ='Premium Income by D.C.(GA+SA)'!N28-'Premium Income by D.C.'!N57 -> 228.70618 | O28: =IF(J28/K28<0,"n.a.",IF(K28>0,ROUND(J28,4)/ROUND(K28,4)-1,IF(K28<0,"n.a."))) -> 4.8188007 | P28: =IF(L28/N28<0,"n.a.",IF(N28>0,ROUND(L28,4)/ROUND(N28,4)-1,IF(N28<0,"n.a."))) -> 0.76128063
G29: 저축보험 (Savings) | J29: ='Premium Income by D.C.(GA+SA)'!J29-'Premium Income by D.C.'!J58 -> 101.64689 | K29: ='Premium Income by D.C.(GA+SA)'!K29-'Premium Income by D.C.'!K58 -> 131.89608 | L29: ='Premium Income by D.C.(GA+SA)'!L29-'Premium Income by D.C.'!L58 -> 48.692573 | M29: ='Premium Income by D.C.(GA+SA)'!M29-'Premium Income by D.C.'!M58 -> 62.951023 | N29: ='Premium Income by D.C.(GA+SA)'!N29-'Premium Income by D.C.'!N58 -> 52.954313 | O29: =IF(J29/K29<0,"n.a.",IF(K29>0,ROUND(J29,4)/ROUND(K29,4)-1,IF(K29<0,"n.a."))) -> -0.22934113 | P29: =IF(L29/N29<0,"n.a.",IF(N29>0,ROUND(L29,4)/ROUND(N29,4)-1,IF(N29<0,"n.a."))) -> -0.080478828
B30: 투자영업 현황 (Investment)
C31: 대출 (Loan)/ 자산건전성 (Asset Quality of Loan) | F31: 특별계정 (Separate Account)
C32: 채권 (Bond) | J32: Accumulated Data | L32: Quarterly Data
F33: 단위 십억원 (KRW bn) | J33: Jun '26 | K33: Jun '25 | L33: Jun '26 | M33: Jun '25 | N33: 46112 | O33: YoY | P33: QoQ
B34: 재무제표 (Full Financial Statements) | F34: 개인 (Tied Agent) | J34: =+SUM(J35,J37,J38) -> 22.360189 | K34: =+SUM(K35,K37,K38) -> 16.760833 | L34: =+SUM(L35,L37,L38) -> 14.125863 | M34: =+SUM(M35,M37,M38) -> 7.9908942 | N34: =+SUM(N35,N37,N38) -> 8.2343261 | O34: =IF(J34/K34<0,"n.a.",IF(K34>0,ROUND(J34,4)/ROUND(K34,4)-1,IF(K34<0,"n.a."))) -> 0.33407713 | P34: =IF(L34/N34<0,"n.a.",IF(N34>0,ROUND(L34,4)/ROUND(N34,4)-1,IF(N34<0,"n.a."))) -> 0.71549494
C35: 재무상태표 (Balance Sheet - KIFRS) | G35: 보장성보험 (Protection-type) | J35: 8.0305117 | K35: 9.3743816 | L35: 3.9204236 | M35: 4.6739862 | N35: 4.110088 | O35: =IF(J35/K35<0,"n.a.",IF(K35>0,ROUND(J35,4)/ROUND(K35,4)-1,IF(K35<0,"n.a."))) -> -0.14335851 | P35: =IF(L35/N35<0,"n.a.",IF(N35>0,ROUND(L35,4)/ROUND(N35,4)-1,IF(N35<0,"n.a."))) -> -0.046154595
C36: 손익계산서 (Income Statement - KIFRS) | G36: % 보장성보험 (% Protection-type) | J36: =J35/J34 -> 0.35914328 | K36: =K35/K34 -> 0.55930285 | L36: =L35/L34 -> 0.27753515 | M36: =M35/M34 -> 0.58491403 | N36: =N35/N34 -> 0.49914079 | O36: =J36-K36 -> -0.20015957 | P36: =L36-N36 -> -0.22160564
G37: 연금보험 (Annuities) | J37: 2.6456636 | K37: 3.9005963 | L37: 1.2862347 | M37: 1.8648705 | N37: 1.3594289 | O37: =IF(J37/K37<0,"n.a.",IF(K37>0,ROUND(J37,4)/ROUND(K37,4)-1,IF(K37<0,"n.a."))) -> -0.32171974 | P37: =IF(L37/N37<0,"n.a.",IF(N37>0,ROUND(L37,4)/ROUND(N37,4)-1,IF(N37<0,"n.a."))) -> -0.053847286
G38: 저축보험 (Savings) | J38: 11.684014 | K38: 3.4858551 | L38: 8.9192049 | M38: 1.4520375 | N38: 2.7648092 | O38: =IF(J38/K38<0,"n.a.",IF(K38>0,ROUND(J38,4)/ROUND(K38,4)-1,IF(K38<0,"n.a."))) -> 2.3517886 | P38: =IF(L38/N38<0,"n.a.",IF(N38>0,ROUND(L38,4)/ROUND(N38,4)-1,IF(N38<0,"n.a."))) -> 2.2259838
F39: 다이렉트 (Tele Marketing) | J39: =+SUM(J40,J42,J43) -> 1.1776033 | K39: =+SUM(K40,K42,K43) -> 0.95980878 | L39: =+SUM(L40,L42,L43) -> 0.58288178 | M39: =+SUM(M40,M42,M43) -> 0.47465456 | N39: =+SUM(N40,N42,N43) -> 0.5947215 | O39: =IF(J39/K39<0,"n.a.",IF(K39>0,ROUND(J39,4)/ROUND(K39,4)-1,IF(K39<0,"n.a."))) -> 0.22692228 | P39: =IF(L39/N39<0,"n.a.",IF(N39>0,ROUND(L39,4)/ROUND(N39,4)-1,IF(N39<0,"n.a."))) -> -0.019841937
G40: 보장성보험 (Protection-type) | J40: 0.72508728 | K40: 0.63637132 | L40: 0.36751579 | M40: 0.31410107 | N40: 0.3575715 | O40: =IF(J40/K40<0,"n.a.",IF(K40>0,ROUND(J40,4)/ROUND(K40,4)-1,IF(K40<0,"n.a."))) -> 0.13937775 | P40: =IF(L40/N40<0,"n.a.",IF(N40>0,ROUND(L40,4)/ROUND(N40,4)-1,IF(N40<0,"n.a."))) -> 0.027684564
G41: % 보장성보험 (% Protection-type) | J41: =J40/J39 -> 0.61573137 | K41: =K40/K39 -> 0.66301886 | L41: =L40/L39 -> 0.63051513 | M41: =M40/M39 -> 0.66174667 | N41: =N40/N39 -> 0.60124191 | O41: =J41-K41 -> -0.047287493 | P41: =L41-N41 -> 0.029273221
G42: 연금보험 (Annuities) | J42: 0.25445567 | K42: 0.15261736 | L42: 0.10089646 | M42: 0.071039953 | N42: 0.15355921 | O42: =IF(J42/K42<0,"n.a.",IF(K42>0,ROUND(J42,4)/ROUND(K42,4)-1,IF(K42<0,"n.a."))) -> 0.66775885 | P42: =IF(L42/N42<0,"n.a.",IF(N42>0,ROUND(L42,4)/ROUND(N42,4)-1,IF(N42<0,"n.a."))) -> -0.34309896
G43: 저축보험 (Savings) | J43: 0.19806034 | K43: 0.1708201 | L43: 0.11446954 | M43: 0.089513535 | N43: 0.083590801 | O43: =IF(J43/K43<0,"n.a.",IF(K43>0,ROUND(J43,4)/ROUND(K43,4)-1,IF(K43<0,"n.a."))) -> 0.15983607 | P43: =IF(L43/N43<0,"n.a.",IF(N43>0,ROUND(L43,4)/ROUND(N43,4)-1,IF(N43<0,"n.a."))) -> 0.36961722
F44: GA (General Agency) | J44: =+SUM(J45,J47,J48) -> 5.7799527 | K44: =+SUM(K45,K47,K48) -> 6.3037853 | L44: =+SUM(L45,L47,L48) -> 2.8717091 | M44: =+SUM(M45,M47,M48) -> 3.0939569 | N44: =+SUM(N45,N47,N48) -> 2.9082436 | O44: =IF(J44/K44<0,"n.a.",IF(K44>0,ROUND(J44,4)/ROUND(K44,4)-1,IF(K44<0,"n.a."))) -> -0.083092738 | P44: =IF(L44/N44<0,"n.a.",IF(N44>0,ROUND(L44,4)/ROUND(N44,4)-1,IF(N44<0,"n.a."))) -> -0.012550719
G45: 보장성보험 (Protection-type) | J45: 3.2625181 | K45: 3.594792 | L45: 1.6270515 | M45: 1.753788 | N45: 1.6354666 | O45: =IF(J45/K45<0,"n.a.",IF(K45>0,ROUND(J45,4)/ROUND(K45,4)-1,IF(K45<0,"n.a."))) -> -0.092439079 | P45: =IF(L45/N45<0,"n.a.",IF(N45>0,ROUND(L45,4)/ROUND(N45,4)-1,IF(N45<0,"n.a."))) -> -0.005136044
G46: % 보장성보험 (% Protection-type) | J46: =J45/J44 -> 0.56445413 | K46: =K45/K44 -> 0.57025928 | L46: =L45/L44 -> 0.56657952 | M46: =M45/M44 -> 0.56684306 | N46: =N45/N44 -> 0.56235544 | O46: =J46-K46 -> -0.0058051461 | P46: =L46-N46 -> 0.0042240812
G47: 연금보험 (Annuities) | J47: 1.4342055 | K47: 1.6674913 | L47: 0.7077871 | M47: 0.82546273 | N47: 0.72641844 | O47: =IF(J47/K47<0,"n.a.",IF(K47>0,ROUND(J47,4)/ROUND(K47,4)-1,IF(K47<0,"n.a."))) -> -0.13991004 | P47: =IF(L47/N47<0,"n.a.",IF(N47>0,ROUND(L47,4)/ROUND(N47,4)-1,IF(N47<0,"n.a."))) -> -0.025605727
G48: 저축보험 (Savings) | J48: 1.083229 | K48: 1.0415019 | L48: 0.53687042 | M48: 0.51470616 | N48: 0.54635855 | O48: =IF(J48/K48<0,"n.a.",IF(K48>0,ROUND(J48,4)/ROUND(K48,4)-1,IF(K48<0,"n.a."))) -> 0.040038406 | P48: =IF(L48/N48<0,"n.a.",IF(N48>0,ROUND(L48,4)/ROUND(N48,4)-1,IF(N48<0,"n.a."))) -> -0.01738653
F49: 방카슈랑스 (Bancassurance) | J49: =+SUM(J50,J52,J53) -> 0.10650503 | K49: =+SUM(K50,K52,K53) -> 0.12967602 | L49: =+SUM(L50,L52,L53) -> 0.049399184 | M49: =+SUM(M50,M52,M53) -> 0.07545363 | N49: =+SUM(N50,N52,N53) -> 0.057105851 | O49: =IF(J49/K49<0,"n.a.",IF(K49>0,ROUND(J49,4)/ROUND(K49,4)-1,IF(K49<0,"n.a."))) -> -0.17887433 | P49: =IF(L49/N49<0,"n.a.",IF(N49>0,ROUND(L49,4)/ROUND(N49,4)-1,IF(N49<0,"n.a."))) -> -0.13485114
G50: 보장성보험 (Protection-type) | J50: 0.005117048 | K50: 0.003862515 | L50: 0.002505075 | M50: 0.001795163 | N50: 0.002611973 | O50: =IF(J50/K50<0,"n.a.",IF(K50>0,ROUND(J50,4)/ROUND(K50,4)-1,IF(K50<0,"n.a."))) -> 0.30769231 | P50: =IF(L50/N50<0,"n.a.",IF(N50>0,ROUND(L50,4)/ROUND(N50,4)-1,IF(N50<0,"n.a."))) -> -0.038461538
G51: % 보장성보험 (% Protection-type) | J51: =J50/J49 -> 0.048045128 | K51: =K50/K49 -> 0.029785886 | L51: =L50/L49 -> 0.050710858 | M51: =M50/M49 -> 0.023791606 | N51: =N50/N49 -> 0.045739149 | O51: =J51-K51 -> 0.018259242 | P51: =L51-N51 -> 0.0049717094
G52: 연금보험 (Annuities) | J52: 0.08192244 | K52: 0.08220034 | L52: 0.03812297 | M52: 0.03987917 | N52: 0.04379947 | O52: =IF(J52/K52<0,"n.a.",IF(K52>0,ROUND(J52,4)/ROUND(K52,4)-1,IF(K52<0,"n.a."))) -> -0.003649635 | P52: =IF(L52/N52<0,"n.a.",IF(N52>0,ROUND(L52,4)/ROUND(N52,4)-1,IF(N52<0,"n.a."))) -> -0.13013699
G53: 저축보험 (Savings) | J53: 0.019465547 | K53: 0.043613162 | L53: 0.008771139 | M53: 0.033779297 | N53: 0.010694408 | O53: =IF(J53/K53<0,"n.a.",IF(K53>0,ROUND(J53,4)/ROUND(K53,4)-1,IF(K53<0,"n.a."))) -> -0.55275229 | P53: =IF(L53/N53<0,"n.a.",IF(N53>0,ROUND(L53,4)/ROUND(N53,4)-1,IF(N53<0,"n.a."))) -> -0.17757009
F54: 합계 (Total) | J54: =SUM(J55,J57:J58) -> 29.42425 | K54: =SUM(K55,K57:K58) -> 24.154103 | L54: =SUM(L55,L57:L58) -> 17.629853 | M54: =SUM(M55,M57:M58) -> 11.634959 | N54: =SUM(N55,N57:N58) -> 11.794397 | O54: =IF(J54/K54<0,"n.a.",IF(K54>0,ROUND(J54,4)/ROUND(K54,4)-1,IF(K54<0,"n.a."))) -> 0.2181907 | P54: =IF(L54/N54<0,"n.a.",IF(N54>0,ROUND(L54,4)/ROUND(N54,4)-1,IF(N54<0,"n.a."))) -> 0.4947687
G55: 보장성보험 (Protection-type) | J55: =SUM(J35,J40,J45,J50) -> 12.023234 | K55: =SUM(K35,K40,K45,K50) -> 13.609408 | L55: =SUM(L35,L40,L45,L50) -> 5.917496 | M55: =SUM(M35,M40,M45,M50) -> 6.7436704 | N55: =SUM(N35,N40,N45,N50) -> 6.1057381 | O55: =IF(J55/K55<0,"n.a.",IF(K55>0,ROUND(J55,4)/ROUND(K55,4)-1,IF(K55<0,"n.a."))) -> -0.1165518 | P55: =IF(L55/N55<0,"n.a.",IF(N55>0,ROUND(L55,4)/ROUND(N55,4)-1,IF(N55<0,"n.a."))) -> -0.030823657
G56: % 보장성보험 (% Protection-type) | J56: =J55/J54 -> 0.4086165 | K56: =K55/K54 -> 0.56344081 | L56: =L55/L54 -> 0.33565203 | M56: =M55/M54 -> 0.57960412 | N56: =N55/N54 -> 0.51768124 | O56: =J56-K56 -> -0.15482432 | P56: =L56-N56 -> -0.18202921
G57: 연금보험 (Annuities) | J57: =SUM(J37,J42,J47,J52) -> 4.4162473 | K57: =SUM(K37,K42,K47,K52) -> 5.8029053 | L57: =SUM(L37,L42,L47,L52) -> 2.1330413 | M57: =SUM(M37,M42,M47,M52) -> 2.8012523 | N57: =SUM(N37,N42,N47,N52) -> 2.283206 | O57: =IF(J57/K57<0,"n.a.",IF(K57>0,ROUND(J57,4)/ROUND(K57,4)-1,IF(K57<0,"n.a."))) -> -0.23896672 | P57: =IF(L57/N57<0,"n.a.",IF(N57>0,ROUND(L57,4)/ROUND(N57,4)-1,IF(N57<0,"n.a."))) -> -0.065784863
G58: 저축보험 (Savings) | J58: =SUM(J38,J43,J48,J53) -> 12.984769 | K58: =SUM(K38,K43,K48,K53) -> 4.7417903 | L58: =SUM(L38,L43,L48,L53) -> 9.579316 | M58: =SUM(M38,M43,M48,M53) -> 2.0900365 | N58: =SUM(N38,N43,N48,N53) -> 3.4054529 | O58: =IF(J58/K58<0,"n.a.",IF(K58>0,ROUND(J58,4)/ROUND(K58,4)-1,IF(K58<0,"n.a."))) -> 1.7383694 | P58: =IF(L58/N58<0,"n.a.",IF(N58>0,ROUND(L58,4)/ROUND(N58,4)-1,IF(N58<0,"n.a."))) -> 1.8128909
F59: *단체, 퇴직 제외

Sheet First-year P. by D.C
F1: 채널별 초년도 보험료 (First-year Premium by Distribution Channel)
F2: 합계 (일반계정 + 특별계정) (Total (General acc. + Separate acc.))
A3: Disclaimer & Contact Information | J3: Accumulated Data | L3: Quarterly Data
F4: 단위 십억원 (KRW bn) | J4: Jun '26 | K4: Jun '25 | L4: Jun '26 | M4: Jun '25 | N4: 46112 | O4: YoY | P4: QoQ
B5: 재무현황 (Financial Highlights) | F5: 개인 (Tied Agent) | J5: 70.040784 | K5: 75.851503 | L5: 34.577132 | M5: 37.750269 | N5: 35.463653 | O5: =IF(J5/K5<0,"n.a.",IF(K5>0,ROUND(J5,4)/ROUND(K5,4)-1,IF(K5<0,"n.a."))) -> -0.076606264 | P5: =IF(L5/N5<0,"n.a.",IF(N5>0,ROUND(L5,4)/ROUND(N5,4)-1,IF(N5<0,"n.a."))) -> -0.025000211
F6: 다이렉트 (Tele Marketing) | J6: 12.149488 | K6: 14.849151 | L6: 5.9633131 | M6: 7.2857801 | N6: 6.1861753 | O6: =IF(J6/K6<0,"n.a.",IF(K6>0,ROUND(J6,4)/ROUND(K6,4)-1,IF(K6<0,"n.a."))) -> -0.18180777 | P6: =IF(L6/N6<0,"n.a.",IF(N6>0,ROUND(L6,4)/ROUND(N6,4)-1,IF(N6<0,"n.a."))) -> -0.036031813
B7: 요약재무상태표 (Selected Balance sheet) | F7: GA (General Agency) | J7: 137.38496 | K7: 227.68306 | L7: 67.79021 | M7: 111.57234 | N7: 69.594749 | O7: =IF(J7/K7<0,"n.a.",IF(K7>0,ROUND(J7,4)/ROUND(K7,4)-1,IF(K7<0,"n.a."))) -> -0.39659553 | P7: =IF(L7/N7<0,"n.a.",IF(N7>0,ROUND(L7,4)/ROUND(N7,4)-1,IF(N7<0,"n.a."))) -> -0.025928699
B8: 요약손익계산서 (Selected Income Statement) | F8: 방카슈랑스 (Bancassurance) | J8: 613.69795 | K8: 100.0507 | L8: 392.54488 | M8: 64.039958 | N8: 221.15307 | O8: =IF(J8/K8<0,"n.a.",IF(K8>0,ROUND(J8,4)/ROUND(K8,4)-1,IF(K8<0,"n.a."))) -> 5.1338691 | P8: =IF(L8/N8<0,"n.a.",IF(N8>0,ROUND(L8,4)/ROUND(N8,4)-1,IF(N8<0,"n.a."))) -> 0.77499162
F9: 합계 (Total) | J9: =SUM(J5:J8) -> 833.27318 | K9: =SUM(K5:K8) -> 418.43441 | L9: =SUM(L5:L8) -> 500.87553 | M9: =SUM(M5:M8) -> 220.64835 | N9: =SUM(N5:N8) -> 332.39764 | O9: =IF(J9/K9<0,"n.a.",IF(K9>0,ROUND(J9,4)/ROUND(K9,4)-1,IF(K9<0,"n.a."))) -> 0.99140702 | P9: =IF(L9/N9<0,"n.a.",IF(N9>0,ROUND(L9,4)/ROUND(N9,4)-1,IF(N9<0,"n.a."))) -> 0.50685655
B10: RA, CSM, BEL Movement
B11: 신계약 CSM (New Business CSM) | F11: [일시납 - Single premium]
B12: 신계약 CSM 배수 (New Business CSM Margin)
J13: Accumulated Data | L13: Quarterly Data
B14: 주요지표 (Key Index) | F14: 단위 십억원 (KRW bn) | J14: Jun '26 | K14: Jun '25 | L14: Jun '26 | M14: Jun '25 | N14: 46112 | O14: YoY | P14: QoQ
C15: 재무 안정성 (Financial Stability) | F15: 개인 (Tied Agent) | J15: 4.9284122 | K15: 2.5153038 | L15: 2.6140487 | M15: 1.3242863 | N15: 2.3143635 | O15: =IF(J15/K15<0,"n.a.",IF(K15>0,ROUND(J15,4)/ROUND(K15,4)-1,IF(K15<0,"n.a."))) -> 0.95936866 | P15: =IF(L15/N15<0,"n.a.",IF(N15>0,ROUND(L15,4)/ROUND(N15,4)-1,IF(N15<0,"n.a."))) -> 0.1294504
C16: 생산성 / 경영효율 (Productivity / Operating Efficiency) | F16: 다이렉트 (Tele Marketing) | J16: 0.18887251 | K16: 0.16579275 | L16: 0.1258146 | M16: 0.076896037 | N16: 0.063057917 | O16: =IF(J16/K16<0,"n.a.",IF(K16>0,ROUND(J16,4)/ROUND(K16,4)-1,IF(K16<0,"n.a."))) -> 0.13932449 | P16: =IF(L16/N16<0,"n.a.",IF(N16>0,ROUND(L16,4)/ROUND(N16,4)-1,IF(N16<0,"n.a."))) -> 0.99366086
F17: GA (General Agency) | J17: 0.80244044 | K17: 1.4105717 | L17: 0.34289235 | M17: 0.69915938 | N17: 0.45954809 | O17: =IF(J17/K17<0,"n.a.",IF(K17>0,ROUND(J17,4)/ROUND(K17,4)-1,IF(K17<0,"n.a."))) -> -0.43116404 | P17: =IF(L17/N17<0,"n.a.",IF(N17>0,ROUND(L17,4)/ROUND(N17,4)-1,IF(N17<0,"n.a."))) -> -0.25375408
B18: 상품별 수입보험료 (Premium by Product-type) | F18: 방카슈랑스 (Bancassurance) | J18: 567.24689 | K18: 25.823446 | L18: 371.64909 | M18: 24.098743 | N18: 195.59781 | O18: =IF(J18/K18<0,"n.a.",IF(K18>0,ROUND(J18,4)/ROUND(K18,4)-1,IF(K18<0,"n.a."))) -> 20.966391 | P18: =IF(L18/N18<0,"n.a.",IF(N18>0,ROUND(L18,4)/ROUND(N18,4)-1,IF(N18<0,"n.a."))) -> 0.90006789
C19: 상품별 APE (Annualized Premium Equivalent (APE)) | F19: 합계 (Total) | J19: =SUM(J15:J18) -> 573.16662 | K19: =SUM(K15:K18) -> 29.915114 | L19: =SUM(L15:L18) -> 374.73184 | M19: =SUM(M15:M18) -> 26.199084 | N19: =SUM(N15:N18) -> 198.43478 | O19: =IF(J19/K19<0,"n.a.",IF(K19>0,ROUND(J19,4)/ROUND(K19,4)-1,IF(K19<0,"n.a."))) -> 18.159775 | P19: =IF(L19/N19<0,"n.a.",IF(N19>0,ROUND(L19,4)/ROUND(N19,4)-1,IF(N19<0,"n.a."))) -> 0.88843792
C20: 상품별 수입보험료 (Premium Income)
C21: 상품별 초회보험료 (Initial Premium) | F21: [비일시납 - Non-single premium]
C22: 상품별 초년도보험료 (First Year Premium)
J23: Accumulated Data | L23: Quarterly Data
B24: 채널별 수입보험료 (Premium by Distribution Channel) | F24: 단위 십억원 (KRW bn) | J24: Jun '26 | K24: Jun '25 | L24: Jun '26 | M24: Jun '25 | N24: 46112 | O24: YoY | P24: QoQ
C25: 채널별 APE (Annualized Premium Equivalent (APE)) | F25: 개인 (Tied Agent) | J25: 65.112372 | K25: 73.336199 | L25: 31.963083 | M25: 36.425982 | N25: 33.149289 | O25: =IF(J25/K25<0,"n.a.",IF(K25>0,ROUND(J25,4)/ROUND(K25,4)-1,IF(K25<0,"n.a."))) -> -0.11213834 | P25: =IF(L25/N25<0,"n.a.",IF(N25>0,ROUND(L25,4)/ROUND(N25,4)-1,IF(N25<0,"n.a."))) -> -0.035783561
C26: 채널별 수입보험료 (Premium Income) | F26: 다이렉트 (Tele Marketing) | J26: 11.960616 | K26: 14.683358 | L26: 5.8374985 | M26: 7.208884 | N26: 6.1231174 | O26: =IF(J26/K26<0,"n.a.",IF(K26>0,ROUND(J26,4)/ROUND(K26,4)-1,IF(K26<0,"n.a."))) -> -0.18543389 | P26: =IF(L26/N26<0,"n.a.",IF(N26>0,ROUND(L26,4)/ROUND(N26,4)-1,IF(N26<0,"n.a."))) -> -0.04664304
C27: 채널별 초년도보험료 (First Year Premium) | F27: GA (General Agency) | J27: 136.58252 | K27: 226.27249 | L27: 67.447317 | M27: 110.87318 | N27: 69.135201 | O27: =IF(J27/K27<0,"n.a.",IF(K27>0,ROUND(J27,4)/ROUND(K27,4)-1,IF(K27<0,"n.a."))) -> -0.39638047 | P27: =IF(L27/N27<0,"n.a.",IF(N27>0,ROUND(L27,4)/ROUND(N27,4)-1,IF(N27<0,"n.a."))) -> -0.024414481
F28: 방카슈랑스 (Bancassurance) | J28: 46.451053 | K28: 74.22725 | L28: 20.895793 | M28: 39.941216 | N28: 25.55526 | O28: =IF(J28/K28<0,"n.a.",IF(K28>0,ROUND(J28,4)/ROUND(K28,4)-1,IF(K28<0,"n.a."))) -> -0.3742038 | P28: =IF(L28/N28<0,"n.a.",IF(N28>0,ROUND(L28,4)/ROUND(N28,4)-1,IF(N28<0,"n.a."))) -> -0.18233008
F29: 합계 (Total) | J29: =SUM(J25:J28) -> 260.10656 | K29: =SUM(K25:K28) -> 388.51929 | L29: =SUM(L25:L28) -> 126.14369 | M29: =SUM(M25:M28) -> 194.44927 | N29: =SUM(N25:N28) -> 133.96287 | O29: =IF(J29/K29<0,"n.a.",IF(K29>0,ROUND(J29,4)/ROUND(K29,4)-1,IF(K29<0,"n.a."))) -> -0.3305182 | P29: =IF(L29/N29<0,"n.a.",IF(N29>0,ROUND(L29,4)/ROUND(N29,4)-1,IF(N29<0,"n.a."))) -> -0.058368399
B30: 투자영업 현황 (Investment)
C31: 대출 (Loan)/ 자산건전성 (Asset Quality of Loan) | F31: *단체, 퇴직 제외
C32: 채권 (Bond)
B34: 재무제표 (Full Financial Statements)
C35: 재무상태표 (Balance Sheet - KIFRS)
C36: 손익계산서 (Income Statement - KIFRS)

Sheet >Loan
F1: 대출 (Loan Breakdown)
J2: FY25 | N2: FY26 | S2: 증감
A3: Disclaimer & Contact Information | F3: 단위 십억원 (KRW bn) | J3: 45747 | K3: 45838 | L3: 45930 | M3: 46022 | N3: 46112 | O3: 46203 | P3: 46295 | Q3: 46387 | S3: YoY | T3: QoQ
F4: 대출채권 (Total Loan) | J4: 5744.8872 | K4: 5538.5204 | L4: 4819.382 | M4: 4722.641 | N4: 4531.7503 | O4: 4293.7464 | S4: =IF(O4/K4<0,"n.a.",IF(K4>0,ROUND(O4,4)/ROUND(K4,4)-1,IF(K4<0,"n.a."))) -> -0.22474847 | T4: =IF(O4/N4<0,"n.a.",IF(N4>0,ROUND(O4,4)/ROUND(N4,4)-1,IF(N4<0,"n.a."))) -> -0.0525192
B5: 재무현황 (Financial Highlights) | I5: 콜론 (Call Loan) | J5: 0 | K5: 0 | L5: 0 | M5: 0 | N5: 0 | O5: 0 | S5: 0 | T5: 0
I6: 보험약관대출금 (Policy Loan) | J6: 0 | K6: 0 | L6: 0 | M6: 0 | N6: 0 | O6: 0 | S6: 0 | T6: 0
B7: 요약재무상태표 (Selected Balance sheet) | I7: 유가증권담보대출금 (Loans on Securities) | J7: 0 | K7: 0 | L7: 0 | M7: 0 | N7: 0 | O7: 0 | S7: 0 | T7: 0
B8: 요약손익계산서 (Selected Income Statement) | I8: 부동산담보대출금 (Housing Collateral Loan) | J8: 1896.6636 | K8: 1928.5514 | L8: 1643.2137 | M8: 1632.4537 | N8: 1486.0726 | O8: 1427.6518 | S8: =IF(O8/K8<0,"n.a.",IF(K8>0,ROUND(O8,4)/ROUND(K8,4)-1,IF(K8<0,"n.a."))) -> -0.25972842 | T8: =IF(O8/N8<0,"n.a.",IF(N8>0,ROUND(O8,4)/ROUND(N8,4)-1,IF(N8<0,"n.a."))) -> -0.039312211
I9: 신용대출금 (Unsecured Loan) | J9: 44.090355 | K9: 41.739146 | L9: 38.802643 | M9: 35.950251 | N9: 33.38427 | O9: 31.365074 | S9: =IF(O9/K9<0,"n.a.",IF(K9>0,ROUND(O9,4)/ROUND(K9,4)-1,IF(K9<0,"n.a."))) -> -0.24854393 | T9: =IF(O9/N9<0,"n.a.",IF(N9>0,ROUND(O9,4)/ROUND(N9,4)-1,IF(N9<0,"n.a."))) -> -0.060483521
B10: RA, CSM, BEL Movement | I10: 지급보증대출금 (Loans on Acceptance and Guarantee) | J10: 797.47915 | K10: 805.17502 | L10: 852.53837 | M10: 904.53983 | N10: 964.28335 | O10: 1001.7694 | S10: =IF(O10/K10<0,"n.a.",IF(K10>0,ROUND(O10,4)/ROUND(K10,4)-1,IF(K10<0,"n.a."))) -> 0.24416357 | T10: =IF(O10/N10<0,"n.a.",IF(N10>0,ROUND(O10,4)/ROUND(N10,4)-1,IF(N10<0,"n.a."))) -> 0.038874464
B11: 신계약 CSM (New Business CSM) | I11: 기타대출금 (Other Loans) | J11: 3006.6541 | K11: 2763.0547 | L11: 2284.8272 | M11: 2149.6972 | N11: 2048.01 | O11: 1832.9601 | S11: =IF(O11/K11<0,"n.a.",IF(K11>0,ROUND(O11,4)/ROUND(K11,4)-1,IF(K11<0,"n.a."))) -> -0.33661824 | T11: =IF(O11/N11<0,"n.a.",IF(N11>0,ROUND(O11,4)/ROUND(N11,4)-1,IF(N11<0,"n.a."))) -> -0.10500432
B12: 신계약 CSM 배수 (New Business CSM Margin) | F12: ※ 보험약관대출금은 부채차감 항목으로 반영
B14: 주요지표 (Key Index)
C15: 재무 안정성 (Financial Stability) | F15: 자산건전성 (Asset Quality of Loan)
C16: 생산성 / 경영효율 (Productivity / Operating Efficiency) | J16: FY25 | N16: FY26 | S16: 증감
F17: 단위 십억원,% (KRW bn, %) | J17: 45747 | K17: 45838 | L17: 45930 | M17: 46022 | N17: 46112 | O17: 46203 | P17: 46295 | Q17: 46387 | S17: YoY | T17: QoQ
B18: 상품별 수입보험료 (Premium by Product-type) | F18: 대출채권 (Total Loan) | J18: 5744.8872 | K18: 5538.5204 | L18: 4789.3819 | M18: 4722.641 | N18: 4531.7503 | O18: 4293.7464 | S18: =IF(O18/K18<0,"n.a.",IF(K18>0,ROUND(O18,4)/ROUND(K18,4)-1,IF(K18<0,"n.a."))) -> -0.22474847 | T18: =IF(O18/N18<0,"n.a.",IF(N18>0,ROUND(O18,4)/ROUND(N18,4)-1,IF(N18<0,"n.a."))) -> -0.0525192
C19: 상품별 APE (Annualized Premium Equivalent (APE)) | G19: 정상 (Normal) | J19: 5647.6523 | K19: 5203.3008 | L19: 4220.7517 | M19: 4349.5473 | N19: 4169.5998 | O19: 4066.9702 | S19: =IF(O19/K19<0,"n.a.",IF(K19>0,ROUND(O19,4)/ROUND(K19,4)-1,IF(K19<0,"n.a."))) -> -0.21838649 | T19: =IF(O19/N19<0,"n.a.",IF(N19>0,ROUND(O19,4)/ROUND(N19,4)-1,IF(N19<0,"n.a."))) -> -0.024613777
C20: 상품별 수입보험료 (Premium Income) | G20: 요주의 (Precautionary) | J20: 50.452539 | K20: 240.21362 | L20: 503.9452 | M20: 307.46338 | N20: 273.18349 | O20: 177.4554 | S20: =IF(O20/K20<0,"n.a.",IF(K20>0,ROUND(O20,4)/ROUND(K20,4)-1,IF(K20<0,"n.a."))) -> -0.26125998 | T20: =IF(O20/N20<0,"n.a.",IF(N20>0,ROUND(O20,4)/ROUND(N20,4)-1,IF(N20<0,"n.a."))) -> -0.35041684
C21: 상품별 초회보험료 (Initial Premium) | G21: 고정이하 (Non Performing Loan (NPL)) | J21: 46.782285 | K21: 95.005941 | L21: 64.684925 | M21: 65.630273 | N21: 88.966989 | O21: 49.320769 | S21: =IF(O21/K21<0,"n.a.",IF(K21>0,ROUND(O21,4)/ROUND(K21,4)-1,IF(K21<0,"n.a."))) -> -0.48086593 | T21: =IF(O21/N21<0,"n.a.",IF(N21>0,ROUND(O21,4)/ROUND(N21,4)-1,IF(N21<0,"n.a."))) -> -0.44562815
C22: 상품별 초년도보험료 (First Year Premium) | H22: 고정 (Substandard) | J22: 32.213761 | K22: 80.77081 | L22: 50.396542 | M22: 42.934192 | N22: 77.838936 | O22: 46.345099 | S22: =IF(O22/K22<0,"n.a.",IF(K22>0,ROUND(O22,4)/ROUND(K22,4)-1,IF(K22<0,"n.a."))) -> -0.42621467 | T22: =IF(O22/N22<0,"n.a.",IF(N22>0,ROUND(O22,4)/ROUND(N22,4)-1,IF(N22<0,"n.a."))) -> -0.40460233
H23: 회수의문 (Doubtful) | J23: 2.1137483 | K23: 2.1705784 | L23: 2.0958632 | M23: 2.264222 | N23: 2.3564555 | O23: 2.1546612 | S23: =IF(O23/K23<0,"n.a.",IF(K23>0,ROUND(O23,4)/ROUND(K23,4)-1,IF(K23<0,"n.a."))) -> -0.0073251635 | T23: =IF(O23/N23<0,"n.a.",IF(N23>0,ROUND(O23,4)/ROUND(N23,4)-1,IF(N23<0,"n.a."))) -> -0.085635476
B24: 채널별 수입보험료 (Premium by Distribution Channel) | H24: 추정손실 (Estimated Loss) | J24: 12.454776 | K24: 12.064553 | L24: 12.19252 | M24: 20.431859 | N24: 8.7715981 | O24: 0.82100905 | S24: =IF(O24/K24<0,"n.a.",IF(K24>0,ROUND(O24,4)/ROUND(K24,4)-1,IF(K24<0,"n.a."))) -> -0.93194967 | T24: =IF(O24/N24<0,"n.a.",IF(N24>0,ROUND(O24,4)/ROUND(N24,4)-1,IF(N24<0,"n.a."))) -> -0.90640248
C25: 채널별 APE (Annualized Premium Equivalent (APE)) | F25: NPL(고정이하) 비율 (NPL ratio) | J25: 0.0081432905 | K25: 0.017153668 | L25: 0.013505903 | M25: 0.013896943 | N25: 0.019631927 | O25: 0.011486652 | S25: =O25-K25 -> -0.0056670166 | T25: =O25-N25 -> -0.0081452751
C26: 채널별 수입보험료 (Premium Income)
C27: 채널별 초년도보험료 (First Year Premium)
B30: 투자영업 현황 (Investment)
C31: 대출 (Loan)/ 자산건전성 (Asset Quality of Loan)
C32: 채권 (Bond)
B34: 재무제표 (Full Financial Statements)
C35: 재무상태표 (Balance Sheet - KIFRS)
C36: 손익계산서 (Income Statement - KIFRS)

Sheet >Bond
F1: 채권 (Bond Breakdown)
F2: < IFRS9 기준 >
A3: Disclaimer & Contact Information | F3: 단위 십억원, % | I3: FY25 | M3: FY26 | R3: 증감
F4: (KRW bn, %) | I4: 45747 | J4: 45838 | K4: 45930 | L4: 46022 | M4: 46112 | N4: 46203 | O4: 46295 | P4: 46387 | R4: YoY | S4: QoQ
B5: 재무현황 (Financial Highlights) | F5: 당기손익-공정가치측정유가증권 (FVPL) | I5: =SUM(I6:I10) -> 1145.2196 | J5: =SUM(J6:J10) -> 771.971 | K5: =SUM(K6:K10) -> 765.87849 | L5: =SUM(L6:L10) -> 756.08882 | M5: =SUM(M6:M10) -> 773.89542 | N5: =SUM(N6:N10) -> 781.8111 | R5: =IF(N5/J5<0,"n.a.",IF(J5>0,ROUND(N5,4)/ROUND(J5,4)-1,IF(J5<0,"n.a."))) -> 0.012746722 | S5: =IF(N5/M5<0,"n.a.",IF(M5>0,ROUND(N5,4)/ROUND(M5,4)-1,IF(M5<0,"n.a."))) -> 0.010228385
G6: 국채 (Government Bonds) | I6: 0 | J6: 0 | K6: 0 | L6: 0 | M6: 0 | N6: 0 | R6: 0 | S6: 0
B7: 요약재무상태표 (Selected Balance sheet) | G7: 특수채 (Special Bonds) | I7: 50.185482 | J7: 0 | K7: 0 | L7: 0 | M7: 0 | N7: 0 | R7: 0 | S7: 0
B8: 요약손익계산서 (Selected Income Statement) | G8: 금융채 (Financial Bonds) | I8: 234.44564 | J8: 117.68276 | K8: 107.52411 | L8: 85.610375 | M8: 83.672682 | N8: 73.245135 | R8: =IF(N8/J8<0,"n.a.",IF(J8>0,ROUND(N8,4)/ROUND(J8,4)-1,IF(J8<0,"n.a."))) -> -0.37760573 | S8: =IF(N8/M8<0,"n.a.",IF(M8>0,ROUND(N8,4)/ROUND(M8,4)-1,IF(M8<0,"n.a."))) -> -0.12462368
G9: 회사채 (Corporate Bonds) | I9: 90.182147 | J9: 50.087049 | K9: 50.130217 | L9: 50.11334 | M9: 50.115909 | N9: 50.101813 | R9: =IF(N9/J9<0,"n.a.",IF(J9>0,ROUND(N9,4)/ROUND(J9,4)-1,IF(J9<0,"n.a."))) -> 0.00029548585 | S9: =IF(N9/M9<0,"n.a.",IF(M9>0,ROUND(N9,4)/ROUND(M9,4)-1,IF(M9<0,"n.a."))) -> -0.00028134784
B10: RA, CSM, BEL Movement | G10: 해외채권(Overseas Bonds) | I10: 770.40636 | J10: 604.20119 | K10: 608.22416 | L10: 620.36511 | M10: 640.10683 | N10: 658.46415 | R10: =IF(N10/J10<0,"n.a.",IF(J10>0,ROUND(N10,4)/ROUND(J10,4)-1,IF(J10<0,"n.a."))) -> 0.089809487 | S10: =IF(N10/M10<0,"n.a.",IF(M10>0,ROUND(N10,4)/ROUND(M10,4)-1,IF(M10<0,"n.a."))) -> 0.028678652
B11: 신계약 CSM (New Business CSM) | F11: 기타포괄손익-공정가치측정유가증권 (FVOCI) | I11: =SUM(I12:I16) -> 20436.132 | J11: =SUM(J12:J16) -> 21214.101 | K11: =SUM(K12:K16) -> 22569.503 | L11: =SUM(L12:L16) -> 22432.214 | M11: =SUM(M12:M16) -> 22022.423 | N11: =SUM(N12:N16) -> 21894.383 | R11: =IF(N11/J11<0,"n.a.",IF(J11>0,ROUND(N11,4)/ROUND(J11,4)-1,IF(J11<0,"n.a."))) -> 0.032067463 | S11: =IF(N11/M11<0,"n.a.",IF(M11>0,ROUND(N11,4)/ROUND(M11,4)-1,IF(M11<0,"n.a."))) -> -0.0058140651
B12: 신계약 CSM 배수 (New Business CSM Margin) | G12: 국채 (Government Bonds) | I12: 9200.786 | J12: 9358.9755 | K12: 9581.8805 | L12: 9063.9458 | M12: 8397.5 | N12: 8001.9418 | R12: =IF(N12/J12<0,"n.a.",IF(J12>0,ROUND(N12,4)/ROUND(J12,4)-1,IF(J12<0,"n.a."))) -> -0.1449981 | S12: =IF(N12/M12<0,"n.a.",IF(M12>0,ROUND(N12,4)/ROUND(M12,4)-1,IF(M12<0,"n.a."))) -> -0.047104281
G13: 특수채 (Special Bonds) | I13: 3042.5846 | J13: 2916.1841 | K13: 2958.2212 | L13: 2943.2981 | M13: 2937.1742 | N13: 3059.5164 | R13: =IF(N13/J13<0,"n.a.",IF(J13>0,ROUND(N13,4)/ROUND(J13,4)-1,IF(J13<0,"n.a."))) -> 0.049150635 | S13: =IF(N13/M13<0,"n.a.",IF(M13>0,ROUND(N13,4)/ROUND(M13,4)-1,IF(M13<0,"n.a."))) -> 0.041653028
B14: 주요지표 (Key Index) | G14: 금융채 (Financial Bonds) | I14: 2382.7671 | J14: 2400.0527 | K14: 2305.5588 | L14: 2297.574 | M14: 2226.7261 | N14: 2132.4974 | R14: =IF(N14/J14<0,"n.a.",IF(J14>0,ROUND(N14,4)/ROUND(J14,4)-1,IF(J14<0,"n.a."))) -> -0.11147893 | S14: =IF(N14/M14<0,"n.a.",IF(M14>0,ROUND(N14,4)/ROUND(M14,4)-1,IF(M14<0,"n.a."))) -> -0.042317149
C15: 재무 안정성 (Financial Stability) | G15: 회사채 (Corporate Bonds) | I15: 1962.3874 | J15: 1593.668 | K15: 1538.7146 | L15: 1499.6578 | M15: 1628.4494 | N15: 1529.09 | R15: =IF(N15/J15<0,"n.a.",IF(J15>0,ROUND(N15,4)/ROUND(J15,4)-1,IF(J15<0,"n.a."))) -> -0.040521614 | S15: =IF(N15/M15<0,"n.a.",IF(M15>0,ROUND(N15,4)/ROUND(M15,4)-1,IF(M15<0,"n.a."))) -> -0.06101473
C16: 생산성 / 경영효율 (Productivity / Operating Efficiency) | G16: 해외채권(Overseas Bonds) | I16: 3847.6064 | J16: 4945.2205 | K16: 6185.1275 | L16: 6627.7385 | M16: 6832.5733 | N16: 7171.3376 | R16: =IF(N16/J16<0,"n.a.",IF(J16>0,ROUND(N16,4)/ROUND(J16,4)-1,IF(J16<0,"n.a."))) -> 0.45015528 | S16: =IF(N16/M16<0,"n.a.",IF(M16>0,ROUND(N16,4)/ROUND(M16,4)-1,IF(M16<0,"n.a."))) -> 0.049580778
F17: 상각후원가측정유가증권 (AC) | I17: =SUM(I18:I22) -> 0 | J17: =SUM(J18:J22) -> 0 | K17: =SUM(K18:K22) -> 0 | L17: =SUM(L18:L22) -> 0 | M17: =SUM(M18:M22) -> 0 | N17: =SUM(N18:N22) -> 0 | R17: 0 | S17: 0
B18: 상품별 수입보험료 (Premium by Product-type) | G18: 국채 (Government Bonds) | I18: 0 | J18: 0 | K18: 0 | L18: 0 | M18: 0 | N18: 0 | R18: 0 | S18: 0
C19: 상품별 APE (Annualized Premium Equivalent (APE)) | G19: 특수채 (Special Bonds) | I19: 0 | J19: 0 | K19: 0 | L19: 0 | M19: 0 | N19: 0 | R19: 0 | S19: 0
C20: 상품별 수입보험료 (Premium Income) | G20: 금융채 (Financial Bonds) | I20: 0 | J20: 0 | K20: 0 | L20: 0 | M20: 0 | N20: 0 | R20: 0 | S20: 0
C21: 상품별 초회보험료 (Initial Premium) | G21: 회사채 (Corporate Bonds) | I21: 0 | J21: 0 | K21: 0 | L21: 0 | M21: 0 | N21: 0 | R21: 0 | S21: 0
C22: 상품별 초년도보험료 (First Year Premium) | G22: 해외채권(Overseas Bonds) | I22: 0 | J22: 0 | K22: 0 | L22: 0 | M22: 0 | N22: 0 | R22: 0 | S22: 0
F23: 합계 (Total) | I23: =SUM(I17,I11,I5) -> 21581.351 | J23: =SUM(J17,J11,J5) -> 21986.072 | K23: =SUM(K17,K11,K5) -> 23335.381 | L23: =SUM(L17,L11,L5) -> 23188.303 | M23: =SUM(M17,M11,M5) -> 22796.318 | N23: =SUM(N17,N11,N5) -> 22676.194 | R23: =IF(N23/J23<0,"n.a.",IF(J23>0,ROUND(N23,4)/ROUND(J23,4)-1,IF(J23<0,"n.a."))) -> 0.031389077 | S23: =IF(N23/M23<0,"n.a.",IF(M23>0,ROUND(N23,4)/ROUND(M23,4)-1,IF(M23<0,"n.a."))) -> -0.0052694518
B24: 채널별 수입보험료 (Premium by Distribution Channel)
C25: 채널별 APE (Annualized Premium Equivalent (APE))
C26: 채널별 수입보험료 (Premium Income)
C27: 채널별 초년도보험료 (First Year Premium)
B30: 투자영업 현황 (Investment)
C31: 대출 (Loan)/ 자산건전성 (Asset Quality of Loan)
C32: 채권 (Bond)
B34: 재무제표 (Full Financial Statements)
C35: 재무상태표 (Balance Sheet - KIFRS)
C36: 손익계산서 (Income Statement - KIFRS)

Sheet BS  K-IFRS
A1: 연 결 재 무 상 태 표 (Balance Sheet) - K-IFRS
A3: As of Jun 30, 2026(Consolidated)
A4: As of Dec 31, 2025(Consolidated)
C5: 단위:원 (KRW)
B6: IFRS17, IFRS9 | C6: IFRS17, IFRS9
B7: FY2026.6월 | C7: FY2025.12월
A8: 자산 (Assets)
A9: Ⅰ. 현금및현금성자산 (Cash and cash equivalents) | B9: 412274565625 | C9: 250369675528
A10: Ⅱ. 금융자산 (Financial assets) | B10: 33996943235837 | C10: 33879553349342
A11: 1. 당기손익공정가치측정금융자산 (Financial assets at fair value through profit or loss) | B11: 6577917640010 | C11: 5383256354415
A12: 2. 기타포괄손익공정가치측정유가증권 (Financial assets at fair value through other comprehensive income) | B12: 22307750465490 | C12: 22837835416401
A13: 3. 상각후원가측정금융자산 (Financial assets at amortized cost) | B13: 5106619327597 | C13: 5630390869393
A14: 4. 위험회피목적파생상품자산 (Derivative financial assets held for hedging) | B14: 4655802740 | C14: 28070709133
A15: Ⅲ. 유형자산 (Property, plant and equipment) | B15: 96713842011 | C15: 91038644921
A16: Ⅳ. 투자부동산 (Invesment properties) | B16: 74350687803 | C16: 296134885468
A17: Ⅴ. 무형자산 (Intangible assets other than goodwill) | B17: 24128872581 | C17: 27795714379
A18: Ⅵ. 매각예정자산 (Disposal of held for sale) | B18: 221376282421 | C18: 0
A19: Ⅶ. 기타자산 (Other assets) | B19: 64773205279 | C19: 353663061713
A20: 1. 순확정급여자산(Net defined benefit assets) | B20: 0 | C20: 3837577921
... A26: 자산 총계 (Total assets) | B26: 35287666008994 | C26: 35347237061940
A27: 부채 (Liabilities)
A28: Ⅰ. 보험계약부채 (Insurance contracts issued that are liabilities) | B28: 25971370444155 | C28: 28145078606219
A29: Ⅱ. 재보험계약부채 (Reinsurance contracts held that are liabilities) | B29: 7752260916 | C29: 9656170210
A30: Ⅲ. 투자계약부채 (Investment contract liabilities) | B30: 4461032316008 | C30: 3702749470978
A31: Ⅳ. 금융부채 (Financial liabilities) | B31: 2401046110259 | C31: 1881172810767
A32: 1. 당기손익인식금융부채 (Financial liabilities at fair value through profit or loss) | B32: 17325436210 | C32: 25515847022
A33: 2. 사채 (Borrowings) | B33: 1263848373770 | C33: 1210212459653
A34: 3. 기타금융부채 (Other financial liabilities) | B34: 88099555801 | C34: 94741873817
A35: 4. 위험회피목적파생상품부채 (Derivative financial liabilities held for hedging) | B35: 1031772744478 | C35: 550702630275
A36: Ⅴ. 기타부채 (Other liabilities) | B36: 109498286982 | C36: 59705326143
A37: 1. 충당부채 (Provisions) | B37: 39606884573 | C37: 39704656726
A38: 2. 순확정급여채무 (Net defined benefit liabilities) | B38: 3409269417 | C38: 2822218288
A39: 3. 당기법인세부채 (Current tax liabilities) | B39: 0 | C39: 0
... A42: 부채 총계 (Total liabilities) | B42: 32950699418320 | C42: 33798362384317
A43: 자본 (Shareholders' equity)
A44: Ⅰ. 자본금 (Issued capital) | B44: 806792925000 | C44: 806792925000
A45: Ⅱ. 자본잉여금 (Capital surplus) | B45: 463680391349 | C45: 463680391349
A46: Ⅲ. 자본조정 (Capital adjustments) | B46: -58355691382 | C46: -116906314396
A47: Ⅳ. 기타포괄손익누계액 (Accumulated other comprehensive income) | B47: -530124468118 | C47: -1223673605446
A48: Ⅴ. 이익잉여금 (Retained earnings) | B48: 1654973433825 | C48: 1618981281116
A49: 자본 총계 (Total shareholders' equity) | B49: 2336966590674 | C49: 1548874677623
A50: 자본과 부채총계 (Total Shareholders' Equity and liabilities) | B50: 35287666008994 | C50: 35347237061940

Sheet IS  K-IFRS
A1: 연 결 손 익 계 산 서 (Income Statement) - K-IFRS
A3: For the 6 months Ends Jun 30, 2026(Consolidated)
A4: For the 6 months Ends Jun 30, 2025(Consolidated)
C5: 단위:원 (KRW)
B6: IFRS17, IFRS9 | C6: IFRS17, IFRS9
B7: FY2026.6월 | C7: FY2025.6월
A8: Ⅰ. 보험손익 (Insurance service result) | B8: 97012121777 | C8: 70419566477
A9: 1. 보험영업수익 (Operating income, insurance) | B9: 664105996330 | C9: 629541286450
A10: (1) 보험수익 (Insurance revenue) | B10: 649473285857 | C10: 606378308828
A11: 가. 예상 발생보험금 (Expected incurred claims) | B11: 312105967821 | C11: 287500464993
A12: 나. 예상 손해조사비용 (Expected claims investigation cost) | B12: 9509396734 | C12: 9361026700
A13: 다. 예상 유지비용 (Expected maintenance cost) | B13: 83910958775 | C13: 80568190362
A14: 라. 예상 투자관리비용 (Expected investment management cost) | B14: 12500204711 | C14: 11938931673
A15: 마. 위험조정 변동 (Changes in the risk adjustment) | B15: 20258790328 | C15: 22144141034
A16: 바. 제공된 서비스의 보험계약마진 (CSM recognized in profit or loss for service provided) | B16: 125511494001 | C16: 126063510783
A17: 사. 보험취득현금흐름 기간배분 (Insurance acquisition cash flows amortization) | B17: 95182823844 | C17: 76003775546
A18: 아. 손실요소 배분액 (Allocation on revenue from onerous contract) | B18: -9506350357 | C18: -7201732263
A19: (2) 재보험수익 (Income from amounts recovered from reinsurer) | B19: 14632710473 | C19: 23162977622
... A63: Ⅷ. 당기순이익(손실) (Net Income) | B63: 91929676843 | C63: 82412271501
